Workbook

Sheet DRE 2026
B2: Demonstrativos Financeiros - 2026 Consolidado | C2: JANEIRO | D2: FEVEREIRO | E2: MARÇO | F2: ABRIL | G2: MAIO | H2: JUNHO | I2: JULHO | J2: AGOSTO | K2: SETEMBRO | L2: OUTUBRO | M2: NOVEMBRO | N2: DEZEMBRO | P2: 1 SEM | Q2: 2 SEM | R2: 2025
B3: DRE (R$)
B4: Receita Operacional Bruta | C4: =SUM(C5:C15) -> 276257.97 | D4: =SUM(D5:D15) -> 302537.98 | E4: =SUM(E5:E15) -> 297990.92 | F4: =SUM(F5:F15) -> 235626.88 | G4: =SUM(G5:G15) -> 242586.46 | H4: =SUM(H5:H15) -> 283604.11 | I4: =IFERROR(__xludf.DUMMYFUNCTION("importrange(""1QxQzD8FYlG3qLn8OXtKW9gfO6pUDR-FCSW3X-_jPPGQ"",""'DRE 2026'!I4:N133"")"),305701.16) -> 305701.16 | J4: =IFERROR(__xludf.DUMMYFUNCTION("""COMPUTED_VALUE"""),414516.74) -> 414516.74 | K4: =IFERROR(__xludf.DUMMYFUNCTION("""COMPUTED_VALUE"""),0) -> 0 | L4: =IFERROR(__xludf.DUMMYFUNCTION("""COMPUTED_VALUE"""),0) -> 0 | M4: =IFERROR(__xludf.DUMMYFUNCTION("""COMPUTED_VALUE"""),0) -> 0 | N4: =IFERROR(__xludf.DUMMYFUNCTION("""COMPUTED_VALUE"""),0) -> 0 | P4: =C4+D4+E4+F4+G4+H4 -> 1638604.3 | Q4: =I4+J4+K4+L4+M4+N4 -> 720217.9 | R4: =Q4+P4 -> 2358822.2
B5: Receita com Taxa de Vendas Online - Formaturas | C5: 110204.65 | D5: 125561.86 | E5: 101436.85 | F5: 64504.04 | G5: 62018.63 | H5: 85436.05 | I5: =IFERROR(__xludf.DUMMYFUNCTION("""COMPUTED_VALUE"""),92571.47) -> 92571.47 | J5: =IFERROR(__xludf.DUMMYFUNCTION("""COMPUTED_VALUE"""),146550.37) -> 146550.37 | P5: =C5+D5+E5+F5+G5+H5 -> 549162.08 | Q5: =I5+J5+K5+L5+M5+N5 -> 239121.84 | R5: =Q5+P5 -> 788283.92
B6: Receita com Taxa de Parcelamento Online - Formaturas | C6: 80333.42 | D6: 81422.18 | E6: 72656.14 | F6: 39955.32 | G6: 42199.76 | H6: 57866.42 | I6: =IFERROR(__xludf.DUMMYFUNCTION("""COMPUTED_VALUE"""),66241.41) -> 66241.41 | J6: =IFERROR(__xludf.DUMMYFUNCTION("""COMPUTED_VALUE"""),100191.14) -> 100191.14 | P6: =C6+D6+E6+F6+G6+H6 -> 374433.24 | Q6: =I6+J6+K6+L6+M6+N6 -> 166432.55 | R6: =Q6+P6 -> 540865.79
B7: Receita com Taxa de Vendas Online - Eventos em Geral | C7: 63839.69 | D7: 62635.2 | E7: 88391.41 | F7: 92904.64 | G7: 101577.49 | H7: 93967.24 | I7: =IFERROR(__xludf.DUMMYFUNCTION("""COMPUTED_VALUE"""),103254.14) -> 103254.14 | J7: =IFERROR(__xludf.DUMMYFUNCTION("""COMPUTED_VALUE"""),121923.04) -> 121923.04 | P7: =C7+D7+E7+F7+G7+H7 -> 503315.67 | Q7: =I7+J7+K7+L7+M7+N7 -> 225177.18 | R7: =Q7+P7 -> 728492.85
B8: Receita com Taxa de Parcelamento Online - Eventos em Geral | C8: 13800.06 | D8: 21745.76 | E8: 25291.26 | F8: 27044.99 | G8: 22268.77 | H8: 29541.43 | I8: =IFERROR(__xludf.DUMMYFUNCTION("""COMPUTED_VALUE"""),28964.19) -> 28964.19 | J8: =IFERROR(__xludf.DUMMYFUNCTION("""COMPUTED_VALUE"""),31761.79) -> 31761.79 | P8: =C8+D8+E8+F8+G8+H8 -> 139692.27 | Q8: =I8+J8+K8+L8+M8+N8 -> 60725.98 | R8: =Q8+P8 -> 200418.25
B9: Receita com Taxa de Cartão | C9: 2006 | D9: 3700 | E9: 2166 | F9: 2562 | G9: 4442 | H9: 2643 | I9: =IFERROR(__xludf.DUMMYFUNCTION("""COMPUTED_VALUE"""),878) -> 878 | J9: =IFERROR(__xludf.DUMMYFUNCTION("""COMPUTED_VALUE"""),2504) -> 2504 | P9: =C9+D9+E9+F9+G9+H9 -> 17519 | Q9: =I9+J9+K9+L9+M9+N9 -> 3382 | R9: =Q9+P9 -> 20901
B10: Receita com Taxa de Administração | C10: 1098.25 | D10: 1452 | E10: 1823.7 | F10: 1539.7 | G10: 1894.79 | H10: 3814.95 | I10: =IFERROR(__xludf.DUMMYFUNCTION("""COMPUTED_VALUE"""),1167.6) -> 1167.6 | J10: =IFERROR(__xludf.DUMMYFUNCTION("""COMPUTED_VALUE"""),2062.4) -> 2062.4 | P10: =C10+D10+E10+F10+G10+H10 -> 11623.39 | Q10: =I10+J10+K10+L10+M10+N10 -> 3230 | R10: =Q10+P10 -> 14853.39
B11: Receita com Taxa de Processamento | C11: 4875.9 | D11: 5461.52 | E11: 5920.56 | F11: 6831.19 | G11: 7684 | H11: 10060.02 | I11: =IFERROR(__xludf.DUMMYFUNCTION("""COMPUTED_VALUE"""),11539.62) -> 11539.62 | J11: =IFERROR(__xludf.DUMMYFUNCTION("""COMPUTED_VALUE"""),9314) -> 9314 | P11: =C11+D11+E11+F11+G11+H11 -> 40833.19 | Q11: =I11+J11+K11+L11+M11+N11 -> 20853.62 | R11: =Q11+P11 -> 61686.81
B12: Receita com Taxas de Antecipação | C12: 0 | D12: 319.46 | E12: 0 | F12: 0 | G12: 327.02 | H12: 0 | I12: =IFERROR(__xludf.DUMMYFUNCTION("""COMPUTED_VALUE"""),949.73) -> 949.73 | J12: =IFERROR(__xludf.DUMMYFUNCTION("""COMPUTED_VALUE"""),0) -> 0 | P12: =C12+D12+E12+F12+G12+H12 -> 646.48 | Q12: =I12+J12+K12+L12+M12+N12 -> 949.73 | R12: =Q12+P12 -> 1596.21
B13: Receita com Locação de Equipamentos | C13: 0 | D13: 0 | E13: 0 | F13: 0 | G13: 0 | H13: 0 | I13: =IFERROR(__xludf.DUMMYFUNCTION("""COMPUTED_VALUE"""),0) -> 0 | J13: =IFERROR(__xludf.DUMMYFUNCTION("""COMPUTED_VALUE"""),0) -> 0 | P13: =C13+D13+E13+F13+G13+H13 -> 0 | Q13: =I13+J13+K13+L13+M13+N13 -> 0 | R13: =Q13+P13 -> 0
B14: Receita com Licença de Uso | C14: 0 | D14: 0 | E14: 0 | F14: 0 | G14: 0 | H14: 0 | I14: =IFERROR(__xludf.DUMMYFUNCTION("""COMPUTED_VALUE"""),0) -> 0 | J14: =IFERROR(__xludf.DUMMYFUNCTION("""COMPUTED_VALUE"""),0) -> 0 | P14: =C14+D14+E14+F14+G14+H14 -> 0 | Q14: =I14+J14+K14+L14+M14+N14 -> 0 | R14: =Q14+P14 -> 0
B15: Receita com Vendas de QR Codes | C15: 100 | D15: 240 | E15: 305 | F15: 285 | G15: 174 | H15: 275 | I15: =IFERROR(__xludf.DUMMYFUNCTION("""COMPUTED_VALUE"""),135) -> 135 | J15: =IFERROR(__xludf.DUMMYFUNCTION("""COMPUTED_VALUE"""),210) -> 210 | P15: =C15+D15+E15+F15+G15+H15 -> 1379 | Q15: =I15+J15+K15+L15+M15+N15 -> 345 | R15: =Q15+P15 -> 1724
B16: Deduções de Receita | C16: =SUM(C17:C19) -> -40017.8 | D16: =SUM(D17:D19) -> -39398.19 | E16: =SUM(E17:E19) -> -27355.42 | F16: =SUM(F17:F19) -> -36236.73 | G16: =SUM(G17:G19) -> -28528.1 | H16: =SUM(H17:H19) -> -39028.04 | I16: =IFERROR(__xludf.DUMMYFUNCTION("""COMPUTED_VALUE"""),-43587.67) -> -43587.67 | J16: =IFERROR(__xludf.DUMMYFUNCTION("""COMPUTED_VALUE"""),-28063.11) -> -28063.11 | K16: =IFERROR(__xludf.DUMMYFUNCTION("""COMPUTED_VALUE"""),0) -> 0 | L16: =IFERROR(__xludf.DUMMYFUNCTION("""COMPUTED_VALUE"""),0) -> 0 | M16: =IFERROR(__xludf.DUMMYFUNCTION("""COMPUTED_VALUE"""),0) -> 0 | N16: =IFERROR(__xludf.DUMMYFUNCTION("""COMPUTED_VALUE"""),0) -> 0 | P16: =C16+D16+E16+F16+G16+H16 -> -210564.28 | Q16: =I16+J16+K16+L16+M16+N16 -> -71650.78 | R16: =Q16+P16 -> -282215.06
B17: Devoluções de Compra de Serviços (Chargeback) | C17: -3999.96 | D17: -6683.42 | E17: -3125.48 | F17: -6677 | G17: -4985.44 | H17: -5484.14 | I17: =IFERROR(__xludf.DUMMYFUNCTION("""COMPUTED_VALUE"""),-14612.15) -> -14612.15 | J17: =IFERROR(__xludf.DUMMYFUNCTION("""COMPUTED_VALUE"""),-19866.11) -> -19866.11 | P17: =C17+D17+E17+F17+G17+H17 -> -30955.44 | Q17: =I17+J17+K17+L17+M17+N17 -> -34478.26 | R17: =Q17+P17 -> -65433.7
B18: Devoluções de Compra (Estornos) | C18: -315 | D18: 0 | E18: 0 | F18: 0 | G18: -368.6 | H18: 0 | I18: =IFERROR(__xludf.DUMMYFUNCTION("""COMPUTED_VALUE"""),-380) -> -380 | J18: =IFERROR(__xludf.DUMMYFUNCTION("""COMPUTED_VALUE"""),0) -> 0 | P18: =C18+D18+E18+F18+G18+H18 -> -683.6 | Q18: =I18+J18+K18+L18+M18+N18 -> -380 | R18: =Q18+P18 -> -1063.6
B19: Simples Nacional (DAS) | C19: -35702.84 | D19: -32714.77 | E19: -24229.94 | F19: -29559.73 | G19: -23174.06 | H19: -33543.9 | I19: =IFERROR(__xludf.DUMMYFUNCTION("""COMPUTED_VALUE"""),-28595.52) -> -28595.52 | J19: =IFERROR(__xludf.DUMMYFUNCTION("""COMPUTED_VALUE"""),-8197) -> -8197 | P19: =C19+D19+E19+F19+G19+H19 -> -178925.24 | Q19: =I19+J19+K19+L19+M19+N19 -> -36792.52 | R19: =Q19+P19 -> -215717.76
B20: Receita Operacional Liquida | C20: =C16+C4 -> 236240.17 | D20: =D16+D4 -> 263139.79 | E20: =E16+E4 -> 270635.5 | F20: =F16+F4 -> 199390.15 | G20: =G16+G4 -> 214058.36 | H20: =H16+H4 -> 244576.07 | I20: =IFERROR(__xludf.DUMMYFUNCTION("""COMPUTED_VALUE"""),262113.49) -> 262113.49 | J20: =IFERROR(__xludf.DUMMYFUNCTION("""COMPUTED_VALUE"""),386453.63) -> 386453.63 | K20: =IFERROR(__xludf.DUMMYFUNCTION("""COMPUTED_VALUE"""),0) -> 0 | L20: =IFERROR(__xludf.DUMMYFUNCTION("""COMPUTED_VALUE"""),0) -> 0 | M20: =IFERROR(__xludf.DUMMYFUNCTION("""COMPUTED_VALUE"""),0) -> 0 | N20: =IFERROR(__xludf.DUMMYFUNCTION("""COMPUTED_VALUE"""),0) -> 0 | P20: =C20+D20+E20+F20+G20+H20 -> 1428040 | Q20: =I20+J20+K20+L20+M20+N20 -> 648567.12 | R20: =Q20+P20 -> 2076607.2
B21: Custos com os Serviços Prestados | C21: =SUM(C22:C26) -> -65505.12 | D21: =SUM(D22:D26) -> -73305.13 | E21: =SUM(E22:E26) -> -69757.14 | F21: =SUM(F22:F26) -> -56260.37 | G21: =SUM(G22:G26) -> -54369.77 | H21: =SUM(H22:H26) -> -73768.21 | I21: =IFERROR(__xludf.DUMMYFUNCTION("""COMPUTED_VALUE"""),-76154.4899999999) -> -76154.49 | J21: =IFERROR(__xludf.DUMMYFUNCTION("""COMPUTED_VALUE"""),-110740.75) -> -110740.75 | K21: =IFERROR(__xludf.DUMMYFUNCTION("""COMPUTED_VALUE"""),0) -> 0 | L21: =IFERROR(__xludf.DUMMYFUNCTION("""COMPUTED_VALUE"""),0) -> 0 | M21: =IFERROR(__xludf.DUMMYFUNCTION("""COMPUTED_VALUE"""),0) -> 0 | N21: =IFERROR(__xludf.DUMMYFUNCTION("""COMPUTED_VALUE"""),0) -> 0 | P21: =C21+D21+E21+F21+G21+H21 -> -392965.74 | Q21: =I21+J21+K21+L21+M21+N21 -> -186895.24 | R21: =Q21+P21 -> -579860.98
B22: Compras de Materia Prima | C22: 0 | D22: 0 | E22: 0 | F22: 0 | G22: 0 | H22: -3925 | I22: =IFERROR(__xludf.DUMMYFUNCTION("""COMPUTED_VALUE"""),0) -> 0 | J22: =IFERROR(__xludf.DUMMYFUNCTION("""COMPUTED_VALUE"""),-4207.6) -> -4207.6 | P22: =C22+D22+E22+F22+G22+H22 -> -3925 | Q22: =I22+J22+K22+L22+M22+N22 -> -4207.6 | R22: =Q22+P22 -> -8132.6
B23: Custo com Gateway de Pagamento | C23: -43699.12 | D23: -50149.13 | E23: -45278.14 | F23: -32563.37 | G23: -32399.77 | H23: -46697.21 | I23: =IFERROR(__xludf.DUMMYFUNCTION("""COMPUTED_VALUE"""),-50637.49) -> -50637.49 | J23: =IFERROR(__xludf.DUMMYFUNCTION("""COMPUTED_VALUE"""),-77538.64) -> -77538.64 | P23: =C23+D23+E23+F23+G23+H23 -> -250786.74 | Q23: =I23+J23+K23+L23+M23+N23 -> -128176.13 | R23: =Q23+P23 -> -378962.87
B24: Serviço de Mão de Obra Eventos / Suporte | C24: -2300 | D24: -2150 | E24: -2600 | F24: -4800 | G24: -1800 | H24: -1800 | I24: =IFERROR(__xludf.DUMMYFUNCTION("""COMPUTED_VALUE"""),-1750) -> -1750 | J24: =IFERROR(__xludf.DUMMYFUNCTION("""COMPUTED_VALUE"""),-3600) -> -3600 | P24: =C24+D24+E24+F24+G24+H24 -> -15450 | Q24: =I24+J24+K24+L24+M24+N24 -> -5350 | R24: =Q24+P24 -> -20800
B25: Royalties | C25: -19506 | D25: -21006 | E25: -21879 | F25: -18897 | G25: -20170 | H25: -21346 | I25: =IFERROR(__xludf.DUMMYFUNCTION("""COMPUTED_VALUE"""),-23767) -> -23767 | J25: =IFERROR(__xludf.DUMMYFUNCTION("""COMPUTED_VALUE"""),-25394.51) -> -25394.51 | P25: =C25+D25+E25+F25+G25+H25 -> -122804 | Q25: =I25+J25+K25+L25+M25+N25 -> -49161.51 | R25: =Q25+P25 -> -171965.51
B26: Compra de Serviços | C26: 0 | D26: 0 | E26: 0 | F26: 0 | G26: 0 | H26: 0 | I26: =IFERROR(__xludf.DUMMYFUNCTION("""COMPUTED_VALUE"""),0) -> 0 | J26: =IFERROR(__xludf.DUMMYFUNCTION("""COMPUTED_VALUE"""),0) -> 0 | P26: =C26+D26+E26+F26+G26+H26 -> 0 | Q26: =I26+J26+K26+L26+M26+N26 -> 0 | R26: =Q26+P26 -> 0
B27: Lucro Operacional Bruto | C27: =C20+C21 -> 170735.05 | D27: =D20+D21 -> 189834.66 | E27: =E20+E21 -> 200878.36 | F27: =F20+F21 -> 143129.78 | G27: =G20+G21 -> 159688.59 | H27: =H20+H21 -> 170807.86 | I27: =IFERROR(__xludf.DUMMYFUNCTION("""COMPUTED_VALUE"""),185959) -> 185959 | J27: =IFERROR(__xludf.DUMMYFUNCTION("""COMPUTED_VALUE"""),275712.88) -> 275712.88 | K27: =IFERROR(__xludf.DUMMYFUNCTION("""COMPUTED_VALUE"""),0) -> 0 | L27: =IFERROR(__xludf.DUMMYFUNCTION("""COMPUTED_VALUE"""),0) -> 0 | M27: =IFERROR(__xludf.DUMMYFUNCTION("""COMPUTED_VALUE"""),0) -> 0 | N27: =IFERROR(__xludf.DUMMYFUNCTION("""COMPUTED_VALUE"""),0) -> 0 | P27: =C27+D27+E27+F27+G27+H27 -> 1035074.3 | Q27: =I27+J27+K27+L27+M27+N27 -> 461671.88 | R27: =Q27+P27 -> 1496746.2
B28: Despesas Operacionais | C28: =C29+C39+C60+C78 -> -112856.77 | D28: =D29+D39+D60+D78 -> -116364.79 | E28: =E29+E39+E60+E78 -> -94723.738 | F28: =F29+F39+F60+F78 -> -127896.35 | G28: =G29+G39+G60+G78 -> -87178.468 | H28: =H29+H39+H60+H78 -> -79811.647 | I28: =IFERROR(__xludf.DUMMYFUNCTION("""COMPUTED_VALUE"""),-133299.7567664) -> -133299.76 | J28: =IFERROR(__xludf.DUMMYFUNCTION("""COMPUTED_VALUE"""),-121493.3609235) -> -121493.36 | K28: =IFERROR(__xludf.DUMMYFUNCTION("""COMPUTED_VALUE"""),0) -> 0 | L28: =IFERROR(__xludf.DUMMYFUNCTION("""COMPUTED_VALUE"""),0) -> 0 | M28: =IFERROR(__xludf.DUMMYFUNCTION("""COMPUTED_VALUE"""),0) -> 0 | N28: =IFERROR(__xludf.DUMMYFUNCTION("""COMPUTED_VALUE"""),0) -> 0 | P28: =C28+D28+E28+F28+G28+H28 -> -618831.76 | Q28: =I28+J28+K28+L28+M28+N28 -> -254793.12 | R28: =Q28+P28 -> -873624.88
B29: Despesas de Vendas e Marketing | C29: =SUM(C30:C38) -> -41486.49 | D29: =SUM(D30:D38) -> -44933.63 | E29: =SUM(E30:E38) -> -31323.43 | F29: =SUM(F30:F38) -> -60289.29 | G29: =SUM(G30:G38) -> -31299.56 | H29: =SUM(H30:H38) -> -24522.11 | I29: =IFERROR(__xludf.DUMMYFUNCTION("""COMPUTED_VALUE"""),-44614.36) -> -44614.36 | J29: =IFERROR(__xludf.DUMMYFUNCTION("""COMPUTED_VALUE"""),-50519.15) -> -50519.15 | K29: =IFERROR(__xludf.DUMMYFUNCTION("""COMPUTED_VALUE"""),0) -> 0 | L29: =IFERROR(__xludf.DUMMYFUNCTION("""COMPUTED_VALUE"""),0) -> 0 | M29: =IFERROR(__xludf.DUMMYFUNCTION("""COMPUTED_VALUE"""),0) -> 0 | N29: =IFERROR(__xludf.DUMMYFUNCTION("""COMPUTED_VALUE"""),0) -> 0 | P29: =C29+D29+E29+F29+G29+H29 -> -233854.51 | Q29: =I29+J29+K29+L29+M29+N29 -> -95133.51 | R29: =Q29+P29 -> -328988.02
B30: Comissões de Vendas - Comercial | C30: -1451.13 | D30: -2288.75 | E30: -1783.99 | F30: -9302.58 | G30: -2014.09 | H30: -233.43 | I30: =IFERROR(__xludf.DUMMYFUNCTION("""COMPUTED_VALUE"""),-84.75) -> -84.75 | J30: =IFERROR(__xludf.DUMMYFUNCTION("""COMPUTED_VALUE"""),-390.18) -> -390.18 | P30: =C30+D30+E30+F30+G30+H30 -> -17073.97 | Q30: =I30+J30+K30+L30+M30+N30 -> -474.93 | R30: =Q30+P30 -> -17548.9
B31: Comissões de Performance - CS | C31: -8204.25 | D31: 0 | E31: 0 | F31: -12208.85 | G31: 0 | H31: 0 | I31: =IFERROR(__xludf.DUMMYFUNCTION("""COMPUTED_VALUE"""),-3390.02) -> -3390.02 | J31: =IFERROR(__xludf.DUMMYFUNCTION("""COMPUTED_VALUE"""),0) -> 0
B32: Marketing | C32: -15649 | D32: -2000 | E32: -2000 | F32: -4719 | G32: -12102.08 | H32: -2752.36 | I32: =IFERROR(__xludf.DUMMYFUNCTION("""COMPUTED_VALUE"""),-3402.36) -> -3402.36 | J32: =IFERROR(__xludf.DUMMYFUNCTION("""COMPUTED_VALUE"""),-4629.67) -> -4629.67 | P32: =C32+D32+E32+F32+G32+H32 -> -39222.44 | Q32: =I32+J32+K32+L32+M32+N32 -> -8032.03 | R32: =Q32+P32 -> -47254.47
B33: Despesas de Viagens | C33: 0 | D33: -5024.12 | E33: -1124.91 | F33: -3559.8 | G33: -580.01 | H33: -1466.5 | I33: =IFERROR(__xludf.DUMMYFUNCTION("""COMPUTED_VALUE"""),0) -> 0 | J33: =IFERROR(__xludf.DUMMYFUNCTION("""COMPUTED_VALUE"""),0) -> 0 | P33: =C33+D33+E33+F33+G33+H33 -> -11755.34 | Q33: =I33+J33+K33+L33+M33+N33 -> 0 | R33: =Q33+P33 -> -11755.34
B34: Cashback - Afiliados | C34: -553.65 | D34: -3109.05 | E34: -3018.19 | F34: =-3230.07-342.55 -> -3572.62 | G34: -3821.33 | H34: -1769.13 | I34: =IFERROR(__xludf.DUMMYFUNCTION("""COMPUTED_VALUE"""),-5015.91) -> -5015.91 | J34: =IFERROR(__xludf.DUMMYFUNCTION("""COMPUTED_VALUE"""),-1762.39) -> -1762.39 | P34: =C34+D34+E34+F34+G34+H34 -> -15843.97 | Q34: =I34+J34+K34+L34+M34+N34 -> -6778.3 | R34: =Q34+P34 -> -22622.27
B35: Cashback - Produtores | C35: -4571.17 | D35: -21204.02 | E35: -10487.02 | F35: =-10315.37-8464.81 -> -18780.18 | G35: -6501.84 | H35: -7321.28 | I35: =IFERROR(__xludf.DUMMYFUNCTION("""COMPUTED_VALUE"""),-9750.44) -> -9750.44 | J35: =IFERROR(__xludf.DUMMYFUNCTION("""COMPUTED_VALUE"""),-13677.71) -> -13677.71 | P35: =C35+D35+E35+F35+G35+H35 -> -68865.51 | Q35: =I35+J35+K35+L35+M35+N35 -> -23428.15 | R35: =Q35+P35 -> -92293.66
B36: Cashback - Franquias | C36: -11057.29 | D36: -11307.69 | E36: -12909.32 | F36: -8146.26 | G36: -6280.21 | H36: -10979.41 | I36: =IFERROR(__xludf.DUMMYFUNCTION("""COMPUTED_VALUE"""),-11485.44) -> -11485.44 | J36: =IFERROR(__xludf.DUMMYFUNCTION("""COMPUTED_VALUE"""),-15029.6) -> -15029.6 | P36: =C36+D36+E36+F36+G36+H36 -> -60680.18 | Q36: =I36+J36+K36+L36+M36+N36 -> -26515.04 | R36: =Q36+P36 -> -87195.22
B37: Cashback - Franqueadora Viva | C37: 0 | D37: 0 | E37: 0 | F37: 0 | G37: 0 | H37: 0 | I37: =IFERROR(__xludf.DUMMYFUNCTION("""COMPUTED_VALUE"""),-11485.44) -> -11485.44 | J37: =IFERROR(__xludf.DUMMYFUNCTION("""COMPUTED_VALUE"""),-15029.6) -> -15029.6
B38: Bonificações | C38: 0 | D38: 0 | E38: 0 | F38: 0 | G38: 0 | H38: 0 | I38: =IFERROR(__xludf.DUMMYFUNCTION("""COMPUTED_VALUE"""),0) -> 0 | J38: =IFERROR(__xludf.DUMMYFUNCTION("""COMPUTED_VALUE"""),0) -> 0 | K38: =IFERROR(__xludf.DUMMYFUNCTION("""COMPUTED_VALUE"""),0) -> 0 | L38: =IFERROR(__xludf.DUMMYFUNCTION("""COMPUTED_VALUE"""),0) -> 0 | M38: =IFERROR(__xludf.DUMMYFUNCTION("""COMPUTED_VALUE"""),0) -> 0 | N38: =IFERROR(__xludf.DUMMYFUNCTION("""COMPUTED_VALUE"""),0) -> 0 | P38: =C38+D38+E38+F38+G38+H38 -> 0 | Q38: =I38+J38+K38+L38+M38+N38 -> 0 | R38: =Q38+P38 -> 0
B39: Despesas com Pessoal | C39: =SUM(C40:C59) -> -55626.043 | D39: =SUM(D40:D59) -> -46514.461 | E39: =SUM(E40:E59) -> -48975.558 | F39: =SUM(F40:F59) -> -56419.866 | G39: =SUM(G40:G59) -> -46331.018 | H39: =SUM(H40:H59) -> -44563.497 | I39: =IFERROR(__xludf.DUMMYFUNCTION("""COMPUTED_VALUE"""),-76280.2267664) -> -76280.227 | J39: =IFERROR(__xludf.DUMMYFUNCTION("""COMPUTED_VALUE"""),-57932.4209235) -> -57932.421 | K39: =IFERROR(__xludf.DUMMYFUNCTION("""COMPUTED_VALUE"""),0) -> 0 | L39: =IFERROR(__xludf.DUMMYFUNCTION("""COMPUTED_VALUE"""),0) -> 0 | M39: =IFERROR(__xludf.DUMMYFUNCTION("""COMPUTED_VALUE"""),0) -> 0 | N39: =IFERROR(__xludf.DUMMYFUNCTION("""COMPUTED_VALUE"""),0) -> 0 | P39: =C39+D39+E39+F39+G39+H39 -> -298430.44 | Q39: =I39+J39+K39+L39+M39+N39 -> -134212.65 | R39: =Q39+P39 -> -432643.09
B40: Salários | C40: -25834.61 | D40: =-3999.62-27516.6 -> -31516.22 | E40: =-26958.56-5022 -> -31980.56 | F40: =-31033.49-6539 -> -37572.49 | G40: -29802.63 | H40: -29662.51 | I40: =IFERROR(__xludf.DUMMYFUNCTION("""COMPUTED_VALUE"""),-24281.12) -> -24281.12 | J40: =IFERROR(__xludf.DUMMYFUNCTION("""COMPUTED_VALUE"""),-28152.55) -> -28152.55 | P40: =C40+D40+E40+F40+G40+H40 -> -186369.02 | Q40: =I40+J40+K40+L40+M40+N40 -> -52433.67 | R40: =Q40+P40 -> -238802.69
B41: Contratados Pessoa Jurídicas | C41: 0 | D41: 0 | E41: 0 | F41: 0 | I41: =IFERROR(__xludf.DUMMYFUNCTION("""COMPUTED_VALUE"""),0) -> 0 | J41: =IFERROR(__xludf.DUMMYFUNCTION("""COMPUTED_VALUE"""),0) -> 0 | K41: =IFERROR(__xludf.DUMMYFUNCTION("""COMPUTED_VALUE"""),0) -> 0 | L41: =IFERROR(__xludf.DUMMYFUNCTION("""COMPUTED_VALUE"""),0) -> 0 | M41: =IFERROR(__xludf.DUMMYFUNCTION("""COMPUTED_VALUE"""),0) -> 0 | N41: =IFERROR(__xludf.DUMMYFUNCTION("""COMPUTED_VALUE"""),0) -> 0 | P41: =C41+D41+E41+F41+G41+H41 -> 0 | Q41: =I41+J41+K41+L41+M41+N41 -> 0 | R41: =Q41+P41 -> 0
B42: Férias | C42: =(((C40+C41)/12)*1.333)*1.08 -> -3099.3782 | D42: =(((D40+D41)/12)*1.333)*1.08 -> -3781.0009 | E42: =(((E40+E41)/12)*1.333)*1.08 -> -3836.7078 | F42: =(((F40+F41)/12)*1.333)*1.08 -> -4507.5716 | G42: =(((G40+G41)/12)*1.333)*1.08 -> -3575.4215 | H42: =(((H40+H41)/12)*1.333)*1.08 -> -3558.6113 | I42: =IFERROR(__xludf.DUMMYFUNCTION("""COMPUTED_VALUE"""),-2913.0059664) -> -2913.006 | J42: =IFERROR(__xludf.DUMMYFUNCTION("""COMPUTED_VALUE"""),-3377.4614235) -> -3377.4614 | K42: =IFERROR(__xludf.DUMMYFUNCTION("""COMPUTED_VALUE"""),0) -> 0 | L42: =IFERROR(__xludf.DUMMYFUNCTION("""COMPUTED_VALUE"""),0) -> 0 | M42: =IFERROR(__xludf.DUMMYFUNCTION("""COMPUTED_VALUE"""),0) -> 0 | N42: =IFERROR(__xludf.DUMMYFUNCTION("""COMPUTED_VALUE"""),0) -> 0 | P42: =C42+D42+E42+F42+G42+H42 -> -22358.691 | Q42: =I42+J42+K42+L42+M42+N42 -> -6290.4674 | R42: =Q42+P42 -> -28649.159
B43: Rescisões | C43: -14954.85 | D43: 0 | E43: 0 | F43: 0 | I43: =IFERROR(__xludf.DUMMYFUNCTION("""COMPUTED_VALUE"""),-18008.73) -> -18008.73 | J43: =IFERROR(__xludf.DUMMYFUNCTION("""COMPUTED_VALUE"""),0) -> 0 | K43: =IFERROR(__xludf.DUMMYFUNCTION("""COMPUTED_VALUE"""),0) -> 0 | L43: =IFERROR(__xludf.DUMMYFUNCTION("""COMPUTED_VALUE"""),0) -> 0 | M43: =IFERROR(__xludf.DUMMYFUNCTION("""COMPUTED_VALUE"""),0) -> 0 | N43: =IFERROR(__xludf.DUMMYFUNCTION("""COMPUTED_VALUE"""),0) -> 0 | P43: =C43+D43+E43+F43+G43+H43 -> -14954.85 | Q43: =I43+J43+K43+L43+M43+N43 -> -18008.73 | R43: =Q43+P43 -> -32963.58
B44: 13º Salário | C44: =(C40/12)*1.08 -> -2325.1149 | D44: =(D40/12)*1.08 -> -2836.4598 | E44: =(E40/12)*1.08 -> -2878.2504 | F44: =(F40/12)*1.08 -> -3381.5241 | G44: =(G40/12)*1.08 -> -2682.2367 | H44: =(H40/12)*1.08 -> -2669.6259 | I44: =IFERROR(__xludf.DUMMYFUNCTION("""COMPUTED_VALUE"""),-2185.3008) -> -2185.3008 | J44: =IFERROR(__xludf.DUMMYFUNCTION("""COMPUTED_VALUE"""),-2533.7295) -> -2533.7295 | K44: =IFERROR(__xludf.DUMMYFUNCTION("""COMPUTED_VALUE"""),0) -> 0 | L44: =IFERROR(__xludf.DUMMYFUNCTION("""COMPUTED_VALUE"""),0) -> 0 | M44: =IFERROR(__xludf.DUMMYFUNCTION("""COMPUTED_VALUE"""),0) -> 0 | N44: =IFERROR(__xludf.DUMMYFUNCTION("""COMPUTED_VALUE"""),0) -> 0 | P44: =C44+D44+E44+F44+G44+H44 -> -16773.212 | Q44: =I44+J44+K44+L44+M44+N44 -> -4719.0303 | R44: =Q44+P44 -> -21492.242
B45: INSS | C45: 0 | D45: 0 | E45: 0 | F45: 0 | G45: 0 | H45: 0 | I45: =IFERROR(__xludf.DUMMYFUNCTION("""COMPUTED_VALUE"""),0) -> 0 | J45: =IFERROR(__xludf.DUMMYFUNCTION("""COMPUTED_VALUE"""),0) -> 0 | K45: =IFERROR(__xludf.DUMMYFUNCTION("""COMPUTED_VALUE"""),0) -> 0 | L45: =IFERROR(__xludf.DUMMYFUNCTION("""COMPUTED_VALUE"""),0) -> 0 | M45: =IFERROR(__xludf.DUMMYFUNCTION("""COMPUTED_VALUE"""),0) -> 0 | N45: =IFERROR(__xludf.DUMMYFUNCTION("""COMPUTED_VALUE"""),0) -> 0 | P45: =C45+D45+E45+F45+G45+H45 -> 0 | Q45: =I45+J45+K45+L45+M45+N45 -> 0 | R45: =Q45+P45 -> 0
B46: FGTS | C46: -2200.44 | D46: -2155.58 | E46: -2170.46 | F46: -3459.72 | G46: -2507.98 | H46: -2522.35 | I46: =IFERROR(__xludf.DUMMYFUNCTION("""COMPUTED_VALUE"""),-2584.56) -> -2584.56 | J46: =IFERROR(__xludf.DUMMYFUNCTION("""COMPUTED_VALUE"""),-2508.3) -> -2508.3 | P46: =C46+D46+E46+F46+G46+H46 -> -15016.53 | Q46: =I46+J46+K46+L46+M46+N46 -> -5092.86 | R46: =Q46+P46 -> -20109.39
B47: IRRF | C47: 0 | D47: 0 | E47: 0 | F47: 0 | I47: =IFERROR(__xludf.DUMMYFUNCTION("""COMPUTED_VALUE"""),0) -> 0 | J47: =IFERROR(__xludf.DUMMYFUNCTION("""COMPUTED_VALUE"""),0) -> 0 | K47: =IFERROR(__xludf.DUMMYFUNCTION("""COMPUTED_VALUE"""),0) -> 0 | L47: =IFERROR(__xludf.DUMMYFUNCTION("""COMPUTED_VALUE"""),0) -> 0 | M47: =IFERROR(__xludf.DUMMYFUNCTION("""COMPUTED_VALUE"""),0) -> 0 | N47: =IFERROR(__xludf.DUMMYFUNCTION("""COMPUTED_VALUE"""),0) -> 0 | P47: =C47+D47+E47+F47+G47+H47 -> 0 | Q47: =I47+J47+K47+L47+M47+N47 -> 0 | R47: =Q47+P47 -> 0
B48: Assistência Médica | C48: -1530.51 | D48: -1520.51 | E48: -248.89 | F48: -220.87 | G48: -231.76 | I48: =IFERROR(__xludf.DUMMYFUNCTION("""COMPUTED_VALUE"""),-695) -> -695 | J48: =IFERROR(__xludf.DUMMYFUNCTION("""COMPUTED_VALUE"""),-297.94) -> -297.94 | P48: =C48+D48+E48+F48+G48+H48 -> -3752.54 | Q48: =I48+J48+K48+L48+M48+N48 -> -992.94 | R48: =Q48+P48 -> -4745.48
B49: Refeições | C49: -33.8 | D49: 0 | E49: 0 | F49: -18 | G49: -88.9 | H49: -34.9 | I49: =IFERROR(__xludf.DUMMYFUNCTION("""COMPUTED_VALUE"""),-34.9) -> -34.9 | J49: =IFERROR(__xludf.DUMMYFUNCTION("""COMPUTED_VALUE"""),-36) -> -36 | P49: =C49+D49+E49+F49+G49+H49 -> -175.6 | Q49: =I49+J49+K49+L49+M49+N49 -> -70.9 | R49: =Q49+P49 -> -246.5
B50: Vale Refeição | C50: -4791.85 | D50: -4299.2 | E50: -4440.2 | F50: -5485.5 | G50: -5485.5 | H50: -5485.5 | I50: =IFERROR(__xludf.DUMMYFUNCTION("""COMPUTED_VALUE"""),-5485.5) -> -5485.5 | J50: =IFERROR(__xludf.DUMMYFUNCTION("""COMPUTED_VALUE"""),-5158.47) -> -5158.47 | P50: =C50+D50+E50+F50+G50+H50 -> -29987.75 | Q50: =I50+J50+K50+L50+M50+N50 -> -10643.97 | R50: =Q50+P50 -> -40631.72
B51: Vale Transporte / Mobilidade | C51: -487.5 | D51: -345 | E51: -435 | F51: -375 | G51: -375 | H51: -405 | I51: =IFERROR(__xludf.DUMMYFUNCTION("""COMPUTED_VALUE"""),-390) -> -390 | J51: =IFERROR(__xludf.DUMMYFUNCTION("""COMPUTED_VALUE"""),-442.5) -> -442.5 | P51: =C51+D51+E51+F51+G51+H51 -> -2422.5 | Q51: =I51+J51+K51+L51+M51+N51 -> -832.5 | R51: =Q51+P51 -> -3255
B52: Seguro de Vida | C52: 0 | D52: 0 | E52: 0 | F52: 0 | G52: 0 | H52: 0 | I52: =IFERROR(__xludf.DUMMYFUNCTION("""COMPUTED_VALUE"""),0) -> 0 | J52: =IFERROR(__xludf.DUMMYFUNCTION("""COMPUTED_VALUE"""),0) -> 0 | K52: =IFERROR(__xludf.DUMMYFUNCTION("""COMPUTED_VALUE"""),0) -> 0 | L52: =IFERROR(__xludf.DUMMYFUNCTION("""COMPUTED_VALUE"""),0) -> 0 | M52: =IFERROR(__xludf.DUMMYFUNCTION("""COMPUTED_VALUE"""),0) -> 0 | N52: =IFERROR(__xludf.DUMMYFUNCTION("""COMPUTED_VALUE"""),0) -> 0 | P52: =C52+D52+E52+F52+G52+H52 -> 0 | Q52: =I52+J52+K52+L52+M52+N52 -> 0 | R52: =Q52+P52 -> 0
B53: Outros Benefícios | C53: 0 | D53: 0 | E53: 0 | F53: 0 | G53: 0 | H53: 0 | I53: =IFERROR(__xludf.DUMMYFUNCTION("""COMPUTED_VALUE"""),0) -> 0 | J53: =IFERROR(__xludf.DUMMYFUNCTION("""COMPUTED_VALUE"""),0) -> 0 | K53: =IFERROR(__xludf.DUMMYFUNCTION("""COMPUTED_VALUE"""),0) -> 0 | L53: =IFERROR(__xludf.DUMMYFUNCTION("""COMPUTED_VALUE"""),0) -> 0 | M53: =IFERROR(__xludf.DUMMYFUNCTION("""COMPUTED_VALUE"""),0) -> 0 | N53: =IFERROR(__xludf.DUMMYFUNCTION("""COMPUTED_VALUE"""),0) -> 0 | P53: =C53+D53+E53+F53+G53+H53 -> 0 | Q53: =I53+J53+K53+L53+M53+N53 -> 0 | R53: =Q53+P53 -> 0
B54: Benefícios - Geral | C54: 0 | D54: 0 | E54: 0 | F54: 0 | G54: 0 | H54: 0 | I54: =IFERROR(__xludf.DUMMYFUNCTION("""COMPUTED_VALUE"""),0) -> 0 | J54: =IFERROR(__xludf.DUMMYFUNCTION("""COMPUTED_VALUE"""),0) -> 0 | K54: =IFERROR(__xludf.DUMMYFUNCTION("""COMPUTED_VALUE"""),0) -> 0 | L54: =IFERROR(__xludf.DUMMYFUNCTION("""COMPUTED_VALUE"""),0) -> 0 | M54: =IFERROR(__xludf.DUMMYFUNCTION("""COMPUTED_VALUE"""),0) -> 0 | N54: =IFERROR(__xludf.DUMMYFUNCTION("""COMPUTED_VALUE"""),0) -> 0 | P54: =C54+D54+E54+F54+G54+H54 -> 0 | Q54: =I54+J54+K54+L54+M54+N54 -> 0 | R54: =Q54+P54 -> 0
B55: Pró Labore Sócios | C55: 0 | D55: 0 | E55: 0 | F55: 0 | G55: 0 | H55: 0 | I55: =IFERROR(__xludf.DUMMYFUNCTION("""COMPUTED_VALUE"""),-15233.84) -> -15233.84 | J55: =IFERROR(__xludf.DUMMYFUNCTION("""COMPUTED_VALUE"""),-14876.73) -> -14876.73 | P55: =C55+D55+E55+F55+G55+H55 -> 0 | Q55: =I55+J55+K55+L55+M55+N55 -> -30110.57 | R55: =Q55+P55 -> -30110.57
B56: Outros ( Contribuição Sindical - PCMO, Exames...) | C56: -367.99 | D56: -60.49 | E56: -395.49 | F56: -285.49 | G56: -467.89 | H56: -225 | I56: =IFERROR(__xludf.DUMMYFUNCTION("""COMPUTED_VALUE"""),-875.49) -> -875.49 | J56: =IFERROR(__xludf.DUMMYFUNCTION("""COMPUTED_VALUE"""),-450.49) -> -450.49 | P56: =C56+D56+E56+F56+G56+H56 -> -1802.35 | Q56: =I56+J56+K56+L56+M56+N56 -> -1325.98 | R56: =Q56+P56 -> -3128.33
B57: Capacitação e Treinamentos | C57: 0 | D57: 0 | E57: -2590 | F57: 0 | G57: 0 | H57: 0 | I57: =IFERROR(__xludf.DUMMYFUNCTION("""COMPUTED_VALUE"""),-3500) -> -3500 | J57: =IFERROR(__xludf.DUMMYFUNCTION("""COMPUTED_VALUE"""),0) -> 0 | P57: =C57+D57+E57+F57+G57+H57 -> -2590 | Q57: =I57+J57+K57+L57+M57+N57 -> -3500 | R57: =Q57+P57 -> -6090
B58: Endomarketing | C58: 0 | D58: 0 | E58: 0 | F58: -1113.7 | G58: -1113.7 | H58: 0 | I58: =IFERROR(__xludf.DUMMYFUNCTION("""COMPUTED_VALUE"""),-92.78) -> -92.78 | J58: =IFERROR(__xludf.DUMMYFUNCTION("""COMPUTED_VALUE"""),-98.25) -> -98.25 | P58: =C58+D58+E58+F58+G58+H58 -> -2227.4 | Q58: =I58+J58+K58+L58+M58+N58 -> -191.03 | R58: =Q58+P58 -> -2418.43
B59: Bônus | C59: 0 | D59: 0 | E59: 0 | F59: 0 | G59: 0 | H59: 0 | I59: =IFERROR(__xludf.DUMMYFUNCTION("""COMPUTED_VALUE"""),0) -> 0 | J59: =IFERROR(__xludf.DUMMYFUNCTION("""COMPUTED_VALUE"""),0) -> 0 | K59: =IFERROR(__xludf.DUMMYFUNCTION("""COMPUTED_VALUE"""),0) -> 0 | L59: =IFERROR(__xludf.DUMMYFUNCTION("""COMPUTED_VALUE"""),0) -> 0 | M59: =IFERROR(__xludf.DUMMYFUNCTION("""COMPUTED_VALUE"""),0) -> 0 | N59: =IFERROR(__xludf.DUMMYFUNCTION("""COMPUTED_VALUE"""),0) -> 0 | P59: =C59+D59+E59+F59+G59+H59 -> 0 | Q59: =I59+J59+K59+L59+M59+N59 -> 0 | R59: =Q59+P59 -> 0
B60: Despesas Administrativas | C60: =SUM(C61:C77) -> -15591.48 | D60: =SUM(D61:D77) -> -24449.71 | E60: =SUM(E61:E77) -> -14341.55 | F60: =SUM(F61:F77) -> -10993.5 | G60: =SUM(G61:G77) -> -9384.12 | H60: =SUM(H61:H77) -> -10563.94 | I60: =IFERROR(__xludf.DUMMYFUNCTION("""COMPUTED_VALUE"""),-12270.0699999999) -> -12270.07 | J60: =IFERROR(__xludf.DUMMYFUNCTION("""COMPUTED_VALUE"""),-12764.93) -> -12764.93 | K60: =IFERROR(__xludf.DUMMYFUNCTION("""COMPUTED_VALUE"""),0) -> 0 | L60: =IFERROR(__xludf.DUMMYFUNCTION("""COMPUTED_VALUE"""),0) -> 0 | M60: =IFERROR(__xludf.DUMMYFUNCTION("""COMPUTED_VALUE"""),0) -> 0 | N60: =IFERROR(__xludf.DUMMYFUNCTION("""COMPUTED_VALUE"""),0) -> 0 | P60: =C60+D60+E60+F60+G60+H60 -> -85324.3 | Q60: =I60+J60+K60+L60+M60+N60 -> -25035 | R60: =Q60+P60 -> -110359.3
B61: Aluguel | C61: 0 | D61: 0 | E61: 0 | F61: 0 | G61: 0 | H61: 0 | I61: =IFERROR(__xludf.DUMMYFUNCTION("""COMPUTED_VALUE"""),0) -> 0 | J61: =IFERROR(__xludf.DUMMYFUNCTION("""COMPUTED_VALUE"""),0) -> 0 | K61: =IFERROR(__xludf.DUMMYFUNCTION("""COMPUTED_VALUE"""),0) -> 0 | L61: =IFERROR(__xludf.DUMMYFUNCTION("""COMPUTED_VALUE"""),0) -> 0 | M61: =IFERROR(__xludf.DUMMYFUNCTION("""COMPUTED_VALUE"""),0) -> 0 | N61: =IFERROR(__xludf.DUMMYFUNCTION("""COMPUTED_VALUE"""),0) -> 0 | P61: =C61+D61+E61+F61+G61+H61 -> 0 | Q61: =I61+J61+K61+L61+M61+N61 -> 0 | R61: =Q61+P61 -> 0
B62: Condomínio | C62: 0 | D62: 0 | E62: 0 | F62: 0 | G62: 0 | H62: 0 | I62: =IFERROR(__xludf.DUMMYFUNCTION("""COMPUTED_VALUE"""),0) -> 0 | J62: =IFERROR(__xludf.DUMMYFUNCTION("""COMPUTED_VALUE"""),0) -> 0 | K62: =IFERROR(__xludf.DUMMYFUNCTION("""COMPUTED_VALUE"""),0) -> 0 | L62: =IFERROR(__xludf.DUMMYFUNCTION("""COMPUTED_VALUE"""),0) -> 0 | M62: =IFERROR(__xludf.DUMMYFUNCTION("""COMPUTED_VALUE"""),0) -> 0 | N62: =IFERROR(__xludf.DUMMYFUNCTION("""COMPUTED_VALUE"""),0) -> 0 | P62: =C62+D62+E62+F62+G62+H62 -> 0 | Q62: =I62+J62+K62+L62+M62+N62 -> 0 | R62: =Q62+P62 -> 0
B63: Água e Esgoto | C63: 0 | D63: 0 | E63: 0 | F63: 0 | G63: 0 | H63: 0 | I63: =IFERROR(__xludf.DUMMYFUNCTION("""COMPUTED_VALUE"""),0) -> 0 | J63: =IFERROR(__xludf.DUMMYFUNCTION("""COMPUTED_VALUE"""),0) -> 0 | K63: =IFERROR(__xludf.DUMMYFUNCTION("""COMPUTED_VALUE"""),0) -> 0 | L63: =IFERROR(__xludf.DUMMYFUNCTION("""COMPUTED_VALUE"""),0) -> 0 | M63: =IFERROR(__xludf.DUMMYFUNCTION("""COMPUTED_VALUE"""),0) -> 0 | N63: =IFERROR(__xludf.DUMMYFUNCTION("""COMPUTED_VALUE"""),0) -> 0 | P63: =C63+D63+E63+F63+G63+H63 -> 0 | Q63: =I63+J63+K63+L63+M63+N63 -> 0 | R63: =Q63+P63 -> 0
B64: Energia Elétrica | C64: 0 | D64: 0 | E64: 0 | F64: 0 | G64: 0 | H64: 0 | I64: =IFERROR(__xludf.DUMMYFUNCTION("""COMPUTED_VALUE"""),0) -> 0 | J64: =IFERROR(__xludf.DUMMYFUNCTION("""COMPUTED_VALUE"""),0) -> 0 | K64: =IFERROR(__xludf.DUMMYFUNCTION("""COMPUTED_VALUE"""),0) -> 0 | L64: =IFERROR(__xludf.DUMMYFUNCTION("""COMPUTED_VALUE"""),0) -> 0 | M64: =IFERROR(__xludf.DUMMYFUNCTION("""COMPUTED_VALUE"""),0) -> 0 | N64: =IFERROR(__xludf.DUMMYFUNCTION("""COMPUTED_VALUE"""),0) -> 0 | P64: =C64+D64+E64+F64+G64+H64 -> 0 | Q64: =I64+J64+K64+L64+M64+N64 -> 0 | R64: =Q64+P64 -> 0
B65: Telefonia | C65: -449.83 | D65: -459.83 | E65: -391.83 | F65: -540.87 | G65: -405.83 | H65: -435.83 | I65: =IFERROR(__xludf.DUMMYFUNCTION("""COMPUTED_VALUE"""),-455.82) -> -455.82 | J65: =IFERROR(__xludf.DUMMYFUNCTION("""COMPUTED_VALUE"""),-617.58) -> -617.58 | P65: =C65+D65+E65+F65+G65+H65 -> -2684.02 | Q65: =I65+J65+K65+L65+M65+N65 -> -1073.4 | R65: =Q65+P65 -> -3757.42
B66: Manutenção de Imobilizado | C66: -585 | D66: 0 | E66: 0 | F66: 0 | G66: 0 | H66: 0 | I66: =IFERROR(__xludf.DUMMYFUNCTION("""COMPUTED_VALUE"""),0) -> 0 | J66: =IFERROR(__xludf.DUMMYFUNCTION("""COMPUTED_VALUE"""),0) -> 0 | K66: =IFERROR(__xludf.DUMMYFUNCTION("""COMPUTED_VALUE"""),0) -> 0 | L66: =IFERROR(__xludf.DUMMYFUNCTION("""COMPUTED_VALUE"""),0) -> 0 | M66: =IFERROR(__xludf.DUMMYFUNCTION("""COMPUTED_VALUE"""),0) -> 0 | N66: =IFERROR(__xludf.DUMMYFUNCTION("""COMPUTED_VALUE"""),0) -> 0 | P66: =C66+D66+E66+F66+G66+H66 -> -585 | Q66: =I66+J66+K66+L66+M66+N66 -> 0 | R66: =Q66+P66 -> -585
B67: Seguros | C67: 0 | D67: 0 | E67: 0 | F67: 0 | G67: 0 | H67: 0 | I67: =IFERROR(__xludf.DUMMYFUNCTION("""COMPUTED_VALUE"""),0) -> 0 | J67: =IFERROR(__xludf.DUMMYFUNCTION("""COMPUTED_VALUE"""),0) -> 0 | K67: =IFERROR(__xludf.DUMMYFUNCTION("""COMPUTED_VALUE"""),0) -> 0 | L67: =IFERROR(__xludf.DUMMYFUNCTION("""COMPUTED_VALUE"""),0) -> 0 | M67: =IFERROR(__xludf.DUMMYFUNCTION("""COMPUTED_VALUE"""),0) -> 0 | N67: =IFERROR(__xludf.DUMMYFUNCTION("""COMPUTED_VALUE"""),0) -> 0 | P67: =C67+D67+E67+F67+G67+H67 -> 0 | Q67: =I67+J67+K67+L67+M67+N67 -> 0 | R67: =Q67+P67 -> 0
B68: IPTU | C68: 0 | D68: 0 | E68: 0 | F68: 0 | G68: 0 | H68: 0 | I68: =IFERROR(__xludf.DUMMYFUNCTION("""COMPUTED_VALUE"""),0) -> 0 | J68: =IFERROR(__xludf.DUMMYFUNCTION("""COMPUTED_VALUE"""),0) -> 0 | K68: =IFERROR(__xludf.DUMMYFUNCTION("""COMPUTED_VALUE"""),0) -> 0 | L68: =IFERROR(__xludf.DUMMYFUNCTION("""COMPUTED_VALUE"""),0) -> 0 | M68: =IFERROR(__xludf.DUMMYFUNCTION("""COMPUTED_VALUE"""),0) -> 0 | N68: =IFERROR(__xludf.DUMMYFUNCTION("""COMPUTED_VALUE"""),0) -> 0 | P68: =C68+D68+E68+F68+G68+H68 -> 0 | Q68: =I68+J68+K68+L68+M68+N68 -> 0 | R68: =Q68+P68 -> 0
B69: Contabilidade | C69: -887 | D69: -887 | E69: -2437 | F69: -887 | G69: -887 | H69: -2437 | I69: =IFERROR(__xludf.DUMMYFUNCTION("""COMPUTED_VALUE"""),-887) -> -887 | J69: =IFERROR(__xludf.DUMMYFUNCTION("""COMPUTED_VALUE"""),-887) -> -887 | P69: =C69+D69+E69+F69+G69+H69 -> -8422 | Q69: =I69+J69+K69+L69+M69+N69 -> -1774 | R69: =Q69+P69 -> -10196
B70: Assessoria Administrativa | C70: -3908.36 | D70: -3720.63 | E70: -2619.69 | F70: -2619.69 | G70: -2619.69 | H70: -2619.69 | I70: =IFERROR(__xludf.DUMMYFUNCTION("""COMPUTED_VALUE"""),-4642.9) -> -4642.9 | J70: =IFERROR(__xludf.DUMMYFUNCTION("""COMPUTED_VALUE"""),-3541.96) -> -3541.96 | P70: =C70+D70+E70+F70+G70+H70 -> -18107.75 | Q70: =I70+J70+K70+L70+M70+N70 -> -8184.86 | R70: =Q70+P70 -> -26292.61
B71: Advogados | C71: -1621 | D71: -1621 | E71: -1621 | F71: -1621 | G71: -1621 | H71: -1621 | I71: =IFERROR(__xludf.DUMMYFUNCTION("""COMPUTED_VALUE"""),-1621) -> -1621 | J71: =IFERROR(__xludf.DUMMYFUNCTION("""COMPUTED_VALUE"""),-1621) -> -1621 | P71: =C71+D71+E71+F71+G71+H71 -> -9726 | Q71: =I71+J71+K71+L71+M71+N71 -> -3242 | R71: =Q71+P71 -> -12968
B72: Segurança | C72: 0 | D72: 0 | E72: 0 | F72: 0 | G72: 0 | H72: 0 | I72: =IFERROR(__xludf.DUMMYFUNCTION("""COMPUTED_VALUE"""),0) -> 0 | J72: =IFERROR(__xludf.DUMMYFUNCTION("""COMPUTED_VALUE"""),0) -> 0 | K72: =IFERROR(__xludf.DUMMYFUNCTION("""COMPUTED_VALUE"""),0) -> 0 | L72: =IFERROR(__xludf.DUMMYFUNCTION("""COMPUTED_VALUE"""),0) -> 0 | M72: =IFERROR(__xludf.DUMMYFUNCTION("""COMPUTED_VALUE"""),0) -> 0 | N72: =IFERROR(__xludf.DUMMYFUNCTION("""COMPUTED_VALUE"""),0) -> 0 | P72: =C72+D72+E72+F72+G72+H72 -> 0 | Q72: =I72+J72+K72+L72+M72+N72 -> 0 | R72: =Q72+P72 -> 0
B73: Softwares, Sistemas e Servidores | C73: -6412.5 | D73: -15014.82 | E73: -5430.25 | F73: -3562.18 | G73: -1666.47 | H73: -1696.03 | I73: =IFERROR(__xludf.DUMMYFUNCTION("""COMPUTED_VALUE"""),-2418.24) -> -2418.24 | J73: =IFERROR(__xludf.DUMMYFUNCTION("""COMPUTED_VALUE"""),-5483.23) -> -5483.23 | P73: =C73+D73+E73+F73+G73+H73 -> -33782.25 | Q73: =I73+J73+K73+L73+M73+N73 -> -7901.47 | R73: =Q73+P73 -> -41683.72
B74: Fretes e Transportes em Geral | C74: -163.22 | D74: -252.01 | E74: -140.56 | F74: -97.29 | G74: -362.67 | H74: -84.02 | I74: =IFERROR(__xludf.DUMMYFUNCTION("""COMPUTED_VALUE"""),-569.97) -> -569.97 | J74: =IFERROR(__xludf.DUMMYFUNCTION("""COMPUTED_VALUE"""),-313.69) -> -313.69 | P74: =C74+D74+E74+F74+G74+H74 -> -1099.77 | Q74: =I74+J74+K74+L74+M74+N74 -> -883.66 | R74: =Q74+P74 -> -1983.43
B75: Outras Despesas Administrativas | C75: 0 | D75: -816.29 | E75: 0 | F75: 0 | G75: 0 | H75: 0 | I75: =IFERROR(__xludf.DUMMYFUNCTION("""COMPUTED_VALUE"""),0) -> 0 | J75: =IFERROR(__xludf.DUMMYFUNCTION("""COMPUTED_VALUE"""),0) -> 0 | K75: =IFERROR(__xludf.DUMMYFUNCTION("""COMPUTED_VALUE"""),0) -> 0 | L75: =IFERROR(__xludf.DUMMYFUNCTION("""COMPUTED_VALUE"""),0) -> 0 | M75: =IFERROR(__xludf.DUMMYFUNCTION("""COMPUTED_VALUE"""),0) -> 0 | N75: =IFERROR(__xludf.DUMMYFUNCTION("""COMPUTED_VALUE"""),0) -> 0 | P75: =C75+D75+E75+F75+G75+H75 -> -816.29 | Q75: =I75+J75+K75+L75+M75+N75 -> 0 | R75: =Q75+P75 -> -816.29
B76: Associações de classe | C76: -300.47 | D76: -300.47 | E76: -304.96 | F76: -300.47 | G76: -300.47 | H76: -300.47 | I76: =IFERROR(__xludf.DUMMYFUNCTION("""COMPUTED_VALUE"""),-305.24) -> -305.24 | J76: =IFERROR(__xludf.DUMMYFUNCTION("""COMPUTED_VALUE"""),-300.47) -> -300.47 | P76: =C76+D76+E76+F76+G76+H76 -> -1807.31 | Q76: =I76+J76+K76+L76+M76+N76 -> -605.71 | R76: =Q76+P76 -> -2413.02
B77: Material Limpeza / Escritório / Mercado / Padaria | C77: -1264.1 | D77: -1377.66 | E77: -1396.26 | F77: -1365 | G77: -1520.99 | H77: -1369.9 | I77: =IFERROR(__xludf.DUMMYFUNCTION("""COMPUTED_VALUE"""),-1369.9) -> -1369.9 | J77: =IFERROR(__xludf.DUMMYFUNCTION("""COMPUTED_VALUE"""),0) -> 0 | P77: =C77+D77+E77+F77+G77+H77 -> -8293.91 | Q77: =I77+J77+K77+L77+M77+N77 -> -1369.9 | R77: =Q77+P77 -> -9663.81
B78: Despesas Financeiras / Bancos | C78: =SUM(C79:C83) -> -152.76 | D78: =SUM(D79:D83) -> -466.99 | E78: =SUM(E79:E83) -> -83.2 | F78: =SUM(F79:F83) -> -193.69 | G78: =SUM(G79:G83) -> -163.77 | H78: =SUM(H79:H83) -> -162.1 | I78: =IFERROR(__xludf.DUMMYFUNCTION("""COMPUTED_VALUE"""),-135.1) -> -135.1 | J78: =IFERROR(__xludf.DUMMYFUNCTION("""COMPUTED_VALUE"""),-276.86) -> -276.86 | K78: =IFERROR(__xludf.DUMMYFUNCTION("""COMPUTED_VALUE"""),0) -> 0 | L78: =IFERROR(__xludf.DUMMYFUNCTION("""COMPUTED_VALUE"""),0) -> 0 | M78: =IFERROR(__xludf.DUMMYFUNCTION("""COMPUTED_VALUE"""),0) -> 0 | N78: =IFERROR(__xludf.DUMMYFUNCTION("""COMPUTED_VALUE"""),0) -> 0 | P78: =C78+D78+E78+F78+G78+H78 -> -1222.51 | Q78: =I78+J78+K78+L78+M78+N78 -> -411.96 | R78: =Q78+P78 -> -1634.47
B79: Despesa com antecipação de Saldo - 2026 | C79: 0 | D79: 0 | E79: 0 | F79: 0 | G79: 0 | H79: 0 | I79: =IFERROR(__xludf.DUMMYFUNCTION("""COMPUTED_VALUE"""),0) -> 0 | J79: =IFERROR(__xludf.DUMMYFUNCTION("""COMPUTED_VALUE"""),0) -> 0 | K79: =IFERROR(__xludf.DUMMYFUNCTION("""COMPUTED_VALUE"""),0) -> 0 | L79: =IFERROR(__xludf.DUMMYFUNCTION("""COMPUTED_VALUE"""),0) -> 0 | M79: =IFERROR(__xludf.DUMMYFUNCTION("""COMPUTED_VALUE"""),0) -> 0 | N79: =IFERROR(__xludf.DUMMYFUNCTION("""COMPUTED_VALUE"""),0) -> 0 | P79: =C79+D79+E79+F79+G79+H79 -> 0 | Q79: =I79+J79+K79+L79+M79+N79 -> 0 | R79: =Q79+P79 -> 0
B80: Juros sobre Empréstimos | C80: 0 | D80: 0 | E80: 0 | F80: 0 | G80: 0 | H80: 0 | I80: =IFERROR(__xludf.DUMMYFUNCTION("""COMPUTED_VALUE"""),0) -> 0 | J80: =IFERROR(__xludf.DUMMYFUNCTION("""COMPUTED_VALUE"""),0) -> 0 | K80: =IFERROR(__xludf.DUMMYFUNCTION("""COMPUTED_VALUE"""),0) -> 0 | L80: =IFERROR(__xludf.DUMMYFUNCTION("""COMPUTED_VALUE"""),0) -> 0 | M80: =IFERROR(__xludf.DUMMYFUNCTION("""COMPUTED_VALUE"""),0) -> 0 | N80: =IFERROR(__xludf.DUMMYFUNCTION("""COMPUTED_VALUE"""),0) -> 0 | P80: =C80+D80+E80+F80+G80+H80 -> 0 | Q80: =I80+J80+K80+L80+M80+N80 -> 0 | R80: =Q80+P80 -> 0
B81: Multas | C81: 0 | D81: 0 | E81: 0 | F81: 0 | G81: 0 | H81: 0 | I81: =IFERROR(__xludf.DUMMYFUNCTION("""COMPUTED_VALUE"""),0) -> 0 | J81: =IFERROR(__xludf.DUMMYFUNCTION("""COMPUTED_VALUE"""),0) -> 0 | K81: =IFERROR(__xludf.DUMMYFUNCTION("""COMPUTED_VALUE"""),0) -> 0 | L81: =IFERROR(__xludf.DUMMYFUNCTION("""COMPUTED_VALUE"""),0) -> 0 | M81: =IFERROR(__xludf.DUMMYFUNCTION("""COMPUTED_VALUE"""),0) -> 0 | N81: =IFERROR(__xludf.DUMMYFUNCTION("""COMPUTED_VALUE"""),0) -> 0 | P81: =C81+D81+E81+F81+G81+H81 -> 0 | Q81: =I81+J81+K81+L81+M81+N81 -> 0 | R81: =Q81+P81 -> 0
B82: IOF | C82: -1.36 | D82: -329.22 | E82: 0 | F82: -46.92 | G82: -0.72 | H82: -8.09 | I82: =IFERROR(__xludf.DUMMYFUNCTION("""COMPUTED_VALUE"""),-0.17) -> -0.17 | J82: =IFERROR(__xludf.DUMMYFUNCTION("""COMPUTED_VALUE"""),-98.81) -> -98.81 | P82: =C82+D82+E82+F82+G82+H82 -> -386.31 | Q82: =I82+J82+K82+L82+M82+N82 -> -98.98 | R82: =Q82+P82 -> -485.29
B83: Tarifas Bancárias | C83: =-147.73-3.67 -> -151.4 | D83: -137.77 | E83: -83.2 | F83: -146.77 | G83: -163.05 | H83: -154.01 | I83: =IFERROR(__xludf.DUMMYFUNCTION("""COMPUTED_VALUE"""),-134.93) -> -134.93 | J83: =IFERROR(__xludf.DUMMYFUNCTION("""COMPUTED_VALUE"""),-178.05) -> -178.05 | P83: =C83+D83+E83+F83+G83+H83 -> -836.2 | Q83: =I83+J83+K83+L83+M83+N83 -> -312.98 | R83: =Q83+P83 -> -1149.18
B84: Receita Financeira | C84: =SUM(C85:C86) -> 8341.45 | D84: =SUM(D85:D86) -> 2824.67 | E84: =SUM(E85:E86) -> 4494.84 | F84: =SUM(F85:F86) -> 871.29 | G84: =SUM(G85:G86) -> 294.24 | H84: =SUM(H85:H86) -> 31.08 | I84: =IFERROR(__xludf.DUMMYFUNCTION("""COMPUTED_VALUE"""),3673.66) -> 3673.66 | J84: =IFERROR(__xludf.DUMMYFUNCTION("""COMPUTED_VALUE"""),476.16) -> 476.16 | K84: =IFERROR(__xludf.DUMMYFUNCTION("""COMPUTED_VALUE"""),0) -> 0 | L84: =IFERROR(__xludf.DUMMYFUNCTION("""COMPUTED_VALUE"""),0) -> 0 | M84: =IFERROR(__xludf.DUMMYFUNCTION("""COMPUTED_VALUE"""),0) -> 0 | N84: =IFERROR(__xludf.DUMMYFUNCTION("""COMPUTED_VALUE"""),0) -> 0 | P84: =C84+D84+E84+F84+G84+H84 -> 16857.57 | Q84: =I84+J84+K84+L84+M84+N84 -> 4149.82 | R84: =Q84+P84 -> 21007.39
B85: Dividendos Recebidos | C85: 0 | D85: 0 | E85: 0 | F85: 0 | G85: 0 | H85: 0 | I85: =IFERROR(__xludf.DUMMYFUNCTION("""COMPUTED_VALUE"""),0) -> 0 | J85: =IFERROR(__xludf.DUMMYFUNCTION("""COMPUTED_VALUE"""),0) -> 0 | K85: =IFERROR(__xludf.DUMMYFUNCTION("""COMPUTED_VALUE"""),0) -> 0 | L85: =IFERROR(__xludf.DUMMYFUNCTION("""COMPUTED_VALUE"""),0) -> 0 | M85: =IFERROR(__xludf.DUMMYFUNCTION("""COMPUTED_VALUE"""),0) -> 0 | N85: =IFERROR(__xludf.DUMMYFUNCTION("""COMPUTED_VALUE"""),0) -> 0 | P85: =C85+D85+E85+F85+G85+H85 -> 0 | Q85: =I85+J85+K85+L85+M85+N85 -> 0 | R85: =Q85+P85 -> 0
B86: Rendimentos de Aplicações | C86: =7999.26+342.19 -> 8341.45 | D86: =2439.29+ 385.38 -> 2824.67 | E86: =1042.62+ 3452.22 -> 4494.84 | F86: 871.29 | G86: 294.24 | H86: 31.08 | I86: =IFERROR(__xludf.DUMMYFUNCTION("""COMPUTED_VALUE"""),3673.66) -> 3673.66 | J86: =IFERROR(__xludf.DUMMYFUNCTION("""COMPUTED_VALUE"""),476.16) -> 476.16 | P86: =C86+D86+E86+F86+G86+H86 -> 16857.57 | Q86: =I86+J86+K86+L86+M86+N86 -> 4149.82 | R86: =Q86+P86 -> 21007.39
B87: Lucro ou Prejuízo Operacional | C87: =C27+C28+C84 -> 66219.727 | D87: =D27+D28+D84 -> 76294.539 | E87: =E27+E28+E84 -> 110649.46 | F87: =F27+F28+F84 -> 16104.724 | G87: =G27+G28+G84 -> 72804.362 | H87: =H27+H28+H84 -> 91027.293 | I87: =IFERROR(__xludf.DUMMYFUNCTION("""COMPUTED_VALUE"""),56332.9032335999) -> 56332.903 | J87: =IFERROR(__xludf.DUMMYFUNCTION("""COMPUTED_VALUE"""),154695.679076499) -> 154695.68 | K87: =IFERROR(__xludf.DUMMYFUNCTION("""COMPUTED_VALUE"""),0) -> 0 | L87: =IFERROR(__xludf.DUMMYFUNCTION("""COMPUTED_VALUE"""),0) -> 0 | M87: =IFERROR(__xludf.DUMMYFUNCTION("""COMPUTED_VALUE"""),0) -> 0 | N87: =IFERROR(__xludf.DUMMYFUNCTION("""COMPUTED_VALUE"""),0) -> 0 | P87: =C87+D87+E87+F87+G87+H87 -> 433100.11 | Q87: =I87+J87+K87+L87+M87+N87 -> 211028.58 | R87: =Q87+P87 -> 644128.69
B88: Receitas Não Operacionais | C88: 0 | D88: 0 | E88: 0 | F88: 0 | G88: 509.43 | H88: 476.73 | I88: =IFERROR(__xludf.DUMMYFUNCTION("""COMPUTED_VALUE"""),650.72) -> 650.72 | J88: =IFERROR(__xludf.DUMMYFUNCTION("""COMPUTED_VALUE"""),906.01) -> 906.01 | K88: =IFERROR(__xludf.DUMMYFUNCTION("""COMPUTED_VALUE"""),1147.25) -> 1147.25 | L88: =IFERROR(__xludf.DUMMYFUNCTION("""COMPUTED_VALUE"""),0) -> 0 | M88: =IFERROR(__xludf.DUMMYFUNCTION("""COMPUTED_VALUE"""),0) -> 0 | N88: =IFERROR(__xludf.DUMMYFUNCTION("""COMPUTED_VALUE"""),0) -> 0 | P88: =C88+D88+E88+F88+G88+H88 -> 986.16 | Q88: =I88+J88+K88+L88+M88+N88 -> 2703.98 | R88: =Q88+P88 -> 3690.14
B89: Despesas Não Operacionais | C89: 0 | D89: 0 | E89: 0 | F89: 0 | G89: 0 | H89: 0 | I89: =IFERROR(__xludf.DUMMYFUNCTION("""COMPUTED_VALUE"""),0) -> 0 | J89: =IFERROR(__xludf.DUMMYFUNCTION("""COMPUTED_VALUE"""),0) -> 0 | K89: =IFERROR(__xludf.DUMMYFUNCTION("""COMPUTED_VALUE"""),0) -> 0 | L89: =IFERROR(__xludf.DUMMYFUNCTION("""COMPUTED_VALUE"""),0) -> 0 | M89: =IFERROR(__xludf.DUMMYFUNCTION("""COMPUTED_VALUE"""),0) -> 0 | N89: =IFERROR(__xludf.DUMMYFUNCTION("""COMPUTED_VALUE"""),0) -> 0 | P89: =C89+D89+E89+F89+G89+H89 -> 0 | Q89: =I89+J89+K89+L89+M89+N89 -> 0 | R89: =Q89+P89 -> 0
B90: Resultado do Exercicio Antes IR e CS | C90: =SUM(C87:C89) -> 66219.727 | D90: =SUM(D87:D89) -> 76294.539 | E90: =SUM(E87:E89) -> 110649.46 | F90: =SUM(F87:F89) -> 16104.724 | G90: =SUM(G87:G89) -> 73313.792 | H90: =SUM(H87:H89) -> 91504.023 | I90: =IFERROR(__xludf.DUMMYFUNCTION("""COMPUTED_VALUE"""),56983.6232335999) -> 56983.623 | J90: =IFERROR(__xludf.DUMMYFUNCTION("""COMPUTED_VALUE"""),155601.689076499) -> 155601.69 | K90: =IFERROR(__xludf.DUMMYFUNCTION("""COMPUTED_VALUE"""),1147.25) -> 1147.25 | L90: =IFERROR(__xludf.DUMMYFUNCTION("""COMPUTED_VALUE"""),0) -> 0 | M90: =IFERROR(__xludf.DUMMYFUNCTION("""COMPUTED_VALUE"""),0) -> 0 | N90: =IFERROR(__xludf.DUMMYFUNCTION("""COMPUTED_VALUE"""),0) -> 0 | P90: =C90+D90+E90+F90+G90+H90 -> 434086.27 | Q90: =I90+J90+K90+L90+M90+N90 -> 213732.56 | R90: =Q90+P90 -> 647818.83
B91: IRPJ | C91: =-2409.27-64.61 -> -2473.88 | D91: =-709.04-39.53 -> -748.57 | E91: =- 1026.55-53.44 -> -1079.99 | F91: -343.01 | G91: -191.18 | H91: -19.29 | I91: =IFERROR(__xludf.DUMMYFUNCTION("""COMPUTED_VALUE"""),-6.33) -> -6.33 | J91: =IFERROR(__xludf.DUMMYFUNCTION("""COMPUTED_VALUE"""),-8.65) -> -8.65 | K91: =IFERROR(__xludf.DUMMYFUNCTION("""COMPUTED_VALUE"""),0) -> 0 | L91: =IFERROR(__xludf.DUMMYFUNCTION("""COMPUTED_VALUE"""),0) -> 0 | M91: =IFERROR(__xludf.DUMMYFUNCTION("""COMPUTED_VALUE"""),0) -> 0 | N91: =IFERROR(__xludf.DUMMYFUNCTION("""COMPUTED_VALUE"""),0) -> 0 | P91: =C91+D91+E91+F91+G91+H91 -> -4855.92 | Q91: =I91+J91+K91+L91+M91+N91 -> -14.98 | R91: =Q91+P91 -> -4870.9
B92: Contribuição Social | C92: 0 | D92: 0 | E92: 0 | F92: 0 | G92: 0 | H92: 0 | P92: =C92+D92+E92+F92+G92+H92 -> 0 | Q92: =I92+J92+K92+L92+M92+N92 -> 0 | R92: =Q92+P92 -> 0
B93: Resultado Após IR e CS | C93: =SUM(C90:C92) -> 63745.847 | D93: =SUM(D90:D92) -> 75545.969 | E93: =SUM(E90:E92) -> 109569.47 | F93: =SUM(F90:F92) -> 15761.714 | G93: =SUM(G90:G92) -> 73122.612 | H93: =SUM(H90:H92) -> 91484.733 | I93: =IFERROR(__xludf.DUMMYFUNCTION("""COMPUTED_VALUE"""),56977.2932335999) -> 56977.293 | J93: =IFERROR(__xludf.DUMMYFUNCTION("""COMPUTED_VALUE"""),155593.0390765) -> 155593.04 | K93: =IFERROR(__xludf.DUMMYFUNCTION("""COMPUTED_VALUE"""),1147.25) -> 1147.25 | L93: =IFERROR(__xludf.DUMMYFUNCTION("""COMPUTED_VALUE"""),0) -> 0 | M93: =IFERROR(__xludf.DUMMYFUNCTION("""COMPUTED_VALUE"""),0) -> 0 | N93: =IFERROR(__xludf.DUMMYFUNCTION("""COMPUTED_VALUE"""),0) -> 0 | P93: =C93+D93+E93+F93+G93+H93 -> 429230.35 | Q93: =I93+J93+K93+L93+M93+N93 -> 213717.58 | R93: =Q93+P93 -> 642947.93
B94: Participações | C94: 0 | D94: 0 | E94: 0 | F94: 0 | G94: 0 | H94: 0 | I94: =IFERROR(__xludf.DUMMYFUNCTION("""COMPUTED_VALUE"""),0) -> 0 | J94: =IFERROR(__xludf.DUMMYFUNCTION("""COMPUTED_VALUE"""),0) -> 0 | K94: =IFERROR(__xludf.DUMMYFUNCTION("""COMPUTED_VALUE"""),0) -> 0 | L94: =IFERROR(__xludf.DUMMYFUNCTION("""COMPUTED_VALUE"""),0) -> 0 | M94: =IFERROR(__xludf.DUMMYFUNCTION("""COMPUTED_VALUE"""),0) -> 0 | N94: =IFERROR(__xludf.DUMMYFUNCTION("""COMPUTED_VALUE"""),0) -> 0 | P94: =C94+D94+E94+F94+G94+H94 -> 0 | Q94: =I94+J94+K94+L94+M94+N94 -> 0 | R94: =Q94+P94 -> 0
B95: Empregados | C95: -20125 | D95: -750 | E95: 0 | F95: 0 | G95: 0 | H95: 0 | I95: =IFERROR(__xludf.DUMMYFUNCTION("""COMPUTED_VALUE"""),0) -> 0 | J95: =IFERROR(__xludf.DUMMYFUNCTION("""COMPUTED_VALUE"""),-12600) -> -12600 | K95: =IFERROR(__xludf.DUMMYFUNCTION("""COMPUTED_VALUE"""),0) -> 0 | L95: =IFERROR(__xludf.DUMMYFUNCTION("""COMPUTED_VALUE"""),0) -> 0 | M95: =IFERROR(__xludf.DUMMYFUNCTION("""COMPUTED_VALUE"""),0) -> 0 | N95: =IFERROR(__xludf.DUMMYFUNCTION("""COMPUTED_VALUE"""),0) -> 0 | P95: =C95+D95+E95+F95+G95+H95 -> -20875 | Q95: =I95+J95+K95+L95+M95+N95 -> -12600 | R95: =Q95+P95 -> -33475
B96: Administradores | C96: 0 | D96: 0 | E96: 0 | F96: 0 | G96: 0 | H96: 0 | I96: =IFERROR(__xludf.DUMMYFUNCTION("""COMPUTED_VALUE"""),0) -> 0 | J96: =IFERROR(__xludf.DUMMYFUNCTION("""COMPUTED_VALUE"""),0) -> 0 | K96: =IFERROR(__xludf.DUMMYFUNCTION("""COMPUTED_VALUE"""),0) -> 0 | L96: =IFERROR(__xludf.DUMMYFUNCTION("""COMPUTED_VALUE"""),0) -> 0 | M96: =IFERROR(__xludf.DUMMYFUNCTION("""COMPUTED_VALUE"""),0) -> 0 | N96: =IFERROR(__xludf.DUMMYFUNCTION("""COMPUTED_VALUE"""),0) -> 0 | P96: =C96+D96+E96+F96+G96+H96 -> 0 | Q96: =I96+J96+K96+L96+M96+N96 -> 0 | R96: =Q96+P96 -> 0
B97: Lucro Prejuízo do Exercicio | C97: =SUM(C93:C96) -> 43620.847 | D97: =SUM(D93:D96) -> 74795.969 | E97: =SUM(E93:E96) -> 109569.47 | F97: =SUM(F93:F96) -> 15761.714 | G97: =SUM(G93:G96) -> 73122.612 | H97: =SUM(H93:H96) -> 91484.733 | I97: =IFERROR(__xludf.DUMMYFUNCTION("""COMPUTED_VALUE"""),56977.2932335999) -> 56977.293 | J97: =IFERROR(__xludf.DUMMYFUNCTION("""COMPUTED_VALUE"""),142993.0390765) -> 142993.04 | K97: =IFERROR(__xludf.DUMMYFUNCTION("""COMPUTED_VALUE"""),1147.25) -> 1147.25 | L97: =IFERROR(__xludf.DUMMYFUNCTION("""COMPUTED_VALUE"""),0) -> 0 | M97: =IFERROR(__xludf.DUMMYFUNCTION("""COMPUTED_VALUE"""),0) -> 0 | N97: =IFERROR(__xludf.DUMMYFUNCTION("""COMPUTED_VALUE"""),0) -> 0 | P97: =C97+D97+E97+F97+G97+H97 -> 408355.35 | Q97: =I97+J97+K97+L97+M97+N97 -> 201117.58 | R97: =Q97+P97 -> 609472.93
P98: =C98+D98+E98+F98+G98+H98 -> 0 | Q98: =I98+J98+K98+L98+M98+N98 -> 0 | R98: =Q98+P98 -> 0
B99: Investimentos | C99: =C100 -> -384.14 | D99: =D100 -> -384.14 | E99: =E100 -> -913.77 | F99: =F100 -> -1194.46 | G99: =G100 -> -913.72 | H99: =H100 -> -416.82 | I99: =IFERROR(__xludf.DUMMYFUNCTION("""COMPUTED_VALUE"""),-1256.71) -> -1256.71 | J99: =IFERROR(__xludf.DUMMYFUNCTION("""COMPUTED_VALUE"""),-1214.69) -> -1214.69 | P99: =C99+D99+E99+F99+G99+H99 -> -4207.05 | Q99: =I99+J99+K99+L99+M99+N99 -> -2471.4 | R99: =Q99+P99 -> -6678.45
B100: Eletrônicos/Eletrodomésticos | C100: -384.14 | D100: -384.14 | E100: -913.77 | F100: -1194.46 | G100: -913.72 | H100: -416.82 | I100: =IFERROR(__xludf.DUMMYFUNCTION("""COMPUTED_VALUE"""),-1256.71) -> -1256.71 | J100: =IFERROR(__xludf.DUMMYFUNCTION("""COMPUTED_VALUE"""),-1214.69) -> -1214.69 | P100: =C100+D100+E100+F100+G100+H100 -> -4207.05 | Q100: =I100+J100+K100+L100+M100+N100 -> -2471.4 | R100: =Q100+P100 -> -6678.45
B101: Resultado Pós Investimento | C101: =C99+C97 -> 43236.707 | D101: =D99+D97 -> 74411.829 | E101: =E99+E97 -> 108655.7 | F101: =F99+F97 -> 14567.254 | G101: =G99+G97 -> 72208.892 | H101: =H99+H97 -> 91067.913 | I101: =IFERROR(__xludf.DUMMYFUNCTION("""COMPUTED_VALUE"""),55720.5832335999) -> 55720.583 | J101: =IFERROR(__xludf.DUMMYFUNCTION("""COMPUTED_VALUE"""),141778.3490765) -> 141778.35 | K101: =IFERROR(__xludf.DUMMYFUNCTION("""COMPUTED_VALUE"""),1147.25) -> 1147.25 | L101: =IFERROR(__xludf.DUMMYFUNCTION("""COMPUTED_VALUE"""),0) -> 0 | M101: =IFERROR(__xludf.DUMMYFUNCTION("""COMPUTED_VALUE"""),0) -> 0 | N101: =IFERROR(__xludf.DUMMYFUNCTION("""COMPUTED_VALUE"""),0) -> 0 | P101: =C101+D101+E101+F101+G101+H101 -> 404148.3 | Q101: =I101+J101+K101+L101+M101+N101 -> 198646.18 | R101: =Q101+P101 -> 602794.48
...

Sheet ORÇADO X REALIZADO
C4: Demonstrativos Financeiros - 2026 Consolidado | D4: JANEIRO | G4: FEVEREIRO | J4: MARÇO | M4: ABRIL | P4: MAIO | S4: JUNHO | V4: JULHO | Y4: AGOSTO | AB4: SETEMBRO | AE4: OUTUBRO | AH4: NOVEMBRO | AK4: DEZEMBRO | AO4: 1 SEM | AR4: 2 SEM | AU4: 2025
C6: DRE (R$) | D6: Orçado | E6: Realizado | F6: % | G6: Orçado | H6: Realizado | I6: % | J6: Orçado | K6: Realizado | L6: % | M6: Orçado | N6: Realizado | O6: % | P6: Orçado | Q6: Realizado | R6: % | S6: Orçado | T6: Realizado | U6: % | V6: Orçado | W6: Realizado | X6: % | Y6: Orçado | Z6: Realizado | AA6: % | AB6: Orçado | AC6: Realizado | AD6: % | AE6: Orçado | AF6: Realizado | AG6: % | AH6: Orçado | AI6: Realizado | AJ6: % | AK6: Orçado | AL6: Realizado | AM6: % | AO6: Orçado | AP6: Realizado | AQ6: % | AR6: Orçado | AS6: Realizado | AT6: % | AU6: Orçado | AV6: Realizado | AW6: %
C7: Receita Operacional Bruta | D7: =Orçamento!B4 -> 321190.32 | E7: ='DRE 2026'!C4 -> 276257.97 | F7: =IF(D7=0, IF(E7=0, 0, 100%), (E7 - D7) / D7) -> -0.13989321 | G7: =Orçamento!C4 -> 262827.35 | H7: ='DRE 2026'!D4 -> 302537.98 | I7: =IF(G7=0, IF(H7=0, 0, 100%), (H7 - G7) / G7) -> 0.15109017 | J7: =Orçamento!D4 -> 353083.28 | K7: ='DRE 2026'!E4 -> 297990.92 | L7: =IF(J7=0, IF(K7=0, 0, 100%), (K7 - J7) / J7) -> -0.15603219 | M7: =Orçamento!E4 -> 284073.18 | N7: ='DRE 2026'!F4 -> 235626.88 | O7: =IF(M7=0, IF(N7=0, 0, 100%), (N7 - M7) / M7) -> -0.17054163 | P7: =Orçamento!F4 -> 359398.21 | Q7: ='DRE 2026'!G4 -> 242586.46 | R7: =IF(P7=0, IF(Q7=0, 0, 100%), (Q7 - P7) / P7) -> -0.32502041 | S7: =Orçamento!G4 -> 304639.77 | T7: ='DRE 2026'!H4 -> 283604.11 | U7: =IF(S7=0, IF(T7=0, 0, 100%), (T7 - S7) / S7) -> -0.069050937 | V7: =Orçamento!H4 -> 387575.87 | W7: ='DRE 2026'!I4 -> 305701.16 | X7: =IF(V7=0, IF(W7=0, 0, 100%), (W7 - V7) / V7) -> -0.21124821 | Y7: =Orçamento!I4 -> 403534.1 | Z7: ='DRE 2026'!J4 -> 414516.74 | AA7: =IF(Y7=0, IF(Z7=0, 0, 100%), (Z7 - Y7) / Y7) -> 0.027216149 | AB7: =Orçamento!J4 -> 339417.39 | AC7: ='DRE 2026'!K4 -> 0 | AD7: =IF(AB7=0, IF(AC7=0, 0, 100%), (AC7 - AB7) / AB7) -> -1 | AE7: =Orçamento!K4 -> 327122.5 | AF7: ='DRE 2026'!L4 -> 0 | AG7: =IF(AE7=0, IF(AF7=0, 0, 100%), (AF7 - AE7) / AE7) -> -1 | AH7: =Orçamento!L4 -> 383439.94 | AI7: ='DRE 2026'!M4 -> 0 | AJ7: =IF(AH7=0, IF(AI7=0, 0, 100%), (AI7 - AH7) / AH7) -> -1 | AK7: =Orçamento!M4 -> 402871.03 | AL7: ='DRE 2026'!N4 -> 0 | AM7: =IF(AK7=0, IF(AL7=0, 0, 100%), (AL7 - AK7) / AK7) -> -1 | AO7: =IF($H$7=0,D7,IF($K$7=0,D7+G7,IF($N$7=0,D7+G7+J7,IF($Q$7=0,D7+G7+J7+M7,IF($T$7=0,D7+G7+J7+M7+P7,D7+G7+J7+M7+P7+S7))))) -> 1885212.1 | AP7: =IF($H$7=0,E7,IF($K$7=0,E7+H7,IF($N$7=0,E7+H7+K7,IF($Q$7=0,E7+H7+K7+N7,IF($T$7=0,E7+H7+K7+N7+Q7,E7+H7+K7+N7+Q7+T7))))) -> 1638604.3 | AQ7: =IF(AO7=0, IF(AP7=0, 0, 100%), (AP7 - AO7) / AO7) -> -0.13081169 | AR7: =IF($Z$7=0,V7,IF($AC$7=0,V7+Y7,IF($AF$7=0,V7+Y7+AB7,IF($AI$7=0,V7+Y7+AB7+AE7,IF($AL$7=0,V7+Y7+AB7+AE7+AH7,V7+Y7+AB7+AE7+AH7+AK7))))) -> 791109.96 | AS7: =IF($Z$7=0,W7,IF($AC$7=0,W7+Z7,IF($AF$7=0,W7+Z7+AC7,IF($AI$7=0,W7+Z7+AC7+AF7,IF($AL$7=0,W7+Z7+AC7+AF7+AI7,W7+Z7+AC7+AF7+AI7+AL7))))) -> 720217.9 | AT7: =IF(AR7=0, IF(AS7=0, 0, 100%), (AS7 - AR7) / AR7) -> -0.089610885 | AU7: =AR7+AO7 -> 2676322.1 | AV7: =AP7+AS7 -> 2358822.2 | AW7: =IF(AU7=0, IF(AV7=0, 0, 100%), (AV7 - AU7) / AU7) -> -0.1186329
C8: Receita com Taxa de Vendas Online - Formaturas | D8: =Orçamento!B5 -> 146619.93 | E8: ='DRE 2026'!C5 -> 110204.65 | F8: =IF(D8=0, IF(E8=0, 0, 100%), (E8 - D8) / D8) -> -0.24836513 | G8: =Orçamento!C5 -> 85759.094 | H8: ='DRE 2026'!D5 -> 125561.86 | I8: =IF(G8=0, IF(H8=0, 0, 100%), (H8 - G8) / G8) -> 0.46412297 | J8: =Orçamento!D5 -> 130922.08 | K8: ='DRE 2026'!E5 -> 101436.85 | L8: =IF(J8=0, IF(K8=0, 0, 100%), (K8 - J8) / J8) -> -0.22521203 | M8: =Orçamento!E5 -> 89831.148 | N8: ='DRE 2026'!F5 -> 64504.04 | O8: =IF(M8=0, IF(N8=0, 0, 100%), (N8 - M8) / M8) -> -0.28194127 | P8: =Orçamento!F5 -> 106962.46 | Q8: ='DRE 2026'!G5 -> 62018.63 | R8: =IF(P8=0, IF(Q8=0, 0, 100%), (Q8 - P8) / P8) -> -0.42018319 | S8: =Orçamento!G5 -> 89356.023 | T8: ='DRE 2026'!H5 -> 85436.05 | U8: =IF(S8=0, IF(T8=0, 0, 100%), (T8 - S8) / S8) -> -0.043869156 | V8: =Orçamento!H5 -> 123696.26 | W8: ='DRE 2026'!I5 -> 92571.47 | X8: =IF(V8=0, IF(W8=0, 0, 100%), (W8 - V8) / V8) -> -0.25162274 | Y8: =Orçamento!I5 -> 147094.86 | Z8: ='DRE 2026'!J5 -> 146550.37 | AA8: =IF(Y8=0, IF(Z8=0, 0, 100%), (Z8 - Y8) / Y8) -> -0.0037016384 | AB8: =Orçamento!J5 -> 135253.9 | AC8: ='DRE 2026'!K5 -> 0 | AD8: =IF(AB8=0, IF(AC8=0, 0, 100%), (AC8 - AB8) / AB8) -> -1 | AE8: =Orçamento!K5 -> 136690.55 | AF8: ='DRE 2026'!L5 -> 0 | AG8: =IF(AE8=0, IF(AF8=0, 0, 100%), (AF8 - AE8) / AE8) -> -1 | AH8: =Orçamento!L5 -> 183799.02 | AI8: ='DRE 2026'!M5 -> 0 | AJ8: =IF(AH8=0, IF(AI8=0, 0, 100%), (AI8 - AH8) / AH8) -> -1 | AK8: =Orçamento!M5 -> 191838.4 | AL8: ='DRE 2026'!N5 -> 0 | AM8: =IF(AK8=0, IF(AL8=0, 0, 100%), (AL8 - AK8) / AK8) -> -1 | AO8: =IF(H8=0,D8,IF(K8=0,D8+G8,IF(N8=0,D8+G8+J8,IF(Q8=0,D8+G8+J8+M8,IF(T8=0,D8+G8+J8+M8+P8,D8+G8+J8+M8+P8+S8))))) -> 649450.73 | AP8: =IF($H$7=0,E8,IF($K$7=0,E8+H8,IF($N$7=0,E8+H8+K8,IF($Q$7=0,E8+H8+K8+N8,IF($T$7=0,E8+H8+K8+N8+Q8,E8+H8+K8+N8+Q8+T8))))) -> 549162.08 | AQ8: =IF(AO8=0, IF(AP8=0, 0, 100%), (AP8 - AO8) / AO8) -> -0.15442072 | AR8: =IF($Z$7=0,V8,IF($AC$7=0,V8+Y8,IF($AF$7=0,V8+Y8+AB8,IF($AI$7=0,V8+Y8+AB8+AE8,IF($AL$7=0,V8+Y8+AB8+AE8+AH8,V8+Y8+AB8+AE8+AH8+AK8))))) -> 270791.12 | AS8: =IF($Z$7=0,W8,IF($AC$7=0,W8+Z8,IF($AF$7=0,W8+Z8+AC8,IF($AI$7=0,W8+Z8+AC8+AF8,IF($AL$7=0,W8+Z8+AC8+AF8+AI8,W8+Z8+AC8+AF8+AI8+AL8))))) -> 239121.84 | AT8: =IF(AR8=0, IF(AS8=0, 0, 100%), (AS8 - AR8) / AR8) -> -0.11695097 | AU8: =AR8+AO8 -> 920241.85 | AV8: =AP8+AS8 -> 788283.92 | AW8: =IF(AU8=0, IF(AV8=0, 0, 100%), (AV8 - AU8) / AU8) -> -0.14339484
C9: Receita com Taxa de Parcelamento Online - Formaturas | D9: =Orçamento!B6 -> 79122.699 | E9: ='DRE 2026'!C6 -> 80333.42 | F9: =IF(D9=0, IF(E9=0, 0, 100%), (E9 - D9) / D9) -> 0.015301822 | G9: =Orçamento!C6 -> 46049.808 | H9: ='DRE 2026'!D6 -> 81422.18 | I9: =IF(G9=0, IF(H9=0, 0, 100%), (H9 - G9) / G9) -> 0.7681329 | J9: =Orçamento!D6 -> 69637.414 | K9: ='DRE 2026'!E6 -> 72656.14 | L9: =IF(J9=0, IF(K9=0, 0, 100%), (K9 - J9) / J9) -> 0.043349198 | M9: =Orçamento!E6 -> 48000.699 | N9: ='DRE 2026'!F6 -> 39955.32 | O9: =IF(M9=0, IF(N9=0, 0, 100%), (N9 - M9) / M9) -> -0.16760962 | P9: =Orçamento!F6 -> 57057.708 | Q9: ='DRE 2026'!G6 -> 42199.76 | R9: =IF(P9=0, IF(Q9=0, 0, 100%), (Q9 - P9) / P9) -> -0.26040212 | S9: =Orçamento!G6 -> 48289.561 | T9: ='DRE 2026'!H6 -> 57866.42 | U9: =IF(S9=0, IF(T9=0, 0, 100%), (T9 - S9) / S9) -> 0.19832153 | V9: =Orçamento!H6 -> 66487.669 | W9: ='DRE 2026'!I6 -> 66241.41 | X9: =IF(V9=0, IF(W9=0, 0, 100%), (W9 - V9) / V9) -> -0.0037038336 | Y9: =Orçamento!I6 -> 79031.323 | Z9: ='DRE 2026'!J6 -> 100191.14 | AA9: =IF(Y9=0, IF(Z9=0, 0, 100%), (Z9 - Y9) / Y9) -> 0.26773962 | AB9: =Orçamento!J6 -> 72637.338 | AC9: ='DRE 2026'!K6 -> 0 | AD9: =IF(AB9=0, IF(AC9=0, 0, 100%), (AC9 - AB9) / AB9) -> -1 | AE9: =Orçamento!K6 -> 74004.077 | AF9: ='DRE 2026'!L6 -> 0 | AG9: =IF(AE9=0, IF(AF9=0, 0, 100%), (AF9 - AE9) / AE9) -> -1 | AH9: =Orçamento!L6 -> 99292.901 | AI9: ='DRE 2026'!M6 -> 0 | AJ9: =IF(AH9=0, IF(AI9=0, 0, 100%), (AI9 - AH9) / AH9) -> -1 | AK9: =Orçamento!M6 -> 104769.79 | AL9: ='DRE 2026'!N6 -> 0 | AM9: =IF(AK9=0, IF(AL9=0, 0, 100%), (AL9 - AK9) / AK9) -> -1 | AO9: =IF(H9=0,D9,IF(K9=0,D9+G9,IF(N9=0,D9+G9+J9,IF(Q9=0,D9+G9+J9+M9,IF(T9=0,D9+G9+J9+M9+P9,D9+G9+J9+M9+P9+S9))))) -> 348157.89 | AP9: =IF(H9=0,E9,IF(K9=0,E9+H9,IF(N9=0,K9+H9+E9,IF(Q9=0,N9+K9+H9+E9,IF(T9<>0,T9+Q9+N9+K9+H9+E9,Q9+N9+K9+H9+E9))))) -> 374433.24 | AQ9: =IF(AO9=0, IF(AP9=0, 0, 100%), (AP9 - AO9) / AO9) -> 0.075469645 | AR9: =IF($Z$7=0,V9,IF($AC$7=0,V9+Y9,IF($AF$7=0,V9+Y9+AB9,IF($AI$7=0,V9+Y9+AB9+AE9,IF($AL$7=0,V9+Y9+AB9+AE9+AH9,V9+Y9+AB9+AE9+AH9+AK9))))) -> 145518.99 | AS9: =IF($Z$7=0,W9,IF($AC$7=0,W9+Z9,IF($AF$7=0,W9+Z9+AC9,IF($AI$7=0,W9+Z9+AC9+AF9,IF($AL$7=0,W9+Z9+AC9+AF9+AI9,W9+Z9+AC9+AF9+AI9+AL9))))) -> 166432.55 | AT9: =IF(AR9=0, IF(AS9=0, 0, 100%), (AS9 - AR9) / AR9) -> 0.14371703 | AU9: =AR9+AO9 -> 493676.88 | AV9: =AP9+AS9 -> 540865.79 | AW9: =IF(AU9=0, IF(AV9=0, 0, 100%), (AV9 - AU9) / AU9) -> 0.09558663
C10: Receita com Taxa de Vendas Online - Eventos em Geral | D10: =Orçamento!B7 -> 68688.24 | E10: ='DRE 2026'!C7 -> 63839.69 | F10: =IF(D10=0, IF(E10=0, 0, 100%), (E10 - D10) / D10) -> -0.070587775 | G10: =Orçamento!C7 -> 94286.48 | H10: ='DRE 2026'!D7 -> 62635.2 | I10: =IF(G10=0, IF(H10=0, 0, 100%), (H10 - G10) / G10) -> -0.33569267 | J10: =Orçamento!D7 -> 109762.64 | K10: ='DRE 2026'!E7 -> 88391.41 | L10: =IF(J10=0, IF(K10=0, 0, 100%), (K10 - J10) / J10) -> -0.19470405 | M10: =Orçamento!E7 -> 105241.52 | N10: ='DRE 2026'!F7 -> 92904.64 | O10: =IF(M10=0, IF(N10=0, 0, 100%), (N10 - M10) / M10) -> -0.11722446 | P10: =Orçamento!F7 -> 140602.4 | Q10: ='DRE 2026'!G7 -> 101577.49 | R10: =IF(P10=0, IF(Q10=0, 0, 100%), (Q10 - P10) / P10) -> -0.27755508 | S10: =Orçamento!G7 -> 120176.16 | T10: ='DRE 2026'!H7 -> 93967.24 | U10: =IF(S10=0, IF(T10=0, 0, 100%), (T10 - S10) / S10) -> -0.21808751 | V10: =Orçamento!H7 -> 142051.68 | W10: ='DRE 2026'!I7 -> 103254.14 | X10: =IF(V10=0, IF(W10=0, 0, 100%), (W10 - V10) / V10) -> -0.27312271 | Y10: =Orçamento!I7 -> 127670.32 | Z10: ='DRE 2026'!J7 -> 121923.04 | AA10: =IF(Y10=0, IF(Z10=0, 0, 100%), (Z10 - Y10) / Y10) -> -0.045016571 | AB10: =Orçamento!J7 -> 94651.84 | AC10: ='DRE 2026'!K7 -> 0 | AD10: =IF(AB10=0, IF(AC10=0, 0, 100%), (AC10 - AB10) / AB10) -> -1 | AE10: =Orçamento!K7 -> 83786.48 | AF10: ='DRE 2026'!L7 -> 0 | AG10: =IF(AE10=0, IF(AF10=0, 0, 100%), (AF10 - AE10) / AE10) -> -1 | AH10: =Orçamento!L7 -> 72214.72 | AI10: ='DRE 2026'!M7 -> 0 | AJ10: =IF(AH10=0, IF(AI10=0, 0, 100%), (AI10 - AH10) / AH10) -> -1 | AK10: =Orçamento!M7 -> 76471.28 | AL10: ='DRE 2026'!N7 -> 0 | AM10: =IF(AK10=0, IF(AL10=0, 0, 100%), (AL10 - AK10) / AK10) -> -1 | AO10: =IF(H10=0,D10,IF(K10=0,D10+G10,IF(N10=0,D10+G10+J10,IF(Q10=0,D10+G10+J10+M10,IF(T10=0,D10+G10+J10+M10+P10,D10+G10+J10+M10+P10+S10))))) -> 638757.44 | AP10: =IF($H$7=0,E10,IF($K$7=0,E10+H10,IF($N$7=0,E10+H10+K10,IF($Q$7=0,E10+H10+K10+N10,IF($T$7=0,E10+H10+K10+N10+Q10,E10+H10+K10+N10+Q10+T10))))) -> 503315.67 | AQ10: =IF(AO10=0, IF(AP10=0, 0, 100%), (AP10 - AO10) / AO10) -> -0.21203944 | AR10: =IF($Z$7=0,V10,IF($AC$7=0,V10+Y10,IF($AF$7=0,V10+Y10+AB10,IF($AI$7=0,V10+Y10+AB10+AE10,IF($AL$7=0,V10+Y10+AB10+AE10+AH10,V10+Y10+AB10+AE10+AH10+AK10))))) -> 269722 | AS10: =IF($Z$7=0,W10,IF($AC$7=0,W10+Z10,IF($AF$7=0,W10+Z10+AC10,IF($AI$7=0,W10+Z10+AC10+AF10,IF($AL$7=0,W10+Z10+AC10+AF10+AI10,W10+Z10+AC10+AF10+AI10+AL10))))) -> 225177.18 | AT10: =IF(AR10=0, IF(AS10=0, 0, 100%), (AS10 - AR10) / AR10) -> -0.16515086 | AU10: =AR10+AO10 -> 908479.44 | AV10: =AP10+AS10 -> 728492.85 | AW10: =IF(AU10=0, IF(AV10=0, 0, 100%), (AV10 - AU10) / AU10) -> -0.19811851
C11: Receita com Taxa de Parcelamento Online - Eventos em Geral | D11: =Orçamento!B8 -> 14836.66 | E11: ='DRE 2026'!C8 -> 13800.06 | F11: =IF(D11=0, IF(E11=0, 0, 100%), (E11 - D11) / D11) -> -0.069867467 | G11: =Orçamento!C8 -> 20365.88 | H11: ='DRE 2026'!D8 -> 21745.76 | I11: =IF(G11=0, IF(H11=0, 0, 100%), (H11 - G11) / G11) -> 0.067754516 | J11: =Orçamento!D8 -> 23708.73 | K11: ='DRE 2026'!E8 -> 25291.26 | L11: =IF(J11=0, IF(K11=0, 0, 100%), (K11 - J11) / J11) -> 0.06674882 | M11: =Orçamento!E8 -> 22732.168 | N11: ='DRE 2026'!F8 -> 27044.99 | O11: =IF(M11=0, IF(N11=0, 0, 100%), (N11 - M11) / M11) -> 0.18972329 | P11: =Orçamento!F8 -> 30370.118 | Q11: ='DRE 2026'!G8 -> 22268.77 | R11: =IF(P11=0, IF(Q11=0, 0, 100%), (Q11 - P11) / P11) -> -0.26675393 | S11: =Orçamento!G8 -> 25958.051 | T11: ='DRE 2026'!H8 -> 29541.43 | U11: =IF(S11=0, IF(T11=0, 0, 100%), (T11 - S11) / S11) -> 0.13804501 | V11: =Orçamento!H8 -> 30683.163 | W11: ='DRE 2026'!I8 -> 28964.19 | X11: =IF(V11=0, IF(W11=0, 0, 100%), (W11 - V11) / V11) -> -0.056023327 | Y11: =Orçamento!I8 -> 27576.789 | Z11: ='DRE 2026'!J8 -> 31761.79 | AA11: =IF(Y11=0, IF(Z11=0, 0, 100%), (Z11 - Y11) / Y11) -> 0.15175809 | AB11: =Orçamento!J8 -> 20444.797 | AC11: ='DRE 2026'!K8 -> 0 | AD11: =IF(AB11=0, IF(AC11=0, 0, 100%), (AC11 - AB11) / AB11) -> -1 | AE11: =Orçamento!K8 -> 18097.88 | AF11: ='DRE 2026'!L8 -> 0 | AG11: =IF(AE11=0, IF(AF11=0, 0, 100%), (AF11 - AE11) / AE11) -> -1 | AH11: =Orçamento!L8 -> 15598.38 | AI11: ='DRE 2026'!M8 -> 0 | AJ11: =IF(AH11=0, IF(AI11=0, 0, 100%), (AI11 - AH11) / AH11) -> -1 | AK11: =Orçamento!M8 -> 16517.796 | AL11: ='DRE 2026'!N8 -> 0 | AM11: =IF(AK11=0, IF(AL11=0, 0, 100%), (AL11 - AK11) / AK11) -> -1 | AO11: =IF(H11=0,D11,IF(K11=0,D11+G11,IF(N11=0,D11+G11+J11,IF(Q11=0,D11+G11+J11+M11,IF(T11=0,D11+G11+J11+M11+P11,D11+G11+J11+M11+P11+S11))))) -> 137971.61 | AP11: =IF($H$7=0,E11,IF($K$7=0,E11+H11,IF($N$7=0,E11+H11+K11,IF($Q$7=0,E11+H11+K11+N11,IF($T$7=0,E11+H11+K11+N11+Q11,E11+H11+K11+N11+Q11+T11))))) -> 139692.27 | AQ11: =IF(AO11=0, IF(AP11=0, 0, 100%), (AP11 - AO11) / AO11) -> 0.012471138 | AR11: =IF($Z$7=0,V11,IF($AC$7=0,V11+Y11,IF($AF$7=0,V11+Y11+AB11,IF($AI$7=0,V11+Y11+AB11+AE11,IF($AL$7=0,V11+Y11+AB11+AE11+AH11,V11+Y11+AB11+AE11+AH11+AK11))))) -> 58259.952 | AS11: =IF($Z$7=0,W11,IF($AC$7=0,W11+Z11,IF($AF$7=0,W11+Z11+AC11,IF($AI$7=0,W11+Z11+AC11+AF11,IF($AL$7=0,W11+Z11+AC11+AF11+AI11,W11+Z11+AC11+AF11+AI11+AL11))))) -> 60725.98 | AT11: =IF(AR11=0, IF(AS11=0, 0, 100%), (AS11 - AR11) / AR11) -> 0.042328013 | AU11: =AR11+AO11 -> 196231.56 | AV11: =AP11+AS11 -> 200418.25 | AW11: =IF(AU11=0, IF(AV11=0, 0, 100%), (AV11 - AU11) / AU11) -> 0.021335462
C12: Receita com Taxa de Cartão | D12: =Orçamento!B9 -> 0 | E12: ='DRE 2026'!C9 -> 2006 | F12: =IF(D12=0, IF(E12=0, 0, 100%), (E12 - D12) / D12) -> 1 | G12: =Orçamento!C9 -> 0 | H12: ='DRE 2026'!D9 -> 3700 | I12: =IF(G12=0, IF(H12=0, 0, 100%), (H12 - G12) / G12) -> 1 | J12: =Orçamento!D9 -> 0 | K12: ='DRE 2026'!E9 -> 2166 | L12: =IF(J12=0, IF(K12=0, 0, 100%), (K12 - J12) / J12) -> 1 | M12: =Orçamento!E9 -> 0 | N12: ='DRE 2026'!F9 -> 2562 | O12: =IF(M12=0, IF(N12=0, 0, 100%), (N12 - M12) / M12) -> 1 | P12: =Orçamento!F9 -> 0 | Q12: ='DRE 2026'!G9 -> 4442 | R12: =IF(P12=0, IF(Q12=0, 0, 100%), (Q12 - P12) / P12) -> 1 | S12: =Orçamento!G9 -> 0 | T12: ='DRE 2026'!H9 -> 2643 | U12: =IF(S12=0, IF(T12=0, 0, 100%), (T12 - S12) / S12) -> 1 | V12: =Orçamento!H9 -> 0 | W12: ='DRE 2026'!I9 -> 878 | X12: =IF(V12=0, IF(W12=0, 0, 100%), (W12 - V12) / V12) -> 1 | Y12: =Orçamento!I9 -> 0 | Z12: ='DRE 2026'!J9 -> 2504 | AA12: =IF(Y12=0, IF(Z12=0, 0, 100%), (Z12 - Y12) / Y12) -> 1 | AB12: =Orçamento!J9 -> 0 | AC12: ='DRE 2026'!K9 -> 0 | AD12: =IF(AB12=0, IF(AC12=0, 0, 100%), (AC12 - AB12) / AB12) -> 0 | AE12: =Orçamento!K9 -> 0 | AF12: ='DRE 2026'!L9 -> 0 | AG12: =IF(AE12=0, IF(AF12=0, 0, 100%), (AF12 - AE12) / AE12) -> 0 | AH12: =Orçamento!L9 -> 0 | AI12: ='DRE 2026'!M9 -> 0 | AJ12: =IF(AH12=0, IF(AI12=0, 0, 100%), (AI12 - AH12) / AH12) -> 0 | AK12: =Orçamento!M9 -> 0 | AL12: ='DRE 2026'!N9 -> 0 | AM12: =IF(AK12=0, IF(AL12=0, 0, 100%), (AL12 - AK12) / AK12) -> 0 | AO12: =IF(H12=0,D12,IF(K12=0,D12+G12,IF(N12=0,D12+G12+J12,IF(Q12=0,D12+G12+J12+M12,IF(T12=0,D12+G12+J12+M12+P12,D12+G12+J12+M12+P12+S12))))) -> 0 | AP12: =IF($H$7=0,E12,IF($K$7=0,E12+H12,IF($N$7=0,E12+H12+K12,IF($Q$7=0,E12+H12+K12+N12,IF($T$7=0,E12+H12+K12+N12+Q12,E12+H12+K12+N12+Q12+T12))))) -> 17519 | AQ12: =IF(AO12=0, IF(AP12=0, 0, 100%), (AP12 - AO12) / AO12) -> 1 | AR12: =IF($Z$7=0,V12,IF($AC$7=0,V12+Y12,IF($AF$7=0,V12+Y12+AB12,IF($AI$7=0,V12+Y12+AB12+AE12,IF($AL$7=0,V12+Y12+AB12+AE12+AH12,V12+Y12+AB12+AE12+AH12+AK12))))) -> 0 | AS12: =IF($Z$7=0,W12,IF($AC$7=0,W12+Z12,IF($AF$7=0,W12+Z12+AC12,IF($AI$7=0,W12+Z12+AC12+AF12,IF($AL$7=0,W12+Z12+AC12+AF12+AI12,W12+Z12+AC12+AF12+AI12+AL12))))) -> 3382 | AT12: =IF(AR12=0, IF(AS12=0, 0, 100%), (AS12 - AR12) / AR12) -> 1 | AU12: =AR12+AO12 -> 0 | AV12: =AP12+AS12 -> 20901 | AW12: =IF(AU12=0, IF(AV12=0, 0, 100%), (AV12 - AU12) / AU12) -> 1
C13: Receita com Taxa de Administração | D13: =Orçamento!B10 -> 3570.5844 | E13: ='DRE 2026'!C10 -> 1098.25 | F13: =IF(D13=0, IF(E13=0, 0, 100%), (E13 - D13) / D13) -> -0.69241729 | G13: =Orçamento!C10 -> 4901.2441 | H13: ='DRE 2026'!D10 -> 1452 | I13: =IF(G13=0, IF(H13=0, 0, 100%), (H13 - G13) / G13) -> -0.70374869 | J13: =Orçamento!D10 -> 5705.7331 | K13: ='DRE 2026'!E10 -> 1823.7 | L13: =IF(J13=0, IF(K13=0, 0, 100%), (K13 - J13) / J13) -> -0.68037411 | M13: =Orçamento!E10 -> 5470.7141 | N13: ='DRE 2026'!F10 -> 1539.7 | O13: =IF(M13=0, IF(N13=0, 0, 100%), (N13 - M13) / M13) -> -0.71855594 | P13: =Orçamento!F10 -> 7308.86 | Q13: ='DRE 2026'!G10 -> 1894.79 | R13: =IF(P13=0, IF(Q13=0, 0, 100%), (Q13 - P13) / P13) -> -0.74075437 | S13: =Orçamento!G10 -> 6247.0536 | T13: ='DRE 2026'!H10 -> 3814.95 | U13: =IF(S13=0, IF(T13=0, 0, 100%), (T13 - S13) / S13) -> -0.38932011 | V13: =Orçamento!H10 -> 7384.1972 | W13: ='DRE 2026'!I10 -> 1167.6 | X13: =IF(V13=0, IF(W13=0, 0, 100%), (W13 - V13) / V13) -> -0.84187855 | Y13: =Orçamento!I10 -> 6636.6186 | Z13: ='DRE 2026'!J10 -> 2062.4 | AA13: =IF(Y13=0, IF(Z13=0, 0, 100%), (Z13 - Y13) / Y13) -> -0.68923933 | AB13: =Orçamento!J10 -> 4920.2364 | AC13: ='DRE 2026'!K10 -> 0 | AD13: =IF(AB13=0, IF(AC13=0, 0, 100%), (AC13 - AB13) / AB13) -> -1 | AE13: =Orçamento!K10 -> 4355.4282 | AF13: ='DRE 2026'!L10 -> 0 | AG13: =IF(AE13=0, IF(AF13=0, 0, 100%), (AF13 - AE13) / AE13) -> -1 | AH13: =Orçamento!L10 -> 3753.8995 | AI13: ='DRE 2026'!M10 -> 0 | AJ13: =IF(AH13=0, IF(AI13=0, 0, 100%), (AI13 - AH13) / AH13) -> -1 | AK13: =Orçamento!M10 -> 3975.166 | AL13: ='DRE 2026'!N10 -> 0 | AM13: =IF(AK13=0, IF(AL13=0, 0, 100%), (AL13 - AK13) / AK13) -> -1 | AO13: =IF(H13=0,D13,IF(K13=0,D13+G13,IF(N13=0,D13+G13+J13,IF(Q13=0,D13+G13+J13+M13,IF(T13=0,D13+G13+J13+M13+P13,D13+G13+J13+M13+P13+S13))))) -> 33204.189 | AP13: =IF($H$7=0,E13,IF($K$7=0,E13+H13,IF($N$7=0,E13+H13+K13,IF($Q$7=0,E13+H13+K13+N13,IF($T$7=0,E13+H13+K13+N13+Q13,E13+H13+K13+N13+Q13+T13))))) -> 11623.39 | AQ13: =IF(AO13=0, IF(AP13=0, 0, 100%), (AP13 - AO13) / AO13) -> -0.64994206 | AR13: =IF($Z$7=0,V13,IF($AC$7=0,V13+Y13,IF($AF$7=0,V13+Y13+AB13,IF($AI$7=0,V13+Y13+AB13+AE13,IF($AL$7=0,V13+Y13+AB13+AE13+AH13,V13+Y13+AB13+AE13+AH13+AK13))))) -> 14020.816 | AS13: =IF($Z$7=0,W13,IF($AC$7=0,W13+Z13,IF($AF$7=0,W13+Z13+AC13,IF($AI$7=0,W13+Z13+AC13+AF13,IF($AL$7=0,W13+Z13+AC13+AF13+AI13,W13+Z13+AC13+AF13+AI13+AL13))))) -> 3230 | AT13: =IF(AR13=0, IF(AS13=0, 0, 100%), (AS13 - AR13) / AR13) -> -0.76962824 | AU13: =AR13+AO13 -> 47225.005 | AV13: =AP13+AS13 -> 14853.39 | AW13: =IF(AU13=0, IF(AV13=0, 0, 100%), (AV13 - AU13) / AU13) -> -0.68547616
C14: Receita com Taxa de Processamento | D14: =Orçamento!B11 -> 6131.1123 | E14: ='DRE 2026'!C11 -> 4875.9 | F14: =IF(D14=0, IF(E14=0, 0, 100%), (E14 - D14) / D14) -> -0.20472832 | G14: =Orçamento!C11 -> 8416.0112 | H14: ='DRE 2026'!D11 -> 5461.52 | I14: =IF(G14=0, IF(H14=0, 0, 100%), (H14 - G14) / G14) -> -0.351056 | J14: =Orçamento!D11 -> 9797.4132 | K14: ='DRE 2026'!E11 -> 5920.56 | L14: =IF(J14=0, IF(K14=0, 0, 100%), (K14 - J14) / J14) -> -0.39570172 | M14: =Orçamento!E11 -> 9393.8581 | N14: ='DRE 2026'!F11 -> 6831.19 | O14: =IF(M14=0, IF(N14=0, 0, 100%), (N14 - M14) / M14) -> -0.27280251 | P14: =Orçamento!F11 -> 12550.17 | Q14: ='DRE 2026'!G11 -> 7684 | R14: =IF(P14=0, IF(Q14=0, 0, 100%), (Q14 - P14) / P14) -> -0.38773739 | S14: =Orçamento!G11 -> 10726.924 | T14: ='DRE 2026'!H11 -> 10060.02 | U14: =IF(S14=0, IF(T14=0, 0, 100%), (T14 - S14) / S14) -> -0.062171042 | V14: =Orçamento!H11 -> 12679.533 | W14: ='DRE 2026'!I11 -> 11539.62 | X14: =IF(V14=0, IF(W14=0, 0, 100%), (W14 - V14) / V14) -> -0.08990181 | Y14: =Orçamento!I11 -> 11395.853 | Z14: ='DRE 2026'!J11 -> 9314 | AA14: =IF(Y14=0, IF(Z14=0, 0, 100%), (Z14 - Y14) / Y14) -> -0.18268512 | AB14: =Orçamento!J11 -> 8448.6232 | AC14: ='DRE 2026'!K11 -> 0 | AD14: =IF(AB14=0, IF(AC14=0, 0, 100%), (AC14 - AB14) / AB14) -> -1 | AE14: =Orçamento!K11 -> 7478.7812 | AF14: ='DRE 2026'!L11 -> 0 | AG14: =IF(AE14=0, IF(AF14=0, 0, 100%), (AF14 - AE14) / AE14) -> -1 | AH14: =Orçamento!L11 -> 6445.8859 | AI14: ='DRE 2026'!M11 -> 0 | AJ14: =IF(AH14=0, IF(AI14=0, 0, 100%), (AI14 - AH14) / AH14) -> -1 | AK14: =Orçamento!M11 -> 6825.8265 | AL14: ='DRE 2026'!N11 -> 0 | AM14: =IF(AK14=0, IF(AL14=0, 0, 100%), (AL14 - AK14) / AK14) -> -1 | AO14: =IF(H14=0,D14,IF(K14=0,D14+G14,IF(N14=0,D14+G14+J14,IF(Q14=0,D14+G14+J14+M14,IF(T14=0,D14+G14+J14+M14+P14,D14+G14+J14+M14+P14+S14))))) -> 57015.489 | AP14: =IF($H$7=0,E14,IF($K$7=0,E14+H14,IF($N$7=0,E14+H14+K14,IF($Q$7=0,E14+H14+K14+N14,IF($T$7=0,E14+H14+K14+N14+Q14,E14+H14+K14+N14+Q14+T14))))) -> 40833.19 | AQ14: =IF(AO14=0, IF(AP14=0, 0, 100%), (AP14 - AO14) / AO14) -> -0.28382286 | AR14: =IF($Z$7=0,V14,IF($AC$7=0,V14+Y14,IF($AF$7=0,V14+Y14+AB14,IF($AI$7=0,V14+Y14+AB14+AE14,IF($AL$7=0,V14+Y14+AB14+AE14+AH14,V14+Y14+AB14+AE14+AH14+AK14))))) -> 24075.386 | AS14: =IF($Z$7=0,W14,IF($AC$7=0,W14+Z14,IF($AF$7=0,W14+Z14+AC14,IF($AI$7=0,W14+Z14+AC14+AF14,IF($AL$7=0,W14+Z14+AC14+AF14+AI14,W14+Z14+AC14+AF14+AI14+AL14))))) -> 20853.62 | AT14: =IF(AR14=0, IF(AS14=0, 0, 100%), (AS14 - AR14) / AR14) -> -0.1338199 | AU14: =AR14+AO14 -> 81090.875 | AV14: =AP14+AS14 -> 61686.81 | AW14: =IF(AU14=0, IF(AV14=0, 0, 100%), (AV14 - AU14) / AU14) -> -0.2392879
C15: Receita com Taxas de Antecipação | D15: =Orçamento!B12 -> 2221.0935 | E15: ='DRE 2026'!C12 -> 0 | F15: =IF(D15=0, IF(E15=0, 0, 100%), (E15 - D15) / D15) -> -1 | G15: =Orçamento!C12 -> 3048.8346 | H15: ='DRE 2026'!D12 -> 319.46 | I15: =IF(G15=0, IF(H15=0, 0, 100%), (H15 - G15) / G15) -> -0.89521898 | J15: =Orçamento!D12 -> 3549.2696 | K15: ='DRE 2026'!E12 -> 0 | L15: =IF(J15=0, IF(K15=0, 0, 100%), (K15 - J15) / J15) -> -1 | M15: =Orçamento!E12 -> 3403.0753 | N15: ='DRE 2026'!F12 -> 0 | O15: =IF(M15=0, IF(N15=0, 0, 100%), (N15 - M15) / M15) -> -1 | P15: =Orçamento!F12 -> 4546.4998 | Q15: ='DRE 2026'!G12 -> 327.02 | R15: =IF(P15=0, IF(Q15=0, 0, 100%), (Q15 - P15) / P15) -> -0.92807214 | S15: =Orçamento!G12 -> 3885.9997 | T15: ='DRE 2026'!H12 -> 0 | U15: =IF(S15=0, IF(T15=0, 0, 100%), (T15 - S15) / S15) -> -1 | V15: =Orçamento!H12 -> 4593.3635 | W15: ='DRE 2026'!I12 -> 949.73 | X15: =IF(V15=0, IF(W15=0, 0, 100%), (W15 - V15) / V15) -> -0.79323866 | Y15: =Orçamento!I12 -> 4128.3299 | Z15: ='DRE 2026'!J12 -> 0 | AA15: =IF(Y15=0, IF(Z15=0, 0, 100%), (Z15 - Y15) / Y15) -> -1 | AB15: =Orçamento!J12 -> 3060.6489 | AC15: ='DRE 2026'!K12 -> 0 | AD15: =IF(AB15=0, IF(AC15=0, 0, 100%), (AC15 - AB15) / AB15) -> -1 | AE15: =Orçamento!K12 -> 2709.3081 | AF15: ='DRE 2026'!L12 -> 0 | AG15: =IF(AE15=0, IF(AF15=0, 0, 100%), (AF15 - AE15) / AE15) -> -1 | AH15: =Orçamento!L12 -> 2335.1252 | AI15: ='DRE 2026'!M12 -> 0 | AJ15: =IF(AH15=0, IF(AI15=0, 0, 100%), (AI15 - AH15) / AH15) -> -1 | AK15: =Orçamento!M12 -> 2472.7648 | AL15: ='DRE 2026'!N12 -> 0 | AM15: =IF(AK15=0, IF(AL15=0, 0, 100%), (AL15 - AK15) / AK15) -> -1 | AO15: =IF(H15=0,D15,IF(K15=0,D15+G15,IF(N15=0,D15+G15+J15,IF(Q15=0,D15+G15+J15+M15,IF(T15=0,D15+G15+J15+M15+P15,D15+G15+J15+M15+P15+S15))))) -> 5269.9281 | AP15: =IF($H$7=0,E15,IF($K$7=0,E15+H15,IF($N$7=0,E15+H15+K15,IF($Q$7=0,E15+H15+K15+N15,IF($T$7=0,E15+H15+K15+N15+Q15,E15+H15+K15+N15+Q15+T15))))) -> 646.48 | AQ15: =IF(AO15=0, IF(AP15=0, 0, 100%), (AP15 - AO15) / AO15) -> -0.8773266 | AR15: =IF($Z$7=0,V15,IF($AC$7=0,V15+Y15,IF($AF$7=0,V15+Y15+AB15,IF($AI$7=0,V15+Y15+AB15+AE15,IF($AL$7=0,V15+Y15+AB15+AE15+AH15,V15+Y15+AB15+AE15+AH15+AK15))))) -> 8721.6934 | AS15: =IF($Z$7=0,W15,IF($AC$7=0,W15+Z15,IF($AF$7=0,W15+Z15+AC15,IF($AI$7=0,W15+Z15+AC15+AF15,IF($AL$7=0,W15+Z15+AC15+AF15+AI15,W15+Z15+AC15+AF15+AI15+AL15))))) -> 949.73 | AT15: =IF(AR15=0, IF(AS15=0, 0, 100%), (AS15 - AR15) / AR15) -> -0.89110716 | AU15: =AR15+AO15 -> 13991.621 | AV15: =AP15+AS15 -> 1596.21 | AW15: =IF(AU15=0, IF(AV15=0, 0, 100%), (AV15 - AU15) / AU15) -> -0.88591673
C16: Receita com Locação de Equipamentos | D16: =Orçamento!B13 -> 0 | E16: ='DRE 2026'!C13 -> 0 | F16: =IF(D16=0, IF(E16=0, 0, 100%), (E16 - D16) / D16) -> 0 | G16: =Orçamento!C13 -> 0 | H16: ='DRE 2026'!D13 -> 0 | I16: =IF(G16=0, IF(H16=0, 0, 100%), (H16 - G16) / G16) -> 0 | J16: =Orçamento!D13 -> 0 | K16: ='DRE 2026'!E13 -> 0 | L16: =IF(J16=0, IF(K16=0, 0, 100%), (K16 - J16) / J16) -> 0 | M16: =Orçamento!E13 -> 0 | N16: ='DRE 2026'!F13 -> 0 | O16: =IF(M16=0, IF(N16=0, 0, 100%), (N16 - M16) / M16) -> 0 | P16: =Orçamento!F13 -> 0 | Q16: ='DRE 2026'!G13 -> 0 | R16: =IF(P16=0, IF(Q16=0, 0, 100%), (Q16 - P16) / P16) -> 0 | S16: =Orçamento!G13 -> 0 | T16: ='DRE 2026'!H13 -> 0 | U16: =IF(S16=0, IF(T16=0, 0, 100%), (T16 - S16) / S16) -> 0 | V16: =Orçamento!H13 -> 0 | W16: ='DRE 2026'!I13 -> 0 | X16: =IF(V16=0, IF(W16=0, 0, 100%), (W16 - V16) / V16) -> 0 | Y16: =Orçamento!I13 -> 0 | Z16: ='DRE 2026'!J13 -> 0 | AA16: =IF(Y16=0, IF(Z16=0, 0, 100%), (Z16 - Y16) / Y16) -> 0 | AB16: =Orçamento!J13 -> 0 | AC16: ='DRE 2026'!K13 -> 0 | AD16: =IF(AB16=0, IF(AC16=0, 0, 100%), (AC16 - AB16) / AB16) -> 0 | AE16: =Orçamento!K13 -> 0 | AF16: ='DRE 2026'!L13 -> 0 | AG16: =IF(AE16=0, IF(AF16=0, 0, 100%), (AF16 - AE16) / AE16) -> 0 | AH16: =Orçamento!L13 -> 0 | AI16: ='DRE 2026'!M13 -> 0 | AJ16: =IF(AH16=0, IF(AI16=0, 0, 100%), (AI16 - AH16) / AH16) -> 0 | AK16: =Orçamento!M13 -> 0 | AL16: ='DRE 2026'!N13 -> 0 | AM16: =IF(AK16=0, IF(AL16=0, 0, 100%), (AL16 - AK16) / AK16) -> 0 | AO16: =IF(H16=0,D16,IF(K16=0,D16+G16,IF(N16=0,D16+G16+J16,IF(Q16=0,D16+G16+J16+M16,IF(T16=0,D16+G16+J16+M16+P16,D16+G16+J16+M16+P16+S16))))) -> 0 | AP16: =IF($H$7=0,E16,IF($K$7=0,E16+H16,IF($N$7=0,E16+H16+K16,IF($Q$7=0,E16+H16+K16+N16,IF($T$7=0,E16+H16+K16+N16+Q16,E16+H16+K16+N16+Q16+T16))))) -> 0 | AQ16: =IF(AO16=0, IF(AP16=0, 0, 100%), (AP16 - AO16) / AO16) -> 0 | AR16: =IF($Z$7=0,V16,IF($AC$7=0,V16+Y16,IF($AF$7=0,V16+Y16+AB16,IF($AI$7=0,V16+Y16+AB16+AE16,IF($AL$7=0,V16+Y16+AB16+AE16+AH16,V16+Y16+AB16+AE16+AH16+AK16))))) -> 0 | AS16: =IF($Z$7=0,W16,IF($AC$7=0,W16+Z16,IF($AF$7=0,W16+Z16+AC16,IF($AI$7=0,W16+Z16+AC16+AF16,IF($AL$7=0,W16+Z16+AC16+AF16+AI16,W16+Z16+AC16+AF16+AI16+AL16))))) -> 0 | AT16: =IF(AR16=0, IF(AS16=0, 0, 100%), (AS16 - AR16) / AR16) -> 0 | AU16: =AR16+AO16 -> 0 | AV16: =AP16+AS16 -> 0 | AW16: =IF(AU16=0, IF(AV16=0, 0, 100%), (AV16 - AU16) / AU16) -> 0
C17: Receita com Licença de Uso | D17: =Orçamento!B14 -> 0 | E17: ='DRE 2026'!C14 -> 0 | F17: =IF(D17=0, IF(E17=0, 0, 100%), (E17 - D17) / D17) -> 0 | G17: =Orçamento!C14 -> 0 | H17: ='DRE 2026'!D14 -> 0 | I17: =IF(G17=0, IF(H17=0, 0, 100%), (H17 - G17) / G17) -> 0 | J17: =Orçamento!D14 -> 0 | K17: ='DRE 2026'!E14 -> 0 | L17: =IF(J17=0, IF(K17=0, 0, 100%), (K17 - J17) / J17) -> 0 | M17: =Orçamento!E14 -> 0 | N17: ='DRE 2026'!F14 -> 0 | O17: =IF(M17=0, IF(N17=0, 0, 100%), (N17 - M17) / M17) -> 0 | P17: =Orçamento!F14 -> 0 | Q17: ='DRE 2026'!G14 -> 0 | R17: =IF(P17=0, IF(Q17=0, 0, 100%), (Q17 - P17) / P17) -> 0 | S17: =Orçamento!G14 -> 0 | T17: ='DRE 2026'!H14 -> 0 | U17: =IF(S17=0, IF(T17=0, 0, 100%), (T17 - S17) / S17) -> 0 | V17: =Orçamento!H14 -> 0 | W17: ='DRE 2026'!I14 -> 0 | X17: =IF(V17=0, IF(W17=0, 0, 100%), (W17 - V17) / V17) -> 0 | Y17: =Orçamento!I14 -> 0 | Z17: ='DRE 2026'!J14 -> 0 | AA17: =IF(Y17=0, IF(Z17=0, 0, 100%), (Z17 - Y17) / Y17) -> 0 | AB17: =Orçamento!J14 -> 0 | AC17: ='DRE 2026'!K14 -> 0 | AD17: =IF(AB17=0, IF(AC17=0, 0, 100%), (AC17 - AB17) / AB17) -> 0 | AE17: =Orçamento!K14 -> 0 | AF17: ='DRE 2026'!L14 -> 0 | AG17: =IF(AE17=0, IF(AF17=0, 0, 100%), (AF17 - AE17) / AE17) -> 0 | AH17: =Orçamento!L14 -> 0 | AI17: ='DRE 2026'!M14 -> 0 | AJ17: =IF(AH17=0, IF(AI17=0, 0, 100%), (AI17 - AH17) / AH17) -> 0 | AK17: =Orçamento!M14 -> 0 | AL17: ='DRE 2026'!N14 -> 0 | AM17: =IF(AK17=0, IF(AL17=0, 0, 100%), (AL17 - AK17) / AK17) -> 0 | AO17: =IF(H17=0,D17,IF(K17=0,D17+G17,IF(N17=0,D17+G17+J17,IF(Q17=0,D17+G17+J17+M17,IF(T17=0,D17+G17+J17+M17+P17,D17+G17+J17+M17+P17+S17))))) -> 0 | AP17: =IF($H$7=0,E17,IF($K$7=0,E17+H17,IF($N$7=0,E17+H17+K17,IF($Q$7=0,E17+H17+K17+N17,IF($T$7=0,E17+H17+K17+N17+Q17,E17+H17+K17+N17+Q17+T17))))) -> 0 | AQ17: =IF(AO17=0, IF(AP17=0, 0, 100%), (AP17 - AO17) / AO17) -> 0 | AR17: =IF($Z$7=0,V17,IF($AC$7=0,V17+Y17,IF($AF$7=0,V17+Y17+AB17,IF($AI$7=0,V17+Y17+AB17+AE17,IF($AL$7=0,V17+Y17+AB17+AE17+AH17,V17+Y17+AB17+AE17+AH17+AK17))))) -> 0 | AS17: =IF($Z$7=0,W17,IF($AC$7=0,W17+Z17,IF($AF$7=0,W17+Z17+AC17,IF($AI$7=0,W17+Z17+AC17+AF17,IF($AL$7=0,W17+Z17+AC17+AF17+AI17,W17+Z17+AC17+AF17+AI17+AL17))))) -> 0 | AT17: =IF(AR17=0, IF(AS17=0, 0, 100%), (AS17 - AR17) / AR17) -> 0 | AU17: =AR17+AO17 -> 0 | AV17: =AP17+AS17 -> 0 | AW17: =IF(AU17=0, IF(AV17=0, 0, 100%), (AV17 - AU17) / AU17) -> 0
C18: Receita com Vendas de QR Codes | D18: =Orçamento!B15 -> 0 | E18: ='DRE 2026'!C15 -> 100 | F18: =IF(D18=0, IF(E18=0, 0, 100%), (E18 - D18) / D18) -> 1 | G18: =Orçamento!C15 -> 0 | H18: ='DRE 2026'!D15 -> 240 | I18: =IF(G18=0, IF(H18=0, 0, 100%), (H18 - G18) / G18) -> 1 | J18: =Orçamento!D15 -> 0 | K18: ='DRE 2026'!E15 -> 305 | L18: =IF(J18=0, IF(K18=0, 0, 100%), (K18 - J18) / J18) -> 1 | M18: =Orçamento!E15 -> 0 | N18: ='DRE 2026'!F15 -> 285 | O18: =IF(M18=0, IF(N18=0, 0, 100%), (N18 - M18) / M18) -> 1 | P18: =Orçamento!F15 -> 0 | Q18: ='DRE 2026'!G15 -> 174 | R18: =IF(P18=0, IF(Q18=0, 0, 100%), (Q18 - P18) / P18) -> 1 | S18: =Orçamento!G15 -> 0 | T18: ='DRE 2026'!H15 -> 275 | U18: =IF(S18=0, IF(T18=0, 0, 100%), (T18 - S18) / S18) -> 1 | V18: =Orçamento!H15 -> 0 | W18: ='DRE 2026'!I15 -> 135 | X18: =IF(V18=0, IF(W18=0, 0, 100%), (W18 - V18) / V18) -> 1 | Y18: =Orçamento!I15 -> 0 | Z18: ='DRE 2026'!J15 -> 210 | AA18: =IF(Y18=0, IF(Z18=0, 0, 100%), (Z18 - Y18) / Y18) -> 1 | AB18: =Orçamento!J15 -> 0 | AC18: ='DRE 2026'!K15 -> 0 | AD18: =IF(AB18=0, IF(AC18=0, 0, 100%), (AC18 - AB18) / AB18) -> 0 | AE18: =Orçamento!K15 -> 0 | AF18: ='DRE 2026'!L15 -> 0 | AG18: =IF(AE18=0, IF(AF18=0, 0, 100%), (AF18 - AE18) / AE18) -> 0 | AH18: =Orçamento!L15 -> 0 | AI18: ='DRE 2026'!M15 -> 0 | AJ18: =IF(AH18=0, IF(AI18=0, 0, 100%), (AI18 - AH18) / AH18) -> 0 | AK18: =Orçamento!M15 -> 0 | AL18: ='DRE 2026'!N15 -> 0 | AM18: =IF(AK18=0, IF(AL18=0, 0, 100%), (AL18 - AK18) / AK18) -> 0 | AO18: =IF(H18=0,D18,IF(K18=0,D18+G18,IF(N18=0,D18+G18+J18,IF(Q18=0,D18+G18+J18+M18,IF(T18=0,D18+G18+J18+M18+P18,D18+G18+J18+M18+P18+S18))))) -> 0 | AP18: =IF($H$7=0,E18,IF($K$7=0,E18+H18,IF($N$7=0,E18+H18+K18,IF($Q$7=0,E18+H18+K18+N18,IF($T$7=0,E18+H18+K18+N18+Q18,E18+H18+K18+N18+Q18+T18))))) -> 1379 | AQ18: =IF(AO18=0, IF(AP18=0, 0, 100%), (AP18 - AO18) / AO18) -> 1 | AR18: =IF($Z$7=0,V18,IF($AC$7=0,V18+Y18,IF($AF$7=0,V18+Y18+AB18,IF($AI$7=0,V18+Y18+AB18+AE18,IF($AL$7=0,V18+Y18+AB18+AE18+AH18,V18+Y18+AB18+AE18+AH18+AK18))))) -> 0 | AS18: =IF($Z$7=0,W18,IF($AC$7=0,W18+Z18,IF($AF$7=0,W18+Z18+AC18,IF($AI$7=0,W18+Z18+AC18+AF18,IF($AL$7=0,W18+Z18+AC18+AF18+AI18,W18+Z18+AC18+AF18+AI18+AL18))))) -> 345 | AT18: =IF(AR18=0, IF(AS18=0, 0, 100%), (AS18 - AR18) / AR18) -> 1 | AU18: =AR18+AO18 -> 0 | AV18: =AP18+AS18 -> 1724 | AW18: =IF(AU18=0, IF(AV18=0, 0, 100%), (AV18 - AU18) / AU18) -> 1
C19: Deduções de Receita | D19: =Orçamento!B17 -> -39923.952 | E19: ='DRE 2026'!C16 -> -40017.8 | F19: =IF(D19=0, IF(E19=0, 0, 100%), (E19 - D19) / D19) -> 0.0023506687 | G19: =Orçamento!C17 -> -31524.092 | H19: ='DRE 2026'!D16 -> -39398.19 | I19: =IF(G19=0, IF(H19=0, 0, 100%), (H19 - G19) / G19) -> 0.24978033 | J19: =Orçamento!D17 -> -45607.451 | K19: ='DRE 2026'!E16 -> -27355.42 | L19: =IF(J19=0, IF(K19=0, 0, 100%), (K19 - J19) / J19) -> -0.40019844 | M19: =Orçamento!E17 -> -35173.806 | N19: ='DRE 2026'!F16 -> -36236.73 | O19: =IF(M19=0, IF(N19=0, 0, 100%), (N19 - M19) / M19) -> 0.03021919 | P19: =Orçamento!F17 -> -44293.662 | Q19: ='DRE 2026'!G16 -> -28528.1 | R19: =IF(P19=0, IF(Q19=0, 0, 100%), (Q19 - P19) / P19) -> -0.35593268 | S19: =Orçamento!G17 -> -36310.428 | T19: ='DRE 2026'!H16 -> -39028.04 | U19: =IF(S19=0, IF(T19=0, 0, 100%), (T19 - S19) / S19) -> 0.074843832 | V19: =Orçamento!H17 -> -47888.93 | W19: ='DRE 2026'!I16 -> -43587.67 | X19: =IF(V19=0, IF(W19=0, 0, 100%), (W19 - V19) / V19) -> -0.089817426 | Y19: =Orçamento!I17 -> -51482.375 | Z19: ='DRE 2026'!J16 -> -28063.11 | AA19: =IF(Y19=0, IF(Z19=0, 0, 100%), (Z19 - Y19) / Y19) -> -0.45489869 | AB19: =Orçamento!J17 -> -43783.786 | AC19: ='DRE 2026'!K16 -> 0 | AD19: =IF(AB19=0, IF(AC19=0, 0, 100%), (AC19 - AB19) / AB19) -> -1 | AE19: =Orçamento!K17 -> -41555.75 | AF19: ='DRE 2026'!L16 -> 0 | AG19: =IF(AE19=0, IF(AF19=0, 0, 100%), (AF19 - AE19) / AE19) -> -1 | AH19: =Orçamento!L17 -> -51494.002 | AI19: ='DRE 2026'!M16 -> 0 | AJ19: =IF(AH19=0, IF(AI19=0, 0, 100%), (AI19 - AH19) / AH19) -> -1 | AK19: =Orçamento!M17 -> -54327.966 | AL19: ='DRE 2026'!N16 -> 0 | AM19: =IF(AK19=0, IF(AL19=0, 0, 100%), (AL19 - AK19) / AK19) -> -1 | AO19: =IF(H19=0,D19,IF(K19=0,D19+G19,IF(N19=0,D19+G19+J19,IF(Q19=0,D19+G19+J19+M19,IF(T19=0,D19+G19+J19+M19+P19,D19+G19+J19+M19+P19+S19))))) -> -232833.39 | AP19: =IF($H$7=0,E19,IF($K$7=0,E19+H19,IF($N$7=0,E19+H19+K19,IF($Q$7=0,E19+H19+K19+N19,IF($T$7=0,E19+H19+K19+N19+Q19,E19+H19+K19+N19+Q19+T19))))) -> -210564.28 | AQ19: =IF(AO19=0, IF(AP19=0, 0, 100%), (AP19 - AO19) / AO19) -> -0.095643974 | AR19: =IF($Z$7=0,V19,IF($AC$7=0,V19+Y19,IF($AF$7=0,V19+Y19+AB19,IF($AI$7=0,V19+Y19+AB19+AE19,IF($AL$7=0,V19+Y19+AB19+AE19+AH19,V19+Y19+AB19+AE19+AH19+AK19))))) -> -99371.305 | AS19: =IF($Z$7=0,W19,IF($AC$7=0,W19+Z19,IF($AF$7=0,W19+Z19+AC19,IF($AI$7=0,W19+Z19+AC19+AF19,IF($AL$7=0,W19+Z19+AC19+AF19+AI19,W19+Z19+AC19+AF19+AI19+AL19))))) -> -71650.78 | AT19: =IF(AR19=0, IF(AS19=0, 0, 100%), (AS19 - AR19) / AR19) -> -0.27895905 | AU19: =AR19+AO19 -> -332204.7 | AV19: =AP19+AS19 -> -282215.06 | AW19: =IF(AU19=0, IF(AV19=0, 0, 100%), (AV19 - AU19) / AU19) -> -0.15047841
C20: Devoluções de Compra de Serviços (Chargeback) | D20: =Orçamento!B18 -> -3448.952 | E20: ='DRE 2026'!C17 -> -3999.96 | F20: =IF(D20=0, IF(E20=0, 0, 100%), (E20 - D20) / D20) -> 0.15976099 | G20: =Orçamento!C18 -> -2884.0919 | H20: ='DRE 2026'!D17 -> -6683.42 | I20: =IF(G20=0, IF(H20=0, 0, 100%), (H20 - G20) / G20) -> 1.3173395 | J20: =Orçamento!D18 -> -3855.4508 | K20: ='DRE 2026'!E17 -> -3125.48 | L20: =IF(J20=0, IF(K20=0, 0, 100%), (K20 - J20) / J20) -> -0.18933474 | M20: =Orçamento!E18 -> -3124.8061 | N20: ='DRE 2026'!F17 -> -6677 | O20: =IF(M20=0, IF(N20=0, 0, 100%), (N20 - M20) / M20) -> 1.1367726 | P20: =Orçamento!F18 -> -3965.6615 | Q20: ='DRE 2026'!G17 -> -4985.44 | R20: =IF(P20=0, IF(Q20=0, 0, 100%), (Q20 - P20) / P20) -> 0.25715218 | S20: =Orçamento!G18 -> -3356.4284 | T20: ='DRE 2026'!H17 -> -5484.14 | U20: =IF(S20=0, IF(T20=0, 0, 100%), (T20 - S20) / S20) -> 0.63392135 | V20: =Orçamento!H18 -> -4256.9305 | W20: ='DRE 2026'!I17 -> -14612.15 | X20: =IF(V20=0, IF(W20=0, 0, 100%), (W20 - V20) / V20) -> 2.4325555 | Y20: =Orçamento!I18 -> -4401.3747 | Z20: ='DRE 2026'!J17 -> -19866.11 | AA20: =IF(Y20=0, IF(Z20=0, 0, 100%), (Z20 - Y20) / Y20) -> 3.5136148 | AB20: =Orçamento!J18 -> -3682.7858 | AC20: ='DRE 2026'!K17 -> 0 | AD20: =IF(AB20=0, IF(AC20=0, 0, 100%), (AC20 - AB20) / AB20) -> -1 | AE20: =Orçamento!K18 -> -3531.7503 | AF20: ='DRE 2026'!L17 -> 0 | AG20: =IF(AE20=0, IF(AF20=0, 0, 100%), (AF20 - AE20) / AE20) -> -1 | AH20: =Orçamento!L18 -> -4101.0015 | AI20: ='DRE 2026'!M17 -> 0 | AJ20: =IF(AH20=0, IF(AI20=0, 0, 100%), (AI20 - AH20) / AH20) -> -1 | AK20: =Orçamento!M18 -> -4297.9662 | AL20: ='DRE 2026'!N17 -> 0 | AM20: =IF(AK20=0, IF(AL20=0, 0, 100%), (AL20 - AK20) / AK20) -> -1 | AO20: =IF(H20=0,D20,IF(K20=0,D20+G20,IF(N20=0,D20+G20+J20,IF(Q20=0,D20+G20+J20+M20,IF(T20=0,D20+G20+J20+M20+P20,D20+G20+J20+M20+P20+S20))))) -> -20635.391 | AP20: =IF($H$7=0,E20,IF($K$7=0,E20+H20,IF($N$7=0,E20+H20+K20,IF($Q$7=0,E20+H20+K20+N20,IF($T$7=0,E20+H20+K20+N20+Q20,E20+H20+K20+N20+Q20+T20))))) -> -30955.44 | AQ20: =IF(AO20=0, IF(AP20=0, 0, 100%), (AP20 - AO20) / AO20) -> 0.50011407 | AR20: =IF($Z$7=0,V20,IF($AC$7=0,V20+Y20,IF($AF$7=0,V20+Y20+AB20,IF($AI$7=0,V20+Y20+AB20+AE20,IF($AL$7=0,V20+Y20+AB20+AE20+AH20,V20+Y20+AB20+AE20+AH20+AK20))))) -> -8658.3052 | AS20: =IF($Z$7=0,W20,IF($AC$7=0,W20+Z20,IF($AF$7=0,W20+Z20+AC20,IF($AI$7=0,W20+Z20+AC20+AF20,IF($AL$7=0,W20+Z20+AC20+AF20+AI20,W20+Z20+AC20+AF20+AI20+AL20))))) -> -34478.26 | AT20: =IF(AR20=0, IF(AS20=0, 0, 100%), (AS20 - AR20) / AR20) -> 2.9821026 | AU20: =AR20+AO20 -> -29293.696 | AV20: =AP20+AS20 -> -65433.7 | AW20: =IF(AU20=0, IF(AV20=0, 0, 100%), (AV20 - AU20) / AU20) -> 1.2337127
C21: Devoluções de Compra (Estornos) | D21: =Orçamento!B19 -> 0 | E21: ='DRE 2026'!C18 -> -315 | F21: =IF(D21=0, IF(E21=0, 0, 100%), (E21 - D21) / D21) -> 1 | G21: =Orçamento!C19 -> 0 | H21: ='DRE 2026'!D18 -> 0 | I21: =IF(G21=0, IF(H21=0, 0, 100%), (H21 - G21) / G21) -> 0 | J21: =Orçamento!D19 -> 0 | K21: ='DRE 2026'!E18 -> 0 | L21: =IF(J21=0, IF(K21=0, 0, 100%), (K21 - J21) / J21) -> 0 | M21: =Orçamento!E19 -> 0 | N21: ='DRE 2026'!F18 -> 0 | O21: =IF(M21=0, IF(N21=0, 0, 100%), (N21 - M21) / M21) -> 0 | P21: =Orçamento!F19 -> 0 | Q21: ='DRE 2026'!G18 -> -368.6 | R21: =IF(P21=0, IF(Q21=0, 0, 100%), (Q21 - P21) / P21) -> 1 | S21: =Orçamento!G19 -> 0 | T21: ='DRE 2026'!H18 -> 0 | U21: =IF(S21=0, IF(T21=0, 0, 100%), (T21 - S21) / S21) -> 0 | V21: =Orçamento!H19 -> 0 | W21: ='DRE 2026'!I18 -> -380 | X21: =IF(V21=0, IF(W21=0, 0, 100%), (W21 - V21) / V21) -> 1 | Y21: =Orçamento!I19 -> 0 | Z21: ='DRE 2026'!J18 -> 0 | AA21: =IF(Y21=0, IF(Z21=0, 0, 100%), (Z21 - Y21) / Y21) -> 0 | AB21: =Orçamento!J19 -> 0 | AC21: ='DRE 2026'!K18 -> 0 | AD21: =IF(AB21=0, IF(AC21=0, 0, 100%), (AC21 - AB21) / AB21) -> 0 | AE21: =Orçamento!K19 -> 0 | AF21: ='DRE 2026'!L18 -> 0 | AG21: =IF(AE21=0, IF(AF21=0, 0, 100%), (AF21 - AE21) / AE21) -> 0 | AH21: =Orçamento!L19 -> 0 | AI21: ='DRE 2026'!M18 -> 0 | AJ21: =IF(AH21=0, IF(AI21=0, 0, 100%), (AI21 - AH21) / AH21) -> 0 | AK21: =Orçamento!M19 -> 0 | AL21: ='DRE 2026'!N18 -> 0 | AM21: =IF(AK21=0, IF(AL21=0, 0, 100%), (AL21 - AK21) / AK21) -> 0 | AO21: =IF(H21=0,D21,IF(K21=0,D21+G21,IF(N21=0,D21+G21+J21,IF(Q21=0,D21+G21+J21+M21,IF(T21=0,D21+G21+J21+M21+P21,D21+G21+J21+M21+P21+S21))))) -> 0 | AP21: =IF($H$7=0,E21,IF($K$7=0,E21+H21,IF($N$7=0,E21+H21+K21,IF($Q$7=0,E21+H21+K21+N21,IF($T$7=0,E21+H21+K21+N21+Q21,E21+H21+K21+N21+Q21+T21))))) -> -683.6 | AQ21: =IF(AO21=0, IF(AP21=0, 0, 100%), (AP21 - AO21) / AO21) -> 1 | AR21: =IF($Z$7=0,V21,IF($AC$7=0,V21+Y21,IF($AF$7=0,V21+Y21+AB21,IF($AI$7=0,V21+Y21+AB21+AE21,IF($AL$7=0,V21+Y21+AB21+AE21+AH21,V21+Y21+AB21+AE21+AH21+AK21))))) -> 0 | AS21: =IF($Z$7=0,W21,IF($AC$7=0,W21+Z21,IF($AF$7=0,W21+Z21+AC21,IF($AI$7=0,W21+Z21+AC21+AF21,IF($AL$7=0,W21+Z21+AC21+AF21+AI21,W21+Z21+AC21+AF21+AI21+AL21))))) -> -380 | AT21: =IF(AR21=0, IF(AS21=0, 0, 100%), (AS21 - AR21) / AR21) -> 1 | AU21: =AR21+AO21 -> 0 | AV21: =AP21+AS21 -> -1063.6 | AW21: =IF(AU21=0, IF(AV21=0, 0, 100%), (AV21 - AU21) / AU21) -> 1
C22: Simples Nacional (DAS) | D22: =Orçamento!B20 -> -36475 | E22: ='DRE 2026'!C19 -> -35702.84 | F22: =IF(D22=0, IF(E22=0, 0, 100%), (E22 - D22) / D22) -> -0.021169568 | G22: =Orçamento!C20 -> -28640 | H22: ='DRE 2026'!D19 -> -32714.77 | I22: =IF(G22=0, IF(H22=0, 0, 100%), (H22 - G22) / G22) -> 0.14227549 | J22: =Orçamento!D20 -> -41752 | K22: ='DRE 2026'!E19 -> -24229.94 | L22: =IF(J22=0, IF(K22=0, 0, 100%), (K22 - J22) / J22) -> -0.41966996 | M22: =Orçamento!E20 -> -32049 | N22: ='DRE 2026'!F19 -> -29559.73 | O22: =IF(M22=0, IF(N22=0, 0, 100%), (N22 - M22) / M22) -> -0.077670754 | P22: =Orçamento!F20 -> -40328 | Q22: ='DRE 2026'!G19 -> -23174.06 | R22: =IF(P22=0, IF(Q22=0, 0, 100%), (Q22 - P22) / P22) -> -0.42536054 | S22: =Orçamento!G20 -> -32954 | T22: ='DRE 2026'!H19 -> -33543.9 | U22: =IF(S22=0, IF(T22=0, 0, 100%), (T22 - S22) / S22) -> 0.01790071 | V22: =Orçamento!H20 -> -43632 | W22: ='DRE 2026'!I19 -> -28595.52 | X22: =IF(V22=0, IF(W22=0, 0, 100%), (W22 - V22) / V22) -> -0.34462046 | Y22: =Orçamento!I20 -> -47081 | Z22: ='DRE 2026'!J19 -> -8197 | AA22: =IF(Y22=0, IF(Z22=0, 0, 100%), (Z22 - Y22) / Y22) -> -0.8258958 | AB22: =Orçamento!J20 -> -40101 | AC22: ='DRE 2026'!K19 -> 0 | AD22: =IF(AB22=0, IF(AC22=0, 0, 100%), (AC22 - AB22) / AB22) -> -1 | AE22: =Orçamento!K20 -> -38024 | AF22: ='DRE 2026'!L19 -> 0 | AG22: =IF(AE22=0, IF(AF22=0, 0, 100%), (AF22 - AE22) / AE22) -> -1 | AH22: =Orçamento!L20 -> -47393 | AI22: ='DRE 2026'!M19 -> 0 | AJ22: =IF(AH22=0, IF(AI22=0, 0, 100%), (AI22 - AH22) / AH22) -> -1 | AK22: =Orçamento!M20 -> -50030 | AL22: ='DRE 2026'!N19 -> 0 | AM22: =IF(AK22=0, IF(AL22=0, 0, 100%), (AL22 - AK22) / AK22) -> -1 | AO22: =IF(H22=0,D22,IF(K22=0,D22+G22,IF(N22=0,D22+G22+J22,IF(Q22=0,D22+G22+J22+M22,IF(T22=0,D22+G22+J22+M22+P22,D22+G22+J22+M22+P22+S22))))) -> -212198 | AP22: =IF($H$7=0,E22,IF($K$7=0,E22+H22,IF($N$7=0,E22+H22+K22,IF($Q$7=0,E22+H22+K22+N22,IF($T$7=0,E22+H22+K22+N22+Q22,E22+H22+K22+N22+Q22+T22))))) -> -178925.24 | AQ22: =IF(AO22=0, IF(AP22=0, 0, 100%), (AP22 - AO22) / AO22) -> -0.15680054 | AR22: =IF($Z$7=0,V22,IF($AC$7=0,V22+Y22,IF($AF$7=0,V22+Y22+AB22,IF($AI$7=0,V22+Y22+AB22+AE22,IF($AL$7=0,V22+Y22+AB22+AE22+AH22,V22+Y22+AB22+AE22+AH22+AK22))))) -> -90713 | AS22: =IF($Z$7=0,W22,IF($AC$7=0,W22+Z22,IF($AF$7=0,W22+Z22+AC22,IF($AI$7=0,W22+Z22+AC22+AF22,IF($AL$7=0,W22+Z22+AC22+AF22+AI22,W22+Z22+AC22+AF22+AI22+AL22))))) -> -36792.52 | AT22: =IF(AR22=0, IF(AS22=0, 0, 100%), (AS22 - AR22) / AR22) -> -0.59440742 | AU22: =AR22+AO22 -> -302911 | AV22: =AP22+AS22 -> -215717.76 | AW22: =IF(AU22=0, IF(AV22=0, 0, 100%), (AV22 - AU22) / AU22) -> -0.28785102
C23: Receita Operacional Liquida | D23: =Orçamento!B21 -> 281266.36 | E23: ='DRE 2026'!C20 -> 236240.17 | F23: =IF(D23=0, IF(E23=0, 0, 100%), (E23 - D23) / D23) -> -0.16008382 | G23: =Orçamento!C21 -> 231303.26 | H23: ='DRE 2026'!D20 -> 263139.79 | I23: =IF(G23=0, IF(H23=0, 0, 100%), (H23 - G23) / G23) -> 0.13763978 | J23: =Orçamento!D21 -> 307475.83 | K23: ='DRE 2026'!E20 -> 270635.5 | L23: =IF(J23=0, IF(K23=0, 0, 100%), (K23 - J23) / J23) -> -0.11981536 | M23: =Orçamento!E21 -> 248899.38 | N23: ='DRE 2026'!F20 -> 199390.15 | O23: =IF(M23=0, IF(N23=0, 0, 100%), (N23 - M23) / M23) -> -0.19891262 | P23: =Orçamento!F21 -> 315104.55 | Q23: ='DRE 2026'!G20 -> 214058.36 | R23: =IF(P23=0, IF(Q23=0, 0, 100%), (Q23 - P23) / P23) -> -0.32067513 | S23: =Orçamento!G21 -> 268329.34 | T23: ='DRE 2026'!H20 -> 244576.07 | U23: =IF(S23=0, IF(T23=0, 0, 100%), (T23 - S23) / S23) -> -0.088522832 | V23: =Orçamento!H21 -> 339686.94 | W23: ='DRE 2026'!I20 -> 262113.49 | X23: =IF(V23=0, IF(W23=0, 0, 100%), (W23 - V23) / V23) -> -0.22836747 | Y23: =Orçamento!I21 -> 352051.72 | Z23: ='DRE 2026'!J20 -> 386453.63 | AA23: =IF(Y23=0, IF(Z23=0, 0, 100%), (Z23 - Y23) / Y23) -> 0.097718338 | AB23: =Orçamento!J21 -> 295633.6 | AC23: ='DRE 2026'!K20 -> 0 | AD23: =IF(AB23=0, IF(AC23=0, 0, 100%), (AC23 - AB23) / AB23) -> -1 | AE23: =Orçamento!K21 -> 285566.75 | AF23: ='DRE 2026'!L20 -> 0 | AG23: =IF(AE23=0, IF(AF23=0, 0, 100%), (AF23 - AE23) / AE23) -> -1 | AH23: =Orçamento!L21 -> 331945.93 | AI23: ='DRE 2026'!M20 -> 0 | AJ23: =IF(AH23=0, IF(AI23=0, 0, 100%), (AI23 - AH23) / AH23) -> -1 | AK23: =Orçamento!M21 -> 348543.06 | AL23: ='DRE 2026'!N20 -> 0 | AM23: =IF(AK23=0, IF(AL23=0, 0, 100%), (AL23 - AK23) / AK23) -> -1 | AO23: =IF(H23=0,D23,IF(K23=0,D23+G23,IF(N23=0,D23+G23+J23,IF(Q23=0,D23+G23+J23+M23,IF(T23=0,D23+G23+J23+M23+P23,D23+G23+J23+M23+P23+S23))))) -> 1652378.7 | AP23: =IF($H$7=0,E23,IF($K$7=0,E23+H23,IF($N$7=0,E23+H23+K23,IF($Q$7=0,E23+H23+K23+N23,IF($T$7=0,E23+H23+K23+N23+Q23,E23+H23+K23+N23+Q23+T23))))) -> 1428040 | AQ23: =IF(AO23=0, IF(AP23=0, 0, 100%), (AP23 - AO23) / AO23) -> -0.13576711 | AR23: =IF($Z$7=0,V23,IF($AC$7=0,V23+Y23,IF($AF$7=0,V23+Y23+AB23,IF($AI$7=0,V23+Y23+AB23+AE23,IF($AL$7=0,V23+Y23+AB23+AE23+AH23,V23+Y23+AB23+AE23+AH23+AK23))))) -> 691738.66 | AS23: =IF($Z$7=0,W23,IF($AC$7=0,W23+Z23,IF($AF$7=0,W23+Z23+AC23,IF($AI$7=0,W23+Z23+AC23+AF23,IF($AL$7=0,W23+Z23+AC23+AF23+AI23,W23+Z23+AC23+AF23+AI23+AL23))))) -> 648567.12 | AT23: =IF(AR23=0, IF(AS23=0, 0, 100%), (AS23 - AR23) / AR23) -> -0.062410186 | AU23: =AR23+AO23 -> 2344117.4 | AV23: =AP23+AS23 -> 2076607.2 | AW23: =IF(AU23=0, IF(AV23=0, 0, 100%), (AV23 - AU23) / AU23) -> -0.11411981
C24: Custos com os Serviços Prestados | D24: =Orçamento!B22 -> -70839.917 | E24: ='DRE 2026'!C21 -> -65505.12 | F24: =IF(D24=0, IF(E24=0, 0, 100%), (E24 - D24) / D24) -> -0.075307786 | G24: =Orçamento!C22 -> -57149.246 | H24: ='DRE 2026'!D21 -> -73305.13 | I24: =IF(G24=0, IF(H24=0, 0, 100%), (H24 - G24) / G24) -> 0.28269636 | J24: =Orçamento!D22 -> -76453.704 | K24: ='DRE 2026'!E21 -> -69757.14 | L24: =IF(J24=0, IF(K24=0, 0, 100%), (K24 - J24) / J24) -> -0.087589793 | M24: =Orçamento!E22 -> -61540.537 | N24: ='DRE 2026'!F21 -> -56260.37 | O24: =IF(M24=0, IF(N24=0, 0, 100%), (N24 - M24) / M24) -> -0.085799814 | P24: =Orçamento!F22 -> -85128.254 | Q24: ='DRE 2026'!G21 -> -54369.77 | R24: =IF(P24=0, IF(Q24=0, 0, 100%), (Q24 - P24) / P24) -> -0.36131933 | S24: =Orçamento!G22 -> -65493.138 | T24: ='DRE 2026'!H21 -> -73768.21 | U24: =IF(S24=0, IF(T24=0, 0, 100%), (T24 - S24) / S24) -> 0.12635022 | V24: =Orçamento!H22 -> -83107.317 | W24: ='DRE 2026'!I21 -> -76154.49 | X24: =IF(V24=0, IF(W24=0, 0, 100%), (W24 - V24) / V24) -> -0.083660827 | Y24: =Orçamento!I22 -> -87043.691 | Z24: ='DRE 2026'!J21 -> -110740.75 | AA24: =IF(Y24=0, IF(Z24=0, 0, 100%), (Z24 - Y24) / Y24) -> 0.27224326 | AB24: =Orçamento!J22 -> -73754.214 | AC24: ='DRE 2026'!K21 -> 0 | AD24: =IF(AB24=0, IF(AC24=0, 0, 100%), (AC24 - AB24) / AB24) -> -1 | AE24: =Orçamento!K22 -> -71846.791 | AF24: ='DRE 2026'!L21 -> 0 | AG24: =IF(AE24=0, IF(AF24=0, 0, 100%), (AF24 - AE24) / AE24) -> -1 | AH24: =Orçamento!L22 -> -83958.933 | AI24: ='DRE 2026'!M21 -> 0 | AJ24: =IF(AH24=0, IF(AI24=0, 0, 100%), (AI24 - AH24) / AH24) -> -1 | AK24: =Orçamento!M22 -> -88444.443 | AL24: ='DRE 2026'!N21 -> 0 | AM24: =IF(AK24=0, IF(AL24=0, 0, 100%), (AL24 - AK24) / AK24) -> -1 | AO24: =IF(H24=0,D24,IF(K24=0,D24+G24,IF(N24=0,D24+G24+J24,IF(Q24=0,D24+G24+J24+M24,IF(T24=0,D24+G24+J24+M24+P24,D24+G24+J24+M24+P24+S24))))) -> -416604.8 | AP24: =IF($H$7=0,E24,IF($K$7=0,E24+H24,IF($N$7=0,E24+H24+K24,IF($Q$7=0,E24+H24+K24+N24,IF($T$7=0,E24+H24+K24+N24+Q24,E24+H24+K24+N24+Q24+T24))))) -> -392965.74 | AQ24: =IF(AO24=0, IF(AP24=0, 0, 100%), (AP24 - AO24) / AO24) -> -0.05674216 | AR24: =IF($Z$7=0,V24,IF($AC$7=0,V24+Y24,IF($AF$7=0,V24+Y24+AB24,IF($AI$7=0,V24+Y24+AB24+AE24,IF($AL$7=0,V24+Y24+AB24+AE24+AH24,V24+Y24+AB24+AE24+AH24+AK24))))) -> -170151.01 | AS24: =IF($Z$7=0,W24,IF($AC$7=0,W24+Z24,IF($AF$7=0,W24+Z24+AC24,IF($AI$7=0,W24+Z24+AC24+AF24,IF($AL$7=0,W24+Z24+AC24+AF24+AI24,W24+Z24+AC24+AF24+AI24+AL24))))) -> -186895.24 | AT24: =IF(AR24=0, IF(AS24=0, 0, 100%), (AS24 - AR24) / AR24) -> 0.098408067 | AU24: =AR24+AO24 -> -586755.8 | AV24: =AP24+AS24 -> -579860.98 | AW24: =IF(AU24=0, IF(AV24=0, 0, 100%), (AV24 - AU24) / AU24) -> -0.011750756
C25: Compras de Matéria Prima | D25: =Orçamento!B23 -> 0 | E25: ='DRE 2026'!C22 -> 0 | F25: =IF(D25=0, IF(E25=0, 0, 100%), (E25 - D25) / D25) -> 0 | G25: =Orçamento!C23 -> 0 | H25: ='DRE 2026'!D22 -> 0 | I25: =IF(G25=0, IF(H25=0, 0, 100%), (H25 - G25) / G25) -> 0 | J25: =Orçamento!D23 -> 0 | K25: ='DRE 2026'!E22 -> 0 | L25: =IF(J25=0, IF(K25=0, 0, 100%), (K25 - J25) / J25) -> 0 | M25: =Orçamento!E23 -> 0 | N25: ='DRE 2026'!F22 -> 0 | O25: =IF(M25=0, IF(N25=0, 0, 100%), (N25 - M25) / M25) -> 0 | P25: =Orçamento!F23 -> -7867.6736 | Q25: ='DRE 2026'!G22 -> 0 | R25: =IF(P25=0, IF(Q25=0, 0, 100%), (Q25 - P25) / P25) -> -1 | S25: =Orçamento!G23 -> 0 | T25: ='DRE 2026'!H22 -> -3925 | U25: =IF(S25=0, IF(T25=0, 0, 100%), (T25 - S25) / S25) -> 1 | V25: =Orçamento!H23 -> 0 | W25: ='DRE 2026'!I22 -> 0 | X25: =IF(V25=0, IF(W25=0, 0, 100%), (W25 - V25) / V25) -> 0 | Y25: =Orçamento!I23 -> 0 | Z25: ='DRE 2026'!J22 -> -4207.6 | AA25: =IF(Y25=0, IF(Z25=0, 0, 100%), (Z25 - Y25) / Y25) -> 1 | AB25: =Orçamento!J23 -> 0 | AC25: ='DRE 2026'!K22 -> 0 | AD25: =IF(AB25=0, IF(AC25=0, 0, 100%), (AC25 - AB25) / AB25) -> 0 | AE25: =Orçamento!K23 -> 0 | AF25: ='DRE 2026'!L22 -> 0 | AG25: =IF(AE25=0, IF(AF25=0, 0, 100%), (AF25 - AE25) / AE25) -> 0 | AH25: =Orçamento!L23 -> 0 | AI25: ='DRE 2026'!M22 -> 0 | AJ25: =IF(AH25=0, IF(AI25=0, 0, 100%), (AI25 - AH25) / AH25) -> 0 | AK25: =Orçamento!M23 -> 0 | AL25: ='DRE 2026'!N22 -> 0 | AM25: =IF(AK25=0, IF(AL25=0, 0, 100%), (AL25 - AK25) / AK25) -> 0 | AO25: =IF(H25=0,D25,IF(K25=0,D25+G25,IF(N25=0,D25+G25+J25,IF(Q25=0,D25+G25+J25+M25,IF(T25=0,D25+G25+J25+M25+P25,D25+G25+J25+M25+P25+S25))))) -> 0 | AP25: =IF($H$7=0,E25,IF($K$7=0,E25+H25,IF($N$7=0,E25+H25+K25,IF($Q$7=0,E25+H25+K25+N25,IF($T$7=0,E25+H25+K25+N25+Q25,E25+H25+K25+N25+Q25+T25))))) -> -3925 | AQ25: =IF(AO25=0, IF(AP25=0, 0, 100%), (AP25 - AO25) / AO25) -> 1 | AR25: =IF($Z$7=0,V25,IF($AC$7=0,V25+Y25,IF($AF$7=0,V25+Y25+AB25,IF($AI$7=0,V25+Y25+AB25+AE25,IF($AL$7=0,V25+Y25+AB25+AE25+AH25,V25+Y25+AB25+AE25+AH25+AK25))))) -> 0 | AS25: =IF($Z$7=0,W25,IF($AC$7=0,W25+Z25,IF($AF$7=0,W25+Z25+AC25,IF($AI$7=0,W25+Z25+AC25+AF25,IF($AL$7=0,W25+Z25+AC25+AF25+AI25,W25+Z25+AC25+AF25+AI25+AL25))))) -> -4207.6 | AT25: =IF(AR25=0, IF(AS25=0, 0, 100%), (AS25 - AR25) / AR25) -> 1 | AU25: =AR25+AO25 -> 0 | AV25: =AP25+AS25 -> -8132.6 | AW25: =IF(AU25=0, IF(AV25=0, 0, 100%), (AV25 - AU25) / AU25) -> 1
C26: Custo com Gateway de Pagamento | D26: =Orçamento!B24 -> -45591.895 | E26: ='DRE 2026'!C23 -> -43699.12 | F26: =IF(D26=0, IF(E26=0, 0, 100%), (E26 - D26) / D26) -> -0.041515595 | G26: =Orçamento!C24 -> -34987.527 | H26: ='DRE 2026'!D23 -> -50149.13 | I26: =IF(G26=0, IF(H26=0, 0, 100%), (H26 - G26) / G26) -> 0.4333431 | J26: =Orçamento!D24 -> -48041.167 | K26: ='DRE 2026'!E23 -> -45278.14 | L26: =IF(J26=0, IF(K26=0, 0, 100%), (K26 - J26) / J26) -> -0.057513727 | M26: =Orçamento!E24 -> -37602.232 | N26: ='DRE 2026'!F23 -> -32563.37 | O26: =IF(M26=0, IF(N26=0, 0, 100%), (N26 - M26) / M26) -> -0.13400433 | P26: =Orçamento!F24 -> -46989.035 | Q26: ='DRE 2026'!G23 -> -32399.77 | R26: =IF(P26=0, IF(Q26=0, 0, 100%), (Q26 - P26) / P26) -> -0.31048232 | S26: =Orçamento!G24 -> -39735.515 | T26: ='DRE 2026'!H23 -> -46697.21 | U26: =IF(S26=0, IF(T26=0, 0, 100%), (T26 - S26) / S26) -> 0.17520081 | V26: =Orçamento!H24 -> -51181.231 | W26: ='DRE 2026'!I23 -> -50637.49 | X26: =IF(V26=0, IF(W26=0, 0, 100%), (W26 - V26) / V26) -> -0.010623829 | Y26: =Orçamento!I24 -> -54575.415 | Z26: ='DRE 2026'!J23 -> -77538.64 | AA26: =IF(Y26=0, IF(Z26=0, 0, 100%), (Z26 - Y26) / Y26) -> 0.42076134 | AB26: =Orçamento!J24 -> -46797.344 | AC26: ='DRE 2026'!K23 -> 0 | AD26: =IF(AB26=0, IF(AC26=0, 0, 100%), (AC26 - AB26) / AB26) -> -1 | AE26: =Orçamento!K24 -> -45504.426 | AF26: ='DRE 2026'!L23 -> 0 | AG26: =IF(AE26=0, IF(AF26=0, 0, 100%), (AF26 - AE26) / AE26) -> -1 | AH26: =Orçamento!L24 -> -54952.191 | AI26: ='DRE 2026'!M23 -> 0 | AJ26: =IF(AH26=0, IF(AI26=0, 0, 100%), (AI26 - AH26) / AH26) -> -1 | AK26: =Orçamento!M24 -> -57501.692 | AL26: ='DRE 2026'!N23 -> 0 | AM26: =IF(AK26=0, IF(AL26=0, 0, 100%), (AL26 - AK26) / AK26) -> -1 | AO26: =IF(H26=0,D26,IF(K26=0,D26+G26,IF(N26=0,D26+G26+J26,IF(Q26=0,D26+G26+J26+M26,IF(T26=0,D26+G26+J26+M26+P26,D26+G26+J26+M26+P26+S26))))) -> -252947.37 | AP26: =IF($H$7=0,E26,IF($K$7=0,E26+H26,IF($N$7=0,E26+H26+K26,IF($Q$7=0,E26+H26+K26+N26,IF($T$7=0,E26+H26+K26+N26+Q26,E26+H26+K26+N26+Q26+T26))))) -> -250786.74 | AQ26: =IF(AO26=0, IF(AP26=0, 0, 100%), (AP26 - AO26) / AO26) -> -0.0085418152 | AR26: =IF($Z$7=0,V26,IF($AC$7=0,V26+Y26,IF($AF$7=0,V26+Y26+AB26,IF($AI$7=0,V26+Y26+AB26+AE26,IF($AL$7=0,V26+Y26+AB26+AE26+AH26,V26+Y26+AB26+AE26+AH26+AK26))))) -> -105756.65 | AS26: =IF($Z$7=0,W26,IF($AC$7=0,W26+Z26,IF($AF$7=0,W26+Z26+AC26,IF($AI$7=0,W26+Z26+AC26+AF26,IF($AL$7=0,W26+Z26+AC26+AF26+AI26,W26+Z26+AC26+AF26+AI26+AL26))))) -> -128176.13 | AT26: =IF(AR26=0, IF(AS26=0, 0, 100%), (AS26 - AR26) / AR26) -> 0.21199126 | AU26: =AR26+AO26 -> -358704.02 | AV26: =AP26+AS26 -> -378962.87 | AW26: =IF(AU26=0, IF(AV26=0, 0, 100%), (AV26 - AU26) / AU26) -> 0.056477914
C27: Serviço de Mão de Obra Eventos / Suporte | D27: =Orçamento!B25 -> -2000 | E27: ='DRE 2026'!C24 -> -2300 | F27: =IF(D27=0, IF(E27=0, 0, 100%), (E27 - D27) / D27) -> 0.15 | G27: =Orçamento!C25 -> -1800 | H27: ='DRE 2026'!D24 -> -2150 | I27: =IF(G27=0, IF(H27=0, 0, 100%), (H27 - G27) / G27) -> 0.19444444 | J27: =Orçamento!D25 -> -1600 | K27: ='DRE 2026'!E24 -> -2600 | L27: =IF(J27=0, IF(K27=0, 0, 100%), (K27 - J27) / J27) -> 0.625 | M27: =Orçamento!E25 -> -1800 | N27: ='DRE 2026'!F24 -> -4800 | O27: =IF(M27=0, IF(N27=0, 0, 100%), (N27 - M27) / M27) -> 1.6666667 | P27: =Orçamento!F25 -> -2000 | Q27: ='DRE 2026'!G24 -> -1800 | R27: =IF(P27=0, IF(Q27=0, 0, 100%), (Q27 - P27) / P27) -> -0.1 | S27: =Orçamento!G25 -> -1800 | T27: ='DRE 2026'!H24 -> -1800 | U27: =IF(S27=0, IF(T27=0, 0, 100%), (T27 - S27) / S27) -> 0 | V27: =Orçamento!H25 -> -1800 | W27: ='DRE 2026'!I24 -> -1750 | X27: =IF(V27=0, IF(W27=0, 0, 100%), (W27 - V27) / V27) -> -0.027777778 | Y27: =Orçamento!I25 -> -1800 | Z27: ='DRE 2026'!J24 -> -3600 | AA27: =IF(Y27=0, IF(Z27=0, 0, 100%), (Z27 - Y27) / Y27) -> 1 | AB27: =Orçamento!J25 -> -1600 | AC27: ='DRE 2026'!K24 -> 0 | AD27: =IF(AB27=0, IF(AC27=0, 0, 100%), (AC27 - AB27) / AB27) -> -1 | AE27: =Orçamento!K25 -> -2200 | AF27: ='DRE 2026'!L24 -> 0 | AG27: =IF(AE27=0, IF(AF27=0, 0, 100%), (AF27 - AE27) / AE27) -> -1 | AH27: =Orçamento!L25 -> -1600 | AI27: ='DRE 2026'!M24 -> 0 | AJ27: =IF(AH27=0, IF(AI27=0, 0, 100%), (AI27 - AH27) / AH27) -> -1 | AK27: =Orçamento!M25 -> -2200 | AL27: ='DRE 2026'!N24 -> 0 | AM27: =IF(AK27=0, IF(AL27=0, 0, 100%), (AL27 - AK27) / AK27) -> -1 | AO27: =IF(H27=0,D27,IF(K27=0,D27+G27,IF(N27=0,D27+G27+J27,IF(Q27=0,D27+G27+J27+M27,IF(T27=0,D27+G27+J27+M27+P27,D27+G27+J27+M27+P27+S27))))) -> -11000 | AP27: =IF($H$7=0,E27,IF($K$7=0,E27+H27,IF($N$7=0,E27+H27+K27,IF($Q$7=0,E27+H27+K27+N27,IF($T$7=0,E27+H27+K27+N27+Q27,E27+H27+K27+N27+Q27+T27))))) -> -15450 | AQ27: =IF(AO27=0, IF(AP27=0, 0, 100%), (AP27 - AO27) / AO27) -> 0.40454545 | AR27: =IF($Z$7=0,V27,IF($AC$7=0,V27+Y27,IF($AF$7=0,V27+Y27+AB27,IF($AI$7=0,V27+Y27+AB27+AE27,IF($AL$7=0,V27+Y27+AB27+AE27+AH27,V27+Y27+AB27+AE27+AH27+AK27))))) -> -3600 | AS27: =IF($Z$7=0,W27,IF($AC$7=0,W27+Z27,IF($AF$7=0,W27+Z27+AC27,IF($AI$7=0,W27+Z27+AC27+AF27,IF($AL$7=0,W27+Z27+AC27+AF27+AI27,W27+Z27+AC27+AF27+AI27+AL27))))) -> -5350 | AT27: =IF(AR27=0, IF(AS27=0, 0, 100%), (AS27 - AR27) / AR27) -> 0.48611111 | AU27: =AR27+AO27 -> -14600 | AV27: =AP27+AS27 -> -20800 | AW27: =IF(AU27=0, IF(AV27=0, 0, 100%), (AV27 - AU27) / AU27) -> 0.42465753
C28: Royalties | D28: =Orçamento!B26 -> -23248.023 | E28: ='DRE 2026'!C25 -> -19506 | F28: =IF(D28=0, IF(E28=0, 0, 100%), (E28 - D28) / D28) -> -0.1609609 | G28: =Orçamento!C26 -> -20361.719 | H28: ='DRE 2026'!D25 -> -21006 | I28: =IF(G28=0, IF(H28=0, 0, 100%), (H28 - G28) / G28) -> 0.031641756 | J28: =Orçamento!D26 -> -26812.538 | K28: ='DRE 2026'!E25 -> -21879 | L28: =IF(J28=0, IF(K28=0, 0, 100%), (K28 - J28) / J28) -> -0.18400114 | M28: =Orçamento!E26 -> -22138.305 | N28: ='DRE 2026'!F25 -> -18897 | O28: =IF(M28=0, IF(N28=0, 0, 100%), (N28 - M28) / M28) -> -0.14641161 | P28: =Orçamento!F26 -> -28271.546 | Q28: ='DRE 2026'!G25 -> -20170 | R28: =IF(P28=0, IF(Q28=0, 0, 100%), (Q28 - P28) / P28) -> -0.28656182 | S28: =Orçamento!G26 -> -23957.622 | T28: ='DRE 2026'!H25 -> -21346 | U28: =IF(S28=0, IF(T28=0, 0, 100%), (T28 - S28) / S28) -> -0.10901008 | V28: =Orçamento!H26 -> -30126.086 | W28: ='DRE 2026'!I25 -> -23767 | X28: =IF(V28=0, IF(W28=0, 0, 100%), (W28 - V28) / V28) -> -0.21108239 | Y28: =Orçamento!I26 -> -30668.276 | Z28: ='DRE 2026'!J25 -> -25394.51 | AA28: =IF(Y28=0, IF(Z28=0, 0, 100%), (Z28 - Y28) / Y28) -> -0.17196161 | AB28: =Orçamento!J26 -> -25356.87 | AC28: ='DRE 2026'!K25 -> 0 | AD28: =IF(AB28=0, IF(AC28=0, 0, 100%), (AC28 - AB28) / AB28) -> -1 | AE28: =Orçamento!K26 -> -24142.365 | AF28: ='DRE 2026'!L25 -> 0 | AG28: =IF(AE28=0, IF(AF28=0, 0, 100%), (AF28 - AE28) / AE28) -> -1 | AH28: =Orçamento!L26 -> -27406.742 | AI28: ='DRE 2026'!M25 -> 0 | AJ28: =IF(AH28=0, IF(AI28=0, 0, 100%), (AI28 - AH28) / AH28) -> -1 | AK28: =Orçamento!M26 -> -28742.75 | AL28: ='DRE 2026'!N25 -> 0 | AM28: =IF(AK28=0, IF(AL28=0, 0, 100%), (AL28 - AK28) / AK28) -> -1 | AO28: =IF(H28=0,D28,IF(K28=0,D28+G28,IF(N28=0,D28+G28+J28,IF(Q28=0,D28+G28+J28+M28,IF(T28=0,D28+G28+J28+M28+P28,D28+G28+J28+M28+P28+S28))))) -> -144789.75 | AP28: =IF($H$7=0,E28,IF($K$7=0,E28+H28,IF($N$7=0,E28+H28+K28,IF($Q$7=0,E28+H28+K28+N28,IF($T$7=0,E28+H28+K28+N28+Q28,E28+H28+K28+N28+Q28+T28))))) -> -122804 | AQ28: =IF(AO28=0, IF(AP28=0, 0, 100%), (AP28 - AO28) / AO28) -> -0.15184605 | AR28: =IF($Z$7=0,V28,IF($AC$7=0,V28+Y28,IF($AF$7=0,V28+Y28+AB28,IF($AI$7=0,V28+Y28+AB28+AE28,IF($AL$7=0,V28+Y28+AB28+AE28+AH28,V28+Y28+AB28+AE28+AH28+AK28))))) -> -60794.362 | AS28: =IF($Z$7=0,W28,IF($AC$7=0,W28+Z28,IF($AF$7=0,W28+Z28+AC28,IF($AI$7=0,W28+Z28+AC28+AF28,IF($AL$7=0,W28+Z28+AC28+AF28+AI28,W28+Z28+AC28+AF28+AI28+AL28))))) -> -49161.51 | AT28: =IF(AR28=0, IF(AS28=0, 0, 100%), (AS28 - AR28) / AR28) -> -0.19134755 | AU28: =AR28+AO28 -> -205584.11 | AV28: =AP28+AS28 -> -171965.51 | AW28: =IF(AU28=0, IF(AV28=0, 0, 100%), (AV28 - AU28) / AU28) -> -0.16352725
C29: Compra de Serviços | D29: =Orçamento!B27 -> 0 | E29: ='DRE 2026'!C26 -> 0 | F29: =IF(D29=0, IF(E29=0, 0, 100%), (E29 - D29) / D29) -> 0 | G29: =Orçamento!C27 -> 0 | H29: ='DRE 2026'!D26 -> 0 | I29: =IF(G29=0, IF(H29=0, 0, 100%), (H29 - G29) / G29) -> 0 | J29: =Orçamento!D27 -> 0 | K29: ='DRE 2026'!E26 -> 0 | L29: =IF(J29=0, IF(K29=0, 0, 100%), (K29 - J29) / J29) -> 0 | M29: =Orçamento!E27 -> 0 | N29: ='DRE 2026'!F26 -> 0 | O29: =IF(M29=0, IF(N29=0, 0, 100%), (N29 - M29) / M29) -> 0 | P29: =Orçamento!F27 -> 0 | Q29: ='DRE 2026'!G26 -> 0 | R29: =IF(P29=0, IF(Q29=0, 0, 100%), (Q29 - P29) / P29) -> 0 | S29: =Orçamento!G27 -> 0 | T29: ='DRE 2026'!H26 -> 0 | U29: =IF(S29=0, IF(T29=0, 0, 100%), (T29 - S29) / S29) -> 0 | V29: =Orçamento!H27 -> 0 | W29: ='DRE 2026'!I26 -> 0 | X29: =IF(V29=0, IF(W29=0, 0, 100%), (W29 - V29) / V29) -> 0 | Y29: =Orçamento!I27 -> 0 | Z29: ='DRE 2026'!J26 -> 0 | AA29: =IF(Y29=0, IF(Z29=0, 0, 100%), (Z29 - Y29) / Y29) -> 0 | AB29: =Orçamento!J27 -> 0 | AC29: ='DRE 2026'!K26 -> 0 | AD29: =IF(AB29=0, IF(AC29=0, 0, 100%), (AC29 - AB29) / AB29) -> 0 | AE29: =Orçamento!K27 -> 0 | AF29: ='DRE 2026'!L26 -> 0 | AG29: =IF(AE29=0, IF(AF29=0, 0, 100%), (AF29 - AE29) / AE29) -> 0 | AH29: =Orçamento!L27 -> 0 | AI29: ='DRE 2026'!M26 -> 0 | AJ29: =IF(AH29=0, IF(AI29=0, 0, 100%), (AI29 - AH29) / AH29) -> 0 | AK29: =Orçamento!M27 -> 0 | AL29: ='DRE 2026'!N26 -> 0 | AM29: =IF(AK29=0, IF(AL29=0, 0, 100%), (AL29 - AK29) / AK29) -> 0 | AO29: =IF(H29=0,D29,IF(K29=0,D29+G29,IF(N29=0,D29+G29+J29,IF(Q29=0,D29+G29+J29+M29,IF(T29=0,D29+G29+J29+M29+P29,D29+G29+J29+M29+P29+S29))))) -> 0 | AP29: =IF($H$7=0,E29,IF($K$7=0,E29+H29,IF($N$7=0,E29+H29+K29,IF($Q$7=0,E29+H29+K29+N29,IF($T$7=0,E29+H29+K29+N29+Q29,E29+H29+K29+N29+Q29+T29))))) -> 0 | AQ29: =IF(AO29=0, IF(AP29=0, 0, 100%), (AP29 - AO29) / AO29) -> 0 | AR29: =IF($Z$7=0,V29,IF($AC$7=0,V29+Y29,IF($AF$7=0,V29+Y29+AB29,IF($AI$7=0,V29+Y29+AB29+AE29,IF($AL$7=0,V29+Y29+AB29+AE29+AH29,V29+Y29+AB29+AE29+AH29+AK29))))) -> 0 | AS29: =IF($Z$7=0,W29,IF($AC$7=0,W29+Z29,IF($AF$7=0,W29+Z29+AC29,IF($AI$7=0,W29+Z29+AC29+AF29,IF($AL$7=0,W29+Z29+AC29+AF29+AI29,W29+Z29+AC29+AF29+AI29+AL29))))) -> 0 | AT29: =IF(AR29=0, IF(AS29=0, 0, 100%), (AS29 - AR29) / AR29) -> 0 | AU29: =AR29+AO29 -> 0 | AV29: =AP29+AS29 -> 0 | AW29: =IF(AU29=0, IF(AV29=0, 0, 100%), (AV29 - AU29) / AU29) -> 0
C30: Lucro Operacional Bruto | D30: =Orçamento!B28 -> 210426.45 | E30: ='DRE 2026'!C27 -> 170735.05 | F30: =IF(D30=0, IF(E30=0, 0, 100%), (E30 - D30) / D30) -> -0.18862361 | G30: =Orçamento!C28 -> 174154.01 | H30: ='DRE 2026'!D27 -> 189834.66 | I30: =IF(G30=0, IF(H30=0, 0, 100%), (H30 - G30) / G30) -> 0.09003896 | J30: =Orçamento!D28 -> 231022.12 | K30: ='DRE 2026'!E27 -> 200878.36 | L30: =IF(J30=0, IF(K30=0, 0, 100%), (K30 - J30) / J30) -> -0.13047998 | M30: =Orçamento!E28 -> 187358.84 | N30: ='DRE 2026'!F27 -> 143129.78 | O30: =IF(M30=0, IF(N30=0, 0, 100%), (N30 - M30) / M30) -> -0.23606604 | P30: =Orçamento!F28 -> 229976.3 | Q30: ='DRE 2026'!G27 -> 159688.59 | R30: =IF(P30=0, IF(Q30=0, 0, 100%), (Q30 - P30) / P30) -> -0.30563023 | S30: =Orçamento!G28 -> 202836.21 | T30: ='DRE 2026'!H27 -> 170807.86 | U30: =IF(S30=0, IF(T30=0, 0, 100%), (T30 - S30) / S30) -> -0.15790251 | V30: =Orçamento!H28 -> 256579.62 | W30: ='DRE 2026'!I27 -> 185959 | X30: =IF(V30=0, IF(W30=0, 0, 100%), (W30 - V30) / V30) -> -0.27523862 | Y30: =Orçamento!I28 -> 265008.03 | Z30: ='DRE 2026'!J27 -> 275712.88 | AA30: =IF(Y30=0, IF(Z30=0, 0, 100%), (Z30 - Y30) / Y30) -> 0.040394438 | AB30: =Orçamento!J28 -> 221879.39 | AC30: ='DRE 2026'!K27 -> 0 | AD30: =IF(AB30=0, IF(AC30=0, 0, 100%), (AC30 - AB30) / AB30) -> -1 | AE30: =Orçamento!K28 -> 213719.96 | AF30: ='DRE 2026'!L27 -> 0 | AG30: =IF(AE30=0, IF(AF30=0, 0, 100%), (AF30 - AE30) / AE30) -> -1 | AH30: =Orçamento!L28 -> 247987 | AI30: ='DRE 2026'!M27 -> 0 | AJ30: =IF(AH30=0, IF(AI30=0, 0, 100%), (AI30 - AH30) / AH30) -> -1 | AK30: =Orçamento!M28 -> 260098.62 | AL30: ='DRE 2026'!N27 -> 0 | AM30: =IF(AK30=0, IF(AL30=0, 0, 100%), (AL30 - AK30) / AK30) -> -1 | AO30: =IF(H30=0,D30,IF(K30=0,D30+G30,IF(N30=0,D30+G30+J30,IF(Q30=0,D30+G30+J30+M30,IF(T30=0,D30+G30+J30+M30+P30,D30+G30+J30+M30+P30+S30))))) -> 1235773.9 | AP30: =IF($H$7=0,E30,IF($K$7=0,E30+H30,IF($N$7=0,E30+H30+K30,IF($Q$7=0,E30+H30+K30+N30,IF($T$7=0,E30+H30+K30+N30+Q30,E30+H30+K30+N30+Q30+T30))))) -> 1035074.3 | AQ30: =IF(AO30=0, IF(AP30=0, 0, 100%), (AP30 - AO30) / AO30) -> -0.16240804 | AR30: =IF($Z$7=0,V30,IF($AC$7=0,V30+Y30,IF($AF$7=0,V30+Y30+AB30,IF($AI$7=0,V30+Y30+AB30+AE30,IF($AL$7=0,V30+Y30+AB30+AE30+AH30,V30+Y30+AB30+AE30+AH30+AK30))))) -> 521587.65 | AS30: =IF($Z$7=0,W30,IF($AC$7=0,W30+Z30,IF($AF$7=0,W30+Z30+AC30,IF($AI$7=0,W30+Z30+AC30+AF30,IF($AL$7=0,W30+Z30+AC30+AF30+AI30,W30+Z30+AC30+AF30+AI30+AL30))))) -> 461671.88 | AT30: =IF(AR30=0, IF(AS30=0, 0, 100%), (AS30 - AR30) / AR30) -> -0.11487191 | AU30: =AR30+AO30 -> 1757361.6 | AV30: =AP30+AS30 -> 1496746.2 | AW30: =IF(AU30=0, IF(AV30=0, 0, 100%), (AV30 - AU30) / AU30) -> -0.14829925
... C100: Lucro Prejuízo do Exercicio | D100: =Orçamento!B98 -> 94806.537 | E100: ='DRE 2026'!C97 -> 43620.847 | F100: =IF(D100=0, IF(E100=0, 0, 100%), (E100 - D100) / D100) -> -0.53989621 | G100: =Orçamento!C98 -> 51694.181 | H100: ='DRE 2026'!D97 -> 74795.969 | I100: =IF(G100=0, IF(H100=0, 0, 100%), (H100 - G100) / G100) -> 0.44689339 | J100: =Orçamento!D98 -> 111063.83 | K100: ='DRE 2026'!E97 -> 109569.47 | L100: =IF(J100=0, IF(K100=0, 0, 100%), (K100 - J100) / J100) -> -0.013454912 | M100: =Orçamento!E98 -> 72645.977 | N100: ='DRE 2026'!F97 -> 15761.714 | O100: =IF(M100=0, IF(N100=0, 0, 100%), (N100 - M100) / M100) -> -0.7830339 | P100: =Orçamento!F98 -> 113329.55 | Q100: ='DRE 2026'!G97 -> 73122.612 | R100: =IF(P100=0, IF(Q100=0, 0, 100%), (Q100 - P100) / P100) -> -0.35477894 | S100: =Orçamento!G98 -> 87033.487 | T100: ='DRE 2026'!H97 -> 91484.733 | U100: =IF(S100=0, IF(T100=0, 0, 100%), (T100 - S100) / S100) -> 0.051144062 | V100: =Orçamento!H98 -> 119658.97 | W100: ='DRE 2026'!I97 -> 56977.293 | X100: =IF(V100=0, IF(W100=0, 0, 100%), (W100 - V100) / V100) -> -0.52383602 | Y100: =Orçamento!I98 -> 130446.71 | Z100: ='DRE 2026'!J97 -> 142993.04 | AA100: =IF(Y100=0, IF(Z100=0, 0, 100%), (Z100 - Y100) / Y100) -> 0.096179721 | AB100: =Orçamento!J98 -> 99059.998 | AC100: ='DRE 2026'!K97 -> 1147.25 | AD100: =IF(AB100=0, IF(AC100=0, 0, 100%), (AC100 - AB100) / AB100) -> -0.98841863 | AE100: =Orçamento!K98 -> 76346.047 | AF100: ='DRE 2026'!L97 -> 0 | AG100: =IF(AE100=0, IF(AF100=0, 0, 100%), (AF100 - AE100) / AE100) -> -1 | AH100: =Orçamento!L98 -> 117121.44 | AI100: ='DRE 2026'!M97 -> 0 | AJ100: =IF(AH100=0, IF(AI100=0, 0, 100%), (AI100 - AH100) / AH100) -> -1 | AK100: =Orçamento!M98 -> 110166.14 | AL100: ='DRE 2026'!N97 -> 0 | AM100: =IF(AK100=0, IF(AL100=0, 0, 100%), (AL100 - AK100) / AK100) -> -1 | AO100: =IF(H100=0,D100,IF(K100=0,D100+G100,IF(N100=0,D100+G100+J100,IF(Q100=0,D100+G100+J100+M100,IF(T100=0,D100+G100+J100+M100+P100,D100+G100+J100+M100+P100+S100))))) -> 530573.56 | AP100: =IF($H$7=0,E100,IF($K$7=0,E100+H100,IF($N$7=0,E100+H100+K100,IF($Q$7=0,E100+H100+K100+N100,IF($T$7=0,E100+H100+K100+N100+Q100,E100+H100+K100+N100+Q100+T100))))) -> 408355.35 | AQ100: =IF(AO100=0, IF(AP100=0, 0, 100%), (AP100 - AO100) / AO100) -> -0.23035111 | AR100: =IF($Z$7=0,V100,IF($AC$7=0,V100+Y100,IF($AF$7=0,V100+Y100+AB100,IF($AI$7=0,V100+Y100+AB100+AE100,IF($AL$7=0,V100+Y100+AB100+AE100+AH100,V100+Y100+AB100+AE100+AH100+AK100))))) -> 250105.68 | AS100: =IF($Z$7=0,W100,IF($AC$7=0,W100+Z100,IF($AF$7=0,W100+Z100+AC100,IF($AI$7=0,W100+Z100+AC100+AF100,IF($AL$7=0,W100+Z100+AC100+AF100+AI100,W100+Z100+AC100+AF100+AI100+AL100))))) -> 199970.33 | AT100: =IF(AR100=0, IF(AS100=0, 0, 100%), (AS100 - AR100) / AR100) -> -0.20045667 | AU100: =AR100+AO100 -> 780679.24 | AV100: =AP100+AS100 -> 608325.68 | AW100: =IF(AU100=0, IF(AV100=0, 0, 100%), (AV100 - AU100) / AU100) -> -0.22077385
D101: =Orçamento!B99 -> 0 | E101: ='DRE 2026'!C98 -> 0 | F101: =IF(D101=0, IF(E101=0, 0, 100%), (E101 - D101) / D101) -> 0 | G101: =Orçamento!C99 -> 0 | H101: ='DRE 2026'!D98 -> 0 | I101: =IF(G101=0, IF(H101=0, 0, 100%), (H101 - G101) / G101) -> 0 | J101: =Orçamento!D99 -> 0 | K101: ='DRE 2026'!E98 -> 0 | L101: =IF(J101=0, IF(K101=0, 0, 100%), (K101 - J101) / J101) -> 0 | M101: =Orçamento!E99 -> 0 | N101: ='DRE 2026'!F98 -> 0 | O101: =IF(M101=0, IF(N101=0, 0, 100%), (N101 - M101) / M101) -> 0 | P101: =Orçamento!F99 -> 0 | Q101: ='DRE 2026'!G98 -> 0 | R101: =IF(P101=0, IF(Q101=0, 0, 100%), (Q101 - P101) / P101) -> 0 | S101: =Orçamento!G99 -> 0 | T101: ='DRE 2026'!H98 -> 0 | U101: =IF(S101=0, IF(T101=0, 0, 100%), (T101 - S101) / S101) -> 0 | V101: =Orçamento!H99 -> 0 | W101: ='DRE 2026'!I98 -> 0 | X101: =IF(V101=0, IF(W101=0, 0, 100%), (W101 - V101) / V101) -> 0 | Y101: =Orçamento!I99 -> 0 | Z101: ='DRE 2026'!J98 -> 0 | AA101: =IF(Y101=0, IF(Z101=0, 0, 100%), (Z101 - Y101) / Y101) -> 0 | AB101: =Orçamento!J99 -> 0 | AC101: ='DRE 2026'!K98 -> 0 | AD101: =IF(AB101=0, IF(AC101=0, 0, 100%), (AC101 - AB101) / AB101) -> 0 | AE101: =Orçamento!K99 -> 0 | AF101: ='DRE 2026'!L98 -> 0 | AG101: =IF(AE101=0, IF(AF101=0, 0, 100%), (AF101 - AE101) / AE101) -> 0 | AH101: =Orçamento!L99 -> 0 | AI101: ='DRE 2026'!M98 -> 0 | AJ101: =IF(AH101=0, IF(AI101=0, 0, 100%), (AI101 - AH101) / AH101) -> 0 | AK101: =Orçamento!M99 -> 0 | AL101: ='DRE 2026'!N98 -> 0 | AM101: =IF(AK101=0, IF(AL101=0, 0, 100%), (AL101 - AK101) / AK101) -> 0 | AO101: =IF(H101=0,D101,IF(K101=0,D101+G101,IF(N101=0,D101+G101+J101,IF(Q101=0,D101+G101+J101+M101,IF(T101=0,D101+G101+J101+M101+P101,D101+G101+J101+M101+P101+S101))))) -> 0 | AP101: =IF($H$7=0,E101,IF($K$7=0,E101+H101,IF($N$7=0,E101+H101+K101,IF($Q$7=0,E101+H101+K101+N101,IF($T$7=0,E101+H101+K101+N101+Q101,E101+H101+K101+N101+Q101+T101))))) -> 0 | AQ101: =IF(AO101=0, IF(AP101=0, 0, 100%), (AP101 - AO101) / AO101) -> 0 | AR101: =IF($Z$7=0,V101,IF($AC$7=0,V101+Y101,IF($AF$7=0,V101+Y101+AB101,IF($AI$7=0,V101+Y101+AB101+AE101,IF($AL$7=0,V101+Y101+AB101+AE101+AH101,V101+Y101+AB101+AE101+AH101+AK101))))) -> 0 | AS101: =IF($Z$7=0,W101,IF($AC$7=0,W101+Z101,IF($AF$7=0,W101+Z101+AC101,IF($AI$7=0,W101+Z101+AC101+AF101,IF($AL$7=0,W101+Z101+AC101+AF101+AI101,W101+Z101+AC101+AF101+AI101+AL101))))) -> 0 | AT101: =IF(AR101=0, IF(AS101=0, 0, 100%), (AS101 - AR101) / AR101) -> 0 | AU101: =AR101+AO101 -> 0 | AV101: =AP101+AS101 -> 0 | AW101: =IF(AU101=0, IF(AV101=0, 0, 100%), (AV101 - AU101) / AU101) -> 0
C102: Investimentos | D102: =Orçamento!B100 -> -700 | E102: ='DRE 2026'!C99 -> -384.14 | F102: =IF(D102=0, IF(E102=0, 0, 100%), (E102 - D102) / D102) -> -0.45122857 | G102: =Orçamento!C100 -> -700 | H102: ='DRE 2026'!D99 -> -384.14 | I102: =IF(G102=0, IF(H102=0, 0, 100%), (H102 - G102) / G102) -> -0.45122857 | J102: =Orçamento!D100 -> -1150 | K102: ='DRE 2026'!E99 -> -913.77 | L102: =IF(J102=0, IF(K102=0, 0, 100%), (K102 - J102) / J102) -> -0.20541739 | M102: =Orçamento!E100 -> -1150 | N102: ='DRE 2026'!F99 -> -1194.46 | O102: =IF(M102=0, IF(N102=0, 0, 100%), (N102 - M102) / M102) -> 0.03866087 | P102: =Orçamento!F100 -> -1150 | Q102: ='DRE 2026'!G99 -> -913.72 | R102: =IF(P102=0, IF(Q102=0, 0, 100%), (Q102 - P102) / P102) -> -0.20546087 | S102: =Orçamento!G100 -> -1150 | T102: ='DRE 2026'!H99 -> -416.82 | U102: =IF(S102=0, IF(T102=0, 0, 100%), (T102 - S102) / S102) -> -0.63754783 | V102: =Orçamento!H100 -> -1150 | W102: ='DRE 2026'!I99 -> -1256.71 | X102: =IF(V102=0, IF(W102=0, 0, 100%), (W102 - V102) / V102) -> 0.092791304 | Y102: =Orçamento!I100 -> -1150 | Z102: ='DRE 2026'!J99 -> -1214.69 | AA102: =IF(Y102=0, IF(Z102=0, 0, 100%), (Z102 - Y102) / Y102) -> 0.056252174 | AB102: =Orçamento!J100 -> -1150 | AC102: ='DRE 2026'!K99 -> 0 | AD102: =IF(AB102=0, IF(AC102=0, 0, 100%), (AC102 - AB102) / AB102) -> -1 | AE102: =Orçamento!K100 -> -1150 | AF102: ='DRE 2026'!L99 -> 0 | AG102: =IF(AE102=0, IF(AF102=0, 0, 100%), (AF102 - AE102) / AE102) -> -1 | AH102: =Orçamento!L100 -> -1150 | AI102: ='DRE 2026'!M99 -> 0 | AJ102: =IF(AH102=0, IF(AI102=0, 0, 100%), (AI102 - AH102) / AH102) -> -1 | AK102: =Orçamento!M100 -> -1150 | AL102: ='DRE 2026'!N99 -> 0 | AM102: =IF(AK102=0, IF(AL102=0, 0, 100%), (AL102 - AK102) / AK102) -> -1 | AO102: =IF(H102=0,D102,IF(K102=0,D102+G102,IF(N102=0,D102+G102+J102,IF(Q102=0,D102+G102+J102+M102,IF(T102=0,D102+G102+J102+M102+P102,D102+G102+J102+M102+P102+S102))))) -> -6000 | AP102: =IF($H$7=0,E102,IF($K$7=0,E102+H102,IF($N$7=0,E102+H102+K102,IF($Q$7=0,E102+H102+K102+N102,IF($T$7=0,E102+H102+K102+N102+Q102,E102+H102+K102+N102+Q102+T102))))) -> -4207.05 | AQ102: =IF(AO102=0, IF(AP102=0, 0, 100%), (AP102 - AO102) / AO102) -> -0.298825 | AR102: =IF($Z$7=0,V102,IF($AC$7=0,V102+Y102,IF($AF$7=0,V102+Y102+AB102,IF($AI$7=0,V102+Y102+AB102+AE102,IF($AL$7=0,V102+Y102+AB102+AE102+AH102,V102+Y102+AB102+AE102+AH102+AK102))))) -> -2300 | AS102: =IF($Z$7=0,W102,IF($AC$7=0,W102+Z102,IF($AF$7=0,W102+Z102+AC102,IF($AI$7=0,W102+Z102+AC102+AF102,IF($AL$7=0,W102+Z102+AC102+AF102+AI102,W102+Z102+AC102+AF102+AI102+AL102))))) -> -2471.4 | AT102: =IF(AR102=0, IF(AS102=0, 0, 100%), (AS102 - AR102) / AR102) -> 0.074521739 | AU102: =AR102+AO102 -> -8300 | AV102: =AP102+AS102 -> -6678.45 | AW102: =IF(AU102=0, IF(AV102=0, 0, 100%), (AV102 - AU102) / AU102) -> -0.19536747
C103: Eletrônicos/Eletrodomésticos | D103: =Orçamento!B101 -> -700 | E103: ='DRE 2026'!C100 -> -384.14 | F103: =IF(D103=0, IF(E103=0, 0, 100%), (E103 - D103) / D103) -> -0.45122857 | G103: =Orçamento!C101 -> -700 | H103: ='DRE 2026'!D100 -> -384.14 | I103: =IF(G103=0, IF(H103=0, 0, 100%), (H103 - G103) / G103) -> -0.45122857 | J103: =Orçamento!D101 -> -1150 | K103: ='DRE 2026'!E100 -> -913.77 | L103: =IF(J103=0, IF(K103=0, 0, 100%), (K103 - J103) / J103) -> -0.20541739 | M103: =Orçamento!E101 -> -1150 | N103: ='DRE 2026'!F100 -> -1194.46 | O103: =IF(M103=0, IF(N103=0, 0, 100%), (N103 - M103) / M103) -> 0.03866087 | P103: =Orçamento!F101 -> -1150 | Q103: ='DRE 2026'!G100 -> -913.72 | R103: =IF(P103=0, IF(Q103=0, 0, 100%), (Q103 - P103) / P103) -> -0.20546087 | S103: =Orçamento!G101 -> -1150 | T103: ='DRE 2026'!H100 -> -416.82 | U103: =IF(S103=0, IF(T103=0, 0, 100%), (T103 - S103) / S103) -> -0.63754783 | V103: =Orçamento!H101 -> -1150 | W103: ='DRE 2026'!I100 -> -1256.71 | X103: =IF(V103=0, IF(W103=0, 0, 100%), (W103 - V103) / V103) -> 0.092791304 | Y103: =Orçamento!I101 -> -1150 | Z103: ='DRE 2026'!J100 -> -1214.69 | AA103: =IF(Y103=0, IF(Z103=0, 0, 100%), (Z103 - Y103) / Y103) -> 0.056252174 | AB103: =Orçamento!J101 -> -1150 | AC103: ='DRE 2026'!K100 -> 0 | AD103: =IF(AB103=0, IF(AC103=0, 0, 100%), (AC103 - AB103) / AB103) -> -1 | AE103: =Orçamento!K101 -> -1150 | AF103: ='DRE 2026'!L100 -> 0 | AG103: =IF(AE103=0, IF(AF103=0, 0, 100%), (AF103 - AE103) / AE103) -> -1 | AH103: =Orçamento!L101 -> -1150 | AI103: ='DRE 2026'!M100 -> 0 | AJ103: =IF(AH103=0, IF(AI103=0, 0, 100%), (AI103 - AH103) / AH103) -> -1 | AK103: =Orçamento!M101 -> -1150 | AL103: ='DRE 2026'!N100 -> 0 | AM103: =IF(AK103=0, IF(AL103=0, 0, 100%), (AL103 - AK103) / AK103) -> -1 | AO103: =IF(H103=0,D103,IF(K103=0,D103+G103,IF(N103=0,D103+G103+J103,IF(Q103=0,D103+G103+J103+M103,IF(T103=0,D103+G103+J103+M103+P103,D103+G103+J103+M103+P103+S103))))) -> -6000 | AP103: =IF($H$7=0,E103,IF($K$7=0,E103+H103,IF($N$7=0,E103+H103+K103,IF($Q$7=0,E103+H103+K103+N103,IF($T$7=0,E103+H103+K103+N103+Q103,E103+H103+K103+N103+Q103+T103))))) -> -4207.05 | AQ103: =IF(AO103=0, IF(AP103=0, 0, 100%), (AP103 - AO103) / AO103) -> -0.298825 | AR103: =IF($Z$7=0,V103,IF($AC$7=0,V103+Y103,IF($AF$7=0,V103+Y103+AB103,IF($AI$7=0,V103+Y103+AB103+AE103,IF($AL$7=0,V103+Y103+AB103+AE103+AH103,V103+Y103+AB103+AE103+AH103+AK103))))) -> -2300 | AS103: =IF($Z$7=0,W103,IF($AC$7=0,W103+Z103,IF($AF$7=0,W103+Z103+AC103,IF($AI$7=0,W103+Z103+AC103+AF103,IF($AL$7=0,W103+Z103+AC103+AF103+AI103,W103+Z103+AC103+AF103+AI103+AL103))))) -> -2471.4 | AT103: =IF(AR103=0, IF(AS103=0, 0, 100%), (AS103 - AR103) / AR103) -> 0.074521739 | AU103: =AR103+AO103 -> -8300 | AV103: =AP103+AS103 -> -6678.45 | AW103: =IF(AU103=0, IF(AV103=0, 0, 100%), (AV103 - AU103) / AU103) -> -0.19536747
C104: Resultado Pós Investimento | D104: =Orçamento!B102 -> 94106.537 | E104: ='DRE 2026'!C101 -> 43236.707 | F104: =IF(D104=0, IF(E104=0, 0, 100%), (E104 - D104) / D104) -> -0.54055575 | G104: =Orçamento!C102 -> 50994.181 | H104: ='DRE 2026'!D101 -> 74411.829 | I104: =IF(G104=0, IF(H104=0, 0, 100%), (H104 - G104) / G104) -> 0.45922196 | J104: =Orçamento!D102 -> 109913.83 | K104: ='DRE 2026'!E101 -> 108655.7 | L104: =IF(J104=0, IF(K104=0, 0, 100%), (K104 - J104) / J104) -> -0.011446458 | M104: =Orçamento!E102 -> 71495.977 | N104: ='DRE 2026'!F101 -> 14567.254 | O104: =IF(M104=0, IF(N104=0, 0, 100%), (N104 - M104) / M104) -> -0.79625071 | P104: =Orçamento!F102 -> 112179.55 | Q104: ='DRE 2026'!G101 -> 72208.892 | R104: =IF(P104=0, IF(Q104=0, 0, 100%), (Q104 - P104) / P104) -> -0.35630966 | S104: =Orçamento!G102 -> 85883.487 | T104: ='DRE 2026'!H101 -> 91067.913 | U104: =IF(S104=0, IF(T104=0, 0, 100%), (T104 - S104) / S104) -> 0.060365808 | V104: =Orçamento!H102 -> 118508.97 | W104: ='DRE 2026'!I101 -> 55720.583 | X104: =IF(V104=0, IF(W104=0, 0, 100%), (W104 - V104) / V104) -> -0.52981971 | Y104: =Orçamento!I102 -> 129296.71 | Z104: ='DRE 2026'!J101 -> 141778.35 | AA104: =IF(Y104=0, IF(Z104=0, 0, 100%), (Z104 - Y104) / Y104) -> 0.096534848 | AB104: =Orçamento!J102 -> 97909.998 | AC104: ='DRE 2026'!K101 -> 1147.25 | AD104: =IF(AB104=0, IF(AC104=0, 0, 100%), (AC104 - AB104) / AB104) -> -0.98828261 | AE104: =Orçamento!K102 -> 75196.047 | AF104: ='DRE 2026'!L101 -> 0 | AG104: =IF(AE104=0, IF(AF104=0, 0, 100%), (AF104 - AE104) / AE104) -> -1 | AH104: =Orçamento!L102 -> 115971.44 | AI104: ='DRE 2026'!M101 -> 0 | AJ104: =IF(AH104=0, IF(AI104=0, 0, 100%), (AI104 - AH104) / AH104) -> -1 | AK104: =Orçamento!M102 -> 109016.14 | AL104: ='DRE 2026'!N101 -> 0 | AM104: =IF(AK104=0, IF(AL104=0, 0, 100%), (AL104 - AK104) / AK104) -> -1 | AO104: =IF(H104=0,D104,IF(K104=0,D104+G104,IF(N104=0,D104+G104+J104,IF(Q104=0,D104+G104+J104+M104,IF(T104=0,D104+G104+J104+M104+P104,D104+G104+J104+M104+P104+S104))))) -> 524573.56 | AP104: =IF($H$7=0,E104,IF($K$7=0,E104+H104,IF($N$7=0,E104+H104+K104,IF($Q$7=0,E104+H104+K104+N104,IF($T$7=0,E104+H104+K104+N104+Q104,E104+H104+K104+N104+Q104+T104))))) -> 404148.3 | AQ104: =IF(AO104=0, IF(AP104=0, 0, 100%), (AP104 - AO104) / AO104) -> -0.22956792 | AR104: =IF($Z$7=0,V104,IF($AC$7=0,V104+Y104,IF($AF$7=0,V104+Y104+AB104,IF($AI$7=0,V104+Y104+AB104+AE104,IF($AL$7=0,V104+Y104+AB104+AE104+AH104,V104+Y104+AB104+AE104+AH104+AK104))))) -> 247805.68 | AS104: =IF($Z$7=0,W104,IF($AC$7=0,W104+Z104,IF($AF$7=0,W104+Z104+AC104,IF($AI$7=0,W104+Z104+AC104+AF104,IF($AL$7=0,W104+Z104+AC104+AF104+AI104,W104+Z104+AC104+AF104+AI104+AL104))))) -> 197498.93 | AT104: =IF(AR104=0, IF(AS104=0, 0, 100%), (AS104 - AR104) / AR104) -> -0.20300887 | AU104: =AR104+AO104 -> 772379.24 | AV104: =AP104+AS104 -> 601647.23 | AW104: =IF(AU104=0, IF(AV104=0, 0, 100%), (AV104 - AU104) / AU104) -> -0.22104687
AG105: =IFERROR(AF105/AE105,"") | AJ105: =IFERROR(AI105/AH105,"") | AM105: =IFERROR(AL105/AK105,"")
AG106: =IFERROR(AF106/AE106,"") | AJ106: =IFERROR(AI106/AH106,"") | AM106: =IFERROR(AL106/AK106,"")
AG107: =IFERROR(AF107/AE107,"")
AG108: =IFERROR(AF108/AE108,"")

Sheet DRE 2025 
C4: Demonstrativos Financeiros - 2025 Consolidado | D4: JANEIRO | E4: FEVEREIRO | F4: MARÇO | G4: ABRIL | H4: MAIO | I4: JUNHO | J4: JULHO | K4: AGOSTO | L4: SETEMBRO | M4: OUTUBRO | N4: NOVEMBRO | O4: DEZEMBRO | Q4: 1 SEM | R4: 2 SEM | S4: 2025
C5: DRE (R$)
C6: Receita Operacional Bruta | D6: 257644.73 | E6: 219780.85 | F6: 288339.24 | G6: 223778.48 | H6: 255032.26 | I6: 226291.41 | J6: 271447.52 | K6: 324157.81 | L6: 314586.98 | M6: 309674.67 | N6: 352613.14 | O6: 263895.42 | Q6: 1470867 | R6: 1836375.5 | S6: 3307242.5
C7: Receita com Taxa de Vendas Online - Formaturas | D7: 131377.79 | E7: 87061.41 | F7: 113490.05 | G7: 78522.63 | H7: 95642.86 | I7: 71881.67 | J7: 91636.94 | K7: 123553.33 | L7: 134608 | M7: 130109.75 | N7: 169692.36 | O7: 116485.85 | Q7: 577976.41 | R7: 766086.23 | S7: 1344062.6
C8: Receita com Taxa de Parcelamento Online - Formaturas | D8: 69705.85 | E8: 48494.43 | F8: 53739.33 | G8: 37871.14 | H8: 21751.03 | I8: 34662.58 | J8: 42340.47 | K8: 58609.19 | L8: 74437.94 | M8: 80899.8 | N8: 94238.71 | O8: 61252.6 | Q8: 266224.36 | R8: 411778.71 | S8: 678003.07
C9: Receita com Taxa de Vendas Online - Eventos em Geral | D9: 45448.87 | E9: 63292.47 | F9: 85649.05 | G9: 81646.95 | H9: 104342.39 | I9: 86198.67 | J9: 91538.69 | K9: 98591.52 | L9: 81716.46 | M9: 76187.97 | N9: 71594.13 | O9: 65663.86 | Q9: 466578.4 | R9: 485292.63 | S9: 951871.03
C10: Receita com Taxa de Parcelamento Online - Eventos em Geral | D10: 9175.99 | E10: 16811.02 | F10: 27315.69 | G10: 18975.33 | H10: 21751.03 | I10: 20945.06 | J10: 35689.52 | K10: 30780.42 | L10: 16546.39 | M10: 15904.31 | N10: 12032.45 | O10: 13171.07 | Q10: 114974.12 | R10: 124124.16 | S10: 239098.28
C11: Receita com Taxa de Cartão | D11: 343 | E11: 1268 | F11: 1623 | G11: 1528 | H11: 2572 | I11: 2244 | J11: -1393 | K11: 3352 | L11: -431 | M11: 1064 | N11: -67 | O11: -36 | Q11: 9578 | R11: 2489 | S11: 12067
C12: Receita com Taxa de Administração | D12: 1295.07 | E12: 1057.66 | F12: 114.73 | G12: 626.95 | H12: 791.76 | I12: 694.63 | J12: 1242.4 | K12: 506.51 | L12: 106.98 | M12: 753.039 | N12: 1237.32 | O12: 2659.8 | Q12: 4580.8 | R12: 6506.049 | S12: 11086.849
C13: Receita com Taxa de Processamento | D13: 298.16 | E13: 1735.47 | F13: 5120.45 | G13: 4607.48 | H13: 8115.19 | I13: 5764.46 | J13: 6765.27 | K13: 8314.47 | L13: 4984.88 | M13: 4600.7 | N13: 3885.17 | O13: 3713.24 | Q13: 25641.21 | R13: 32263.73 | S13: 57904.94
C14: Receita com Taxas de Antecipação | D14: 0 | E14: 60.39 | F14: 1286.94 | G14: 0 | H14: 66 | I14: 1018.85 | J14: 3341.73 | K14: 335.37 | L14: 787.33 | M14: 0 | N14: 0 | O14: 0 | Q14: 2432.18 | R14: 4464.43 | S14: 6896.61
C15: Receita com Locação de Equipamentos | D15: 0 | E15: 0 | F15: 0 | G15: 0 | H15: 0 | I15: 144.49 | J15: 0 | K15: 0 | L15: 0 | M15: 0 | N15: 0 | O15: 0 | Q15: 144.49 | R15: 0 | S15: 144.49
C16: Receita com Licença de Uso | D16: 0 | E16: 0 | F16: 0 | G16: 0 | H16: 0 | I16: 0 | J16: 0 | K16: 0 | L16: 0 | M16: 0 | N16: 0 | O16: 0 | Q16: 0 | R16: 0 | S16: 0
C17: Receita com Vendas de QR Codes | D17: 0 | E17: 0 | F17: 0 | G17: 0 | H17: 0 | I17: 2737 | J17: 285.5 | K17: 115 | L17: 1830 | M17: 155.1 | N17: 0 | O17: 985 | Q17: 2737 | R17: 3370.6 | S17: 6107.6
... C98: Lucro Prejuízo do Exercicio | D98: 81816.29 | E98: 32461.457 | F98: 105124.46 | G98: 69324.376 | H98: 75314.673 | I98: 69103.504 | J98: 73120.532 | K98: 117702.28 | L98: 100372.8 | M98: 99427.87 | N98: 149149.79 | O98: 95943.467 | Q98: 433144.76 | R98: 635716.74 | S98: 1068861.5
Q99: 0 | R99: 0 | S99: 0
C100: Investimentos | D100: -1680.66 | E100: -2744.85 | F100: -623.22 | G100: -573.35 | H100: -573.35 | I100: -500.79 | J100: -500.79 | K100: -1373.19 | L100: -409.66 | M100: -359.76 | N100: -425.04 | O100: -4025.33 | Q100: -6696.22 | R100: -7093.77 | S100: -13789.99
C101: Eletrônicos/Eletrodomésticos | D101: -1680.66 | E101: -2744.85 | F101: -623.22 | G101: -573.35 | H101: -573.35 | I101: -500.79 | J101: -500.79 | K101: -1373.19 | L101: -409.66 | M101: -359.76 | N101: -425.04 | O101: -4025.33 | Q101: -6696.22 | R101: -7093.77 | S101: -13789.99
C102: Resultado Pós Investimento | D102: 80135.63 | E102: 29716.607 | F102: 104501.24 | G102: 68751.026 | H102: 74741.323 | I102: 68602.714 | J102: 72619.742 | K102: 116329.09 | L102: 99963.135 | M102: 99068.11 | N102: 148724.75 | O102: 91918.137 | Q102: 426448.54 | R102: 628622.97 | S102: 1055071.5
C105: -
C108: Empréstimos | Q108: 0 | R108: 0 | S108: 0
C109: Empréstimos Bancários | D109: 0 | E109: 0 | F109: 0 | G109: 0 | H109: 0 | I109: 0 | J109: 0 | K109: 0 | L109: 0 | M109: 0 | N109: 0 | O109: 0 | Q109: 0 | R109: 0 | S109: 0
C110: Pagamento de Empréstimos | D110: 0 | E110: 0 | F110: 0 | G110: 0 | H110: 0 | I110: 0 | J110: 0 | K110: 0 | L110: 0 | M110: 0 | N110: 0 | O110: 0 | Q110: 0 | R110: 0 | S110: 0
C112: Investimentos | Q112: 0 | R112: 0 | S112: 0
C113: Investimentos | D113: 0 | E113: 0 | F113: 0 | G113: 0 | H113: 0 | I113: 0 | J113: 0 | K113: 0 | L113: 0 | M113: 0 | N113: 0 | O113: 0 | Q113: 0 | R113: 0 | S113: 0
C115: Pagamento de dividendos - 2025 | Q115: 0 | R115: 0 | S115: 0
C116: V Company | D116: 0 | E116: 0 | F116: 0 | G116: -90000 | H116: 0 | I116: 0 | J116: -120000 | K116: 0 | L116: 0 | M116: -150000 | N116: 0 | O116: -180000 | Q116: -90000 | R116: -450000 | S116: -540000
C117: Zine | D117: 0 | E117: 0 | F117: 0 | G117: -60000 | H117: 0 | I117: -50000 | J117: -29999.98 | K117: 0 | L117: 0 | M117: -99999 | N117: 0 | O117: -120000 | Q117: -110000 | R117: -249998.98 | S117: -359998.98
C119: Aportes | Q119: 0 | R119: 0 | S119: 0
C120: V Company | D120: 0 | E120: 0 | F120: 0 | G120: 0 | H120: 0 | I120: 0 | J120: 0 | K120: 0 | L120: 0 | M120: 0 | N120: 0 | O120: 0 | Q120: 0 | R120: 0 | S120: 0
C121: Zine | D121: 0 | E121: 0 | F121: 0 | G121: 0 | H121: 0 | I121: 0 | J121: 0 | K121: 0 | L121: 0 | M121: 0 | N121: 0 | O121: 0 | Q121: 0 | R121: 0 | S121: 0
C123: FLUXO DE CAIXA | Q123: 0 | R123: 0 | S123: 0
C124: Saldo Inicial de Caixa | D124: 58543.48 | E124: 31936.65 | F124: 160332.03 | G124: 279872.71 | H124: 184522.97 | I124: 273434.62 | J124: 308447.46 | K124: 268887.07 | L124: 249837.56 | M124: 460546.87 | N124: 302005.48 | O124: 353643.46 | Q124: 988642.46 | R124: 1943367.9 | S124: 2932010.4
C125: Caixa Gerado/Consumido | D125: -26606.83 | E125: 128395.38 | F125: 119540.68 | G125: -95349.74 | H125: 88911.65 | I125: 35012.84 | J125: -39560.39 | K125: -19049.51 | L125: 210709.31 | M125: -158541.39 | N125: 51637.98 | O125: -96996.88 | Q125: 249903.98 | R125: -51800.88 | S125: 198103.1
C126: Caixa Final | D126: 31936.65 | E126: 160332.03 | F126: 279872.71 | G126: 184522.97 | H126: 273434.62 | I126: 308447.46 | J126: 268887.07 | K126: 249837.56 | L126: 460546.87 | M126: 302005.48 | N126: 353643.46 | O126: 256646.58 | Q126: 1238546.4 | R126: 1891567 | S126: 3130113.5
Q127: 0 | R127: 0 | S127: 0
C128: APORTES ACUMULADOS | D128: 0 | E128: 0 | F128: 0 | G128: 0 | H128: 0 | I128: 0 | J128: 0 | K128: 0 | L128: 0 | M128: 0 | N128: 0 | O128: 0 | Q128: 0 | R128: 0 | S128: 0
C129: V Company | D129: 0 | E129: 0 | F129: 0 | G129: 0 | H129: 0 | I129: 0 | J129: 0 | K129: 0 | L129: 0 | M129: 0 | N129: 0 | O129: 0 | Q129: 0 | R129: 0 | S129: 0
C130: Zine | D130: 0 | E130: 0 | F130: 0 | G130: 0 | H130: 0 | I130: 0 | J130: 0 | K130: 0 | L130: 0 | M130: 0 | N130: 0 | O130: 0 | Q130: 0 | R130: 0 | S130: 0
C132: DIVIDENDOS ACUMULADOS - a partir de 2023 | D132: -1473724 | E132: -1473724 | F132: -1473724 | G132: -1623724 | H132: -1623724 | I132: -1673724 | J132: -1823724 | K132: -1823724 | L132: -1823724 | M132: -2073723 | N132: -2073723 | O132: -2373723 | Q132: -9342344 | R132: -11992341 | S132: -21334685
C133: V Company | D133: -877625 | E133: -877625 | F133: -877625 | G133: -967625 | H133: -967625 | I133: -967625 | J133: -1087625 | K133: -1087625 | L133: -1087625 | M133: -1237625 | N133: -1237625 | O133: -1417625 | Q133: -5535750 | R133: -7155750 | S133: -12691500
C134: Zine | D134: -596099 | E134: -596099 | F134: -596099 | G134: -656099 | H134: -656099 | I134: -706099 | J134: -736098.98 | K134: -736098.98 | L134: -736098.98 | M134: -836097.98 | N134: -836097.98 | O134: -956097.98 | Q134: -3806594 | R134: -4836590.9 | S134: -8643184.9
C135: DIVIDENDOS ACUMULADOS - a partir de 2023 | D135: =SUM(D136:D137) -> -823723 | E135: =SUM(E136:E137) -> -823723 | F135: =SUM(F136:F137) -> -823723 | G135: =SUM(G136:G137) -> -973723 | H135: =SUM(H136:H137) -> -973723 | I135: =SUM(I136:I137) -> -1023723 | J135: =SUM(J136:J137) -> -1173723 | K135: =SUM(K136:K137) -> -1173723 | ... O135: =SUM(O136:O137) -> -1723722
C136: V Company | D136: -553625 | E136: =D136+E116 -> -553625 | F136: =E136+F116 -> -553625 | G136: =F136+G116 -> -643625 | H136: =G136+H116 -> -643625 | I136: =H136+I116 -> -643625 | J136: =I136+J116 -> -763625 | K136: =J136+K116 -> -763625 | L136: =K136+L116 -> -763625 | ... O136: =N136+O116 -> -1093625
C137: Zine | D137: -270098 | E137: =D137+E117 -> -270098 | F137: =E137+F117 -> -270098 | G137: =F137+G117 -> -330098 | H137: =G137+H117 -> -330098 | I137: =H137+I117 -> -380098 | J137: =I137+J117 -> -410097.98 | K137: =J137+K117 -> -410097.98 | L137: =K137+L117 -> -410097.98 | ... O137: =N137+O117 -> -630096.98

Sheet Orçamento
A2: =IFERROR(__xludf.DUMMYFUNCTION("IMPORTRANGE(""1A_nphiEMdqoD6JURpjp80VdUZdzmj8xq2xkL2X5qaTk"",""'Resumo'!B:O"")"),"")
A3: =IFERROR(__xludf.DUMMYFUNCTION("""COMPUTED_VALUE"""),"DRE (R$)") -> DRE (R$) | B3: =IFERROR(__xludf.DUMMYFUNCTION("""COMPUTED_VALUE"""),1) -> 1 | C3: =IFERROR(__xludf.DUMMYFUNCTION("""COMPUTED_VALUE"""),2) -> 2 | D3: =IFERROR(__xludf.DUMMYFUNCTION("""COMPUTED_VALUE"""),3) -> 3 | E3: =IFERROR(__xludf.DUMMYFUNCTION("""COMPUTED_VALUE"""),4) -> 4 | F3: =IFERROR(__xludf.DUMMYFUNCTION("""COMPUTED_VALUE"""),5) -> 5 | G3: =IFERROR(__xludf.DUMMYFUNCTION("""COMPUTED_VALUE"""),6) -> 6 | H3: =IFERROR(__xludf.DUMMYFUNCTION("""COMPUTED_VALUE"""),7) -> 7 | I3: =IFERROR(__xludf.DUMMYFUNCTION("""COMPUTED_VALUE"""),8) -> 8 | J3: =IFERROR(__xludf.DUMMYFUNCTION("""COMPUTED_VALUE"""),9) -> 9 | K3: =IFERROR(__xludf.DUMMYFUNCTION("""COMPUTED_VALUE"""),10) -> 10 | L3: =IFERROR(__xludf.DUMMYFUNCTION("""COMPUTED_VALUE"""),11) -> 11 | M3: =IFERROR(__xludf.DUMMYFUNCTION("""COMPUTED_VALUE"""),12) -> 12 | N3: =IFERROR(__xludf.DUMMYFUNCTION("""COMPUTED_VALUE"""),"TOTAL") -> TOTAL
A4: =IFERROR(__xludf.DUMMYFUNCTION("""COMPUTED_VALUE"""),"Receita Operacional Bruta") -> Receita Operacional Bruta | B4: =IFERROR(__xludf.DUMMYFUNCTION("""COMPUTED_VALUE"""),321190.315685233) -> 321190.32 | C4: =IFERROR(__xludf.DUMMYFUNCTION("""COMPUTED_VALUE"""),262827.351674854) -> 262827.35 | D4: =IFERROR(__xludf.DUMMYFUNCTION("""COMPUTED_VALUE"""),353083.276102289) -> 353083.28 | E4: =IFERROR(__xludf.DUMMYFUNCTION("""COMPUTED_VALUE"""),284073.182719342) -> 284073.18 | F4: =IFERROR(__xludf.DUMMYFUNCTION("""COMPUTED_VALUE"""),359398.213207259) -> 359398.21 | G4: =IFERROR(__xludf.DUMMYFUNCTION("""COMPUTED_VALUE"""),304639.771775322) -> 304639.77 | H4: =IFERROR(__xludf.DUMMYFUNCTION("""COMPUTED_VALUE"""),387575.868113303) -> 387575.87 | I4: =IFERROR(__xludf.DUMMYFUNCTION("""COMPUTED_VALUE"""),403534.095781551) -> 403534.1 | J4: =IFERROR(__xludf.DUMMYFUNCTION("""COMPUTED_VALUE"""),339417.385176907) -> 339417.39 | K4: =IFERROR(__xludf.DUMMYFUNCTION("""COMPUTED_VALUE"""),327122.502699042) -> 327122.5 | L4: =IFERROR(__xludf.DUMMYFUNCTION("""COMPUTED_VALUE"""),383439.935515298) -> 383439.94 | M4: =IFERROR(__xludf.DUMMYFUNCTION("""COMPUTED_VALUE"""),402871.027093359) -> 402871.03 | N4: =IFERROR(__xludf.DUMMYFUNCTION("""COMPUTED_VALUE"""),4129172.92554376) -> 4129172.9
A5: =IFERROR(__xludf.DUMMYFUNCTION("""COMPUTED_VALUE"""),"Receita com Taxa de Vendas Online - Formaturas") -> Receita com Taxa de Vendas Online - Formaturas | B5: =IFERROR(__xludf.DUMMYFUNCTION("""COMPUTED_VALUE"""),146619.9271623) -> 146619.93 | C5: =IFERROR(__xludf.DUMMYFUNCTION("""COMPUTED_VALUE"""),85759.09433085) -> 85759.094 | D5: =IFERROR(__xludf.DUMMYFUNCTION("""COMPUTED_VALUE"""),130922.07592845) -> 130922.08 | E5: =IFERROR(__xludf.DUMMYFUNCTION("""COMPUTED_VALUE"""),89831.1479473) -> 89831.148 | F5: =IFERROR(__xludf.DUMMYFUNCTION("""COMPUTED_VALUE"""),106962.45670205) -> 106962.46 | G5: =IFERROR(__xludf.DUMMYFUNCTION("""COMPUTED_VALUE"""),89356.02331055) -> 89356.023 | H5: =IFERROR(__xludf.DUMMYFUNCTION("""COMPUTED_VALUE"""),123696.26229965) -> 123696.26 | I5: =IFERROR(__xludf.DUMMYFUNCTION("""COMPUTED_VALUE"""),147094.86198435) -> 147094.86 | J5: =IFERROR(__xludf.DUMMYFUNCTION("""COMPUTED_VALUE"""),135253.90085375) -> 135253.9 | K5: =IFERROR(__xludf.DUMMYFUNCTION("""COMPUTED_VALUE"""),136690.5490228) -> 136690.55 | L5: =IFERROR(__xludf.DUMMYFUNCTION("""COMPUTED_VALUE"""),183799.02461665) -> 183799.02 | M5: =IFERROR(__xludf.DUMMYFUNCTION("""COMPUTED_VALUE"""),191838.4030077) -> 191838.4 | N5: =IFERROR(__xludf.DUMMYFUNCTION("""COMPUTED_VALUE"""),1567823.7271664) -> 1567823.7
A6: =IFERROR(__xludf.DUMMYFUNCTION("""COMPUTED_VALUE"""),"Receita com Taxa de Parcelamento Online - Formaturas") -> Receita com Taxa de Parcelamento Online - Formaturas | B6: =IFERROR(__xludf.DUMMYFUNCTION("""COMPUTED_VALUE"""),79122.6985565634) -> 79122.699 | C6: =IFERROR(__xludf.DUMMYFUNCTION("""COMPUTED_VALUE"""),46049.8077366143) -> 46049.808 | D6: =IFERROR(__xludf.DUMMYFUNCTION("""COMPUTED_VALUE"""),69637.4139680751) -> 69637.414 | E6: =IFERROR(__xludf.DUMMYFUNCTION("""COMPUTED_VALUE"""),48000.6989545934) -> 48000.699 | F6: =IFERROR(__xludf.DUMMYFUNCTION("""COMPUTED_VALUE"""),57057.7080397438) -> 57057.708 | G6: =IFERROR(__xludf.DUMMYFUNCTION("""COMPUTED_VALUE"""),48289.5605072869) -> 48289.561 | H6: =IFERROR(__xludf.DUMMYFUNCTION("""COMPUTED_VALUE"""),66487.6692632047) -> 66487.669 | I6: =IFERROR(__xludf.DUMMYFUNCTION("""COMPUTED_VALUE"""),79031.3234872672) -> 79031.323 | J6: =IFERROR(__xludf.DUMMYFUNCTION("""COMPUTED_VALUE"""),72637.3383763925) -> 72637.338 | K6: =IFERROR(__xludf.DUMMYFUNCTION("""COMPUTED_VALUE"""),74004.0765547224) -> 74004.077 | L6: =IFERROR(__xludf.DUMMYFUNCTION("""COMPUTED_VALUE"""),99292.9007360907) -> 99292.901 | M6: =IFERROR(__xludf.DUMMYFUNCTION("""COMPUTED_VALUE"""),104769.790378296) -> 104769.79 | N6: =IFERROR(__xludf.DUMMYFUNCTION("""COMPUTED_VALUE"""),844380.986558851) -> 844380.99
A7: =IFERROR(__xludf.DUMMYFUNCTION("""COMPUTED_VALUE"""),"Receita com Taxa de Vendas Online - Eventos em Geral") -> Receita com Taxa de Vendas Online - Eventos em Geral | B7: =IFERROR(__xludf.DUMMYFUNCTION("""COMPUTED_VALUE"""),68688.24) -> 68688.24 | C7: =IFERROR(__xludf.DUMMYFUNCTION("""COMPUTED_VALUE"""),94286.48) -> 94286.48 | D7: =IFERROR(__xludf.DUMMYFUNCTION("""COMPUTED_VALUE"""),109762.64) -> 109762.64 | E7: =IFERROR(__xludf.DUMMYFUNCTION("""COMPUTED_VALUE"""),105241.52) -> 105241.52 | F7: =IFERROR(__xludf.DUMMYFUNCTION("""COMPUTED_VALUE"""),140602.4) -> 140602.4 | G7: =IFERROR(__xludf.DUMMYFUNCTION("""COMPUTED_VALUE"""),120176.16) -> 120176.16 | H7: =IFERROR(__xludf.DUMMYFUNCTION("""COMPUTED_VALUE"""),142051.68) -> 142051.68 | I7: =IFERROR(__xludf.DUMMYFUNCTION("""COMPUTED_VALUE"""),127670.32) -> 127670.32 | J7: =IFERROR(__xludf.DUMMYFUNCTION("""COMPUTED_VALUE"""),94651.84) -> 94651.84 | K7: =IFERROR(__xludf.DUMMYFUNCTION("""COMPUTED_VALUE"""),83786.48) -> 83786.48 | L7: =IFERROR(__xludf.DUMMYFUNCTION("""COMPUTED_VALUE"""),72214.72) -> 72214.72 | M7: =IFERROR(__xludf.DUMMYFUNCTION("""COMPUTED_VALUE"""),76471.28) -> 76471.28 | N7: =IFERROR(__xludf.DUMMYFUNCTION("""COMPUTED_VALUE"""),1235603.76) -> 1235603.8
A8: =IFERROR(__xludf.DUMMYFUNCTION("""COMPUTED_VALUE"""),"Receita com Taxa de Parcelamento Online - Eventos em Geral") -> Receita com Taxa de Parcelamento Online - Eventos em Geral | B8: =IFERROR(__xludf.DUMMYFUNCTION("""COMPUTED_VALUE"""),14836.65984) -> 14836.66 | C8: =IFERROR(__xludf.DUMMYFUNCTION("""COMPUTED_VALUE"""),20365.87968) -> 20365.88 | D8: =IFERROR(__xludf.DUMMYFUNCTION("""COMPUTED_VALUE"""),23708.73024) -> 23708.73 | E8: =IFERROR(__xludf.DUMMYFUNCTION("""COMPUTED_VALUE"""),22732.16832) -> 22732.168 | F8: =IFERROR(__xludf.DUMMYFUNCTION("""COMPUTED_VALUE"""),30370.1184) -> 30370.118 | G8: =IFERROR(__xludf.DUMMYFUNCTION("""COMPUTED_VALUE"""),25958.05056) -> 25958.051 | H8: =IFERROR(__xludf.DUMMYFUNCTION("""COMPUTED_VALUE"""),30683.16288) -> 30683.163 | I8: =IFERROR(__xludf.DUMMYFUNCTION("""COMPUTED_VALUE"""),27576.78912) -> 27576.789 | J8: =IFERROR(__xludf.DUMMYFUNCTION("""COMPUTED_VALUE"""),20444.79744) -> 20444.797 | K8: =IFERROR(__xludf.DUMMYFUNCTION("""COMPUTED_VALUE"""),18097.87968) -> 18097.88 | L8: =IFERROR(__xludf.DUMMYFUNCTION("""COMPUTED_VALUE"""),15598.37952) -> 15598.38 | M8: =IFERROR(__xludf.DUMMYFUNCTION("""COMPUTED_VALUE"""),16517.79648) -> 16517.796 | N8: =IFERROR(__xludf.DUMMYFUNCTION("""COMPUTED_VALUE"""),266890.41216) -> 266890.41
A9: =IFERROR(__xludf.DUMMYFUNCTION("""COMPUTED_VALUE"""),"Receita com Taxa de Cartão") -> Receita com Taxa de Cartão | B9: =IFERROR(__xludf.DUMMYFUNCTION("""COMPUTED_VALUE"""),0) -> 0 | C9: =IFERROR(__xludf.DUMMYFUNCTION("""COMPUTED_VALUE"""),0) -> 0 | D9: =IFERROR(__xludf.DUMMYFUNCTION("""COMPUTED_VALUE"""),0) -> 0 | E9: =IFERROR(__xludf.DUMMYFUNCTION("""COMPUTED_VALUE"""),0) -> 0 | F9: =IFERROR(__xludf.DUMMYFUNCTION("""COMPUTED_VALUE"""),0) -> 0 | G9: =IFERROR(__xludf.DUMMYFUNCTION("""COMPUTED_VALUE"""),0) -> 0 | H9: =IFERROR(__xludf.DUMMYFUNCTION("""COMPUTED_VALUE"""),0) -> 0 | I9: =IFERROR(__xludf.DUMMYFUNCTION("""COMPUTED_VALUE"""),0) -> 0 | ... N9: =IFERROR(__xludf.DUMMYFUNCTION("""COMPUTED_VALUE"""),0) -> 0
A10: =IFERROR(__xludf.DUMMYFUNCTION("""COMPUTED_VALUE"""),"Receita com Taxa de Administração") -> Receita com Taxa de Administração | B10: =IFERROR(__xludf.DUMMYFUNCTION("""COMPUTED_VALUE"""),3570.58436260798) -> 3570.5844 | C10: =IFERROR(__xludf.DUMMYFUNCTION("""COMPUTED_VALUE"""),4901.24410078567) -> 4901.2441 | D10: =IFERROR(__xludf.DUMMYFUNCTION("""COMPUTED_VALUE"""),5705.7331208744) -> 5705.7331 | E10: =IFERROR(__xludf.DUMMYFUNCTION("""COMPUTED_VALUE"""),5470.71413693371) -> 5470.7141 | F10: =IFERROR(__xludf.DUMMYFUNCTION("""COMPUTED_VALUE"""),7308.8600142492) -> 7308.86 | G10: =IFERROR(__xludf.DUMMYFUNCTION("""COMPUTED_VALUE"""),6247.05360996693) -> 6247.0536 | H10: =IFERROR(__xludf.DUMMYFUNCTION("""COMPUTED_VALUE"""),7384.19716810612) -> 7384.1972 | I10: =IFERROR(__xludf.DUMMYFUNCTION("""COMPUTED_VALUE"""),6636.61855597344) -> 6636.6186 | J10: =IFERROR(__xludf.DUMMYFUNCTION("""COMPUTED_VALUE"""),4920.23641595814) -> 4920.2364 | K10: =IFERROR(__xludf.DUMMYFUNCTION("""COMPUTED_VALUE"""),4355.42816770333) -> 4355.4282 | L10: =IFERROR(__xludf.DUMMYFUNCTION("""COMPUTED_VALUE"""),3753.89950276953) -> 3753.8995 | M10: =IFERROR(__xludf.DUMMYFUNCTION("""COMPUTED_VALUE"""),3975.16600449533) -> 3975.166 | N10: =IFERROR(__xludf.DUMMYFUNCTION("""COMPUTED_VALUE"""),64229.7351604238) -> 64229.735
A11: =IFERROR(__xludf.DUMMYFUNCTION("""COMPUTED_VALUE"""),"Receita com Taxa de Processamento") -> Receita com Taxa de Processamento | B11: =IFERROR(__xludf.DUMMYFUNCTION("""COMPUTED_VALUE"""),6131.1123024) -> 6131.1123 | C11: =IFERROR(__xludf.DUMMYFUNCTION("""COMPUTED_VALUE"""),8416.0112048) -> 8416.0112 | D11: =IFERROR(__xludf.DUMMYFUNCTION("""COMPUTED_VALUE"""),9797.4132464) -> 9797.4132 | E11: =IFERROR(__xludf.DUMMYFUNCTION("""COMPUTED_VALUE"""),9393.8580752) -> 9393.8581 | F11: =IFERROR(__xludf.DUMMYFUNCTION("""COMPUTED_VALUE"""),12550.170224) -> 12550.17 | G11: =IFERROR(__xludf.DUMMYFUNCTION("""COMPUTED_VALUE"""),10726.9240416) -> 10726.924 | H11: =IFERROR(__xludf.DUMMYFUNCTION("""COMPUTED_VALUE"""),12679.5329568) -> 12679.533 | I11: =IFERROR(__xludf.DUMMYFUNCTION("""COMPUTED_VALUE"""),11395.8527632) -> 11395.853 | J11: =IFERROR(__xludf.DUMMYFUNCTION("""COMPUTED_VALUE"""),8448.6232384) -> 8448.6232 | K11: =IFERROR(__xludf.DUMMYFUNCTION("""COMPUTED_VALUE"""),7478.7812048) -> 7478.7812 | L11: =IFERROR(__xludf.DUMMYFUNCTION("""COMPUTED_VALUE"""),6445.8859072) -> 6445.8859 | M11: =IFERROR(__xludf.DUMMYFUNCTION("""COMPUTED_VALUE"""),6825.8264528) -> 6825.8265 | N11: =IFERROR(__xludf.DUMMYFUNCTION("""COMPUTED_VALUE"""),110289.9916176) -> 110289.99
A12: =IFERROR(__xludf.DUMMYFUNCTION("""COMPUTED_VALUE"""),"Receita com Taxas de Antecipação") -> Receita com Taxas de Antecipação | B12: =IFERROR(__xludf.DUMMYFUNCTION("""COMPUTED_VALUE"""),2221.09346136182) -> 2221.0935 | C12: =IFERROR(__xludf.DUMMYFUNCTION("""COMPUTED_VALUE"""),3048.83462180458) -> 3048.8346 | D12: =IFERROR(__xludf.DUMMYFUNCTION("""COMPUTED_VALUE"""),3549.26959849039) -> 3549.2696 | E12: =IFERROR(__xludf.DUMMYFUNCTION("""COMPUTED_VALUE"""),3403.07528531491) -> 3403.0753 | F12: =IFERROR(__xludf.DUMMYFUNCTION("""COMPUTED_VALUE"""),4546.49982721612) -> 4546.4998 | G12: =IFERROR(__xludf.DUMMYFUNCTION("""COMPUTED_VALUE"""),3885.99974591825) -> 3885.9997 | H12: =IFERROR(__xludf.DUMMYFUNCTION("""COMPUTED_VALUE"""),4593.36354554232) -> 4593.3635 | I12: =IFERROR(__xludf.DUMMYFUNCTION("""COMPUTED_VALUE"""),4128.32987076057) -> 4128.3299 | J12: =IFERROR(__xludf.DUMMYFUNCTION("""COMPUTED_VALUE"""),3060.64885240712) -> 3060.6489 | K12: =IFERROR(__xludf.DUMMYFUNCTION("""COMPUTED_VALUE"""),2709.30806901622) -> 2709.3081 | L12: =IFERROR(__xludf.DUMMYFUNCTION("""COMPUTED_VALUE"""),2335.12523258821) -> 2335.1252 | M12: =IFERROR(__xludf.DUMMYFUNCTION("""COMPUTED_VALUE"""),2472.7647700679) -> 2472.7648 | N12: =IFERROR(__xludf.DUMMYFUNCTION("""COMPUTED_VALUE"""),39954.3128804884) -> 39954.313
A13: =IFERROR(__xludf.DUMMYFUNCTION("""COMPUTED_VALUE"""),"Receita com Locação de Equipamentos") -> Receita com Locação de Equipamentos | B13: =IFERROR(__xludf.DUMMYFUNCTION("""COMPUTED_VALUE"""),0) -> 0 | C13: =IFERROR(__xludf.DUMMYFUNCTION("""COMPUTED_VALUE"""),0) -> 0 | D13: =IFERROR(__xludf.DUMMYFUNCTION("""COMPUTED_VALUE"""),0) -> 0 | E13: =IFERROR(__xludf.DUMMYFUNCTION("""COMPUTED_VALUE"""),0) -> 0 | F13: =IFERROR(__xludf.DUMMYFUNCTION("""COMPUTED_VALUE"""),0) -> 0 | G13: =IFERROR(__xludf.DUMMYFUNCTION("""COMPUTED_VALUE"""),0) -> 0 | H13: =IFERROR(__xludf.DUMMYFUNCTION("""COMPUTED_VALUE"""),0) -> 0 | I13: =IFERROR(__xludf.DUMMYFUNCTION("""COMPUTED_VALUE"""),0) -> 0 | ... N13: =IFERROR(__xludf.DUMMYFUNCTION("""COMPUTED_VALUE"""),0) -> 0
A14: =IFERROR(__xludf.DUMMYFUNCTION("""COMPUTED_VALUE"""),"Receita com Licença de Uso") -> Receita com Licença de Uso | B14: =IFERROR(__xludf.DUMMYFUNCTION("""COMPUTED_VALUE"""),0) -> 0 | C14: =IFERROR(__xludf.DUMMYFUNCTION("""COMPUTED_VALUE"""),0) -> 0 | D14: =IFERROR(__xludf.DUMMYFUNCTION("""COMPUTED_VALUE"""),0) -> 0 | E14: =IFERROR(__xludf.DUMMYFUNCTION("""COMPUTED_VALUE"""),0) -> 0 | F14: =IFERROR(__xludf.DUMMYFUNCTION("""COMPUTED_VALUE"""),0) -> 0 | G14: =IFERROR(__xludf.DUMMYFUNCTION("""COMPUTED_VALUE"""),0) -> 0 | H14: =IFERROR(__xludf.DUMMYFUNCTION("""COMPUTED_VALUE"""),0) -> 0 | I14: =IFERROR(__xludf.DUMMYFUNCTION("""COMPUTED_VALUE"""),0) -> 0 | ... N14: =IFERROR(__xludf.DUMMYFUNCTION("""COMPUTED_VALUE"""),0) -> 0
A15: =IFERROR(__xludf.DUMMYFUNCTION("""COMPUTED_VALUE"""),"Receita com Venda de QR Code") -> Receita com Venda de QR Code | B15: =IFERROR(__xludf.DUMMYFUNCTION("""COMPUTED_VALUE"""),0) -> 0 | C15: =IFERROR(__xludf.DUMMYFUNCTION("""COMPUTED_VALUE"""),0) -> 0 | D15: =IFERROR(__xludf.DUMMYFUNCTION("""COMPUTED_VALUE"""),0) -> 0 | E15: =IFERROR(__xludf.DUMMYFUNCTION("""COMPUTED_VALUE"""),0) -> 0 | F15: =IFERROR(__xludf.DUMMYFUNCTION("""COMPUTED_VALUE"""),0) -> 0 | G15: =IFERROR(__xludf.DUMMYFUNCTION("""COMPUTED_VALUE"""),0) -> 0 | H15: =IFERROR(__xludf.DUMMYFUNCTION("""COMPUTED_VALUE"""),0) -> 0 | I15: =IFERROR(__xludf.DUMMYFUNCTION("""COMPUTED_VALUE"""),0) -> 0 | ... N15: =IFERROR(__xludf.DUMMYFUNCTION("""COMPUTED_VALUE"""),0) -> 0
A16: =IFERROR(__xludf.DUMMYFUNCTION("""COMPUTED_VALUE"""),"Receita - Comissão Paytime") -> Receita - Comissão Paytime | B16: =IFERROR(__xludf.DUMMYFUNCTION("""COMPUTED_VALUE"""),0) -> 0 | C16: =IFERROR(__xludf.DUMMYFUNCTION("""COMPUTED_VALUE"""),0) -> 0 | D16: =IFERROR(__xludf.DUMMYFUNCTION("""COMPUTED_VALUE"""),0) -> 0 | E16: =IFERROR(__xludf.DUMMYFUNCTION("""COMPUTED_VALUE"""),0) -> 0 | F16: =IFERROR(__xludf.DUMMYFUNCTION("""COMPUTED_VALUE"""),0) -> 0 | G16: =IFERROR(__xludf.DUMMYFUNCTION("""COMPUTED_VALUE"""),0) -> 0 | H16: =IFERROR(__xludf.DUMMYFUNCTION("""COMPUTED_VALUE"""),0) -> 0 | I16: =IFERROR(__xludf.DUMMYFUNCTION("""COMPUTED_VALUE"""),0) -> 0 | ... N16: =IFERROR(__xludf.DUMMYFUNCTION("""COMPUTED_VALUE"""),0) -> 0
A17: =IFERROR(__xludf.DUMMYFUNCTION("""COMPUTED_VALUE"""),"Deduções de Receita") -> Deduções de Receita | B17: =IFERROR(__xludf.DUMMYFUNCTION("""COMPUTED_VALUE"""),-39923.9520169825) -> -39923.952 | C17: =IFERROR(__xludf.DUMMYFUNCTION("""COMPUTED_VALUE"""),-31524.0919270334) -> -31524.092 | D17: =IFERROR(__xludf.DUMMYFUNCTION("""COMPUTED_VALUE"""),-45607.450758784) -> -45607.451 | E17: =IFERROR(__xludf.DUMMYFUNCTION("""COMPUTED_VALUE"""),-35173.8060881399) -> -35173.806 | F17: =IFERROR(__xludf.DUMMYFUNCTION("""COMPUTED_VALUE"""),-44293.6615125653) -> -44293.662 | G17: =IFERROR(__xludf.DUMMYFUNCTION("""COMPUTED_VALUE"""),-36310.4283964524) -> -36310.428 | H17: =IFERROR(__xludf.DUMMYFUNCTION("""COMPUTED_VALUE"""),-47888.9304902977) -> -47888.93 | I17: =IFERROR(__xludf.DUMMYFUNCTION("""COMPUTED_VALUE"""),-51482.3747415681) -> -51482.375 | J17: =IFERROR(__xludf.DUMMYFUNCTION("""COMPUTED_VALUE"""),-43783.7858370819) -> -43783.786 | K17: =IFERROR(__xludf.DUMMYFUNCTION("""COMPUTED_VALUE"""),-41555.7503463456) -> -41555.75 | L17: =IFERROR(__xludf.DUMMYFUNCTION("""COMPUTED_VALUE"""),-51494.0015203243) -> -51494.002 | M17: =IFERROR(__xludf.DUMMYFUNCTION("""COMPUTED_VALUE"""),-54327.9661876355) -> -54327.966 | N17: =IFERROR(__xludf.DUMMYFUNCTION("""COMPUTED_VALUE"""),-523366.199823211) -> -523366.2
A18: =IFERROR(__xludf.DUMMYFUNCTION("""COMPUTED_VALUE"""),"Devoluções de Compra de Serviços (Chargeback)") -> Devoluções de Compra de Serviços (Chargeback) | B18: =IFERROR(__xludf.DUMMYFUNCTION("""COMPUTED_VALUE"""),-3448.9520169825) -> -3448.952 | C18: =IFERROR(__xludf.DUMMYFUNCTION("""COMPUTED_VALUE"""),-2884.09192703345) -> -2884.0919 | D18: =IFERROR(__xludf.DUMMYFUNCTION("""COMPUTED_VALUE"""),-3855.45075878403) -> -3855.4508 | E18: =IFERROR(__xludf.DUMMYFUNCTION("""COMPUTED_VALUE"""),-3124.80608813989) -> -3124.8061 | F18: =IFERROR(__xludf.DUMMYFUNCTION("""COMPUTED_VALUE"""),-3965.66151256534) -> -3965.6615 | G18: =IFERROR(__xludf.DUMMYFUNCTION("""COMPUTED_VALUE"""),-3356.42839645242) -> -3356.4284 | H18: =IFERROR(__xludf.DUMMYFUNCTION("""COMPUTED_VALUE"""),-4256.93049029778) -> -4256.9305 | I18: =IFERROR(__xludf.DUMMYFUNCTION("""COMPUTED_VALUE"""),-4401.37474156818) -> -4401.3747 | J18: =IFERROR(__xludf.DUMMYFUNCTION("""COMPUTED_VALUE"""),-3682.78583708197) -> -3682.7858 | K18: =IFERROR(__xludf.DUMMYFUNCTION("""COMPUTED_VALUE"""),-3531.75034634563) -> -3531.7503 | L18: =IFERROR(__xludf.DUMMYFUNCTION("""COMPUTED_VALUE"""),-4101.00152032433) -> -4101.0015 | M18: =IFERROR(__xludf.DUMMYFUNCTION("""COMPUTED_VALUE"""),-4297.96618763552) -> -4297.9662 | N18: =IFERROR(__xludf.DUMMYFUNCTION("""COMPUTED_VALUE"""),-44907.199823211) -> -44907.2
A19: =IFERROR(__xludf.DUMMYFUNCTION("""COMPUTED_VALUE"""),"Devoluções de Compra (Estornos)") -> Devoluções de Compra (Estornos) | B19: =IFERROR(__xludf.DUMMYFUNCTION("""COMPUTED_VALUE"""),0) -> 0 | C19: =IFERROR(__xludf.DUMMYFUNCTION("""COMPUTED_VALUE"""),0) -> 0 | D19: =IFERROR(__xludf.DUMMYFUNCTION("""COMPUTED_VALUE"""),0) -> 0 | E19: =IFERROR(__xludf.DUMMYFUNCTION("""COMPUTED_VALUE"""),0) -> 0 | F19: =IFERROR(__xludf.DUMMYFUNCTION("""COMPUTED_VALUE"""),0) -> 0 | G19: =IFERROR(__xludf.DUMMYFUNCTION("""COMPUTED_VALUE"""),0) -> 0 | H19: =IFERROR(__xludf.DUMMYFUNCTION("""COMPUTED_VALUE"""),0) -> 0 | I19: =IFERROR(__xludf.DUMMYFUNCTION("""COMPUTED_VALUE"""),0) -> 0 | ... N19: =IFERROR(__xludf.DUMMYFUNCTION("""COMPUTED_VALUE"""),0) -> 0
A20: =IFERROR(__xludf.DUMMYFUNCTION("""COMPUTED_VALUE"""),"Simples Nacional (DAS)") -> Simples Nacional (DAS) | B20: =IFERROR(__xludf.DUMMYFUNCTION("""COMPUTED_VALUE"""),-36475) -> -36475 | C20: =IFERROR(__xludf.DUMMYFUNCTION("""COMPUTED_VALUE"""),-28640) -> -28640 | D20: =IFERROR(__xludf.DUMMYFUNCTION("""COMPUTED_VALUE"""),-41752) -> -41752 | E20: =IFERROR(__xludf.DUMMYFUNCTION("""COMPUTED_VALUE"""),-32049) -> -32049 | F20: =IFERROR(__xludf.DUMMYFUNCTION("""COMPUTED_VALUE"""),-40328) -> -40328 | G20: =IFERROR(__xludf.DUMMYFUNCTION("""COMPUTED_VALUE"""),-32954) -> -32954 | H20: =IFERROR(__xludf.DUMMYFUNCTION("""COMPUTED_VALUE"""),-43632) -> -43632 | I20: =IFERROR(__xludf.DUMMYFUNCTION("""COMPUTED_VALUE"""),-47081) -> -47081 | J20: =IFERROR(__xludf.DUMMYFUNCTION("""COMPUTED_VALUE"""),-40101) -> -40101 | K20: =IFERROR(__xludf.DUMMYFUNCTION("""COMPUTED_VALUE"""),-38024) -> -38024 | L20: =IFERROR(__xludf.DUMMYFUNCTION("""COMPUTED_VALUE"""),-47393) -> -47393 | M20: =IFERROR(__xludf.DUMMYFUNCTION("""COMPUTED_VALUE"""),-50030) -> -50030 | N20: =IFERROR(__xludf.DUMMYFUNCTION("""COMPUTED_VALUE"""),-478459) -> -478459
A21: =IFERROR(__xludf.DUMMYFUNCTION("""COMPUTED_VALUE"""),"Receita Operacional Liquida") -> Receita Operacional Liquida | B21: =IFERROR(__xludf.DUMMYFUNCTION("""COMPUTED_VALUE"""),281266.36366825) -> 281266.36 | C21: =IFERROR(__xludf.DUMMYFUNCTION("""COMPUTED_VALUE"""),231303.259747821) -> 231303.26 | D21: =IFERROR(__xludf.DUMMYFUNCTION("""COMPUTED_VALUE"""),307475.825343505) -> 307475.83 | E21: =IFERROR(__xludf.DUMMYFUNCTION("""COMPUTED_VALUE"""),248899.376631202) -> 248899.38 | F21: =IFERROR(__xludf.DUMMYFUNCTION("""COMPUTED_VALUE"""),315104.551694693) -> 315104.55 | G21: =IFERROR(__xludf.DUMMYFUNCTION("""COMPUTED_VALUE"""),268329.343378869) -> 268329.34 | H21: =IFERROR(__xludf.DUMMYFUNCTION("""COMPUTED_VALUE"""),339686.937623005) -> 339686.94 | I21: =IFERROR(__xludf.DUMMYFUNCTION("""COMPUTED_VALUE"""),352051.721039983) -> 352051.72 | J21: =IFERROR(__xludf.DUMMYFUNCTION("""COMPUTED_VALUE"""),295633.599339825) -> 295633.6 | K21: =IFERROR(__xludf.DUMMYFUNCTION("""COMPUTED_VALUE"""),285566.752352696) -> 285566.75 | L21: =IFERROR(__xludf.DUMMYFUNCTION("""COMPUTED_VALUE"""),331945.933994974) -> 331945.93 | M21: =IFERROR(__xludf.DUMMYFUNCTION("""COMPUTED_VALUE"""),348543.060905724) -> 348543.06 | N21: =IFERROR(__xludf.DUMMYFUNCTION("""COMPUTED_VALUE"""),3605806.72572055) -> 3605806.7
A22: =IFERROR(__xludf.DUMMYFUNCTION("""COMPUTED_VALUE"""),"Custos com os Serviços Prestados") -> Custos com os Serviços Prestados | B22: =IFERROR(__xludf.DUMMYFUNCTION("""COMPUTED_VALUE"""),-70839.9173543627) -> -70839.917 | C22: =IFERROR(__xludf.DUMMYFUNCTION("""COMPUTED_VALUE"""),-57149.2460776148) -> -57149.246 | D22: =IFERROR(__xludf.DUMMYFUNCTION("""COMPUTED_VALUE"""),-76453.7041395721) -> -76453.704 | E22: =IFERROR(__xludf.DUMMYFUNCTION("""COMPUTED_VALUE"""),-61540.5365601339) -> -61540.537 | F22: =IFERROR(__xludf.DUMMYFUNCTION("""COMPUTED_VALUE"""),-85128.2539722517) -> -85128.254 | G22: =IFERROR(__xludf.DUMMYFUNCTION("""COMPUTED_VALUE"""),-65493.1377259527) -> -65493.138 | H22: =IFERROR(__xludf.DUMMYFUNCTION("""COMPUTED_VALUE"""),-83107.3168517209) -> -83107.317 | I22: =IFERROR(__xludf.DUMMYFUNCTION("""COMPUTED_VALUE"""),-87043.6913686561) -> -87043.691 | J22: =IFERROR(__xludf.DUMMYFUNCTION("""COMPUTED_VALUE"""),-73754.213824326) -> -73754.214 | K22: =IFERROR(__xludf.DUMMYFUNCTION("""COMPUTED_VALUE"""),-71846.7912667839) -> -71846.791 | L22: =IFERROR(__xludf.DUMMYFUNCTION("""COMPUTED_VALUE"""),-83958.9330441495) -> -83958.933 | M22: =IFERROR(__xludf.DUMMYFUNCTION("""COMPUTED_VALUE"""),-88444.4427744857) -> -88444.443 | N22: =IFERROR(__xludf.DUMMYFUNCTION("""COMPUTED_VALUE"""),-904760.18496001) -> -904760.18
A23: =IFERROR(__xludf.DUMMYFUNCTION("""COMPUTED_VALUE"""),"Compras de Materia Prima") -> Compras de Materia Prima | B23: =IFERROR(__xludf.DUMMYFUNCTION("""COMPUTED_VALUE"""),0) -> 0 | C23: =IFERROR(__xludf.DUMMYFUNCTION("""COMPUTED_VALUE"""),0) -> 0 | D23: =IFERROR(__xludf.DUMMYFUNCTION("""COMPUTED_VALUE"""),0) -> 0 | E23: =IFERROR(__xludf.DUMMYFUNCTION("""COMPUTED_VALUE"""),0) -> 0 | F23: =IFERROR(__xludf.DUMMYFUNCTION("""COMPUTED_VALUE"""),-7867.6736) -> -7867.6736 | G23: =IFERROR(__xludf.DUMMYFUNCTION("""COMPUTED_VALUE"""),0) -> 0 | H23: =IFERROR(__xludf.DUMMYFUNCTION("""COMPUTED_VALUE"""),0) -> 0 | I23: =IFERROR(__xludf.DUMMYFUNCTION("""COMPUTED_VALUE"""),0) -> 0 | J23: =IFERROR(__xludf.DUMMYFUNCTION("""COMPUTED_VALUE"""),0) -> 0 | K23: =IFERROR(__xludf.DUMMYFUNCTION("""COMPUTED_VALUE"""),0) -> 0 | L23: =IFERROR(__xludf.DUMMYFUNCTION("""COMPUTED_VALUE"""),0) -> 0 | M23: =IFERROR(__xludf.DUMMYFUNCTION("""COMPUTED_VALUE"""),0) -> 0 | N23: =IFERROR(__xludf.DUMMYFUNCTION("""COMPUTED_VALUE"""),-7867.6736) -> -7867.6736
A24: =IFERROR(__xludf.DUMMYFUNCTION("""COMPUTED_VALUE"""),"Custo com Gateway de Pagamento") -> Custo com Gateway de Pagamento | B24: =IFERROR(__xludf.DUMMYFUNCTION("""COMPUTED_VALUE"""),-45591.8946381327) -> -45591.895 | C24: =IFERROR(__xludf.DUMMYFUNCTION("""COMPUTED_VALUE"""),-34987.5266445298) -> -34987.527 | D24: =IFERROR(__xludf.DUMMYFUNCTION("""COMPUTED_VALUE"""),-48041.166546727) -> -48041.167 | E24: =IFERROR(__xludf.DUMMYFUNCTION("""COMPUTED_VALUE"""),-37602.2317654039) -> -37602.232 | F24: =IFERROR(__xludf.DUMMYFUNCTION("""COMPUTED_VALUE"""),-46989.0347020467) -> -46989.035 | G24: =IFERROR(__xludf.DUMMYFUNCTION("""COMPUTED_VALUE"""),-39735.5153948976) -> -39735.515 | H24: =IFERROR(__xludf.DUMMYFUNCTION("""COMPUTED_VALUE"""),-51181.2306217559) -> -51181.231 | I24: =IFERROR(__xludf.DUMMYFUNCTION("""COMPUTED_VALUE"""),-54575.4151702211) -> -54575.415 | J24: =IFERROR(__xludf.DUMMYFUNCTION("""COMPUTED_VALUE"""),-46797.343738951) -> -46797.344 | K24: =IFERROR(__xludf.DUMMYFUNCTION("""COMPUTED_VALUE"""),-45504.4263645039) -> -45504.426 | L24: =IFERROR(__xludf.DUMMYFUNCTION("""COMPUTED_VALUE"""),-54952.1905824845) -> -54952.191 | M24: =IFERROR(__xludf.DUMMYFUNCTION("""COMPUTED_VALUE"""),-57501.6924737157) -> -57501.692 | N24: =IFERROR(__xludf.DUMMYFUNCTION("""COMPUTED_VALUE"""),-563459.66864337) -> -563459.67
A25: =IFERROR(__xludf.DUMMYFUNCTION("""COMPUTED_VALUE"""),"Serviço de Mão de Obra Eventos / Suporte") -> Serviço de Mão de Obra Eventos / Suporte | B25: =IFERROR(__xludf.DUMMYFUNCTION("""COMPUTED_VALUE"""),-2000) -> -2000 | C25: =IFERROR(__xludf.DUMMYFUNCTION("""COMPUTED_VALUE"""),-1800) -> -1800 | D25: =IFERROR(__xludf.DUMMYFUNCTION("""COMPUTED_VALUE"""),-1600) -> -1600 | E25: =IFERROR(__xludf.DUMMYFUNCTION("""COMPUTED_VALUE"""),-1800) -> -1800 | F25: =IFERROR(__xludf.DUMMYFUNCTION("""COMPUTED_VALUE"""),-2000) -> -2000 | G25: =IFERROR(__xludf.DUMMYFUNCTION("""COMPUTED_VALUE"""),-1800) -> -1800 | H25: =IFERROR(__xludf.DUMMYFUNCTION("""COMPUTED_VALUE"""),-1800) -> -1800 | I25: =IFERROR(__xludf.DUMMYFUNCTION("""COMPUTED_VALUE"""),-1800) -> -1800 | J25: =IFERROR(__xludf.DUMMYFUNCTION("""COMPUTED_VALUE"""),-1600) -> -1600 | K25: =IFERROR(__xludf.DUMMYFUNCTION("""COMPUTED_VALUE"""),-2200) -> -2200 | L25: =IFERROR(__xludf.DUMMYFUNCTION("""COMPUTED_VALUE"""),-1600) -> -1600 | M25: =IFERROR(__xludf.DUMMYFUNCTION("""COMPUTED_VALUE"""),-2200) -> -2200 | N25: =IFERROR(__xludf.DUMMYFUNCTION("""COMPUTED_VALUE"""),-22200) -> -22200
A26: =IFERROR(__xludf.DUMMYFUNCTION("""COMPUTED_VALUE"""),"Royalties") -> Royalties | B26: =IFERROR(__xludf.DUMMYFUNCTION("""COMPUTED_VALUE"""),-23248.02271623) -> -23248.023 | C26: =IFERROR(__xludf.DUMMYFUNCTION("""COMPUTED_VALUE"""),-20361.719433085) -> -20361.719 | D26: =IFERROR(__xludf.DUMMYFUNCTION("""COMPUTED_VALUE"""),-26812.537592845) -> -26812.538 | E26: =IFERROR(__xludf.DUMMYFUNCTION("""COMPUTED_VALUE"""),-22138.30479473) -> -22138.305 | F26: =IFERROR(__xludf.DUMMYFUNCTION("""COMPUTED_VALUE"""),-28271.545670205) -> -28271.546 | G26: =IFERROR(__xludf.DUMMYFUNCTION("""COMPUTED_VALUE"""),-23957.622331055) -> -23957.622 | H26: =IFERROR(__xludf.DUMMYFUNCTION("""COMPUTED_VALUE"""),-30126.086229965) -> -30126.086 | I26: =IFERROR(__xludf.DUMMYFUNCTION("""COMPUTED_VALUE"""),-30668.276198435) -> -30668.276 | J26: =IFERROR(__xludf.DUMMYFUNCTION("""COMPUTED_VALUE"""),-25356.870085375) -> -25356.87 | K26: =IFERROR(__xludf.DUMMYFUNCTION("""COMPUTED_VALUE"""),-24142.36490228) -> -24142.365 | L26: =IFERROR(__xludf.DUMMYFUNCTION("""COMPUTED_VALUE"""),-27406.742461665) -> -27406.742 | M26: =IFERROR(__xludf.DUMMYFUNCTION("""COMPUTED_VALUE"""),-28742.75030077) -> -28742.75 | N26: =IFERROR(__xludf.DUMMYFUNCTION("""COMPUTED_VALUE"""),-311232.84271664) -> -311232.84
A27: =IFERROR(__xludf.DUMMYFUNCTION("""COMPUTED_VALUE"""),"Compra de Serviços") -> Compra de Serviços | B27: =IFERROR(__xludf.DUMMYFUNCTION("""COMPUTED_VALUE"""),0) -> 0 | C27: =IFERROR(__xludf.DUMMYFUNCTION("""COMPUTED_VALUE"""),0) -> 0 | D27: =IFERROR(__xludf.DUMMYFUNCTION("""COMPUTED_VALUE"""),0) -> 0 | E27: =IFERROR(__xludf.DUMMYFUNCTION("""COMPUTED_VALUE"""),0) -> 0 | F27: =IFERROR(__xludf.DUMMYFUNCTION("""COMPUTED_VALUE"""),0) -> 0 | G27: =IFERROR(__xludf.DUMMYFUNCTION("""COMPUTED_VALUE"""),0) -> 0 | H27: =IFERROR(__xludf.DUMMYFUNCTION("""COMPUTED_VALUE"""),0) -> 0 | I27: =IFERROR(__xludf.DUMMYFUNCTION("""COMPUTED_VALUE"""),0) -> 0 | ... N27: =IFERROR(__xludf.DUMMYFUNCTION("""COMPUTED_VALUE"""),0) -> 0
A28: =IFERROR(__xludf.DUMMYFUNCTION("""COMPUTED_VALUE"""),"Lucro Operacional Bruto") -> Lucro Operacional Bruto | B28: =IFERROR(__xludf.DUMMYFUNCTION("""COMPUTED_VALUE"""),210426.446313887) -> 210426.45 | C28: =IFERROR(__xludf.DUMMYFUNCTION("""COMPUTED_VALUE"""),174154.013670206) -> 174154.01 | D28: =IFERROR(__xludf.DUMMYFUNCTION("""COMPUTED_VALUE"""),231022.121203933) -> 231022.12 | E28: =IFERROR(__xludf.DUMMYFUNCTION("""COMPUTED_VALUE"""),187358.840071068) -> 187358.84 | F28: =IFERROR(__xludf.DUMMYFUNCTION("""COMPUTED_VALUE"""),229976.297722442) -> 229976.3 | G28: =IFERROR(__xludf.DUMMYFUNCTION("""COMPUTED_VALUE"""),202836.205652917) -> 202836.21 | H28: =IFERROR(__xludf.DUMMYFUNCTION("""COMPUTED_VALUE"""),256579.620771284) -> 256579.62 | I28: =IFERROR(__xludf.DUMMYFUNCTION("""COMPUTED_VALUE"""),265008.029671327) -> 265008.03 | J28: =IFERROR(__xludf.DUMMYFUNCTION("""COMPUTED_VALUE"""),221879.385515499) -> 221879.39 | K28: =IFERROR(__xludf.DUMMYFUNCTION("""COMPUTED_VALUE"""),213719.961085912) -> 213719.96 | L28: =IFERROR(__xludf.DUMMYFUNCTION("""COMPUTED_VALUE"""),247987.000950824) -> 247987 | M28: =IFERROR(__xludf.DUMMYFUNCTION("""COMPUTED_VALUE"""),260098.618131238) -> 260098.62 | N28: =IFERROR(__xludf.DUMMYFUNCTION("""COMPUTED_VALUE"""),2701046.54076054) -> 2701046.5
A29: =IFERROR(__xludf.DUMMYFUNCTION("""COMPUTED_VALUE"""),"Despesas Operacionais") -> Despesas Operacionais | B29: =IFERROR(__xludf.DUMMYFUNCTION("""COMPUTED_VALUE"""),-115619.909455241) -> -115619.91 | C29: =IFERROR(__xludf.DUMMYFUNCTION("""COMPUTED_VALUE"""),-122459.832240344) -> -122459.83 | D29: =IFERROR(__xludf.DUMMYFUNCTION("""COMPUTED_VALUE"""),-119958.295343097) -> -119958.3 | E29: =IFERROR(__xludf.DUMMYFUNCTION("""COMPUTED_VALUE"""),-114712.863336696) -> -114712.86 | F29: =IFERROR(__xludf.DUMMYFUNCTION("""COMPUTED_VALUE"""),-116646.748382568) -> -116646.75 | G29: =IFERROR(__xludf.DUMMYFUNCTION("""COMPUTED_VALUE"""),-115802.718945448) -> -115802.72 | H29: =IFERROR(__xludf.DUMMYFUNCTION("""COMPUTED_VALUE"""),-136920.647383291) -> -136920.65 | I29: =IFERROR(__xludf.DUMMYFUNCTION("""COMPUTED_VALUE"""),-134561.318861798) -> -134561.32 | J29: =IFERROR(__xludf.DUMMYFUNCTION("""COMPUTED_VALUE"""),-122819.387165904) -> -122819.39 | K29: =IFERROR(__xludf.DUMMYFUNCTION("""COMPUTED_VALUE"""),-137373.913842069) -> -137373.91 | L29: =IFERROR(__xludf.DUMMYFUNCTION("""COMPUTED_VALUE"""),-130865.561077823) -> -130865.56 | M29: =IFERROR(__xludf.DUMMYFUNCTION("""COMPUTED_VALUE"""),-149932.474500941) -> -149932.47 | N29: =IFERROR(__xludf.DUMMYFUNCTION("""COMPUTED_VALUE"""),-1517673.67053522) -> -1517673.7
A30: =IFERROR(__xludf.DUMMYFUNCTION("""COMPUTED_VALUE"""),"Despesas de Vendas e Marketing") -> Despesas de Vendas e Marketing | B30: =IFERROR(__xludf.DUMMYFUNCTION("""COMPUTED_VALUE"""),-53255.7895933264) -> -53255.79 | C30: =IFERROR(__xludf.DUMMYFUNCTION("""COMPUTED_VALUE"""),-53170.3049289637) -> -53170.305 | D30: =IFERROR(__xludf.DUMMYFUNCTION("""COMPUTED_VALUE"""),-46890.776472545) -> -46890.776 | E30: =IFERROR(__xludf.DUMMYFUNCTION("""COMPUTED_VALUE"""),-41697.2956871827) -> -41697.296 | F30: =IFERROR(__xludf.DUMMYFUNCTION("""COMPUTED_VALUE"""),-50771.0398787892) -> -50771.04 | G30: =IFERROR(__xludf.DUMMYFUNCTION("""COMPUTED_VALUE"""),-50255.5448550526) -> -50255.545 | H30: =IFERROR(__xludf.DUMMYFUNCTION("""COMPUTED_VALUE"""),-66803.5810160009) -> -66803.581 | I30: =IFERROR(__xludf.DUMMYFUNCTION("""COMPUTED_VALUE"""),-63752.1934963221) -> -63752.193 | J30: =IFERROR(__xludf.DUMMYFUNCTION("""COMPUTED_VALUE"""),-54389.6151295222) -> -54389.615 | K30: =IFERROR(__xludf.DUMMYFUNCTION("""COMPUTED_VALUE"""),-68844.8198108937) -> -68844.82 | L30: =IFERROR(__xludf.DUMMYFUNCTION("""COMPUTED_VALUE"""),-61536.3515200686) -> -61536.352 | M30: =IFERROR(__xludf.DUMMYFUNCTION("""COMPUTED_VALUE"""),-76311.7760691343) -> -76311.776 | N30: =IFERROR(__xludf.DUMMYFUNCTION("""COMPUTED_VALUE"""),-687679.088457801) -> -687679.09
A31: =IFERROR(__xludf.DUMMYFUNCTION("""COMPUTED_VALUE"""),"Comissões de Vendas - Comercial") -> Comissões de Vendas - Comercial | B31: =IFERROR(__xludf.DUMMYFUNCTION("""COMPUTED_VALUE"""),-5496.62203110807) -> -5496.622 | C31: =IFERROR(__xludf.DUMMYFUNCTION("""COMPUTED_VALUE"""),-4497.8398819769) -> -4497.8399 | D31: =IFERROR(__xludf.DUMMYFUNCTION("""COMPUTED_VALUE"""),-6042.41541373748) -> -6042.4154 | E31: =IFERROR(__xludf.DUMMYFUNCTION("""COMPUTED_VALUE"""),-4861.42588468433) -> -4861.4259 | F31: =IFERROR(__xludf.DUMMYFUNCTION("""COMPUTED_VALUE"""),-6150.48474435283) -> -6150.4847 | G31: =IFERROR(__xludf.DUMMYFUNCTION("""COMPUTED_VALUE"""),-5213.38782434826) -> -5213.3878 | H31: =IFERROR(__xludf.DUMMYFUNCTION("""COMPUTED_VALUE"""),-6632.69703774372) -> -6632.697 | I31: =IFERROR(__xludf.DUMMYFUNCTION("""COMPUTED_VALUE"""),-6905.7947667073) -> -6905.7948 | J31: =IFERROR(__xludf.DUMMYFUNCTION("""COMPUTED_VALUE"""),-5808.54710119225) -> -5808.5471 | K31: =IFERROR(__xludf.DUMMYFUNCTION("""COMPUTED_VALUE"""),-5598.14124959132) -> -5598.1412 | L31: =IFERROR(__xludf.DUMMYFUNCTION("""COMPUTED_VALUE"""),-6561.91763647544) -> -6561.9176 | M31: =IFERROR(__xludf.DUMMYFUNCTION("""COMPUTED_VALUE"""),-6894.4474819927) -> -6894.4475 | N31: =IFERROR(__xludf.DUMMYFUNCTION("""COMPUTED_VALUE"""),-70663.7210539106) -> -70663.721
A32: =IFERROR(__xludf.DUMMYFUNCTION("""COMPUTED_VALUE"""),"Comissões de Performance - CS") -> Comissões de Performance - CS | B32: =IFERROR(__xludf.DUMMYFUNCTION("""COMPUTED_VALUE"""),-1722.4653372984) -> -1722.4653 | C32: =IFERROR(__xludf.DUMMYFUNCTION("""COMPUTED_VALUE"""),-1440.3645946468) -> -1440.3646 | D32: =IFERROR(__xludf.DUMMYFUNCTION("""COMPUTED_VALUE"""),-1925.4777274276) -> -1925.4777 | E32: =IFERROR(__xludf.DUMMYFUNCTION("""COMPUTED_VALUE"""),-1560.5813435784) -> -1560.5813 | F32: =IFERROR(__xludf.DUMMYFUNCTION("""COMPUTED_VALUE"""),-1980.5188536164) -> -1980.5189 | G32: =IFERROR(__xludf.DUMMYFUNCTION("""COMPUTED_VALUE"""),-1676.2574664844) -> -1676.2575 | H32: =IFERROR(__xludf.DUMMYFUNCTION("""COMPUTED_VALUE"""),-2125.9835383972) -> -2125.9835 | I32: =IFERROR(__xludf.DUMMYFUNCTION("""COMPUTED_VALUE"""),-2198.1214558748) -> -2198.1215 | J32: =IFERROR(__xludf.DUMMYFUNCTION("""COMPUTED_VALUE"""),-1839.24592683) -> -1839.2459 | K32: =IFERROR(__xludf.DUMMYFUNCTION("""COMPUTED_VALUE"""),-1763.8162321824) -> -1763.8162 | L32: =IFERROR(__xludf.DUMMYFUNCTION("""COMPUTED_VALUE"""),-2048.1099569332) -> -2048.11 | M32: =IFERROR(__xludf.DUMMYFUNCTION("""COMPUTED_VALUE"""),-2146.4774640616) -> -2146.4775 | N32: =IFERROR(__xludf.DUMMYFUNCTION("""COMPUTED_VALUE"""),-22427.4198973312) -> -22427.42
A33: =IFERROR(__xludf.DUMMYFUNCTION("""COMPUTED_VALUE"""),"Marketing") -> Marketing | B33: =IFERROR(__xludf.DUMMYFUNCTION("""COMPUTED_VALUE"""),-3952.5) -> -3952.5 | C33: =IFERROR(__xludf.DUMMYFUNCTION("""COMPUTED_VALUE"""),-15952.5) -> -15952.5 | D33: =IFERROR(__xludf.DUMMYFUNCTION("""COMPUTED_VALUE"""),-4022.5) -> -4022.5 | E33: =IFERROR(__xludf.DUMMYFUNCTION("""COMPUTED_VALUE"""),-3952.5) -> -3952.5 | F33: =IFERROR(__xludf.DUMMYFUNCTION("""COMPUTED_VALUE"""),-3952.5) -> -3952.5 | G33: =IFERROR(__xludf.DUMMYFUNCTION("""COMPUTED_VALUE"""),-3952.5) -> -3952.5 | H33: =IFERROR(__xludf.DUMMYFUNCTION("""COMPUTED_VALUE"""),-11452.5) -> -11452.5 | I33: =IFERROR(__xludf.DUMMYFUNCTION("""COMPUTED_VALUE"""),-6452.5) -> -6452.5 | J33: =IFERROR(__xludf.DUMMYFUNCTION("""COMPUTED_VALUE"""),-6452.5) -> -6452.5 | K33: =IFERROR(__xludf.DUMMYFUNCTION("""COMPUTED_VALUE"""),-16452.5) -> -16452.5 | L33: =IFERROR(__xludf.DUMMYFUNCTION("""COMPUTED_VALUE"""),-1452.5) -> -1452.5 | M33: =IFERROR(__xludf.DUMMYFUNCTION("""COMPUTED_VALUE"""),-1452.5) -> -1452.5 | N33: =IFERROR(__xludf.DUMMYFUNCTION("""COMPUTED_VALUE"""),-79500) -> -79500
A34: =IFERROR(__xludf.DUMMYFUNCTION("""COMPUTED_VALUE"""),"Despesas de Viagens") -> Despesas de Viagens | B34: =IFERROR(__xludf.DUMMYFUNCTION("""COMPUTED_VALUE"""),-500) -> -500 | C34: =IFERROR(__xludf.DUMMYFUNCTION("""COMPUTED_VALUE"""),-500) -> -500 | D34: =IFERROR(__xludf.DUMMYFUNCTION("""COMPUTED_VALUE"""),-500) -> -500 | E34: =IFERROR(__xludf.DUMMYFUNCTION("""COMPUTED_VALUE"""),-500) -> -500 | F34: =IFERROR(__xludf.DUMMYFUNCTION("""COMPUTED_VALUE"""),-500) -> -500 | G34: =IFERROR(__xludf.DUMMYFUNCTION("""COMPUTED_VALUE"""),-500) -> -500 | H34: =IFERROR(__xludf.DUMMYFUNCTION("""COMPUTED_VALUE"""),-500) -> -500 | I34: =IFERROR(__xludf.DUMMYFUNCTION("""COMPUTED_VALUE"""),-500) -> -500 | ... M34: =IFERROR(__xludf.DUMMYFUNCTION("""COMPUTED_VALUE"""),-500) -> -500 | N34: =IFERROR(__xludf.DUMMYFUNCTION("""COMPUTED_VALUE"""),-6000) -> -6000
A35: =IFERROR(__xludf.DUMMYFUNCTION("""COMPUTED_VALUE"""),"Cashback - Afiliados") -> Cashback - Afiliados | B35: =IFERROR(__xludf.DUMMYFUNCTION("""COMPUTED_VALUE"""),-1373.7648) -> -1373.7648 | C35: =IFERROR(__xludf.DUMMYFUNCTION("""COMPUTED_VALUE"""),-1885.7296) -> -1885.7296 | D35: =IFERROR(__xludf.DUMMYFUNCTION("""COMPUTED_VALUE"""),-2195.2528) -> -2195.2528 | E35: =IFERROR(__xludf.DUMMYFUNCTION("""COMPUTED_VALUE"""),-2104.8304) -> -2104.8304 | F35: =IFERROR(__xludf.DUMMYFUNCTION("""COMPUTED_VALUE"""),-2812.048) -> -2812.048 | G35: =IFERROR(__xludf.DUMMYFUNCTION("""COMPUTED_VALUE"""),-2403.5232) -> -2403.5232 | H35: =IFERROR(__xludf.DUMMYFUNCTION("""COMPUTED_VALUE"""),-2841.0336) -> -2841.0336 | I35: =IFERROR(__xludf.DUMMYFUNCTION("""COMPUTED_VALUE"""),-2553.4064) -> -2553.4064 | J35: =IFERROR(__xludf.DUMMYFUNCTION("""COMPUTED_VALUE"""),-1893.0368) -> -1893.0368 | K35: =IFERROR(__xludf.DUMMYFUNCTION("""COMPUTED_VALUE"""),-1675.7296) -> -1675.7296 | L35: =IFERROR(__xludf.DUMMYFUNCTION("""COMPUTED_VALUE"""),-1444.2944) -> -1444.2944 | M35: =IFERROR(__xludf.DUMMYFUNCTION("""COMPUTED_VALUE"""),-1529.4256) -> -1529.4256 | N35: =IFERROR(__xludf.DUMMYFUNCTION("""COMPUTED_VALUE"""),-24712.0752) -> -24712.075
A36: =IFERROR(__xludf.DUMMYFUNCTION("""COMPUTED_VALUE"""),"Cashback - Produtores") -> Cashback - Produtores | B36: =IFERROR(__xludf.DUMMYFUNCTION("""COMPUTED_VALUE"""),-9891.10656) -> -9891.1066 | C36: =IFERROR(__xludf.DUMMYFUNCTION("""COMPUTED_VALUE"""),-13577.25312) -> -13577.253 | D36: =IFERROR(__xludf.DUMMYFUNCTION("""COMPUTED_VALUE"""),-15805.82016) -> -15805.82 | E36: =IFERROR(__xludf.DUMMYFUNCTION("""COMPUTED_VALUE"""),-15154.7788799999) -> -15154.779 | F36: =IFERROR(__xludf.DUMMYFUNCTION("""COMPUTED_VALUE"""),-20246.7456) -> -20246.746 | G36: =IFERROR(__xludf.DUMMYFUNCTION("""COMPUTED_VALUE"""),-17305.36704) -> -17305.367 | H36: =IFERROR(__xludf.DUMMYFUNCTION("""COMPUTED_VALUE"""),-20455.44192) -> -20455.442 | I36: =IFERROR(__xludf.DUMMYFUNCTION("""COMPUTED_VALUE"""),-18384.52608) -> -18384.526 | J36: =IFERROR(__xludf.DUMMYFUNCTION("""COMPUTED_VALUE"""),-13629.86496) -> -13629.865 | K36: =IFERROR(__xludf.DUMMYFUNCTION("""COMPUTED_VALUE"""),-12065.25312) -> -12065.253 | L36: =IFERROR(__xludf.DUMMYFUNCTION("""COMPUTED_VALUE"""),-10398.91968) -> -10398.92 | M36: =IFERROR(__xludf.DUMMYFUNCTION("""COMPUTED_VALUE"""),-11011.86432) -> -11011.864 | N36: =IFERROR(__xludf.DUMMYFUNCTION("""COMPUTED_VALUE"""),-177926.94144) -> -177926.94
A37: =IFERROR(__xludf.DUMMYFUNCTION("""COMPUTED_VALUE"""),"Cashback - Franquias") -> Cashback - Franquias | B37: =IFERROR(__xludf.DUMMYFUNCTION("""COMPUTED_VALUE"""),-15159.6654324599) -> -15159.665 | C37: =IFERROR(__xludf.DUMMYFUNCTION("""COMPUTED_VALUE"""),-7658.30886617) -> -7658.3089 | D37: =IFERROR(__xludf.DUMMYFUNCTION("""COMPUTED_VALUE"""),-8199.65518568999) -> -8199.6552 | E37: =IFERROR(__xludf.DUMMYFUNCTION("""COMPUTED_VALUE"""),-6781.58958946) -> -6781.5896 | F37: =IFERROR(__xludf.DUMMYFUNCTION("""COMPUTED_VALUE"""),-7564.37134041) -> -7564.3713 | G37: =IFERROR(__xludf.DUMMYFUNCTION("""COMPUTED_VALUE"""),-9602.25466211) -> -9602.2547 | H37: =IFERROR(__xludf.DUMMYFUNCTION("""COMPUTED_VALUE"""),-11397.96245993) -> -11397.962 | I37: =IFERROR(__xludf.DUMMYFUNCTION("""COMPUTED_VALUE"""),-13378.92239687) -> -13378.922 | J37: =IFERROR(__xludf.DUMMYFUNCTION("""COMPUTED_VALUE"""),-12133.21017075) -> -12133.21 | K37: =IFERROR(__xludf.DUMMYFUNCTION("""COMPUTED_VALUE"""),-15394.68980456) -> -15394.69 | L37: =IFERROR(__xludf.DUMMYFUNCTION("""COMPUTED_VALUE"""),-19565.30492333) -> -19565.305 | M37: =IFERROR(__xludf.DUMMYFUNCTION("""COMPUTED_VALUE"""),-26388.53060154) -> -26388.531 | N37: =IFERROR(__xludf.DUMMYFUNCTION("""COMPUTED_VALUE"""),-153224.465433279) -> -153224.47
A38: =IFERROR(__xludf.DUMMYFUNCTION("""COMPUTED_VALUE"""),"Cashback - Franqueadora Viva") -> Cashback - Franqueadora Viva | B38: =IFERROR(__xludf.DUMMYFUNCTION("""COMPUTED_VALUE"""),-15159.6654324599) -> -15159.665 | C38: =IFERROR(__xludf.DUMMYFUNCTION("""COMPUTED_VALUE"""),-7658.30886617) -> -7658.3089 | D38: =IFERROR(__xludf.DUMMYFUNCTION("""COMPUTED_VALUE"""),-8199.65518568999) -> -8199.6552 | E38: =IFERROR(__xludf.DUMMYFUNCTION("""COMPUTED_VALUE"""),-6781.58958946) -> -6781.5896 | F38: =IFERROR(__xludf.DUMMYFUNCTION("""COMPUTED_VALUE"""),-7564.37134041) -> -7564.3713 | G38: =IFERROR(__xludf.DUMMYFUNCTION("""COMPUTED_VALUE"""),-9602.25466211) -> -9602.2547 | H38: =IFERROR(__xludf.DUMMYFUNCTION("""COMPUTED_VALUE"""),-11397.96245993) -> -11397.962 | I38: =IFERROR(__xludf.DUMMYFUNCTION("""COMPUTED_VALUE"""),-13378.92239687) -> -13378.922 | J38: =IFERROR(__xludf.DUMMYFUNCTION("""COMPUTED_VALUE"""),-12133.21017075) -> -12133.21 | K38: =IFERROR(__xludf.DUMMYFUNCTION("""COMPUTED_VALUE"""),-15394.68980456) -> -15394.69 | L38: =IFERROR(__xludf.DUMMYFUNCTION("""COMPUTED_VALUE"""),-19565.30492333) -> -19565.305 | M38: =IFERROR(__xludf.DUMMYFUNCTION("""COMPUTED_VALUE"""),-26388.53060154) -> -26388.531 | N38: =IFERROR(__xludf.DUMMYFUNCTION("""COMPUTED_VALUE"""),-153224.465433279) -> -153224.47
A39: =IFERROR(__xludf.DUMMYFUNCTION("""COMPUTED_VALUE"""),"Bonificações") -> Bonificações | B39: =IFERROR(__xludf.DUMMYFUNCTION("""COMPUTED_VALUE"""),0) -> 0 | C39: =IFERROR(__xludf.DUMMYFUNCTION("""COMPUTED_VALUE"""),0) -> 0 | D39: =IFERROR(__xludf.DUMMYFUNCTION("""COMPUTED_VALUE"""),0) -> 0 | E39: =IFERROR(__xludf.DUMMYFUNCTION("""COMPUTED_VALUE"""),0) -> 0 | F39: =IFERROR(__xludf.DUMMYFUNCTION("""COMPUTED_VALUE"""),0) -> 0 | G39: =IFERROR(__xludf.DUMMYFUNCTION("""COMPUTED_VALUE"""),0) -> 0 | H39: =IFERROR(__xludf.DUMMYFUNCTION("""COMPUTED_VALUE"""),0) -> 0 | I39: =IFERROR(__xludf.DUMMYFUNCTION("""COMPUTED_VALUE"""),0) -> 0 | ... N39: =IFERROR(__xludf.DUMMYFUNCTION("""COMPUTED_VALUE"""),0) -> 0
A40: =IFERROR(__xludf.DUMMYFUNCTION("""COMPUTED_VALUE"""),"Despesas com Pessoal") -> Despesas com Pessoal | B40: =IFERROR(__xludf.DUMMYFUNCTION("""COMPUTED_VALUE"""),-52334.8998619148) -> -52334.9 | C40: =IFERROR(__xludf.DUMMYFUNCTION("""COMPUTED_VALUE"""),-52199.4733113806) -> -52199.473 | D40: =IFERROR(__xludf.DUMMYFUNCTION("""COMPUTED_VALUE"""),-55758.4648705519) -> -55758.465 | E40: =IFERROR(__xludf.DUMMYFUNCTION("""COMPUTED_VALUE"""),-55763.633649514) -> -55763.634 | F40: =IFERROR(__xludf.DUMMYFUNCTION("""COMPUTED_VALUE"""),-56325.6085037795) -> -56325.609 | G40: =IFERROR(__xludf.DUMMYFUNCTION("""COMPUTED_VALUE"""),-55917.0740903954) -> -55917.074 | H40: =IFERROR(__xludf.DUMMYFUNCTION("""COMPUTED_VALUE"""),-59940.9663672904) -> -59940.966 | I40: =IFERROR(__xludf.DUMMYFUNCTION("""COMPUTED_VALUE"""),-59460.0253654761) -> -59460.025 | J40: =IFERROR(__xludf.DUMMYFUNCTION("""COMPUTED_VALUE"""),-58981.6720363818) -> -58981.672 | K40: =IFERROR(__xludf.DUMMYFUNCTION("""COMPUTED_VALUE"""),-58889.9440311762) -> -58889.944 | L40: =IFERROR(__xludf.DUMMYFUNCTION("""COMPUTED_VALUE"""),-59310.109557755) -> -59310.11 | M40: =IFERROR(__xludf.DUMMYFUNCTION("""COMPUTED_VALUE"""),-62155.0784318074) -> -62155.078 | N40: =IFERROR(__xludf.DUMMYFUNCTION("""COMPUTED_VALUE"""),-687036.950077423) -> -687036.95
A41: =IFERROR(__xludf.DUMMYFUNCTION("""COMPUTED_VALUE"""),"Salários") -> Salários | B41: =IFERROR(__xludf.DUMMYFUNCTION("""COMPUTED_VALUE"""),-25414.56) -> -25414.56 | C41: =IFERROR(__xludf.DUMMYFUNCTION("""COMPUTED_VALUE"""),-25414.56) -> -25414.56 | D41: =IFERROR(__xludf.DUMMYFUNCTION("""COMPUTED_VALUE"""),-28004.56) -> -28004.56 | E41: =IFERROR(__xludf.DUMMYFUNCTION("""COMPUTED_VALUE"""),-28004.56) -> -28004.56 | F41: =IFERROR(__xludf.DUMMYFUNCTION("""COMPUTED_VALUE"""),-28004.56) -> -28004.56 | G41: =IFERROR(__xludf.DUMMYFUNCTION("""COMPUTED_VALUE"""),-28004.56) -> -28004.56 | H41: =IFERROR(__xludf.DUMMYFUNCTION("""COMPUTED_VALUE"""),-29964.8792) -> -29964.879 | I41: =IFERROR(__xludf.DUMMYFUNCTION("""COMPUTED_VALUE"""),-29964.8792) -> -29964.879 | J41: =IFERROR(__xludf.DUMMYFUNCTION("""COMPUTED_VALUE"""),-29964.8792) -> -29964.879 | K41: =IFERROR(__xludf.DUMMYFUNCTION("""COMPUTED_VALUE"""),-29964.8792) -> -29964.879 | L41: =IFERROR(__xludf.DUMMYFUNCTION("""COMPUTED_VALUE"""),-29964.8792) -> -29964.879 | M41: =IFERROR(__xludf.DUMMYFUNCTION("""COMPUTED_VALUE"""),-29964.8792) -> -29964.879 | N41: =IFERROR(__xludf.DUMMYFUNCTION("""COMPUTED_VALUE"""),-342636.6352) -> -342636.64
A42: =IFERROR(__xludf.DUMMYFUNCTION("""COMPUTED_VALUE"""),"Contratados Pessoa Jurídicas") -> Contratados Pessoa Jurídicas | B42: =IFERROR(__xludf.DUMMYFUNCTION("""COMPUTED_VALUE"""),0) -> 0 | C42: =IFERROR(__xludf.DUMMYFUNCTION("""COMPUTED_VALUE"""),0) -> 0 | D42: =IFERROR(__xludf.DUMMYFUNCTION("""COMPUTED_VALUE"""),0) -> 0 | E42: =IFERROR(__xludf.DUMMYFUNCTION("""COMPUTED_VALUE"""),0) -> 0 | F42: =IFERROR(__xludf.DUMMYFUNCTION("""COMPUTED_VALUE"""),0) -> 0 | G42: =IFERROR(__xludf.DUMMYFUNCTION("""COMPUTED_VALUE"""),0) -> 0 | H42: =IFERROR(__xludf.DUMMYFUNCTION("""COMPUTED_VALUE"""),0) -> 0 | I42: =IFERROR(__xludf.DUMMYFUNCTION("""COMPUTED_VALUE"""),0) -> 0 | ... N42: =IFERROR(__xludf.DUMMYFUNCTION("""COMPUTED_VALUE"""),0) -> 0
A43: =IFERROR(__xludf.DUMMYFUNCTION("""COMPUTED_VALUE"""),"Férias") -> Férias | B43: =IFERROR(__xludf.DUMMYFUNCTION("""COMPUTED_VALUE"""),-3048.9847632) -> -3048.9848 | C43: =IFERROR(__xludf.DUMMYFUNCTION("""COMPUTED_VALUE"""),-3048.9847632) -> -3048.9848 | D43: =IFERROR(__xludf.DUMMYFUNCTION("""COMPUTED_VALUE"""),-3359.7070632) -> -3359.7071 | E43: =IFERROR(__xludf.DUMMYFUNCTION("""COMPUTED_VALUE"""),-3359.7070632) -> -3359.7071 | F43: =IFERROR(__xludf.DUMMYFUNCTION("""COMPUTED_VALUE"""),-3359.7070632) -> -3359.7071 | G43: =IFERROR(__xludf.DUMMYFUNCTION("""COMPUTED_VALUE"""),-3359.7070632) -> -3359.7071 | H43: =IFERROR(__xludf.DUMMYFUNCTION("""COMPUTED_VALUE"""),-3594.886557624) -> -3594.8866 | I43: =IFERROR(__xludf.DUMMYFUNCTION("""COMPUTED_VALUE"""),-3594.886557624) -> -3594.8866 | J43: =IFERROR(__xludf.DUMMYFUNCTION("""COMPUTED_VALUE"""),-3594.886557624) -> -3594.8866 | K43: =IFERROR(__xludf.DUMMYFUNCTION("""COMPUTED_VALUE"""),-3594.886557624) -> -3594.8866 | L43: =IFERROR(__xludf.DUMMYFUNCTION("""COMPUTED_VALUE"""),-3594.886557624) -> -3594.8866 | M43: =IFERROR(__xludf.DUMMYFUNCTION("""COMPUTED_VALUE"""),-3594.886557624) -> -3594.8866 | N43: =IFERROR(__xludf.DUMMYFUNCTION("""COMPUTED_VALUE"""),-41106.117124944) -> -41106.117
A44: =IFERROR(__xludf.DUMMYFUNCTION("""COMPUTED_VALUE"""),"Rescisões") -> Rescisões | B44: =IFERROR(__xludf.DUMMYFUNCTION("""COMPUTED_VALUE"""),0) -> 0 | C44: =IFERROR(__xludf.DUMMYFUNCTION("""COMPUTED_VALUE"""),0) -> 0 | D44: =IFERROR(__xludf.DUMMYFUNCTION("""COMPUTED_VALUE"""),0) -> 0 | E44: =IFERROR(__xludf.DUMMYFUNCTION("""COMPUTED_VALUE"""),0) -> 0 | F44: =IFERROR(__xludf.DUMMYFUNCTION("""COMPUTED_VALUE"""),0) -> 0 | G44: =IFERROR(__xludf.DUMMYFUNCTION("""COMPUTED_VALUE"""),0) -> 0 | H44: =IFERROR(__xludf.DUMMYFUNCTION("""COMPUTED_VALUE"""),0) -> 0 | I44: =IFERROR(__xludf.DUMMYFUNCTION("""COMPUTED_VALUE"""),0) -> 0 | ... N44: =IFERROR(__xludf.DUMMYFUNCTION("""COMPUTED_VALUE"""),0) -> 0
A45: =IFERROR(__xludf.DUMMYFUNCTION("""COMPUTED_VALUE"""),"13º Salário") -> 13º Salário | B45: =IFERROR(__xludf.DUMMYFUNCTION("""COMPUTED_VALUE"""),-2287.3104) -> -2287.3104 | C45: =IFERROR(__xludf.DUMMYFUNCTION("""COMPUTED_VALUE"""),-2287.3104) -> -2287.3104 | D45: =IFERROR(__xludf.DUMMYFUNCTION("""COMPUTED_VALUE"""),-2520.4104) -> -2520.4104 | E45: =IFERROR(__xludf.DUMMYFUNCTION("""COMPUTED_VALUE"""),-2520.4104) -> -2520.4104 | F45: =IFERROR(__xludf.DUMMYFUNCTION("""COMPUTED_VALUE"""),-2520.4104) -> -2520.4104 | G45: =IFERROR(__xludf.DUMMYFUNCTION("""COMPUTED_VALUE"""),-2520.4104) -> -2520.4104 | H45: =IFERROR(__xludf.DUMMYFUNCTION("""COMPUTED_VALUE"""),-2696.839128) -> -2696.8391 | I45: =IFERROR(__xludf.DUMMYFUNCTION("""COMPUTED_VALUE"""),-2696.839128) -> -2696.8391 | J45: =IFERROR(__xludf.DUMMYFUNCTION("""COMPUTED_VALUE"""),-2696.839128) -> -2696.8391 | K45: =IFERROR(__xludf.DUMMYFUNCTION("""COMPUTED_VALUE"""),-2696.839128) -> -2696.8391 | L45: =IFERROR(__xludf.DUMMYFUNCTION("""COMPUTED_VALUE"""),-2696.839128) -> -2696.8391 | M45: =IFERROR(__xludf.DUMMYFUNCTION("""COMPUTED_VALUE"""),-2696.839128) -> -2696.8391 | N45: =IFERROR(__xludf.DUMMYFUNCTION("""COMPUTED_VALUE"""),-30837.297168) -> -30837.297
A46: =IFERROR(__xludf.DUMMYFUNCTION("""COMPUTED_VALUE"""),"INSS") -> INSS | B46: =IFERROR(__xludf.DUMMYFUNCTION("""COMPUTED_VALUE"""),0) -> 0 | C46: =IFERROR(__xludf.DUMMYFUNCTION("""COMPUTED_VALUE"""),0) -> 0 | D46: =IFERROR(__xludf.DUMMYFUNCTION("""COMPUTED_VALUE"""),0) -> 0 | E46: =IFERROR(__xludf.DUMMYFUNCTION("""COMPUTED_VALUE"""),0) -> 0 | F46: =IFERROR(__xludf.DUMMYFUNCTION("""COMPUTED_VALUE"""),0) -> 0 | G46: =IFERROR(__xludf.DUMMYFUNCTION("""COMPUTED_VALUE"""),0) -> 0 | H46: =IFERROR(__xludf.DUMMYFUNCTION("""COMPUTED_VALUE"""),0) -> 0 | I46: =IFERROR(__xludf.DUMMYFUNCTION("""COMPUTED_VALUE"""),0) -> 0 | ... N46: =IFERROR(__xludf.DUMMYFUNCTION("""COMPUTED_VALUE"""),0) -> 0
A47: =IFERROR(__xludf.DUMMYFUNCTION("""COMPUTED_VALUE"""),"FGTS") -> FGTS | B47: =IFERROR(__xludf.DUMMYFUNCTION("""COMPUTED_VALUE"""),-2396.29349871483) -> -2396.2935 | C47: =IFERROR(__xludf.DUMMYFUNCTION("""COMPUTED_VALUE"""),-1960.86694818068) -> -1960.8669 | D47: =IFERROR(__xludf.DUMMYFUNCTION("""COMPUTED_VALUE"""),-2634.23620735197) -> -2634.2362 | E47: =IFERROR(__xludf.DUMMYFUNCTION("""COMPUTED_VALUE"""),-2119.37498631403) -> -2119.375 | F47: =IFERROR(__xludf.DUMMYFUNCTION("""COMPUTED_VALUE"""),-2681.34984057951) -> -2681.3498 | G47: =IFERROR(__xludf.DUMMYFUNCTION("""COMPUTED_VALUE"""),-2272.81542719545) -> -2272.8154 | H47: =IFERROR(__xludf.DUMMYFUNCTION("""COMPUTED_VALUE"""),-2891.57389766645) -> -2891.5739 | I47: =IFERROR(__xludf.DUMMYFUNCTION("""COMPUTED_VALUE"""),-3010.63289585215) -> -3010.6329 | J47: =IFERROR(__xludf.DUMMYFUNCTION("""COMPUTED_VALUE"""),-2532.27956675783) -> -2532.2796 | K47: =IFERROR(__xludf.DUMMYFUNCTION("""COMPUTED_VALUE"""),-2440.5515615522) -> -2440.5516 | L47: =IFERROR(__xludf.DUMMYFUNCTION("""COMPUTED_VALUE"""),-2860.71708813103) -> -2860.7171 | M47: =IFERROR(__xludf.DUMMYFUNCTION("""COMPUTED_VALUE"""),-3005.68596218348) -> -3005.686 | N47: =IFERROR(__xludf.DUMMYFUNCTION("""COMPUTED_VALUE"""),-30806.3778804796) -> -30806.378
A48: =IFERROR(__xludf.DUMMYFUNCTION("""COMPUTED_VALUE"""),"IRRF") -> IRRF | B48: =IFERROR(__xludf.DUMMYFUNCTION("""COMPUTED_VALUE"""),0) -> 0 | C48: =IFERROR(__xludf.DUMMYFUNCTION("""COMPUTED_VALUE"""),0) -> 0 | D48: =IFERROR(__xludf.DUMMYFUNCTION("""COMPUTED_VALUE"""),0) -> 0 | E48: =IFERROR(__xludf.DUMMYFUNCTION("""COMPUTED_VALUE"""),0) -> 0 | F48: =IFERROR(__xludf.DUMMYFUNCTION("""COMPUTED_VALUE"""),0) -> 0 | G48: =IFERROR(__xludf.DUMMYFUNCTION("""COMPUTED_VALUE"""),0) -> 0 | H48: =IFERROR(__xludf.DUMMYFUNCTION("""COMPUTED_VALUE"""),0) -> 0 | I48: =IFERROR(__xludf.DUMMYFUNCTION("""COMPUTED_VALUE"""),0) -> 0 | ... N48: =IFERROR(__xludf.DUMMYFUNCTION("""COMPUTED_VALUE"""),0) -> 0
A49: =IFERROR(__xludf.DUMMYFUNCTION("""COMPUTED_VALUE"""),"Assistência Médica") -> Assistência Médica | B49: =IFERROR(__xludf.DUMMYFUNCTION("""COMPUTED_VALUE"""),-650) -> -650 | C49: =IFERROR(__xludf.DUMMYFUNCTION("""COMPUTED_VALUE"""),-650) -> -650 | D49: =IFERROR(__xludf.DUMMYFUNCTION("""COMPUTED_VALUE"""),-650) -> -650 | E49: =IFERROR(__xludf.DUMMYFUNCTION("""COMPUTED_VALUE"""),-650) -> -650 | F49: =IFERROR(__xludf.DUMMYFUNCTION("""COMPUTED_VALUE"""),-650) -> -650 | G49: =IFERROR(__xludf.DUMMYFUNCTION("""COMPUTED_VALUE"""),-650) -> -650 | H49: =IFERROR(__xludf.DUMMYFUNCTION("""COMPUTED_VALUE"""),-650) -> -650 | I49: =IFERROR(__xludf.DUMMYFUNCTION("""COMPUTED_VALUE"""),-650) -> -650 | ... M49: =IFERROR(__xludf.DUMMYFUNCTION("""COMPUTED_VALUE"""),-650) -> -650 | N49: =IFERROR(__xludf.DUMMYFUNCTION("""COMPUTED_VALUE"""),-7800) -> -7800
A50: =IFERROR(__xludf.DUMMYFUNCTION("""COMPUTED_VALUE"""),"Refeições") -> Refeições | B50: =IFERROR(__xludf.DUMMYFUNCTION("""COMPUTED_VALUE"""),-120) -> -120 | C50: =IFERROR(__xludf.DUMMYFUNCTION("""COMPUTED_VALUE"""),-120) -> -120 | D50: =IFERROR(__xludf.DUMMYFUNCTION("""COMPUTED_VALUE"""),-120) -> -120 | E50: =IFERROR(__xludf.DUMMYFUNCTION("""COMPUTED_VALUE"""),-120) -> -120 | F50: =IFERROR(__xludf.DUMMYFUNCTION("""COMPUTED_VALUE"""),-120) -> -120 | G50: =IFERROR(__xludf.DUMMYFUNCTION("""COMPUTED_VALUE"""),-120) -> -120 | H50: =IFERROR(__xludf.DUMMYFUNCTION("""COMPUTED_VALUE"""),-120) -> -120 | I50: =IFERROR(__xludf.DUMMYFUNCTION("""COMPUTED_VALUE"""),-120) -> -120 | ... M50: =IFERROR(__xludf.DUMMYFUNCTION("""COMPUTED_VALUE"""),-120) -> -120 | N50: =IFERROR(__xludf.DUMMYFUNCTION("""COMPUTED_VALUE"""),-1440) -> -1440
A51: =IFERROR(__xludf.DUMMYFUNCTION("""COMPUTED_VALUE"""),"Vale Refeição") -> Vale Refeição | B51: =IFERROR(__xludf.DUMMYFUNCTION("""COMPUTED_VALUE"""),-5113.97) -> -5113.97 | C51: =IFERROR(__xludf.DUMMYFUNCTION("""COMPUTED_VALUE"""),-5113.97) -> -5113.97 | D51: =IFERROR(__xludf.DUMMYFUNCTION("""COMPUTED_VALUE"""),-5113.97) -> -5113.97 | E51: =IFERROR(__xludf.DUMMYFUNCTION("""COMPUTED_VALUE"""),-5634) -> -5634 | F51: =IFERROR(__xludf.DUMMYFUNCTION("""COMPUTED_VALUE"""),-5634) -> -5634 | G51: =IFERROR(__xludf.DUMMYFUNCTION("""COMPUTED_VALUE"""),-5634) -> -5634 | H51: =IFERROR(__xludf.DUMMYFUNCTION("""COMPUTED_VALUE"""),-6028) -> -6028 | I51: =IFERROR(__xludf.DUMMYFUNCTION("""COMPUTED_VALUE"""),-6028) -> -6028 | J51: =IFERROR(__xludf.DUMMYFUNCTION("""COMPUTED_VALUE"""),-6028) -> -6028 | K51: =IFERROR(__xludf.DUMMYFUNCTION("""COMPUTED_VALUE"""),-6028) -> -6028 | L51: =IFERROR(__xludf.DUMMYFUNCTION("""COMPUTED_VALUE"""),-6028) -> -6028 | M51: =IFERROR(__xludf.DUMMYFUNCTION("""COMPUTED_VALUE"""),-6028) -> -6028 | N51: =IFERROR(__xludf.DUMMYFUNCTION("""COMPUTED_VALUE"""),-68411.91) -> -68411.91
A52: =IFERROR(__xludf.DUMMYFUNCTION("""COMPUTED_VALUE"""),"Vale Transporte / Mobilidade") -> Vale Transporte / Mobilidade | B52: =IFERROR(__xludf.DUMMYFUNCTION("""COMPUTED_VALUE"""),-385) -> -385 | C52: =IFERROR(__xludf.DUMMYFUNCTION("""COMPUTED_VALUE"""),-385) -> -385 | D52: =IFERROR(__xludf.DUMMYFUNCTION("""COMPUTED_VALUE"""),-385) -> -385 | E52: =IFERROR(__xludf.DUMMYFUNCTION("""COMPUTED_VALUE"""),-385) -> -385 | F52: =IFERROR(__xludf.DUMMYFUNCTION("""COMPUTED_VALUE"""),-385) -> -385 | G52: =IFERROR(__xludf.DUMMYFUNCTION("""COMPUTED_VALUE"""),-385) -> -385 | H52: =IFERROR(__xludf.DUMMYFUNCTION("""COMPUTED_VALUE"""),-385) -> -385 | I52: =IFERROR(__xludf.DUMMYFUNCTION("""COMPUTED_VALUE"""),-385) -> -385 | ... M52: =IFERROR(__xludf.DUMMYFUNCTION("""COMPUTED_VALUE"""),-385) -> -385 | N52: =IFERROR(__xludf.DUMMYFUNCTION("""COMPUTED_VALUE"""),-4620) -> -4620
A53: =IFERROR(__xludf.DUMMYFUNCTION("""COMPUTED_VALUE"""),"Seguro de Vida") -> Seguro de Vida | B53: =IFERROR(__xludf.DUMMYFUNCTION("""COMPUTED_VALUE"""),0) -> 0 | C53: =IFERROR(__xludf.DUMMYFUNCTION("""COMPUTED_VALUE"""),0) -> 0 | D53: =IFERROR(__xludf.DUMMYFUNCTION("""COMPUTED_VALUE"""),0) -> 0 | E53: =IFERROR(__xludf.DUMMYFUNCTION("""COMPUTED_VALUE"""),0) -> 0 | F53: =IFERROR(__xludf.DUMMYFUNCTION("""COMPUTED_VALUE"""),0) -> 0 | G53: =IFERROR(__xludf.DUMMYFUNCTION("""COMPUTED_VALUE"""),0) -> 0 | H53: =IFERROR(__xludf.DUMMYFUNCTION("""COMPUTED_VALUE"""),0) -> 0 | I53: =IFERROR(__xludf.DUMMYFUNCTION("""COMPUTED_VALUE"""),0) -> 0 | ... N53: =IFERROR(__xludf.DUMMYFUNCTION("""COMPUTED_VALUE"""),0) -> 0
A54: =IFERROR(__xludf.DUMMYFUNCTION("""COMPUTED_VALUE"""),"Outros Benefícios") -> Outros Benefícios | B54: =IFERROR(__xludf.DUMMYFUNCTION("""COMPUTED_VALUE"""),0) -> 0 | C54: =IFERROR(__xludf.DUMMYFUNCTION("""COMPUTED_VALUE"""),0) -> 0 | D54: =IFERROR(__xludf.DUMMYFUNCTION("""COMPUTED_VALUE"""),0) -> 0 | E54: =IFERROR(__xludf.DUMMYFUNCTION("""COMPUTED_VALUE"""),0) -> 0 | F54: =IFERROR(__xludf.DUMMYFUNCTION("""COMPUTED_VALUE"""),0) -> 0 | G54: =IFERROR(__xludf.DUMMYFUNCTION("""COMPUTED_VALUE"""),0) -> 0 | H54: =IFERROR(__xludf.DUMMYFUNCTION("""COMPUTED_VALUE"""),0) -> 0 | I54: =IFERROR(__xludf.DUMMYFUNCTION("""COMPUTED_VALUE"""),0) -> 0 | ... N54: =IFERROR(__xludf.DUMMYFUNCTION("""COMPUTED_VALUE"""),0) -> 0
A55: =IFERROR(__xludf.DUMMYFUNCTION("""COMPUTED_VALUE"""),"Benefícios - Geral") -> Benefícios - Geral | B55: =IFERROR(__xludf.DUMMYFUNCTION("""COMPUTED_VALUE"""),0) -> 0 | C55: =IFERROR(__xludf.DUMMYFUNCTION("""COMPUTED_VALUE"""),0) -> 0 | D55: =IFERROR(__xludf.DUMMYFUNCTION("""COMPUTED_VALUE"""),0) -> 0 | E55: =IFERROR(__xludf.DUMMYFUNCTION("""COMPUTED_VALUE"""),0) -> 0 | F55: =IFERROR(__xludf.DUMMYFUNCTION("""COMPUTED_VALUE"""),0) -> 0 | G55: =IFERROR(__xludf.DUMMYFUNCTION("""COMPUTED_VALUE"""),0) -> 0 | H55: =IFERROR(__xludf.DUMMYFUNCTION("""COMPUTED_VALUE"""),0) -> 0 | I55: =IFERROR(__xludf.DUMMYFUNCTION("""COMPUTED_VALUE"""),0) -> 0 | ... N55: =IFERROR(__xludf.DUMMYFUNCTION("""COMPUTED_VALUE"""),0) -> 0
A56: =IFERROR(__xludf.DUMMYFUNCTION("""COMPUTED_VALUE"""),"Pró Labore Sócios") -> Pró Labore Sócios | B56: =IFERROR(__xludf.DUMMYFUNCTION("""COMPUTED_VALUE"""),-12000) -> -12000 | C56: =IFERROR(__xludf.DUMMYFUNCTION("""COMPUTED_VALUE"""),-12000) -> -12000 | D56: =IFERROR(__xludf.DUMMYFUNCTION("""COMPUTED_VALUE"""),-12000) -> -12000 | E56: =IFERROR(__xludf.DUMMYFUNCTION("""COMPUTED_VALUE"""),-12000) -> -12000 | F56: =IFERROR(__xludf.DUMMYFUNCTION("""COMPUTED_VALUE"""),-12000) -> -12000 | G56: =IFERROR(__xludf.DUMMYFUNCTION("""COMPUTED_VALUE"""),-12000) -> -12000 | H56: =IFERROR(__xludf.DUMMYFUNCTION("""COMPUTED_VALUE"""),-12000) -> -12000 | I56: =IFERROR(__xludf.DUMMYFUNCTION("""COMPUTED_VALUE"""),-12000) -> -12000 | ... M56: =IFERROR(__xludf.DUMMYFUNCTION("""COMPUTED_VALUE"""),-12000) -> -12000 | N56: =IFERROR(__xludf.DUMMYFUNCTION("""COMPUTED_VALUE"""),-144000) -> -144000
A57: =IFERROR(__xludf.DUMMYFUNCTION("""COMPUTED_VALUE"""),"Outros ( Contribuição Sindical - PCMO, Exames...)") -> Outros ( Contribuição Sindical - PCMO, Exames...) | B57: =IFERROR(__xludf.DUMMYFUNCTION("""COMPUTED_VALUE"""),-110.49) -> -110.49 | C57: =IFERROR(__xludf.DUMMYFUNCTION("""COMPUTED_VALUE"""),-110.49) -> -110.49 | D57: =IFERROR(__xludf.DUMMYFUNCTION("""COMPUTED_VALUE"""),-110.49) -> -110.49 | E57: =IFERROR(__xludf.DUMMYFUNCTION("""COMPUTED_VALUE"""),-110.49) -> -110.49 | F57: =IFERROR(__xludf.DUMMYFUNCTION("""COMPUTED_VALUE"""),-110.49) -> -110.49 | G57: =IFERROR(__xludf.DUMMYFUNCTION("""COMPUTED_VALUE"""),-110.49) -> -110.49 | H57: =IFERROR(__xludf.DUMMYFUNCTION("""COMPUTED_VALUE"""),-110.49) -> -110.49 | I57: =IFERROR(__xludf.DUMMYFUNCTION("""COMPUTED_VALUE"""),-110.49) -> -110.49 | ... M57: =IFERROR(__xludf.DUMMYFUNCTION("""COMPUTED_VALUE"""),-110.49) -> -110.49 | N57: =IFERROR(__xludf.DUMMYFUNCTION("""COMPUTED_VALUE"""),-1325.87999999999) -> -1325.88
A58: =IFERROR(__xludf.DUMMYFUNCTION("""COMPUTED_VALUE"""),"Capacitação e Treinamentos") -> Capacitação e Treinamentos | B58: =IFERROR(__xludf.DUMMYFUNCTION("""COMPUTED_VALUE"""),-508.2912) -> -508.2912 | C58: =IFERROR(__xludf.DUMMYFUNCTION("""COMPUTED_VALUE"""),-508.2912) -> -508.2912 | D58: =IFERROR(__xludf.DUMMYFUNCTION("""COMPUTED_VALUE"""),-560.0912) -> -560.0912 | E58: =IFERROR(__xludf.DUMMYFUNCTION("""COMPUTED_VALUE"""),-560.0912) -> -560.0912 | F58: =IFERROR(__xludf.DUMMYFUNCTION("""COMPUTED_VALUE"""),-560.0912) -> -560.0912 | G58: =IFERROR(__xludf.DUMMYFUNCTION("""COMPUTED_VALUE"""),-560.0912) -> -560.0912 | H58: =IFERROR(__xludf.DUMMYFUNCTION("""COMPUTED_VALUE"""),-599.297584) -> -599.29758 | I58: =IFERROR(__xludf.DUMMYFUNCTION("""COMPUTED_VALUE"""),-599.297584) -> -599.29758 | J58: =IFERROR(__xludf.DUMMYFUNCTION("""COMPUTED_VALUE"""),-599.297584) -> -599.29758 | K58: =IFERROR(__xludf.DUMMYFUNCTION("""COMPUTED_VALUE"""),-599.297584) -> -599.29758 | L58: =IFERROR(__xludf.DUMMYFUNCTION("""COMPUTED_VALUE"""),-599.297584) -> -599.29758 | M58: =IFERROR(__xludf.DUMMYFUNCTION("""COMPUTED_VALUE"""),-599.297584) -> -599.29758 | N58: =IFERROR(__xludf.DUMMYFUNCTION("""COMPUTED_VALUE"""),-6852.73270399999) -> -6852.7327
A59: =IFERROR(__xludf.DUMMYFUNCTION("""COMPUTED_VALUE"""),"Endomarketing") -> Endomarketing | B59: =IFERROR(__xludf.DUMMYFUNCTION("""COMPUTED_VALUE"""),-300) -> -300 | C59: =IFERROR(__xludf.DUMMYFUNCTION("""COMPUTED_VALUE"""),-600) -> -600 | D59: =IFERROR(__xludf.DUMMYFUNCTION("""COMPUTED_VALUE"""),-300) -> -300 | E59: =IFERROR(__xludf.DUMMYFUNCTION("""COMPUTED_VALUE"""),-300) -> -300 | F59: =IFERROR(__xludf.DUMMYFUNCTION("""COMPUTED_VALUE"""),-300) -> -300 | G59: =IFERROR(__xludf.DUMMYFUNCTION("""COMPUTED_VALUE"""),-300) -> -300 | H59: =IFERROR(__xludf.DUMMYFUNCTION("""COMPUTED_VALUE"""),-900) -> -900 | I59: =IFERROR(__xludf.DUMMYFUNCTION("""COMPUTED_VALUE"""),-300) -> -300 | J59: =IFERROR(__xludf.DUMMYFUNCTION("""COMPUTED_VALUE"""),-300) -> -300 | K59: =IFERROR(__xludf.DUMMYFUNCTION("""COMPUTED_VALUE"""),-300) -> -300 | L59: =IFERROR(__xludf.DUMMYFUNCTION("""COMPUTED_VALUE"""),-300) -> -300 | M59: =IFERROR(__xludf.DUMMYFUNCTION("""COMPUTED_VALUE"""),-3000) -> -3000 | N59: =IFERROR(__xludf.DUMMYFUNCTION("""COMPUTED_VALUE"""),-7200) -> -7200
A60: =IFERROR(__xludf.DUMMYFUNCTION("""COMPUTED_VALUE"""),"Bônus") -> Bônus | B60: =IFERROR(__xludf.DUMMYFUNCTION("""COMPUTED_VALUE"""),0) -> 0 | C60: =IFERROR(__xludf.DUMMYFUNCTION("""COMPUTED_VALUE"""),0) -> 0 | D60: =IFERROR(__xludf.DUMMYFUNCTION("""COMPUTED_VALUE"""),0) -> 0 | E60: =IFERROR(__xludf.DUMMYFUNCTION("""COMPUTED_VALUE"""),0) -> 0 | F60: =IFERROR(__xludf.DUMMYFUNCTION("""COMPUTED_VALUE"""),0) -> 0 | G60: =IFERROR(__xludf.DUMMYFUNCTION("""COMPUTED_VALUE"""),0) -> 0 | H60: =IFERROR(__xludf.DUMMYFUNCTION("""COMPUTED_VALUE"""),0) -> 0 | I60: =IFERROR(__xludf.DUMMYFUNCTION("""COMPUTED_VALUE"""),0) -> 0 | ... N60: =IFERROR(__xludf.DUMMYFUNCTION("""COMPUTED_VALUE"""),0) -> 0
A61: =IFERROR(__xludf.DUMMYFUNCTION("""COMPUTED_VALUE"""),"Despesas Administrativas") -> Despesas Administrativas | B61: =IFERROR(__xludf.DUMMYFUNCTION("""COMPUTED_VALUE"""),-9869.22) -> -9869.22 | C61: =IFERROR(__xludf.DUMMYFUNCTION("""COMPUTED_VALUE"""),-16930.054) -> -16930.054 | D61: =IFERROR(__xludf.DUMMYFUNCTION("""COMPUTED_VALUE"""),-17149.054) -> -17149.054 | E61: =IFERROR(__xludf.DUMMYFUNCTION("""COMPUTED_VALUE"""),-17091.934) -> -17091.934 | F61: =IFERROR(__xludf.DUMMYFUNCTION("""COMPUTED_VALUE"""),-9390.1) -> -9390.1 | G61: =IFERROR(__xludf.DUMMYFUNCTION("""COMPUTED_VALUE"""),-9470.1) -> -9470.1 | H61: =IFERROR(__xludf.DUMMYFUNCTION("""COMPUTED_VALUE"""),-10016.1) -> -10016.1 | I61: =IFERROR(__xludf.DUMMYFUNCTION("""COMPUTED_VALUE"""),-11189.1) -> -11189.1 | J61: =IFERROR(__xludf.DUMMYFUNCTION("""COMPUTED_VALUE"""),-9288.1) -> -9288.1 | K61: =IFERROR(__xludf.DUMMYFUNCTION("""COMPUTED_VALUE"""),-9479.15) -> -9479.15 | L61: =IFERROR(__xludf.DUMMYFUNCTION("""COMPUTED_VALUE"""),-9859.1) -> -9859.1 | M61: =IFERROR(__xludf.DUMMYFUNCTION("""COMPUTED_VALUE"""),-11305.6199999999) -> -11305.62 | N61: =IFERROR(__xludf.DUMMYFUNCTION("""COMPUTED_VALUE"""),-141037.632) -> -141037.63
A62: =IFERROR(__xludf.DUMMYFUNCTION("""COMPUTED_VALUE"""),"Aluguel") -> Aluguel | B62: =IFERROR(__xludf.DUMMYFUNCTION("""COMPUTED_VALUE"""),0) -> 0 | C62: =IFERROR(__xludf.DUMMYFUNCTION("""COMPUTED_VALUE"""),0) -> 0 | D62: =IFERROR(__xludf.DUMMYFUNCTION("""COMPUTED_VALUE"""),0) -> 0 | E62: =IFERROR(__xludf.DUMMYFUNCTION("""COMPUTED_VALUE"""),0) -> 0 | F62: =IFERROR(__xludf.DUMMYFUNCTION("""COMPUTED_VALUE"""),0) -> 0 | G62: =IFERROR(__xludf.DUMMYFUNCTION("""COMPUTED_VALUE"""),0) -> 0 | H62: =IFERROR(__xludf.DUMMYFUNCTION("""COMPUTED_VALUE"""),0) -> 0 | I62: =IFERROR(__xludf.DUMMYFUNCTION("""COMPUTED_VALUE"""),0) -> 0 | ... N62: =IFERROR(__xludf.DUMMYFUNCTION("""COMPUTED_VALUE"""),0) -> 0
