Workbook

Sheet Resultados
F2: janeiro | G2: fevereiro | H2: março | I2: abril | J2: maio | K2: junho | L2: julho | M2: agosto | N2: setembro | O2: outubro | P2: novembro | Q2: dezembro | R2: 2026 | T2: 1 SEM | U2: 2 SEM | V2: 2024
B4: Receita Operacional Bruta | F4: =F5+F8+F11+F14+F15+F16+F17+F21+F22+F23 -> 1686702.6 | G4: =G5+G8+G11+G14+G15+G16+G17+G21+G22+G23 -> 1279880.2 | H4: =H5+H8+H11+H14+H15+H16+H17+H21+H22+H23 -> 1452060.6 | I4: =I5+I8+I11+I14+I15+I16+I17+I21+I22+I23 -> 1422561.5 | J4: =J5+J8+J11+J14+J15+J16+J17+J21+J22+J23 -> 1596280.6 | K4: =K5+K8+K11+K14+K15+K16+K17+K21+K22+K23 -> 1566052 | L4: =L5+L8+L11+L14+L15+L16+L17+L21+L22+L23 -> 1647475.2 | M4: =M5+M8+M11+M14+M15+M16+M17+M21+M22+M23 -> 1388629.3 | ... R4: =R5+R8+R11+R14+R15+R16+R17+R21+R22+R23 -> 12039642 | T4: =SUM(F4:K4) -> 9003537.4 | U4: =SUM(L4:Q4) -> 3036104.5 | V4: =T4+U4 -> 12039642
C5: Royalties | F5: =SUM(F6:F7) -> 858569.87 | G5: =SUM(G6:G7) -> 598623.74 | H5: =SUM(H6:H7) -> 606841.34 | I5: =SUM(I6:I7) -> 632427.22 | J5: =SUM(J6:J7) -> 530748.99 | K5: =SUM(K6:K7) -> 750091.11 | L5: =SUM(L6:L7) -> 765899.31 | M5: =SUM(M6:M7) -> 606346.88 | ... R5: =SUM(R6:R7) -> 5349548.5 | T5: =SUM(F5:K5) -> 3977302.3 | U5: =SUM(L5:Q5) -> 1372246.2 | V5: =T5+U5 -> 5349548.5
D6: Royalties - Recorrentes | F6: ='Cálculos de Impostos'!F6 -> 742596.16 | G6: ='Cálculos de Impostos'!G6 -> 520688.71 | H6: ='Cálculos de Impostos'!H6 -> 578703 | I6: ='Cálculos de Impostos'!I6 -> 609147.54 | J6: ='Cálculos de Impostos'!J6 -> 518335.49 | K6: ='Cálculos de Impostos'!K6 -> 638364.5 | L6: ='Cálculos de Impostos'!L6 -> 678311.33 | M6: ='Cálculos de Impostos'!M6 -> 534530.06 | ... Q6: ='Cálculos de Impostos'!Q6 -> 0 | R6: =SUM(F6:Q6) -> 4820676.8 | T6: =SUM(F6:K6) -> 3607835.4 | U6: =SUM(L6:Q6) -> 1212841.4 | V6: =T6+U6 -> 4820676.8
D7: Royalties - Fechamentos | F7: ='Cálculos de Impostos'!F7 -> 115973.71 | G7: ='Cálculos de Impostos'!G7 -> 77935.03 | H7: ='Cálculos de Impostos'!H7 -> 28138.34 | I7: ='Cálculos de Impostos'!I7 -> 23279.68 | J7: ='Cálculos de Impostos'!J7 -> 12413.5 | K7: ='Cálculos de Impostos'!K7 -> 111726.61 | L7: ='Cálculos de Impostos'!L7 -> 87587.98 | M7: ='Cálculos de Impostos'!M7 -> 71816.82 | ... Q7: ='Cálculos de Impostos'!Q7 -> 0 | R7: =SUM(F7:Q7) -> 528871.67 | T7: =SUM(F7:K7) -> 369466.87 | U7: =SUM(L7:Q7) -> 159404.8 | V7: =T7+U7 -> 528871.67
C8: Fundo de Marketing | F8: =SUM(F9:F10) -> 53494.86 | G8: =SUM(G9:G10) -> 36027.51 | H8: =SUM(H9:H10) -> 40270.14 | I8: =SUM(I9:I10) -> 37264.5 | J8: =SUM(J9:J10) -> 36951.48 | K8: =SUM(K9:K10) -> 46118.45 | L8: =SUM(L9:L10) -> 45244.39 | M8: =SUM(M9:M10) -> 38702.04 | ... R8: =SUM(R9:R10) -> 334073.37 | T8: =SUM(F8:K8) -> 250126.94 | U8: =SUM(L8:Q8) -> 83946.43 | V8: =T8+U8 -> 334073.37
D9: Fundo de Marketing - Recorrentes | F9: ='Cálculos de Impostos'!F9 -> 46209.41 | G9: ='Cálculos de Impostos'!G9 -> 30939.14 | H9: ='Cálculos de Impostos'!H9 -> 38474.08 | I9: ='Cálculos de Impostos'!I9 -> 35766.61 | J9: ='Cálculos de Impostos'!J9 -> 32874.72 | K9: ='Cálculos de Impostos'!K9 -> 44826.72 | L9: ='Cálculos de Impostos'!L9 -> 43952.66 | M9: ='Cálculos de Impostos'!M9 -> 36368.87 | ... Q9: ='Cálculos de Impostos'!Q9 -> 0 | R9: =SUM(F9:Q9) -> 309412.21 | T9: =SUM(F9:K9) -> 229090.68 | U9: =SUM(L9:Q9) -> 80321.53 | V9: =T9+U9 -> 309412.21
D10: Fundo de Marketing - Fechamentos | F10: ='Cálculos de Impostos'!F10 -> 7285.45 | G10: ='Cálculos de Impostos'!G10 -> 5088.37 | H10: ='Cálculos de Impostos'!H10 -> 1796.06 | I10: ='Cálculos de Impostos'!I10 -> 1497.89 | J10: ='Cálculos de Impostos'!J10 -> 4076.76 | K10: ='Cálculos de Impostos'!K10 -> 1291.73 | L10: ='Cálculos de Impostos'!L10 -> 1291.73 | M10: ='Cálculos de Impostos'!M10 -> 2333.17 | ... Q10: ='Cálculos de Impostos'!Q10 -> 0 | R10: =SUM(F10:Q10) -> 24661.16 | T10: =SUM(F10:K10) -> 21036.26 | U10: =SUM(L10:Q10) -> 3624.9 | V10: =T10+U10 -> 24661.16
C11: Taxas de Franquias | F11: =F12+F13 -> 0 | G11: =G12+G13 -> 0 | H11: =H12+H13 -> 0 | I11: =I12+I13 -> 0 | J11: =J12+J13 -> 0 | K11: =K12+K13 -> 0 | L11: =L12+L13 -> 0 | M11: =M12+M13 -> 0 | ... R11: =R12+R13 -> 0 | T11: =SUM(F11:K11) -> 0 | U11: =SUM(L11:Q11) -> 0 | V11: =T11+U11 -> 0
D12: Taxa Inicial de Franquia | F12: ='Cálculos de Impostos'!F12 -> 0 | G12: ='Cálculos de Impostos'!G12 -> 0 | H12: ='Cálculos de Impostos'!H12 -> 0 | I12: ='Cálculos de Impostos'!I12 -> 0 | J12: ='Cálculos de Impostos'!J12 -> 0 | K12: ='Cálculos de Impostos'!K12 -> 0 | L12: ='Cálculos de Impostos'!L12 -> 0 | M12: ='Cálculos de Impostos'!M12 -> 0 | ... Q12: ='Cálculos de Impostos'!Q12 -> 0 | R12: =SUM(F12:Q12) -> 0 | T12: =SUM(F12:K12) -> 0 | U12: =SUM(L12:Q12) -> 0 | V12: =T12+U12 -> 0
D13: Renovação de Franquias | F13: ='Cálculos de Impostos'!F13 -> 0 | G13: ='Cálculos de Impostos'!G13 -> 0 | H13: ='Cálculos de Impostos'!H13 -> 0 | I13: ='Cálculos de Impostos'!I13 -> 0 | J13: ='Cálculos de Impostos'!J13 -> 0 | K13: ='Cálculos de Impostos'!K13 -> 0 | L13: ='Cálculos de Impostos'!L13 -> 0 | M13: ='Cálculos de Impostos'!M13 -> 0 | ... Q13: ='Cálculos de Impostos'!Q13 -> 0 | R13: =SUM(F13:Q13) -> 0 | T13: =SUM(F13:K13) -> 0 | U13: =SUM(L13:Q13) -> 0 | V13: =T13+U13 -> 0
C14: Receita com Patrocínios | F14: ='Cálculos de Impostos'!F14 -> 0 | G14: ='Cálculos de Impostos'!G14 -> 0 | H14: ='Cálculos de Impostos'!H14 -> 0 | I14: ='Cálculos de Impostos'!I14 -> 0 | J14: ='Cálculos de Impostos'!J14 -> 0 | K14: ='Cálculos de Impostos'!K14 -> 0 | L14: ='Cálculos de Impostos'!L14 -> 0 | M14: ='Cálculos de Impostos'!M14 -> 0 | ... Q14: ='Cálculos de Impostos'!Q14 -> 0 | R14: =SUM(F14:Q14) -> 0 | T14: =SUM(F14:K14) -> 0 | U14: =SUM(L14:Q14) -> 0 | V14: =T14+U14 -> 0
C15: Receita SPDX | F15: ='Cálculos de Impostos'!F15 -> 435100.22 | G15: ='Cálculos de Impostos'!G15 -> 385150.49 | H15: ='Cálculos de Impostos'!H15 -> 538232.09 | I15: ='Cálculos de Impostos'!I15 -> 487174.31 | J15: ='Cálculos de Impostos'!J15 -> 486610.35 | K15: ='Cálculos de Impostos'!K15 -> 486259.18 | L15: ='Cálculos de Impostos'!L15 -> 517608.2 | M15: ='Cálculos de Impostos'!M15 -> 467285.15 | ... Q15: ='Cálculos de Impostos'!Q15 -> 0 | R15: =SUM(F15:Q15) -> 3803420 | T15: =SUM(F15:K15) -> 2818526.6 | U15: =SUM(L15:Q15) -> 984893.35 | V15: =T15+U15 -> 3803420
C16: Receitas - Taxa Mundo Viva | F16: ='Cálculos de Impostos'!F16 -> 76119.7 | G16: ='Cálculos de Impostos'!G16 -> 73017 | H16: ='Cálculos de Impostos'!H16 -> 71232.9 | I16: ='Cálculos de Impostos'!I16 -> 70336.1 | J16: ='Cálculos de Impostos'!J16 -> 73790.3 | K16: ='Cálculos de Impostos'!K16 -> 73663 | L16: ='Cálculos de Impostos'!L16 -> 76239.4 | M16: ='Cálculos de Impostos'!M16 -> 77537.1 | ... Q16: ='Cálculos de Impostos'!Q16 -> 0 | R16: =SUM(F16:Q16) -> 591935.5 | T16: =SUM(F16:K16) -> 438159 | U16: =SUM(L16:Q16) -> 153776.5 | V16: =T16+U16 -> 591935.5
C17: Receitas - Markup de Tarifas | F17: =F18+F19+F20 -> 175537.31 | G17: =G18+G19+G20 -> 105459.15 | H17: =H18+H19+H20 -> 115377.65 | I17: =I18+I19+I20 -> 107690.23 | J17: =J18+J19+J20 -> 125373.64 | K17: =K18+K19+K20 -> 130235.64 | L17: =L18+L19+L20 -> 159580.33 | M17: =M18+M19+M20 -> 110404.67 | ... R17: =R18+R19+R20 -> 1029658.6 | T17: =SUM(F17:K17) -> 759673.62 | U17: =SUM(L17:Q17) -> 269985 | V17: =T17+U17 -> 1029658.6
D18: Markup de Liquidação de boletos | F18: ='Cálculos de Impostos'!F18 -> 33721.79 | G18: ='Cálculos de Impostos'!G18 -> 29503.82 | H18: ='Cálculos de Impostos'!H18 -> 37861.57 | I18: ='Cálculos de Impostos'!I18 -> 31977.18 | J18: ='Cálculos de Impostos'!J18 -> 32255.93 | K18: ='Cálculos de Impostos'!K18 -> 37591.02 | L18: ='Cálculos de Impostos'!L18 -> 39603.36 | M18: ='Cálculos de Impostos'!M18 -> 36696.37 | ... Q18: ='Cálculos de Impostos'!Q18 -> 0 | R18: =SUM(F18:Q18) -> 279211.04 | T18: =SUM(F18:K18) -> 202911.31 | U18: =SUM(L18:Q18) -> 76299.73 | V18: =T18+U18 -> 279211.04
D19: Markup de cartão | F19: ='Cálculos de Impostos'!F19 -> 138056.49 | G19: ='Cálculos de Impostos'!G19 -> 72990.74 | H19: ='Cálculos de Impostos'!H19 -> 73001.08 | I19: ='Cálculos de Impostos'!I19 -> 73181.66 | J19: ='Cálculos de Impostos'!J19 -> 90920.72 | K19: ='Cálculos de Impostos'!K19 -> 89856.48 | L19: ='Cálculos de Impostos'!L19 -> 116286.7 | M19: ='Cálculos de Impostos'!M19 -> 70079.12 | ... Q19: ='Cálculos de Impostos'!Q19 -> 0 | R19: =SUM(F19:Q19) -> 724372.99 | T19: =SUM(F19:K19) -> 538007.17 | U19: =SUM(L19:Q19) -> 186365.82 | V19: =T19+U19 -> 724372.99
D20: Markup de tarifas bancárias | F20: ='Cálculos de Impostos'!F20 -> 3759.03 | G20: ='Cálculos de Impostos'!G20 -> 2964.59 | H20: ='Cálculos de Impostos'!H20 -> 4515 | I20: ='Cálculos de Impostos'!I20 -> 2531.39 | J20: ='Cálculos de Impostos'!J20 -> 2196.99 | K20: ='Cálculos de Impostos'!K20 -> 2788.14 | L20: ='Cálculos de Impostos'!L20 -> 3690.27 | M20: ='Cálculos de Impostos'!M20 -> 3629.18 | ... Q20: ='Cálculos de Impostos'!Q20 -> 0 | R20: =SUM(F20:Q20) -> 26074.59 | T20: =SUM(F20:K20) -> 18755.14 | U20: =SUM(L20:Q20) -> 7319.45 | V20: =T20+U20 -> 26074.59
C21: Receitas - Festas de Arrecadação | F21: ='Cálculos de Impostos'!F21 -> 3762.29 | G21: ='Cálculos de Impostos'!G21 -> 6307.8 | H21: ='Cálculos de Impostos'!H21 -> 6771.63 | I21: ='Cálculos de Impostos'!I21 -> 7115.56 | J21: ='Cálculos de Impostos'!J21 -> 263540.41 | K21: ='Cálculos de Impostos'!K21 -> 12085.48 | L21: ='Cálculos de Impostos'!L21 -> 9083.4 | M21: ='Cálculos de Impostos'!M21 -> 10163.01 | ... Q21: ='Cálculos de Impostos'!Q21 -> 0 | R21: =SUM(F21:Q21) -> 318829.58 | T21: =SUM(F21:K21) -> 299583.17 | U21: =SUM(L21:Q21) -> 19246.41 | V21: =T21+U21 -> 318829.58
C22: Receita com Projetos | F22: ='Cálculos de Impostos'!F22 -> 1640.5782 | G22: ='Cálculos de Impostos'!G22 -> 1146.6088 | H22: ='Cálculos de Impostos'!H22 -> 1200.1852 | I22: ='Cálculos de Impostos'!I22 -> 220.52859 | J22: ='Cálculos de Impostos'!J22 -> 146.8843 | K22: ='Cálculos de Impostos'!K22 -> 984.60246 | L22: ='Cálculos de Impostos'!L22 -> 2093.0596 | M22: ='Cálculos de Impostos'!M22 -> 1140.343 | ... Q22: ='Cálculos de Impostos'!Q22 -> 0 | R22: =SUM(F22:Q22) -> 8572.7901 | T22: =SUM(F22:K22) -> 5339.3876 | U22: =SUM(L22:Q22) -> 3233.4026 | V22: =T22+U22 -> 8572.7901
C23: Receitas - Assessoria CSC | F23: =F24+F25+F26 -> 82477.8 | G23: =G24+G25+G26 -> 74147.94 | H23: =H24+H25+H26 -> 72134.63 | I23: =I24+I25+I26 -> 80333.03 | J23: =J24+J25+J26 -> 79118.51 | K23: =K24+K25+K26 -> 66614.5 | L23: =L24+L25+L26 -> 71727.16 | M23: =M24+M25+M26 -> 77050.1 | ... R23: =R24+R25+R26 -> 603603.67 | T23: =SUM(F23:K23) -> 454826.41 | U23: =SUM(L23:Q23) -> 148777.26 | V23: =T23+U23 -> 603603.67
D24: Assessoria CSC - Quokka | F24: ='Cálculos de Impostos'!F24 -> 49703 | G24: ='Cálculos de Impostos'!G24 -> 46767 | H24: ='Cálculos de Impostos'!H24 -> 41835.5 | I24: ='Cálculos de Impostos'!I24 -> 41835.5 | J24: ='Cálculos de Impostos'!J24 -> 45335.5 | K24: ='Cálculos de Impostos'!K24 -> 40214.5 | L24: ='Cálculos de Impostos'!L24 -> 39404 | M24: ='Cálculos de Impostos'!M24 -> 37783 | ... Q24: ='Cálculos de Impostos'!Q24 -> 0 | R24: =SUM(F24:Q24) -> 342878 | T24: =SUM(F24:K24) -> 265691 | U24: =SUM(L24:Q24) -> 77187 | V24: =T24+U24 -> 342878
D25: Assessoria Central de Talentos | F25: ='Cálculos de Impostos'!F25 -> 3774.8 | G25: ='Cálculos de Impostos'!G25 -> 3380.94 | H25: ='Cálculos de Impostos'!H25 -> 5299.13 | I25: ='Cálculos de Impostos'!I25 -> 12245.03 | J25: ='Cálculos de Impostos'!J25 -> 4283.01 | K25: ='Cálculos de Impostos'!K25 -> 0 | L25: ='Cálculos de Impostos'!L25 -> 3023.16 | M25: ='Cálculos de Impostos'!M25 -> 4967.1 | ... Q25: ='Cálculos de Impostos'!Q25 -> 0 | R25: =SUM(F25:Q25) -> 36973.17 | T25: =SUM(F25:K25) -> 28982.91 | U25: =SUM(L25:Q25) -> 7990.26 | V25: =T25+U25 -> 36973.17
D26: Assessoria CSC - Atendimento | F26: ='Cálculos de Impostos'!F26 -> 29000 | G26: ='Cálculos de Impostos'!G26 -> 24000 | H26: ='Cálculos de Impostos'!H26 -> 25000 | I26: ='Cálculos de Impostos'!I26 -> 26252.5 | J26: ='Cálculos de Impostos'!J26 -> 29500 | K26: ='Cálculos de Impostos'!K26 -> 26400 | L26: ='Cálculos de Impostos'!L26 -> 29300 | M26: ='Cálculos de Impostos'!M26 -> 34300 | ... Q26: ='Cálculos de Impostos'!Q26 -> 0 | R26: =SUM(F26:Q26) -> 223752.5 | T26: =SUM(F26:K26) -> 160152.5 | U26: =SUM(L26:Q26) -> 63600 | V26: =T26+U26 -> 223752.5
B27: Deduções de Receita | F27: =F28+F29+F33+F37 -> -104494.82 | G27: =G28+G29+G33+G37 -> -75622.536 | H27: =H28+H29+H33+H37 -> -80727.962 | I27: =I28+I29+I33+I37 -> -78716.017 | J27: =J28+J29+J33+J37 -> -74576.061 | K27: =K28+K29+K33+K37 -> -187978.64 | L27: =L28+L29+L33+L37 -> -75289.378 | M27: =M28+M29+M33+M37 -> -61021.424 | ... Q27: =Q28+Q29+Q33+Q37 -> 0 | R27: =SUM(F27:Q27) -> -738426.84 | T27: =SUM(F27:K27) -> -602116.04 | U27: =SUM(L27:Q27) -> -136310.8 | V27: =T27+U27 -> -738426.84
C28: Devoluções de Vendas de Serviços Prestados | F28: ='Cálculos de Impostos'!F28 -> -19.64 | G28: ='Cálculos de Impostos'!G28 -> -1292.74 | H28: ='Cálculos de Impostos'!H28 -> -4648.39 | I28: ='Cálculos de Impostos'!I28 -> -526.91 | J28: ='Cálculos de Impostos'!J28 -> 0 | K28: ='Cálculos de Impostos'!K28 -> -120275.68 | L28: ='Cálculos de Impostos'!L28 -> 0 | M28: ='Cálculos de Impostos'!M28 -> -2177.59 | ... Q28: ='Cálculos de Impostos'!Q28 -> 0 | R28: =SUM(F28:Q28) -> -128940.95 | T28: =SUM(F28:K28) -> -126763.36 | U28: =SUM(L28:Q28) -> -2177.59 | V28: =T28+U28 -> -128940.95
C29: PIS | F29: =F30+F31+F32 -> -7418.9965 | G29: =G30+G31+G32 -> -5264.8179 | H29: =H30+H31+H32 -> -5383.3907 | I29: =I30+I31+I32 -> -5540.4929 | J29: =J30+J31+J32 -> -6046.1741 | K29: =K30+K31+K32 -> -6415.9908 | L29: =L30+L31+L32 -> -6732.5094 | M29: =M30+M31+M32 -> -5410.7675 | ... R29: =R30+R31+R32 -> -48213.14 | T29: =SUM(F29:K29) -> -36069.863 | U29: =SUM(L29:Q29) -> -12143.277 | V29: =T29+U29 -> -48213.14
D30: PIS - V E | F30: ='Cálculos de Impostos'!F30 -> -6029.7188 | G30: ='Cálculos de Impostos'!G30 -> -4217.776 | H30: ='Cálculos de Impostos'!H30 -> -4298.4151 | I30: ='Cálculos de Impostos'!I30 -> -4451.9056 | J30: ='Cálculos de Impostos'!J30 -> -3775.9162 | K30: ='Cálculos de Impostos'!K30 -> -5232.0488 | L30: ='Cálculos de Impostos'!L30 -> -5385.7768 | M30: ='Cálculos de Impostos'!M30 -> -4268.6898 | ... Q30: ='Cálculos de Impostos'!Q30 -> 0 | R30: =SUM(F30:Q30) -> -37660.247 | T30: =SUM(F30:K30) -> -28005.78 | U30: =SUM(L30:Q30) -> -9654.4666 | V30: =T30+U30 -> -37660.247
D31: PIS - SPDX | F31: ='Cálculos de Impostos'!F31 -> -282.76946 | G31: ='Cálculos de Impostos'!G31 -> -271.67581 | H31: ='Cálculos de Impostos'!H31 -> -265.45937 | I31: ='Cálculos de Impostos'!I31 -> -262.53371 | J31: ='Cálculos de Impostos'!J31 -> -276.3004 | K31: ='Cálculos de Impostos'!K31 -> -276.47786 | L31: ='Cálculos de Impostos'!L31 -> -284.34247 | M31: ='Cálculos de Impostos'!M31 -> -291.70698 | ... Q31: ='Cálculos de Impostos'!Q31 -> 0 | R31: =SUM(F31:Q31) -> -2211.2661 | T31: =SUM(F31:K31) -> -1635.2166 | U31: =SUM(L31:Q31) -> -576.04944 | V31: =T31+U31 -> -2211.2661
D32: PIS - Dataforte | F32: ='Cálculos de Impostos'!F32 -> -1106.5083 | G32: ='Cálculos de Impostos'!G32 -> -775.36617 | H32: ='Cálculos de Impostos'!H32 -> -819.51624 | I32: ='Cálculos de Impostos'!I32 -> -826.05356 | J32: ='Cálculos de Impostos'!J32 -> -1993.9575 | K32: ='Cálculos de Impostos'!K32 -> -907.46413 | L32: ='Cálculos de Impostos'!L32 -> -1062.3901 | M32: ='Cálculos de Impostos'!M32 -> -850.37073 | ... Q32: ='Cálculos de Impostos'!Q32 -> 0 | R32: =SUM(F32:Q32) -> -8341.6267 | T32: =SUM(F32:K32) -> -6428.8659 | U32: =SUM(L32:Q32) -> -1912.7608 | V32: =T32+U32 -> -8341.6267
C33: COFINS | F33: =F34+F35+F36 -> -34235.178 | G33: =G34+G35+G36 -> -24294.179 | H33: =H34+H35+H36 -> -24841.312 | I33: =I34+I35+I36 -> -25566.395 | J33: =J34+J35+J36 -> -27895.684 | K33: =K34+K35+K36 -> -29606.738 | L33: =L34+L35+L36 -> -31066.936 | M33: =M34+M35+M36 -> -24967.356 | ... R33: =R34+R35+R36 -> -222473.78 | T33: =SUM(F33:K33) -> -166439.49 | U33: =SUM(L33:Q33) -> -56034.292 | V33: =T33+U33 -> -222473.78
D34: COFINS - V E | F34: ='Cálculos de Impostos'!F34 -> -27829.471 | G34: ='Cálculos de Impostos'!G34 -> -19466.658 | H34: ='Cálculos de Impostos'!H34 -> -19838.839 | I34: ='Cálculos de Impostos'!I34 -> -20547.256 | J34: ='Cálculos de Impostos'!J34 -> -17427.305 | K34: ='Cálculos de Impostos'!K34 -> -24147.918 | L34: ='Cálculos de Impostos'!L34 -> -24857.431 | M34: ='Cálculos de Impostos'!M34 -> -19701.645 | ... Q34: ='Cálculos de Impostos'!Q34 -> 0 | R34: =SUM(F34:Q34) -> -173816.52 | T34: =SUM(F34:K34) -> -129257.45 | U34: =SUM(L34:Q34) -> -44559.077 | V34: =T34+U34 -> -173816.52
D35: COFINS - SPDX | F35: ='Cálculos de Impostos'!F35 -> -1303.0322 | G35: ='Cálculos de Impostos'!G35 -> -1251.9115 | H35: ='Cálculos de Impostos'!H35 -> -1223.2655 | I35: ='Cálculos de Impostos'!I35 -> -1209.7837 | J35: ='Cálculos de Impostos'!J35 -> -1273.2221 | K35: ='Cálculos de Impostos'!K35 -> -1274.0399 | L35: ='Cálculos de Impostos'!L35 -> -1310.2808 | M35: ='Cálculos de Impostos'!M35 -> -1344.2173 | ... Q35: ='Cálculos de Impostos'!Q35 -> 0 | R35: =SUM(F35:Q35) -> -10189.753 | T35: =SUM(F35:K35) -> -7535.255 | U35: =SUM(L35:Q35) -> -2654.4981 | V35: =T35+U35 -> -10189.753
D36: COFINS - Dataforte | F36: ='Cálculos de Impostos'!F36 -> -5102.6749 | G36: ='Cálculos de Impostos'!G36 -> -3575.6095 | H36: ='Cálculos de Impostos'!H36 -> -3779.208 | I36: ='Cálculos de Impostos'!I36 -> -3809.3549 | J36: ='Cálculos de Impostos'!J36 -> -9195.1566 | K36: ='Cálculos de Impostos'!K36 -> -4184.7806 | L36: ='Cálculos de Impostos'!L36 -> -4899.2233 | M36: ='Cálculos de Impostos'!M36 -> -3921.4938 | ... Q36: ='Cálculos de Impostos'!Q36 -> 0 | R36: =SUM(F36:Q36) -> -38467.502 | T36: =SUM(F36:K36) -> -29646.785 | U36: =SUM(L36:Q36) -> -8820.7171 | V36: =T36+U36 -> -38467.502
C37: ISS | F37: =F38+F39+F40 -> -62821.007 | G37: =G38+G39+G40 -> -44770.799 | H37: =H38+H39+H40 -> -45854.869 | I37: =I38+I39+I40 -> -47082.219 | J37: =J38+J39+J40 -> -40634.203 | K37: =K38+K39+K40 -> -31680.229 | L37: =L38+L39+L40 -> -37489.933 | M37: =M38+M39+M40 -> -28465.71 | ... R37: =R38+R39+R40 -> -338798.97 | T37: =SUM(F37:K37) -> -272843.33 | U37: =SUM(L37:Q37) -> -65955.644 | V37: =T37+U37 -> -338798.97
D38: ISS - V E | F38: ='Cálculos de Impostos'!F38 -> -46382.452 | G38: ='Cálculos de Impostos'!G38 -> -32444.43 | H38: ='Cálculos de Impostos'!H38 -> -33064.732 | I38: ='Cálculos de Impostos'!I38 -> -34245.428 | J38: ='Cálculos de Impostos'!J38 -> -13572.593 | K38: ='Cálculos de Impostos'!K38 -> -17709.308 | L38: ='Cálculos de Impostos'!L38 -> -21565.747 | M38: ='Cálculos de Impostos'!M38 -> -15015.573 | ... Q38: ='Cálculos de Impostos'!Q38 -> 0 | R38: =SUM(F38:Q38) -> -214000.26 | T38: =SUM(F38:K38) -> -177418.94 | U38: =SUM(L38:Q38) -> -36581.321 | V38: =T38+U38 -> -214000.26
D39: ISS - SPDX | F39: ='Cálculos de Impostos'!F39 -> -3104.7323 | G39: ='Cálculos de Impostos'!G39 -> -2982.927 | H39: ='Cálculos de Impostos'!H39 -> -2914.6722 | I39: ='Cálculos de Impostos'!I39 -> -2882.5492 | J39: ='Cálculos de Impostos'!J39 -> -3033.7037 | K39: ='Cálculos de Impostos'!K39 -> -3035.6522 | L39: ='Cálculos de Impostos'!L39 -> -3122.0034 | M39: ='Cálculos de Impostos'!M39 -> -3202.8638 | ... Q39: ='Cálculos de Impostos'!Q39 -> 0 | R39: =SUM(F39:Q39) -> -24279.104 | T39: =SUM(F39:K39) -> -17954.237 | U39: =SUM(L39:Q39) -> -6324.8672 | V39: =T39+U39 -> -24279.104
D40: ISS - Dataforte | F40: ='Cálculos de Impostos'!F40 -> -13333.823 | G40: ='Cálculos de Impostos'!G40 -> -9343.4413 | H40: ='Cálculos de Impostos'!H40 -> -9875.4655 | I40: ='Cálculos de Impostos'!I40 -> -9954.2426 | J40: ='Cálculos de Impostos'!J40 -> -24027.905 | K40: ='Cálculos de Impostos'!K40 -> -10935.269 | L40: ='Cálculos de Impostos'!L40 -> -12802.183 | M40: ='Cálculos de Impostos'!M40 -> -10247.273 | ... Q40: ='Cálculos de Impostos'!Q40 -> 0 | R40: =SUM(F40:Q40) -> -100519.6 | T40: =SUM(F40:K40) -> -77470.147 | U40: =SUM(L40:Q40) -> -23049.456 | V40: =T40+U40 -> -100519.6
B41: Receita Operacional Líquida | F41: =F4+F27 -> 1582207.8 | G41: =G4+G27 -> 1204257.7 | H41: =H4+H27 -> 1371332.6 | I41: =I4+I27 -> 1343845.5 | J41: =J4+J27 -> 1521704.5 | K41: =K4+K27 -> 1378073.3 | L41: =L4+L27 -> 1572185.9 | M41: =M4+M27 -> 1327607.9 | ... R41: =R4+R27 -> 11301215 | T41: =SUM(F41:K41) -> 8401421.4 | U41: =SUM(L41:Q41) -> 2899793.7 | V41: =T41+U41 -> 11301215
B42: Custos com os Serviços Prestados | F42: =SUM(F43:F47) -> -75616.964 | G42: =SUM(G43:G47) -> -46012.15 | H42: =SUM(H43:H47) -> -61394.776 | I42: =SUM(I43:I47) -> -52504.502 | J42: =SUM(J43:J47) -> -235852.36 | K42: =SUM(K43:K47) -> -30271.711 | L42: =SUM(L43:L47) -> -54339.315 | M42: =SUM(M43:M47) -> -14711.093 | ... R42: =SUM(R43:R47) -> -570702.87 | T42: =SUM(F42:K42) -> -501652.47 | U42: =SUM(L42:Q42) -> -69050.408 | V42: =T42+U42 -> -570702.87
C43: Comissões | F43: ='Cálculos de Impostos'!F43 -> -12966.67 | G43: ='Cálculos de Impostos'!G43 -> -12966.67 | H43: ='Cálculos de Impostos'!H43 -> -12966.67 | I43: ='Cálculos de Impostos'!I43 -> -12966.67 | J43: ='Cálculos de Impostos'!J43 -> -23166.67 | K43: ='Cálculos de Impostos'!K43 -> -12966.67 | L43: ='Cálculos de Impostos'!L43 -> -12966.67 | M43: ='Cálculos de Impostos'!M43 -> -12966.67 | ... Q43: ='Cálculos de Impostos'!Q43 -> 0 | R43: =SUM(F43:Q43) -> -113933.36 | T43: =SUM(F43:K43) -> -88000.02 | U43: =SUM(L43:Q43) -> -25933.34 | V43: =T43+U43 -> -113933.36
C44: Custos com Festas de Arrecadação | F44: ='Cálculos de Impostos'!F44 -> -1535.494 | G44: ='Cálculos de Impostos'!G44 -> -2166.0599 | H44: ='Cálculos de Impostos'!H44 -> -2401.7164 | I44: ='Cálculos de Impostos'!I44 -> -3363.4121 | J44: ='Cálculos de Impostos'!J44 -> -188587.8 | K44: ='Cálculos de Impostos'!K44 -> -4360.0908 | L44: ='Cálculos de Impostos'!L44 -> -5077.9446 | M44: ='Cálculos de Impostos'!M44 -> -1744.4233 | ... Q44: ='Cálculos de Impostos'!Q44 -> 0 | R44: =SUM(F44:Q44) -> -209236.94 | T44: =SUM(F44:K44) -> -202414.58 | U44: =SUM(L44:Q44) -> -6822.368 | V44: =T44+U44 -> -209236.94
C45: Custos com Treinamentos | F45: ='Cálculos de Impostos'!F45 -> -45074.34 | G45: ='Cálculos de Impostos'!G45 -> -9114.12 | H45: ='Cálculos de Impostos'!H45 -> -2700 | I45: ='Cálculos de Impostos'!I45 -> -3658 | J45: ='Cálculos de Impostos'!J45 -> -4595.65 | K45: ='Cálculos de Impostos'!K45 -> -5880.9 | L45: ='Cálculos de Impostos'!L45 -> -20072.44 | M45: ='Cálculos de Impostos'!M45 -> 0 | ... Q45: ='Cálculos de Impostos'!Q45 -> 0 | R45: =SUM(F45:Q45) -> -91095.45 | T45: =SUM(F45:K45) -> -71023.01 | U45: =SUM(L45:Q45) -> -20072.44 | V45: =T45+U45 -> -91095.45
C46: Custos Serviços Prestados - Diárias Consultorias | F46: ='Cálculos de Impostos'!F46 -> -9757.37 | G46: ='Cálculos de Impostos'!G46 -> -21765.3 | H46: ='Cálculos de Impostos'!H46 -> -43326.39 | I46: ='Cálculos de Impostos'!I46 -> -32516.42 | J46: ='Cálculos de Impostos'!J46 -> -19502.24 | K46: ='Cálculos de Impostos'!K46 -> -7064.05 | L46: ='Cálculos de Impostos'!L46 -> -16222.26 | M46: ='Cálculos de Impostos'!M46 -> 0 | ... Q46: ='Cálculos de Impostos'!Q46 -> 0 | R46: =SUM(F46:Q46) -> -150154.03 | T46: =SUM(F46:K46) -> -133931.77 | U46: =SUM(L46:Q46) -> -16222.26 | V46: =T46+U46 -> -150154.03
C47: Custo de Seguro da Arrecadação | F47: ='Cálculos de Impostos'!F47 -> -6283.09 | G47: ='Cálculos de Impostos'!G47 -> 0 | H47: ='Cálculos de Impostos'!H47 -> 0 | I47: ='Cálculos de Impostos'!I47 -> 0 | J47: ='Cálculos de Impostos'!J47 -> 0 | K47: ='Cálculos de Impostos'!K47 -> 0 | L47: ='Cálculos de Impostos'!L47 -> 0 | M47: ='Cálculos de Impostos'!M47 -> 0 | ... Q47: ='Cálculos de Impostos'!Q47 -> 0 | R47: =SUM(F47:Q47) -> -6283.09 | T47: =SUM(F47:K47) -> -6283.09 | U47: =SUM(L47:Q47) -> 0 | V47: =T47+U47 -> -6283.09
B48: Lucro Operacional Bruto | F48: =F41+F42 -> 1506590.8 | G48: =G41+G42 -> 1158245.6 | H48: =H41+H42 -> 1309937.8 | I48: =I41+I42 -> 1291341 | J48: =J41+J42 -> 1285852.1 | K48: =K41+K42 -> 1347801.6 | L48: =L41+L42 -> 1517846.6 | M48: =M41+M42 -> 1312896.8 | ... R48: =R41+R42 -> 10730512 | T48: =SUM(F48:K48) -> 7899768.9 | U48: =SUM(L48:Q48) -> 2830743.3 | V48: =T48+U48 -> 10730512
B49: Despesas Operacionais | F49: =F50+F52+F77+F93+F98 -> -840219.09 | G49: =G50+G52+G77+G93+G98 -> -815784.65 | H49: =H50+H52+H77+H93+H98 -> -837720.96 | I49: =I50+I52+I77+I93+I98 -> -844375.58 | J49: =J50+J52+J77+J93+J98 -> -838063.11 | K49: =K50+K52+K77+K93+K98 -> -819946.91 | L49: =L50+L52+L77+L93+L98 -> -827938.24 | M49: =M50+M52+M77+M93+M98 -> -801762.4 | ... R49: =R50+R52+R77+R93+R98 -> -6625810.9 | T49: =SUM(F49:K49) -> -4996110.3 | U49: =SUM(L49:Q49) -> -1629700.6 | V49: =T49+U49 -> -6625810.9
C50: Despesas de Vendas e Marketing | F50: =F51 -> -5904.09 | G50: =G51 -> -1572.44 | H50: =H51 -> -1868.52 | I50: =I51 -> -18760.59 | J50: =J51 -> -6865.39 | K50: =K51 -> -10164.83 | L50: =L51 -> -3093.07 | M50: =M51 -> -6624.71 | ... R50: =R51 -> -54853.64 | T50: =SUM(F50:K50) -> -45135.86 | U50: =SUM(L50:Q50) -> -9717.78 | V50: =T50+U50 -> -54853.64
D51: Marketing | F51: ='Cálculos de Impostos'!F51 -> -5904.09 | G51: ='Cálculos de Impostos'!G51 -> -1572.44 | H51: ='Cálculos de Impostos'!H51 -> -1868.52 | I51: ='Cálculos de Impostos'!I51 -> -18760.59 | J51: ='Cálculos de Impostos'!J51 -> -6865.39 | K51: ='Cálculos de Impostos'!K51 -> -10164.83 | L51: ='Cálculos de Impostos'!L51 -> -3093.07 | M51: ='Cálculos de Impostos'!M51 -> -6624.71 | ... Q51: ='Cálculos de Impostos'!Q51 -> 0 | R51: =SUM(F51:Q51) -> -54853.64 | T51: =SUM(F51:K51) -> -45135.86 | U51: =SUM(L51:Q51) -> -9717.78 | V51: =T51+U51 -> -54853.64
C52: Despesas com Pessoal | F52: =SUM(F53:F57,F61:F76) -> -713882.79 | G52: =SUM(G53:G57,G61:G76) -> -713624.07 | H52: =SUM(H53:H57,H61:H76) -> -736612.74 | I52: =SUM(I53:I57,I61:I76) -> -705418.37 | J52: =SUM(J53:J57,J61:J76) -> -719795.21 | K52: =SUM(K53:K57,K61:K76) -> -707198.46 | L52: =SUM(L53:L57,L61:L76) -> -744724.47 | M52: =SUM(M53:M57,M61:M76) -> -713274.01 | ... R52: =SUM(R53:R57,R61:R76) -> -5754530.1 | T52: =SUM(F52:K52) -> -4296531.6 | U52: =SUM(L52:Q52) -> -1457998.5 | V52: =T52+U52 -> -5754530.1
D53: Salários | F53: ='Cálculos de Impostos'!F53 -> -240113.48 | G53: ='Cálculos de Impostos'!G53 -> -242102.74 | H53: ='Cálculos de Impostos'!H53 -> -236025.11 | I53: ='Cálculos de Impostos'!I53 -> -225382.29 | J53: ='Cálculos de Impostos'!J53 -> -225809.01 | K53: ='Cálculos de Impostos'!K53 -> -232624.79 | L53: ='Cálculos de Impostos'!L53 -> -236097.42 | M53: ='Cálculos de Impostos'!M53 -> -237979.84 | ... Q53: ='Cálculos de Impostos'!Q53 -> 0 | R53: =SUM(F53:Q53) -> -1876134.7 | T53: =SUM(F53:K53) -> -1402057.4 | U53: =SUM(L53:Q53) -> -474077.26 | V53: =T53+U53 -> -1876134.7
D54: Férias | F54: ='Cálculos de Impostos'!F54 -> -8011.5885 | G54: ='Cálculos de Impostos'!G54 -> -8109.3939 | H54: ='Cálculos de Impostos'!H54 -> -8022.6528 | I54: ='Cálculos de Impostos'!I54 -> -7659.9706 | J54: ='Cálculos de Impostos'!J54 -> -7627.16 | K54: ='Cálculos de Impostos'!K54 -> -7863.8277 | L54: ='Cálculos de Impostos'!L54 -> -7856.1561 | M54: ='Cálculos de Impostos'!M54 -> -7883.5261 | ... Q54: ='Cálculos de Impostos'!Q54 -> 0 | R54: =SUM(F54:Q54) -> -63034.276 | T54: =SUM(F54:K54) -> -47294.594 | U54: =SUM(L54:Q54) -> -15739.682 | V54: =T54+U54 -> -63034.276
D55: Rescisões | F55: ='Cálculos de Impostos'!F55 -> -1800.23 | G55: ='Cálculos de Impostos'!G55 -> 0 | H55: ='Cálculos de Impostos'!H55 -> -25560.77 | I55: ='Cálculos de Impostos'!I55 -> -11451.61 | J55: ='Cálculos de Impostos'!J55 -> -4477.71 | K55: ='Cálculos de Impostos'!K55 -> -3847.35 | L55: ='Cálculos de Impostos'!L55 -> -14621.74 | M55: ='Cálculos de Impostos'!M55 -> 0 | ... Q55: ='Cálculos de Impostos'!Q55 -> 0 | R55: =SUM(F55:Q55) -> -61759.41 | T55: =SUM(F55:K55) -> -47137.67 | U55: =SUM(L55:Q55) -> -14621.74 | V55: =T55+U55 -> -61759.41
D56: 13º Salário | F56: ='Cálculos de Impostos'!F56 -> -24034.756 | G56: ='Cálculos de Impostos'!G56 -> -24328.182 | H56: ='Cálculos de Impostos'!H56 -> -24067.958 | I56: ='Cálculos de Impostos'!I56 -> -22979.912 | J56: ='Cálculos de Impostos'!J56 -> -22881.48 | K56: ='Cálculos de Impostos'!K56 -> -23594.403 | L56: ='Cálculos de Impostos'!L56 -> -23504.748 | M56: ='Cálculos de Impostos'!M56 -> -23536.878 | ... Q56: ='Cálculos de Impostos'!Q56 -> 0 | R56: =SUM(F56:Q56) -> -188928.32 | T56: =SUM(F56:K56) -> -141886.69 | U56: =SUM(L56:Q56) -> -47041.625 | V56: =T56+U56 -> -188928.32
D57: INSS | F57: ='Cálculos de Impostos'!F57 -> -58074.727 | G57: ='Cálculos de Impostos'!G57 -> -54927.448 | H57: ='Cálculos de Impostos'!H57 -> -54131.204 | I57: ='Cálculos de Impostos'!I57 -> -50530.478 | J57: ='Cálculos de Impostos'!J57 -> -69114.838 | K57: ='Cálculos de Impostos'!K57 -> -53713.328 | L57: ='Cálculos de Impostos'!L57 -> -56424.701 | M57: ='Cálculos de Impostos'!M57 -> -53351.47 | ... Q57: ='Cálculos de Impostos'!Q57 -> 0 | R57: =R58+R59+R60 -> -450268.19 | T57: =SUM(F57:K57) -> -340492.02 | U57: =SUM(L57:Q57) -> -109776.17 | V57: =T57+U57 -> -450268.19
E58: INSS - V E | F58: ='Cálculos de Impostos'!F58 -> -36654.449 | G58: ='Cálculos de Impostos'!G58 -> -38839.456 | H58: ='Cálculos de Impostos'!H58 -> -37445.109 | I58: ='Cálculos de Impostos'!I58 -> -33785.222 | J58: ='Cálculos de Impostos'!J58 -> -33934.988 | K58: ='Cálculos de Impostos'!K58 -> -35492.679 | L58: ='Cálculos de Impostos'!L58 -> -35670.112 | M58: ='Cálculos de Impostos'!M58 -> -35798.843 | ... Q58: ='Cálculos de Impostos'!Q58 -> 0 | R58: =SUM(F58:Q58) -> -287620.86 | T58: =SUM(F58:K58) -> -216151.9 | U58: =SUM(L58:Q58) -> -71468.955
E59: INSS - SPDX | F59: ='Cálculos de Impostos'!F59 -> -4146.0117 | G59: ='Cálculos de Impostos'!G59 -> -3983.3548 | H59: ='Cálculos de Impostos'!H59 -> -3892.2084 | I59: ='Cálculos de Impostos'!I59 -> -3849.3119 | J59: ='Cálculos de Impostos'!J59 -> -4051.1613 | K59: ='Cálculos de Impostos'!K59 -> -4053.7633 | L59: ='Cálculos de Impostos'!L59 -> -4169.0753 | M59: ='Cálculos de Impostos'!M59 -> -4277.055 | ... Q59: ='Cálculos de Impostos'!Q59 -> 0 | R59: =SUM(F59:Q59) -> -32421.942 | T59: =SUM(F59:K59) -> -23975.811 | U59: =SUM(L59:Q59) -> -8446.1303
E60: INSS - Dataforte | F60: ='Cálculos de Impostos'!F60 -> -17274.266 | G60: ='Cálculos de Impostos'!G60 -> -12104.637 | H60: ='Cálculos de Impostos'!H60 -> -12793.887 | I60: ='Cálculos de Impostos'!I60 -> -12895.944 | J60: ='Cálculos de Impostos'!J60 -> -31128.689 | K60: ='Cálculos de Impostos'!K60 -> -14166.886 | L60: ='Cálculos de Impostos'!L60 -> -16585.514 | M60: ='Cálculos de Impostos'!M60 -> -13275.572 | ... Q60: ='Cálculos de Impostos'!Q60 -> 0 | R60: =SUM(F60:Q60) -> -130225.4 | T60: =SUM(F60:K60) -> -100364.31 | U60: =SUM(L60:Q60) -> -29861.086
D61: FGTS | F61: ='Cálculos de Impostos'!F61 -> -18649.078 | G61: ='Cálculos de Impostos'!G61 -> -18808.219 | H61: ='Cálculos de Impostos'!H61 -> -18402.009 | I61: ='Cálculos de Impostos'!I61 -> -17550.583 | J61: ='Cálculos de Impostos'!J61 -> -17664.721 | K61: ='Cálculos de Impostos'!K61 -> -18209.983 | L61: ='Cálculos de Impostos'!L61 -> -17683.278 | M61: ='Cálculos de Impostos'!M61 -> -17833.871 | ... Q61: ='Cálculos de Impostos'!Q61 -> 0 | R61: =SUM(F61:Q61) -> -144801.74 | T61: =SUM(F61:K61) -> -109284.59 | U61: =SUM(L61:Q61) -> -35517.149 | V61: =T61+U61 -> -144801.74
D62: IRRF | F62: ='Cálculos de Impostos'!F62 -> 0 | G62: ='Cálculos de Impostos'!G62 -> 0 | H62: ='Cálculos de Impostos'!H62 -> 0 | I62: ='Cálculos de Impostos'!I62 -> 0 | J62: ='Cálculos de Impostos'!J62 -> 0 | K62: ='Cálculos de Impostos'!K62 -> 0 | L62: ='Cálculos de Impostos'!L62 -> 0 | M62: ='Cálculos de Impostos'!M62 -> 0 | ... Q62: ='Cálculos de Impostos'!Q62 -> 0 | R62: =SUM(F62:Q62) -> 0 | T62: =SUM(F62:K62) -> 0 | U62: =SUM(L62:Q62) -> 0 | V62: =T62+U62 -> 0
D63: Pensão Alimentícia | F63: ='Cálculos de Impostos'!F63 -> 0 | G63: ='Cálculos de Impostos'!G63 -> 0 | H63: ='Cálculos de Impostos'!H63 -> 0 | I63: ='Cálculos de Impostos'!I63 -> 0 | J63: ='Cálculos de Impostos'!J63 -> 0 | K63: ='Cálculos de Impostos'!K63 -> 0 | L63: ='Cálculos de Impostos'!L63 -> 0 | M63: ='Cálculos de Impostos'!M63 -> 0 | ... Q63: ='Cálculos de Impostos'!Q63 -> 0 | R63: =SUM(F63:Q63) -> 0 | T63: =SUM(F63:K63) -> 0 | U63: =SUM(L63:Q63) -> 0 | V63: =T63+U63 -> 0
D64: Assistência Médica | F64: ='Cálculos de Impostos'!F64 -> -8370.35 | G64: ='Cálculos de Impostos'!G64 -> -6571.82 | H64: ='Cálculos de Impostos'!H64 -> -3866.92 | I64: ='Cálculos de Impostos'!I64 -> -2196.5 | J64: ='Cálculos de Impostos'!J64 -> -3276.4 | K64: ='Cálculos de Impostos'!K64 -> -2115.08 | L64: ='Cálculos de Impostos'!L64 -> -3812.39 | M64: ='Cálculos de Impostos'!M64 -> -3677.87 | ... Q64: ='Cálculos de Impostos'!Q64 -> 0 | R64: =SUM(F64:Q64) -> -33887.33 | T64: =SUM(F64:K64) -> -26397.07 | U64: =SUM(L64:Q64) -> -7490.26 | V64: =T64+U64 -> -33887.33
D65: Benefícios Flexíveis | F65: ='Cálculos de Impostos'!F65 -> -37118.14 | G65: ='Cálculos de Impostos'!G65 -> -39531.39 | H65: ='Cálculos de Impostos'!H65 -> -40001.38 | I65: ='Cálculos de Impostos'!I65 -> -39103.17 | J65: ='Cálculos de Impostos'!J65 -> -38078.13 | K65: ='Cálculos de Impostos'!K65 -> -38841.6 | L65: ='Cálculos de Impostos'!L65 -> -37844.81 | M65: ='Cálculos de Impostos'!M65 -> -37735.17 | ... Q65: ='Cálculos de Impostos'!Q65 -> 0 | R65: =SUM(F65:Q65) -> -308253.79 | T65: =SUM(F65:K65) -> -232673.81 | U65: =SUM(L65:Q65) -> -75579.98 | V65: =T65+U65 -> -308253.79
D66: Vale Transporte / Mobilidade | F66: ='Cálculos de Impostos'!F66 -> -464.81 | G66: ='Cálculos de Impostos'!G66 -> -404.1 | H66: ='Cálculos de Impostos'!H66 -> -506.76 | I66: ='Cálculos de Impostos'!I66 -> -227.53 | J66: ='Cálculos de Impostos'!J66 -> -150 | K66: ='Cálculos de Impostos'!K66 -> -157.5 | L66: ='Cálculos de Impostos'!L66 -> -90 | M66: ='Cálculos de Impostos'!M66 -> -157.5 | ... Q66: ='Cálculos de Impostos'!Q66 -> 0 | R66: =SUM(F66:Q66) -> -2158.2 | T66: =SUM(F66:K66) -> -1910.7 | U66: =SUM(L66:Q66) -> -247.5 | V66: =T66+U66 -> -2158.2
D67: Seguro de Vida | F67: ='Cálculos de Impostos'!F67 -> 0 | G67: ='Cálculos de Impostos'!G67 -> 0 | H67: ='Cálculos de Impostos'!H67 -> 0 | I67: ='Cálculos de Impostos'!I67 -> 0 | J67: ='Cálculos de Impostos'!J67 -> 0 | K67: ='Cálculos de Impostos'!K67 -> -26.25 | L67: ='Cálculos de Impostos'!L67 -> 0 | M67: ='Cálculos de Impostos'!M67 -> 0 | ... Q67: ='Cálculos de Impostos'!Q67 -> 0 | R67: =SUM(F67:Q67) -> -26.25 | T67: =SUM(F67:K67) -> -26.25 | U67: =SUM(L67:Q67) -> 0 | V67: =T67+U67 -> -26.25
D68: Refeições | F68: ='Cálculos de Impostos'!F68 -> -15429.9 | G68: ='Cálculos de Impostos'!G68 -> -17038.6 | H68: ='Cálculos de Impostos'!H68 -> -18171.3 | I68: ='Cálculos de Impostos'!I68 -> -16265 | J68: ='Cálculos de Impostos'!J68 -> -16897.6 | K68: ='Cálculos de Impostos'!K68 -> -16980.9 | L68: ='Cálculos de Impostos'!L68 -> -21649.6 | M68: ='Cálculos de Impostos'!M68 -> -20481.1 | ... Q68: ='Cálculos de Impostos'!Q68 -> 0 | R68: =SUM(F68:Q68) -> -142914 | T68: =SUM(F68:K68) -> -100783.3 | U68: =SUM(L68:Q68) -> -42130.7 | V68: =T68+U68 -> -142914
D69: Auxílio Home Office | F69: ='Cálculos de Impostos'!F69 -> -3690 | G69: ='Cálculos de Impostos'!G69 -> -3540 | H69: ='Cálculos de Impostos'!H69 -> -3540 | I69: ='Cálculos de Impostos'!I69 -> -3540 | J69: ='Cálculos de Impostos'!J69 -> -3240 | K69: ='Cálculos de Impostos'!K69 -> -3390 | L69: ='Cálculos de Impostos'!L69 -> -3390 | M69: ='Cálculos de Impostos'!M69 -> -3390 | ... Q69: ='Cálculos de Impostos'!Q69 -> 0 | R69: =SUM(F69:Q69) -> -27720 | T69: =SUM(F69:K69) -> -20940 | U69: =SUM(L69:Q69) -> -6780 | V69: =T69+U69 -> -27720
D70: Pró Labore Sócios | F70: ='Cálculos de Impostos'!F70 -> -205685 | G70: ='Cálculos de Impostos'!G70 -> -226448.95 | H70: ='Cálculos de Impostos'!H70 -> -226448.95 | I70: ='Cálculos de Impostos'!I70 -> -226448.95 | J70: ='Cálculos de Impostos'!J70 -> -226448.95 | K70: ='Cálculos de Impostos'!K70 -> -226448.95 | L70: ='Cálculos de Impostos'!L70 -> -226448.95 | M70: ='Cálculos de Impostos'!M70 -> -226448.95 | ... Q70: ='Cálculos de Impostos'!Q70 -> 0 | R70: =SUM(F70:Q70) -> -1790827.6 | T70: =SUM(F70:K70) -> -1337929.8 | U70: =SUM(L70:Q70) -> -452897.9 | V70: =T70+U70 -> -1790827.6
D71: Bônus EBITDA | F71: ='Cálculos de Impostos'!F71 -> -36375 | G71: ='Cálculos de Impostos'!G71 -> -36375 | H71: ='Cálculos de Impostos'!H71 -> -36375 | I71: ='Cálculos de Impostos'!I71 -> -36375 | J71: ='Cálculos de Impostos'!J71 -> -36375 | K71: ='Cálculos de Impostos'!K71 -> -36375 | L71: ='Cálculos de Impostos'!L71 -> -36375 | M71: ='Cálculos de Impostos'!M71 -> -36375 | ... Q71: ='Cálculos de Impostos'!Q71 -> 0 | R71: =SUM(F71:Q71) -> -291000 | T71: =SUM(F71:K71) -> -218250 | U71: =SUM(L71:Q71) -> -72750 | V71: =T71+U71 -> -291000
D72: Outros ( Contribuição Sindical - PCMO, Exames...) | F72: ='Cálculos de Impostos'!F72 -> -460.56 | G72: ='Cálculos de Impostos'!G72 -> -540.87 | H72: ='Cálculos de Impostos'!H72 -> -603.97 | I72: ='Cálculos de Impostos'!I72 -> -440.23 | J72: ='Cálculos de Impostos'!J72 -> -714.85 | K72: ='Cálculos de Impostos'!K72 -> -1250.76 | L72: ='Cálculos de Impostos'!L72 -> -501.73 | M72: ='Cálculos de Impostos'!M72 -> -505 | ... Q72: ='Cálculos de Impostos'!Q72 -> 0 | R72: =SUM(F72:Q72) -> -5017.97 | T72: =SUM(F72:K72) -> -4011.24 | U72: =SUM(L72:Q72) -> -1006.73 | V72: =T72+U72 -> -5017.97
... D75: Transporte e Hospedagem Colaboradores para Sede da Empresa | F75: ='Cálculos de Impostos'!F75 -> 0 | G75: ='Cálculos de Impostos'!G75 -> 0 | H75: ='Cálculos de Impostos'!H75 -> 0 | I75: ='Cálculos de Impostos'!I75 -> 0 | J75: ='Cálculos de Impostos'!J75 -> 0 | K75: ='Cálculos de Impostos'!K75 -> 0 | L75: ='Cálculos de Impostos'!L75 -> 0 | M75: ='Cálculos de Impostos'!M75 -> 0 | ... Q75: ='Cálculos de Impostos'!Q75 -> 0 | R75: =SUM(F75:Q75) -> 0 | T75: =SUM(F75:K75) -> 0 | U75: =SUM(L75:Q75) -> 0 | V75: =T75+U75 -> 0
D76: Participação nos Lucros e Resultados | F76: =-'Cálculos de Impostos'!$A$76*'Cálculos de Impostos'!F115 -> -41539.321 | G76: =-'Cálculos de Impostos'!$A$76*'Cálculos de Impostos'!G115 -> -17881.719 | H76: =-'Cálculos de Impostos'!$A$76*'Cálculos de Impostos'!H115 -> -26312.135 | I76: =-'Cálculos de Impostos'!$A$76*'Cálculos de Impostos'!I115 -> -24716.713 | J76: =-'Cálculos de Impostos'!$A$76*'Cálculos de Impostos'!J115 -> -25420.221 | K76: =-'Cálculos de Impostos'!$A$76*'Cálculos de Impostos'!K115 -> -29786.429 | L76: =-'Cálculos de Impostos'!$A$76*'Cálculos de Impostos'!L115 -> -43600.189 | M76: =-'Cálculos de Impostos'!$A$76*'Cálculos de Impostos'!M115 -> -30151.334 | ... Q76: =-'Cálculos de Impostos'!$A$76*'Cálculos de Impostos'!Q115 -> 0 | R76: =SUM(F76:Q76) -> -239408.06 | T76: =SUM(F76:K76) -> -165656.54 | U76: =SUM(L76:Q76) -> -73751.523 | V76: =T76+U76 -> -239408.06
C77: Despesas Administrativas | F77: =SUM(F78:F92) -> -118408.19 | G77: =SUM(G78:G92) -> -98402.51 | H77: =SUM(H78:H92) -> -96863.74 | I77: =SUM(I78:I92) -> -116123.89 | J77: =SUM(J78:J92) -> -110268.5 | K77: =SUM(K78:K92) -> -100921.62 | L77: =SUM(L78:L92) -> -77424.04 | M77: =SUM(M78:M92) -> -80931.22 | ... R77: =SUM(R78:R92) -> -799343.71 | T77: =SUM(F77:K77) -> -640988.45 | U77: =SUM(L77:Q77) -> -158355.26 | V77: =T77+U77 -> -799343.71
D78: Aluguel | F78: ='Cálculos de Impostos'!F78 -> -16414 | G78: ='Cálculos de Impostos'!G78 -> -17589.54 | H78: ='Cálculos de Impostos'!H78 -> -17001.77 | I78: ='Cálculos de Impostos'!I78 -> -17014.45 | J78: ='Cálculos de Impostos'!J78 -> -17014.45 | K78: ='Cálculos de Impostos'!K78 -> -17014.45 | L78: ='Cálculos de Impostos'!L78 -> -17014.45 | M78: ='Cálculos de Impostos'!M78 -> -17014.45 | ... Q78: ='Cálculos de Impostos'!Q78 -> 0 | R78: =SUM(F78:Q78) -> -136077.56 | T78: =SUM(F78:K78) -> -102048.66 | U78: =SUM(L78:Q78) -> -34028.9 | V78: =T78+U78 -> -136077.56
D79: Energia Elétrica | F79: ='Cálculos de Impostos'!F79 -> -2591.85 | G79: ='Cálculos de Impostos'!G79 -> -3025.01 | H79: ='Cálculos de Impostos'!H79 -> -2739.52 | I79: ='Cálculos de Impostos'!I79 -> -2655.52 | J79: ='Cálculos de Impostos'!J79 -> -2448.71 | K79: ='Cálculos de Impostos'!K79 -> -2257.34 | L79: ='Cálculos de Impostos'!L79 -> -2517.6 | M79: ='Cálculos de Impostos'!M79 -> -2177.1 | ... Q79: ='Cálculos de Impostos'!Q79 -> 0 | R79: =SUM(F79:Q79) -> -20412.65 | T79: =SUM(F79:K79) -> -15717.95 | U79: =SUM(L79:Q79) -> -4694.7 | V79: =T79+U79 -> -20412.65
D80: Telefonia e Internet | F80: ='Cálculos de Impostos'!F80 -> -1115.34 | G80: ='Cálculos de Impostos'!G80 -> -1752.44 | H80: ='Cálculos de Impostos'!H80 -> -1258.79 | I80: ='Cálculos de Impostos'!I80 -> -1985.67 | J80: ='Cálculos de Impostos'!J80 -> -1202.11 | K80: ='Cálculos de Impostos'!K80 -> -1897.54 | L80: ='Cálculos de Impostos'!L80 -> -1171.51 | M80: ='Cálculos de Impostos'!M80 -> -1277.68 | ... Q80: ='Cálculos de Impostos'!Q80 -> 0 | R80: =SUM(F80:Q80) -> -11661.08 | T80: =SUM(F80:K80) -> -9211.89 | U80: =SUM(L80:Q80) -> -2449.19 | V80: =T80+U80 -> -11661.08
D81: Manutenção de Imobilizado | F81: ='Cálculos de Impostos'!F81 -> -1937.6 | G81: ='Cálculos de Impostos'!G81 -> -1585 | H81: ='Cálculos de Impostos'!H81 -> -1900 | I81: ='Cálculos de Impostos'!I81 -> -942.29 | J81: ='Cálculos de Impostos'!J81 -> -1298.1 | K81: ='Cálculos de Impostos'!K81 -> -3244.9 | L81: ='Cálculos de Impostos'!L81 -> -2092.56 | M81: ='Cálculos de Impostos'!M81 -> -1219.2 | ... Q81: ='Cálculos de Impostos'!Q81 -> 0 | R81: =SUM(F81:Q81) -> -14219.65 | T81: =SUM(F81:K81) -> -10907.89 | U81: =SUM(L81:Q81) -> -3311.76 | V81: =T81+U81 -> -14219.65
D82: Seguros | F82: ='Cálculos de Impostos'!F82 -> 0 | G82: ='Cálculos de Impostos'!G82 -> 0 | H82: ='Cálculos de Impostos'!H82 -> 0 | I82: ='Cálculos de Impostos'!I82 -> 0 | J82: ='Cálculos de Impostos'!J82 -> 0 | K82: ='Cálculos de Impostos'!K82 -> 0 | L82: ='Cálculos de Impostos'!L82 -> 0 | M82: ='Cálculos de Impostos'!M82 -> 0 | ... Q82: ='Cálculos de Impostos'!Q82 -> 0 | R82: =SUM(F82:Q82) -> 0 | T82: =SUM(F82:K82) -> 0 | U82: =SUM(L82:Q82) -> 0 | V82: =T82+U82 -> 0
D83: Contabilidade | F83: ='Cálculos de Impostos'!F83 -> -10450.89 | G83: ='Cálculos de Impostos'!G83 -> -7580.89 | H83: ='Cálculos de Impostos'!H83 -> -7611.05 | I83: ='Cálculos de Impostos'!I83 -> -9799.69 | J83: ='Cálculos de Impostos'!J83 -> -8326.25 | K83: ='Cálculos de Impostos'!K83 -> -8382.65 | L83: ='Cálculos de Impostos'!L83 -> -8382.65 | M83: ='Cálculos de Impostos'!M83 -> -10700.47 | ... Q83: ='Cálculos de Impostos'!Q83 -> 0 | R83: =SUM(F83:Q83) -> -71234.54 | T83: =SUM(F83:K83) -> -52151.42 | U83: =SUM(L83:Q83) -> -19083.12 | V83: =T83+U83 -> -71234.54
D84: Advogados | F84: ='Cálculos de Impostos'!F84 -> -7285.66 | G84: ='Cálculos de Impostos'!G84 -> -7285.66 | H84: ='Cálculos de Impostos'!H84 -> -7285.66 | I84: ='Cálculos de Impostos'!I84 -> -7285.66 | J84: ='Cálculos de Impostos'!J84 -> -7646.31 | K84: ='Cálculos de Impostos'!K84 -> -7285.66 | L84: ='Cálculos de Impostos'!L84 -> -7285.66 | M84: ='Cálculos de Impostos'!M84 -> -7285.66 | ... Q84: ='Cálculos de Impostos'!Q84 -> 0 | R84: =SUM(F84:Q84) -> -58645.93 | T84: =SUM(F84:K84) -> -44074.61 | U84: =SUM(L84:Q84) -> -14571.32 | V84: =T84+U84 -> -58645.93
D85: Segurança | F85: ='Cálculos de Impostos'!F85 -> 0 | G85: ='Cálculos de Impostos'!G85 -> 0 | H85: ='Cálculos de Impostos'!H85 -> 0 | I85: ='Cálculos de Impostos'!I85 -> 0 | J85: ='Cálculos de Impostos'!J85 -> 0 | K85: ='Cálculos de Impostos'!K85 -> 0 | L85: ='Cálculos de Impostos'!L85 -> 0 | M85: ='Cálculos de Impostos'!M85 -> 0 | ... Q85: ='Cálculos de Impostos'!Q85 -> 0 | R85: =SUM(F85:Q85) -> 0 | T85: =SUM(F85:K85) -> 0 | U85: =SUM(L85:Q85) -> 0 | V85: =T85+U85 -> 0
D86: Softwares, Sistemas e Servidores | F86: ='Cálculos de Impostos'!F86 -> -51072.67 | G86: ='Cálculos de Impostos'!G86 -> -35665.6 | H86: ='Cálculos de Impostos'!H86 -> -27032.5 | I86: ='Cálculos de Impostos'!I86 -> -34367.67 | J86: ='Cálculos de Impostos'!J86 -> -24784.68 | K86: ='Cálculos de Impostos'!K86 -> -29033.32 | L86: ='Cálculos de Impostos'!L86 -> -23828.51 | M86: ='Cálculos de Impostos'!M86 -> -29329.72 | ... Q86: ='Cálculos de Impostos'!Q86 -> 0 | R86: =SUM(F86:Q86) -> -255114.67 | T86: =SUM(F86:K86) -> -201956.44 | U86: =SUM(L86:Q86) -> -53158.23 | V86: =T86+U86 -> -255114.67
D87: Outras Despesas Administrativas | F87: ='Cálculos de Impostos'!F87 -> -700 | G87: ='Cálculos de Impostos'!G87 -> -499.37 | H87: ='Cálculos de Impostos'!H87 -> -3796.26 | I87: ='Cálculos de Impostos'!I87 -> -3444.99 | J87: ='Cálculos de Impostos'!J87 -> -13735.64 | K87: ='Cálculos de Impostos'!K87 -> -5976.48 | L87: ='Cálculos de Impostos'!L87 -> -1735.47 | M87: ='Cálculos de Impostos'!M87 -> -2904.59 | ... Q87: ='Cálculos de Impostos'!Q87 -> 0 | R87: =SUM(F87:Q87) -> -32792.8 | T87: =SUM(F87:K87) -> -28152.74 | U87: =SUM(L87:Q87) -> -4640.06 | V87: =T87+U87 -> -32792.8
D88: Material Limpeza / Escritório / Mercado / Padaria | F88: ='Cálculos de Impostos'!F88 -> -2240.56 | G88: ='Cálculos de Impostos'!G88 -> -2146.37 | H88: ='Cálculos de Impostos'!H88 -> -4186.5 | I88: ='Cálculos de Impostos'!I88 -> -2283.37 | J88: ='Cálculos de Impostos'!J88 -> -4127.13 | K88: ='Cálculos de Impostos'!K88 -> -2695.64 | L88: ='Cálculos de Impostos'!L88 -> -2947.17 | M88: ='Cálculos de Impostos'!M88 -> -4247.05 | ... Q88: ='Cálculos de Impostos'!Q88 -> 0 | R88: =SUM(F88:Q88) -> -24873.79 | T88: =SUM(F88:K88) -> -17679.57 | U88: =SUM(L88:Q88) -> -7194.22 | V88: =T88+U88 -> -24873.79
D89: Fretes e Transportes em Geral | F89: ='Cálculos de Impostos'!F89 -> -1286.69 | G89: ='Cálculos de Impostos'!G89 -> -1215.98 | H89: ='Cálculos de Impostos'!H89 -> -1194.08 | I89: ='Cálculos de Impostos'!I89 -> -1260.93 | J89: ='Cálculos de Impostos'!J89 -> -642.47 | K89: ='Cálculos de Impostos'!K89 -> -466.6 | L89: ='Cálculos de Impostos'!L89 -> -1148.81 | M89: ='Cálculos de Impostos'!M89 -> -1076.8 | ... Q89: ='Cálculos de Impostos'!Q89 -> 0 | R89: =SUM(F89:Q89) -> -8292.36 | T89: =SUM(F89:K89) -> -6066.75 | U89: =SUM(L89:Q89) -> -2225.61 | V89: =T89+U89 -> -8292.36
... D92: Taxas Municipais | F92: ='Cálculos de Impostos'!F92 -> -157.28 | G92: ='Cálculos de Impostos'!G92 -> 0 | H92: ='Cálculos de Impostos'!H92 -> 0 | I92: ='Cálculos de Impostos'!I92 -> 0 | J92: ='Cálculos de Impostos'!J92 -> 0 | K92: ='Cálculos de Impostos'!K92 -> -636.33 | L92: ='Cálculos de Impostos'!L92 -> 0 | M92: ='Cálculos de Impostos'!M92 -> 0 | ... Q92: ='Cálculos de Impostos'!Q92 -> 0 | R92: =SUM(F92:Q92) -> -793.61 | T92: =SUM(F92:K92) -> -793.61 | U92: =SUM(L92:Q92) -> 0 | V92: =T92+U92 -> -793.61
C93: Despesas Financeiras / Bancos | F93: =SUM(F94:F97) -> -1905.02 | G93: =SUM(G94:G97) -> -2066.63 | H93: =SUM(H94:H97) -> -2208.3 | I93: =SUM(I94:I97) -> -1825.06 | J93: =SUM(J94:J97) -> -870.58 | K93: =SUM(K94:K97) -> -1353.55 | L93: =SUM(L94:L97) -> -1123.21 | M93: =SUM(M94:M97) -> -807.76 | ... R93: =SUM(R94:R97) -> -12160.11 | T93: =SUM(F93:K93) -> -10229.14 | U93: =SUM(L93:Q93) -> -1930.97 | V93: =T93+U93 -> -12160.11
D94: Juros sobre Empréstimos | F94: ='Cálculos de Impostos'!F94 -> 0 | G94: ='Cálculos de Impostos'!G94 -> 0 | H94: ='Cálculos de Impostos'!H94 -> 0 | I94: ='Cálculos de Impostos'!I94 -> 0 | J94: ='Cálculos de Impostos'!J94 -> 0 | K94: ='Cálculos de Impostos'!K94 -> 0 | L94: ='Cálculos de Impostos'!L94 -> 0 | M94: ='Cálculos de Impostos'!M94 -> 0 | ... Q94: ='Cálculos de Impostos'!Q94 -> 0 | R94: =SUM(F94:Q94) -> 0 | T94: =SUM(F94:K94) -> 0 | U94: =SUM(L94:Q94) -> 0 | V94: =T94+U94 -> 0
D95: Multas | F95: ='Cálculos de Impostos'!F95 -> 0 | G95: ='Cálculos de Impostos'!G95 -> 0 | H95: ='Cálculos de Impostos'!H95 -> 0 | I95: ='Cálculos de Impostos'!I95 -> 0 | J95: ='Cálculos de Impostos'!J95 -> 0 | K95: ='Cálculos de Impostos'!K95 -> 0 | L95: ='Cálculos de Impostos'!L95 -> 0 | M95: ='Cálculos de Impostos'!M95 -> 0 | ... Q95: ='Cálculos de Impostos'!Q95 -> 0 | R95: =SUM(F95:Q95) -> 0 | T95: =SUM(F95:K95) -> 0 | U95: =SUM(L95:Q95) -> 0 | V95: =T95+U95 -> 0
D96: Tarifas Bancárias | F96: ='Cálculos de Impostos'!F96 -> -1035.33 | G96: ='Cálculos de Impostos'!G96 -> -1383.57 | H96: ='Cálculos de Impostos'!H96 -> -1878.89 | I96: ='Cálculos de Impostos'!I96 -> -983.22 | J96: ='Cálculos de Impostos'!J96 -> -838.97 | K96: ='Cálculos de Impostos'!K96 -> -1254.83 | L96: ='Cálculos de Impostos'!L96 -> -1093 | M96: ='Cálculos de Impostos'!M96 -> -807.76 | ... Q96: ='Cálculos de Impostos'!Q96 -> 0 | R96: =SUM(F96:Q96) -> -9275.57 | T96: =SUM(F96:K96) -> -7374.81 | U96: =SUM(L96:Q96) -> -1900.76 | V96: =T96+U96 -> -9275.57
D97: IOF | F97: ='Cálculos de Impostos'!F97 -> -869.69 | G97: ='Cálculos de Impostos'!G97 -> -683.06 | H97: ='Cálculos de Impostos'!H97 -> -329.41 | I97: ='Cálculos de Impostos'!I97 -> -841.84 | J97: ='Cálculos de Impostos'!J97 -> -31.61 | K97: ='Cálculos de Impostos'!K97 -> -98.72 | L97: ='Cálculos de Impostos'!L97 -> -30.21 | M97: ='Cálculos de Impostos'!M97 -> 0 | ... Q97: ='Cálculos de Impostos'!Q97 -> 0 | R97: =SUM(F97:Q97) -> -2884.54 | T97: =SUM(F97:K97) -> -2854.33 | U97: =SUM(L97:Q97) -> -30.21 | V97: =T97+U97 -> -2884.54
C98: Outras Despesas | F98: =SUM(F99:F100) -> -119 | G98: =SUM(G99:G100) -> -119 | H98: =SUM(H99:H100) -> -167.66 | I98: =SUM(I99:I100) -> -2247.67 | J98: =SUM(J99:J100) -> -263.43 | K98: =SUM(K99:K100) -> -308.45 | L98: =SUM(L99:L100) -> -1573.45 | M98: =SUM(M99:M100) -> -124.7 | ... R98: =SUM(R99:R100) -> -4923.36 | T98: =SUM(F98:K98) -> -3225.21 | U98: =SUM(L98:Q98) -> -1698.15 | V98: =T98+U98 -> -4923.36
D99: Doações | F99: ='Cálculos de Impostos'!F99 -> -119 | G99: ='Cálculos de Impostos'!G99 -> -119 | H99: ='Cálculos de Impostos'!H99 -> -124.7 | I99: ='Cálculos de Impostos'!I99 -> -482.94 | J99: ='Cálculos de Impostos'!J99 -> -124.7 | K99: ='Cálculos de Impostos'!K99 -> -124.7 | L99: ='Cálculos de Impostos'!L99 -> -1389.7 | M99: ='Cálculos de Impostos'!M99 -> -124.7 | ... Q99: ='Cálculos de Impostos'!Q99 -> 0 | R99: =SUM(F99:Q99) -> -2609.44 | T99: =SUM(F99:K99) -> -1095.04 | U99: =SUM(L99:Q99) -> -1514.4 | V99: =T99+U99 -> -2609.44
D100: Pesquisa e Desenvolvimento | F100: ='Cálculos de Impostos'!F100 -> 0 | G100: ='Cálculos de Impostos'!G100 -> 0 | H100: ='Cálculos de Impostos'!H100 -> -42.96 | I100: ='Cálculos de Impostos'!I100 -> -1764.73 | J100: ='Cálculos de Impostos'!J100 -> -138.73 | K100: ='Cálculos de Impostos'!K100 -> -183.75 | L100: ='Cálculos de Impostos'!L100 -> -183.75 | M100: ='Cálculos de Impostos'!M100 -> 0 | ... Q100: ='Cálculos de Impostos'!Q100 -> 0 | R100: =SUM(F100:Q100) -> -2313.92 | T100: =SUM(F100:K100) -> -2130.17 | U100: =SUM(L100:Q100) -> -183.75 | V100: =T100+U100 -> -2313.92
B101: Lucro ou Prejuízo Operacional | F101: =F48+F49 -> 666371.75 | G101: =G48+G49 -> 342460.9 | H101: =H48+H49 -> 472216.87 | I101: =I48+I49 -> 446965.38 | J101: =J48+J49 -> 447789.03 | K101: =K48+K49 -> 527854.7 | L101: =L48+L49 -> 689908.31 | M101: =M48+M49 -> 511134.38 | ... R101: =R48+R49 -> 4104701.3 | T101: =SUM(F101:K101) -> 2903658.6 | U101: =SUM(L101:Q101) -> 1201042.7 | V101: =T101+U101 -> 4104701.3
C102: Receitas Não Operacionais | F102: ='Cálculos de Impostos'!F102 -> 15584.31 | G102: ='Cálculos de Impostos'!G102 -> 14237.36 | H102: ='Cálculos de Impostos'!H102 -> 14183.15 | I102: ='Cálculos de Impostos'!I102 -> 15216.83 | J102: ='Cálculos de Impostos'!J102 -> 13209.71 | K102: ='Cálculos de Impostos'!K102 -> 8721.03 | L102: ='Cálculos de Impostos'!L102 -> 17437.35 | M102: ='Cálculos de Impostos'!M102 -> 11672.58 | ... Q102: ='Cálculos de Impostos'!Q102 -> 0 | R102: =SUM(F102:Q102) -> 110262.32 | T102: =SUM(F102:K102) -> 81152.39 | U102: =SUM(L102:Q102) -> 29109.93 | V102: =T102+U102 -> 110262.32
C103: Despesas Não Operacionais | F103: ='Cálculos de Impostos'!F103 -> 0 | G103: ='Cálculos de Impostos'!G103 -> 0 | H103: ='Cálculos de Impostos'!H103 -> 0 | I103: ='Cálculos de Impostos'!I103 -> 0 | J103: ='Cálculos de Impostos'!J103 -> 0 | K103: ='Cálculos de Impostos'!K103 -> 0 | L103: ='Cálculos de Impostos'!L103 -> 0 | M103: ='Cálculos de Impostos'!M103 -> 0 | ... Q103: ='Cálculos de Impostos'!Q103 -> 0 | R103: =SUM(F103:Q103) -> 0 | T103: =SUM(F103:K103) -> 0 | U103: =SUM(L103:Q103) -> 0 | V103: =T103+U103 -> 0
B104: Resultado do Exercicio Antes IR e CS | F104: =F101+F102+F103 -> 681956.06 | G104: =G101+G102+G103 -> 356698.26 | H104: =H101+H102+H103 -> 486400.02 | I104: =I101+I102+I103 -> 462182.21 | J104: =J101+J102+J103 -> 460998.74 | K104: =K101+K102+K103 -> 536575.73 | L104: =L101+L102+L103 -> 707345.66 | M104: =M101+M102+M103 -> 522806.96 | ... R104: =R101+R102+R103 -> 4214963.6 | T104: =SUM(F104:K104) -> 2984811 | U104: =SUM(L104:Q104) -> 1230152.6 | V104: =T104+U104 -> 4214963.6
C105: IRPJ | F105: =SUM(F106:F109) -> -143908.21 | G105: =SUM(G106:G109) -> -116879.28 | H105: =SUM(H106:H109) -> -142948.1 | I105: =SUM(I106:I109) -> -136789.48 | J105: =SUM(J106:J109) -> -128916.59 | K105: =SUM(K106:K109) -> -145561.71 | L105: =SUM(L106:L109) -> -145719.75 | M105: =SUM(M106:M109) -> -131901.66 | ... R105: =SUM(R106:R109) -> -1092624.8 | T105: =SUM(F105:K105) -> -815003.37 | U105: =SUM(L105:Q105) -> -277621.41
D106: IRPJ - V E | F106: ='Cálculos de Impostos'!F106 -> -70312.858 | G106: ='Cálculos de Impostos'!G106 -> -52651.581 | H106: ='Cálculos de Impostos'!H106 -> -53739.949 | I106: ='Cálculos de Impostos'!I106 -> -55882.062 | J106: ='Cálculos de Impostos'!J106 -> -46605.764 | K106: ='Cálculos de Impostos'!K106 -> -66041.262 | L106: ='Cálculos de Impostos'!L106 -> -61048.544 | M106: ='Cálculos de Impostos'!M106 -> -53181.859 | ... Q106: ='Cálculos de Impostos'!Q106 -> 0 | R106: =SUM(F106:Q106) -> -459463.88 | T106: =SUM(F106:K106) -> -345233.48 | U106: =SUM(L106:Q106) -> -114230.4 | V106: =T106+U106 -> -459463.88
...

Sheet Cálculos de Impostos
F2: janeiro | G2: fevereiro | H2: março | I2: abril | J2: maio | K2: junho | L2: julho | M2: agosto | N2: setembro | O2: outubro | P2: novembro | Q2: dezembro | R2: 2026 | T2: 1 SEM | U2: 2 SEM | V2: 2024
B4: Receita Operacional Bruta | F4: =F5+F8+F11+F14+F15+F16+F17+F21+F22+F23 -> 1686702.6 | G4: =G5+G8+G11+G14+G15+G16+G17+G21+G22+G23 -> 1279880.2 | H4: =H5+H8+H11+H14+H15+H16+H17+H21+H22+H23 -> 1452060.6 | I4: =I5+I8+I11+I14+I15+I16+I17+I21+I22+I23 -> 1422561.5 | J4: =J5+J8+J11+J14+J15+J16+J17+J21+J22+J23 -> 1596280.6 | K4: =K5+K8+K11+K14+K15+K16+K17+K21+K22+K23 -> 1566052 | L4: =L5+L8+L11+L14+L15+L16+L17+L21+L22+L23 -> 1647475.2 | M4: =M5+M8+M11+M14+M15+M16+M17+M21+M22+M23 -> 1388629.3 | ... R4: =R5+R8+R11+R14+R15+R16+R17+R21+R22+R23 -> 12039642 | T4: =SUM(F4:K4) -> 9003537.4 | U4: =SUM(L4:Q4) -> 3036104.5 | V4: =T4+U4 -> 12039642
C5: Royalties | F5: =SUM(F6:F7) -> 858569.87 | G5: =SUM(G6:G7) -> 598623.74 | H5: =SUM(H6:H7) -> 606841.34 | I5: =SUM(I6:I7) -> 632427.22 | J5: =SUM(J6:J7) -> 530748.99 | K5: =SUM(K6:K7) -> 750091.11 | L5: =SUM(L6:L7) -> 765899.31 | M5: =SUM(M6:M7) -> 606346.88 | ... R5: =SUM(R6:R7) -> 5349548.5 | T5: =SUM(F5:K5) -> 3977302.3 | U5: =SUM(L5:Q5) -> 1372246.2 | V5: =T5+U5 -> 5349548.5
D6: Royalties - Recorrentes | F6: ='Outras Informações'!B5 -> 742596.16 | G6: ='Outras Informações'!C5 -> 520688.71 | H6: ='Outras Informações'!D5 -> 578703 | I6: ='Outras Informações'!E5 -> 609147.54 | J6: ='Outras Informações'!F5 -> 518335.49 | K6: ='Outras Informações'!G5 -> 638364.5 | L6: ='Outras Informações'!H5 -> 678311.33 | M6: ='Outras Informações'!I5 -> 534530.06 | ... Q6: ='Outras Informações'!M5 -> 0 | R6: =SUM(F6:Q6) -> 4820676.8 | T6: =SUM(F6:K6) -> 3607835.4 | U6: =SUM(L6:Q6) -> 1212841.4 | V6: =T6+U6 -> 4820676.8
D7: Royalties - Fechamentos | F7: ='Outras Informações'!B6 -> 115973.71 | G7: ='Outras Informações'!C6 -> 77935.03 | H7: ='Outras Informações'!D6 -> 28138.34 | I7: ='Outras Informações'!E6 -> 23279.68 | J7: ='Outras Informações'!F6 -> 12413.5 | K7: ='Outras Informações'!G6 -> 111726.61 | L7: ='Outras Informações'!H6 -> 87587.98 | M7: ='Outras Informações'!I6 -> 71816.82 | ... Q7: ='Outras Informações'!M6 -> 0 | R7: =SUM(F7:Q7) -> 528871.67 | T7: =SUM(F7:K7) -> 369466.87 | U7: =SUM(L7:Q7) -> 159404.8 | V7: =T7+U7 -> 528871.67
C8: Fundo de Marketing | F8: =SUM(F9:F10) -> 53494.86 | G8: =SUM(G9:G10) -> 36027.51 | H8: =SUM(H9:H10) -> 40270.14 | I8: =SUM(I9:I10) -> 37264.5 | J8: =SUM(J9:J10) -> 36951.48 | K8: =SUM(K9:K10) -> 46118.45 | L8: =SUM(L9:L10) -> 45244.39 | M8: =SUM(M9:M10) -> 38702.04 | ... R8: =SUM(R9:R10) -> 334073.37 | T8: =SUM(F8:K8) -> 250126.94 | U8: =SUM(L8:Q8) -> 83946.43 | V8: =T8+U8 -> 334073.37
D9: Fundo de Marketing - Recorrentes | F9: ='Outras Informações'!B7 -> 46209.41 | G9: ='Outras Informações'!C7 -> 30939.14 | H9: ='Outras Informações'!D7 -> 38474.08 | I9: ='Outras Informações'!E7 -> 35766.61 | J9: ='Outras Informações'!F7 -> 32874.72 | K9: ='Outras Informações'!G7 -> 44826.72 | L9: ='Outras Informações'!H7 -> 43952.66 | M9: ='Outras Informações'!I7 -> 36368.87 | ... Q9: ='Outras Informações'!M7 -> 0 | R9: =SUM(F9:Q9) -> 309412.21 | T9: =SUM(F9:K9) -> 229090.68 | U9: =SUM(L9:Q9) -> 80321.53 | V9: =T9+U9 -> 309412.21
D10: Fundo de Marketing - Fechamentos | F10: ='Outras Informações'!B8 -> 7285.45 | G10: ='Outras Informações'!C8 -> 5088.37 | H10: ='Outras Informações'!D8 -> 1796.06 | I10: ='Outras Informações'!E8 -> 1497.89 | J10: ='Outras Informações'!F8 -> 4076.76 | K10: ='Outras Informações'!G8 -> 1291.73 | L10: ='Outras Informações'!H8 -> 1291.73 | M10: ='Outras Informações'!I8 -> 2333.17 | ... Q10: ='Outras Informações'!M8 -> 0 | R10: =SUM(F10:Q10) -> 24661.16 | T10: =SUM(F10:K10) -> 21036.26 | U10: =SUM(L10:Q10) -> 3624.9 | V10: =T10+U10 -> 24661.16
C11: Taxas de Franquias | F11: =F12+F13 -> 0 | G11: =G12+G13 -> 0 | H11: =H12+H13 -> 0 | I11: =I12+I13 -> 0 | J11: =J12+J13 -> 0 | K11: =K12+K13 -> 0 | L11: =L12+L13 -> 0 | M11: =M12+M13 -> 0 | ... R11: =R12+R13 -> 0 | T11: =SUM(F11:K11) -> 0 | U11: =SUM(L11:Q11) -> 0 | V11: =T11+U11 -> 0
D12: Taxa Inicial de Franquia | F12: ='Outras Informações'!B65 -> 0 | G12: ='Outras Informações'!C65 -> 0 | H12: ='Outras Informações'!D65 -> 0 | I12: ='Outras Informações'!E65 -> 0 | J12: ='Outras Informações'!F65 -> 0 | K12: ='Outras Informações'!G65 -> 0 | L12: ='Outras Informações'!H65 -> 0 | M12: ='Outras Informações'!I65 -> 0 | ... Q12: ='Outras Informações'!M65 -> 0 | R12: =SUM(F12:Q12) -> 0 | T12: =SUM(F12:K12) -> 0 | U12: =SUM(L12:Q12) -> 0 | V12: =T12+U12 -> 0
D13: Renovação de Franquias | F13: ='Outras Informações'!B74 -> 0 | G13: ='Outras Informações'!C74 -> 0 | H13: ='Outras Informações'!D74 -> 0 | I13: ='Outras Informações'!E74 -> 0 | J13: ='Outras Informações'!F74 -> 0 | K13: ='Outras Informações'!G74 -> 0 | L13: ='Outras Informações'!H74 -> 0 | M13: ='Outras Informações'!I74 -> 0 | ... Q13: ='Outras Informações'!M74 -> 0 | R13: =SUM(F13:Q13) -> 0 | T13: =SUM(F13:K13) -> 0 | U13: =SUM(L13:Q13) -> 0 | V13: =T13+U13 -> 0
C14: Receita com Patrocínios | F14: ='Outras Informações'!B9 -> 0 | G14: ='Outras Informações'!C9 -> 0 | H14: ='Outras Informações'!D9 -> 0 | I14: ='Outras Informações'!E9 -> 0 | J14: ='Outras Informações'!F9 -> 0 | K14: ='Outras Informações'!G9 -> 0 | L14: ='Outras Informações'!H9 -> 0 | M14: ='Outras Informações'!I9 -> 0 | ... Q14: ='Outras Informações'!M9 -> 0 | R14: =SUM(F14:Q14) -> 0 | T14: =SUM(F14:K14) -> 0 | U14: =SUM(L14:Q14) -> 0 | V14: =T14+U14 -> 0
C15: Receita SPDX | F15: ='Outras Informações'!B10 -> 435100.22 | G15: ='Outras Informações'!C10 -> 385150.49 | H15: ='Outras Informações'!D10 -> 538232.09 | I15: ='Outras Informações'!E10 -> 487174.31 | J15: ='Outras Informações'!F10 -> 486610.35 | K15: ='Outras Informações'!G10 -> 486259.18 | L15: ='Outras Informações'!H10 -> 517608.2 | M15: ='Outras Informações'!I10 -> 467285.15 | ... Q15: ='Outras Informações'!M10 -> 0 | R15: =SUM(F15:Q15) -> 3803420 | T15: =SUM(F15:K15) -> 2818526.6 | U15: =SUM(L15:Q15) -> 984893.35 | V15: =T15+U15 -> 3803420
C16: Receitas - Taxa Mundo Viva | F16: ='Outras Informações'!B11 -> 76119.7 | G16: ='Outras Informações'!C11 -> 73017 | H16: ='Outras Informações'!D11 -> 71232.9 | I16: ='Outras Informações'!E11 -> 70336.1 | J16: ='Outras Informações'!F11 -> 73790.3 | K16: ='Outras Informações'!G11 -> 73663 | L16: ='Outras Informações'!H11 -> 76239.4 | M16: ='Outras Informações'!I11 -> 77537.1 | ... Q16: ='Outras Informações'!M11 -> 0 | R16: =SUM(F16:Q16) -> 591935.5 | T16: =SUM(F16:K16) -> 438159 | U16: =SUM(L16:Q16) -> 153776.5 | V16: =T16+U16 -> 591935.5
C17: Receitas - Markup de Tarifas | F17: =F18+F19+F20 -> 175537.31 | G17: =G18+G19+G20 -> 105459.15 | H17: =H18+H19+H20 -> 115377.65 | I17: =I18+I19+I20 -> 107690.23 | J17: =J18+J19+J20 -> 125373.64 | K17: =K18+K19+K20 -> 130235.64 | L17: =L18+L19+L20 -> 159580.33 | M17: =M18+M19+M20 -> 110404.67 | ... R17: =R18+R19+R20 -> 1029658.6 | T17: =SUM(F17:K17) -> 759673.62 | U17: =SUM(L17:Q17) -> 269985 | V17: =T17+U17 -> 1029658.6
D18: Markup de Liquidação de boletos | F18: ='Outras Informações'!B12 -> 33721.79 | G18: ='Outras Informações'!C12 -> 29503.82 | H18: ='Outras Informações'!D12 -> 37861.57 | I18: ='Outras Informações'!E12 -> 31977.18 | J18: ='Outras Informações'!F12 -> 32255.93 | K18: ='Outras Informações'!G12 -> 37591.02 | L18: ='Outras Informações'!H12 -> 39603.36 | M18: ='Outras Informações'!I12 -> 36696.37 | ... Q18: ='Outras Informações'!M12 -> 0 | R18: =SUM(F18:Q18) -> 279211.04 | T18: =SUM(F18:K18) -> 202911.31 | U18: =SUM(L18:Q18) -> 76299.73 | V18: =T18+U18 -> 279211.04
D19: Markup de cartão | F19: ='Outras Informações'!B13 -> 138056.49 | G19: ='Outras Informações'!C13 -> 72990.74 | H19: ='Outras Informações'!D13 -> 73001.08 | I19: ='Outras Informações'!E13 -> 73181.66 | J19: ='Outras Informações'!F13 -> 90920.72 | K19: ='Outras Informações'!G13 -> 89856.48 | L19: ='Outras Informações'!H13 -> 116286.7 | M19: ='Outras Informações'!I13 -> 70079.12 | ... Q19: ='Outras Informações'!M13 -> 0 | R19: =SUM(F19:Q19) -> 724372.99 | T19: =SUM(F19:K19) -> 538007.17 | U19: =SUM(L19:Q19) -> 186365.82 | V19: =T19+U19 -> 724372.99
D20: Markup de tarifas bancárias | F20: ='Outras Informações'!B14 -> 3759.03 | G20: ='Outras Informações'!C14 -> 2964.59 | H20: ='Outras Informações'!D14 -> 4515 | I20: ='Outras Informações'!E14 -> 2531.39 | J20: ='Outras Informações'!F14 -> 2196.99 | K20: ='Outras Informações'!G14 -> 2788.14 | L20: ='Outras Informações'!H14 -> 3690.27 | M20: ='Outras Informações'!I14 -> 3629.18 | ... Q20: ='Outras Informações'!M14 -> 0 | R20: =SUM(F20:Q20) -> 26074.59 | T20: =SUM(F20:K20) -> 18755.14 | U20: =SUM(L20:Q20) -> 7319.45 | V20: =T20+U20 -> 26074.59
C21: Receitas - Festas de Arrecadação | F21: ='Outras Informações'!B15 -> 3762.29 | G21: ='Outras Informações'!C15 -> 6307.8 | H21: ='Outras Informações'!D15 -> 6771.63 | I21: ='Outras Informações'!E15 -> 7115.56 | J21: ='Outras Informações'!F15 -> 263540.41 | K21: ='Outras Informações'!G15 -> 12085.48 | L21: ='Outras Informações'!H15 -> 9083.4 | M21: ='Outras Informações'!I15 -> 10163.01 | ... Q21: ='Outras Informações'!M15 -> 0 | R21: =SUM(F21:Q21) -> 318829.58 | T21: =SUM(F21:K21) -> 299583.17 | U21: =SUM(L21:Q21) -> 19246.41 | V21: =T21+U21 -> 318829.58
C22: Receita com Projetos | F22: ='Outras Informações'!B16 -> 1640.5782 | G22: ='Outras Informações'!C16 -> 1146.6088 | H22: ='Outras Informações'!D16 -> 1200.1852 | I22: ='Outras Informações'!E16 -> 220.52859 | J22: ='Outras Informações'!F16 -> 146.8843 | K22: ='Outras Informações'!G16 -> 984.60246 | L22: ='Outras Informações'!H16 -> 2093.0596 | M22: ='Outras Informações'!I16 -> 1140.343 | ... Q22: ='Outras Informações'!M16 -> 0 | R22: =SUM(F22:Q22) -> 8572.7901 | T22: =SUM(F22:K22) -> 5339.3876 | U22: =SUM(L22:Q22) -> 3233.4026 | V22: =T22+U22 -> 8572.7901
C23: Receitas - Assessoria CSC | F23: =F24+F25+F26 -> 82477.8 | G23: =G24+G25+G26 -> 74147.94 | H23: =H24+H25+H26 -> 72134.63 | I23: =I24+I25+I26 -> 80333.03 | J23: =J24+J25+J26 -> 79118.51 | K23: =K24+K25+K26 -> 66614.5 | L23: =L24+L25+L26 -> 71727.16 | M23: =M24+M25+M26 -> 77050.1 | ... R23: =R24+R25+R26 -> 603603.67 | T23: =SUM(F23:K23) -> 454826.41 | U23: =SUM(L23:Q23) -> 148777.26 | V23: =T23+U23 -> 603603.67
D24: Assessoria CSC - Quokka | F24: ='Outras Informações'!B17 -> 49703 | G24: ='Outras Informações'!C17 -> 46767 | H24: ='Outras Informações'!D17 -> 41835.5 | I24: ='Outras Informações'!E17 -> 41835.5 | J24: ='Outras Informações'!F17 -> 45335.5 | K24: ='Outras Informações'!G17 -> 40214.5 | L24: ='Outras Informações'!H17 -> 39404 | M24: ='Outras Informações'!I17 -> 37783 | ... Q24: ='Outras Informações'!M17 -> 0 | R24: =SUM(F24:Q24) -> 342878 | T24: =SUM(F24:K24) -> 265691 | U24: =SUM(L24:Q24) -> 77187 | V24: =T24+U24 -> 342878
D25: Assessoria Central de Talentos | F25: ='Outras Informações'!B18 -> 3774.8 | G25: ='Outras Informações'!C18 -> 3380.94 | H25: ='Outras Informações'!D18 -> 5299.13 | I25: ='Outras Informações'!E18 -> 12245.03 | J25: ='Outras Informações'!F18 -> 4283.01 | K25: ='Outras Informações'!G18 -> 0 | L25: ='Outras Informações'!H18 -> 3023.16 | M25: ='Outras Informações'!I18 -> 4967.1 | ... Q25: ='Outras Informações'!M18 -> 0 | R25: =SUM(F25:Q25) -> 36973.17 | T25: =SUM(F25:K25) -> 28982.91 | U25: =SUM(L25:Q25) -> 7990.26 | V25: =T25+U25 -> 36973.17
D26: Assessoria CSC - Atendimento | F26: ='Outras Informações'!B19 -> 29000 | G26: ='Outras Informações'!C19 -> 24000 | H26: ='Outras Informações'!D19 -> 25000 | I26: ='Outras Informações'!E19 -> 26252.5 | J26: ='Outras Informações'!F19 -> 29500 | K26: ='Outras Informações'!G19 -> 26400 | L26: ='Outras Informações'!H19 -> 29300 | M26: ='Outras Informações'!I19 -> 34300 | ... Q26: ='Outras Informações'!M19 -> 0 | R26: =SUM(F26:Q26) -> 223752.5 | T26: =SUM(F26:K26) -> 160152.5 | U26: =SUM(L26:Q26) -> 63600 | V26: =T26+U26 -> 223752.5
B27: Deduções de Receita | F27: =F28+F29+F33+F37 -> -104494.82 | G27: =G28+G29+G33+G37 -> -75622.536 | H27: =H28+H29+H33+H37 -> -80727.962 | I27: =I28+I29+I33+I37 -> -78716.017 | J27: =J28+J29+J33+J37 -> -74576.061 | K27: =K28+K29+K33+K37 -> -187978.64 | L27: =L28+L29+L33+L37 -> -75289.378 | M27: =M28+M29+M33+M37 -> -61021.424 | ... Q27: =Q28+Q29+Q33+Q37 -> 0 | R27: =SUM(F27:Q27) -> -738426.84 | T27: =SUM(F27:K27) -> -602116.04 | U27: =SUM(L27:Q27) -> -136310.8 | V27: =T27+U27 -> -738426.84
C28: Devoluções de Vendas de Serviços Prestados | F28: =SUMIFS('Lançamentos Omie'!$G:$G,'Lançamentos Omie'!$I:$I,$C28,'Lançamentos Omie'!$F:$F,F$2) -> -19.64 | G28: =SUMIFS('Lançamentos Omie'!$G:$G,'Lançamentos Omie'!$I:$I,$C28,'Lançamentos Omie'!$F:$F,G$2) -> -1292.74 | H28: =SUMIFS('Lançamentos Omie'!$G:$G,'Lançamentos Omie'!$I:$I,$C28,'Lançamentos Omie'!$F:$F,H$2) -> -4648.39 | I28: =SUMIFS('Lançamentos Omie'!$G:$G,'Lançamentos Omie'!$I:$I,$C28,'Lançamentos Omie'!$F:$F,I$2) -> -526.91 | J28: =SUMIFS('Lançamentos Omie'!$G:$G,'Lançamentos Omie'!$I:$I,$C28,'Lançamentos Omie'!$F:$F,J$2) -> 0 | K28: =SUMIFS('Lançamentos Omie'!$G:$G,'Lançamentos Omie'!$I:$I,$C28,'Lançamentos Omie'!$F:$F,K$2) -> -120275.68 | L28: =SUMIFS('Lançamentos Omie'!$G:$G,'Lançamentos Omie'!$I:$I,$C28,'Lançamentos Omie'!$F:$F,L$2) -> 0 | M28: =SUMIFS('Lançamentos Omie'!$G:$G,'Lançamentos Omie'!$I:$I,$C28,'Lançamentos Omie'!$F:$F,M$2) -> -2177.59 | ... Q28: =SUMIFS('Lançamentos Omie'!$G:$G,'Lançamentos Omie'!$I:$I,$C28,'Lançamentos Omie'!$F:$F,Q$2) -> 0 | R28: =SUM(F28:Q28) -> -128940.95 | T28: =SUM(F28:K28) -> -126763.36 | U28: =SUM(L28:Q28) -> -2177.59 | V28: =T28+U28 -> -128940.95
C29: PIS | F29: =F30+F31+F32 -> -7418.9965 | G29: =G30+G31+G32 -> -5264.8179 | H29: =H30+H31+H32 -> -5383.3907 | I29: =I30+I31+I32 -> -5540.4929 | J29: =J30+J31+J32 -> -6046.1741 | K29: =K30+K31+K32 -> -6415.9908 | L29: =L30+L31+L32 -> -6732.5094 | M29: =M30+M31+M32 -> -5410.7675 | ... R29: =R30+R31+R32 -> -48213.14 | T29: =SUM(F29:K29) -> -36069.863 | U29: =SUM(L29:Q29) -> -12143.277 | V29: =T29+U29 -> -48213.14
D30: PIS - V E | F30: =-0.65%*(F5+F8+F11+F14)-0.65%*F102 -> -6029.7188 | G30: =-0.65%*(G5+G8+G11+G14)-0.65%*G102 -> -4217.776 | H30: =-0.65%*(H5+H8+H11+H14)-0.65%*H102 -> -4298.4151 | I30: =-0.65%*(I5+I8+I11+I14)-0.65%*I102 -> -4451.9056 | J30: =-0.65%*(J5+J8+J11+J14)-0.65%*J102 -> -3775.9162 | K30: =-0.65%*(K5+K8+K11+K14)-0.65%*K102 -> -5232.0488 | L30: =-0.65%*(L5+L8+L11+L14)-0.65%*L102 -> -5385.7768 | M30: =-0.65%*(M5+M8+M11+M14)-0.65%*M102 -> -4268.6898 | ... Q30: =-0.65%*(Q5+Q8+Q11+Q14)-0.65%*Q102 -> 0 | R30: =SUM(F30:Q30) -> -37660.247 | T30: =SUM(F30:K30) -> -28005.78 | U30: =SUM(L30:Q30) -> -9654.4666 | V30: =T30+U30 -> -37660.247
D31: PIS - SPDX | F31: =-('Outras Informações'!B90*2.96%*(F16)) -> -282.76946 | G31: =-('Outras Informações'!C90*2.96%*(G16)) -> -271.67581 | H31: =-('Outras Informações'!D90*2.96%*(H16)) -> -265.45937 | I31: =-('Outras Informações'!E90*2.96%*(I16)) -> -262.53371 | J31: =-('Outras Informações'!F90*2.96%*(J16)) -> -276.3004 | K31: =-('Outras Informações'!G90*2.96%*(K16)) -> -276.47786 | L31: =-('Outras Informações'!H90*2.96%*(L16)) -> -284.34247 | M31: =-('Outras Informações'!I90*2.96%*(M16)) -> -291.70698 | ... Q31: =-('Outras Informações'!M90*2.96%*(Q16)) -> 0 | R31: =SUM(F31:Q31) -> -2211.2661 | T31: =SUM(F31:K31) -> -1635.2166 | U31: =SUM(L31:Q31) -> -576.04944 | V31: =T31+U31 -> -2211.2661
D32: PIS - Dataforte | F32: =-('Outras Informações'!B89*2.78%*(F17+F21+F22+F23)) -> -1106.5083 | G32: =-('Outras Informações'!C89*2.78%*(G17+G21+G22+G23)) -> -775.36617 | H32: =-('Outras Informações'!D89*2.78%*(H17+H21+H22+H23)) -> -819.51624 | I32: =-('Outras Informações'!E89*2.78%*(I17+I21+I22+I23)) -> -826.05356 | J32: =-('Outras Informações'!F89*2.78%*(J17+J21+J22+J23)) -> -1993.9575 | K32: =-('Outras Informações'!G89*2.78%*(K17+K21+K22+K23)) -> -907.46413 | L32: =-('Outras Informações'!H89*2.78%*(L17+L21+L22+L23)) -> -1062.3901 | M32: =-('Outras Informações'!I89*2.78%*(M17+M21+M22+M23)) -> -850.37073 | ... Q32: =-('Outras Informações'!M89*2.78%*(Q17+Q21+Q22+Q23)) -> 0 | R32: =SUM(F32:Q32) -> -8341.6267 | T32: =SUM(F32:K32) -> -6428.8659 | U32: =SUM(L32:Q32) -> -1912.7608 | V32: =T32+U32 -> -8341.6267
C33: COFINS | F33: =F34+F35+F36 -> -34235.178 | G33: =G34+G35+G36 -> -24294.179 | H33: =H34+H35+H36 -> -24841.312 | I33: =I34+I35+I36 -> -25566.395 | J33: =J34+J35+J36 -> -27895.684 | K33: =K34+K35+K36 -> -29606.738 | L33: =L34+L35+L36 -> -31066.936 | M33: =M34+M35+M36 -> -24967.356 | ... R33: =R34+R35+R36 -> -222473.78 | T33: =SUM(F33:K33) -> -166439.49 | U33: =SUM(L33:Q33) -> -56034.292 | V33: =T33+U33 -> -222473.78
D34: COFINS - V E | F34: =-3%*(F5+F8+F11+F14)-3%*F102 -> -27829.471 | G34: =-3%*(G5+G8+G11+G14)-3%*G102 -> -19466.658 | H34: =-3%*(H5+H8+H11+H14)-3%*H102 -> -19838.839 | I34: =-3%*(I5+I8+I11+I14)-3%*I102 -> -20547.256 | J34: =-3%*(J5+J8+J11+J14)-3%*J102 -> -17427.305 | K34: =-3%*(K5+K8+K11+K14)-3%*K102 -> -24147.918 | L34: =-3%*(L5+L8+L11+L14)-3%*L102 -> -24857.431 | M34: =-3%*(M5+M8+M11+M14)-3%*M102 -> -19701.645 | ... Q34: =-3%*(Q5+Q8+Q11+Q14)-3%*Q102 -> 0 | R34: =SUM(F34:Q34) -> -173816.52 | T34: =SUM(F34:K34) -> -129257.45 | U34: =SUM(L34:Q34) -> -44559.077 | V34: =T34+U34 -> -173816.52
D35: COFINS - SPDX | F35: =-('Outras Informações'!B90*13.64%*(F16)) -> -1303.0322 | G35: =-('Outras Informações'!C90*13.64%*(G16)) -> -1251.9115 | H35: =-('Outras Informações'!D90*13.64%*(H16)) -> -1223.2655 | I35: =-('Outras Informações'!E90*13.64%*(I16)) -> -1209.7837 | J35: =-('Outras Informações'!F90*13.64%*(J16)) -> -1273.2221 | K35: =-('Outras Informações'!G90*13.64%*(K16)) -> -1274.0399 | L35: =-('Outras Informações'!H90*13.64%*(L16)) -> -1310.2808 | M35: =-('Outras Informações'!I90*13.64%*(M16)) -> -1344.2173 | ... Q35: =-('Outras Informações'!M90*13.64%*(Q16)) -> 0 | R35: =SUM(F35:Q35) -> -10189.753 | T35: =SUM(F35:K35) -> -7535.255 | U35: =SUM(L35:Q35) -> -2654.4981 | V35: =T35+U35 -> -10189.753
D36: COFINS - Dataforte | F36: =-('Outras Informações'!B89*12.82%*(F17+F21+F22+F23)) -> -5102.6749 | G36: =-('Outras Informações'!C89*12.82%*(G17+G21+G22+G23)) -> -3575.6095 | H36: =-('Outras Informações'!D89*12.82%*(H17+H21+H22+H23)) -> -3779.208 | I36: =-('Outras Informações'!E89*12.82%*(I17+I21+I22+I23)) -> -3809.3549 | J36: =-('Outras Informações'!F89*12.82%*(J17+J21+J22+J23)) -> -9195.1566 | K36: =-('Outras Informações'!G89*12.82%*(K17+K21+K22+K23)) -> -4184.7806 | L36: =-('Outras Informações'!H89*12.82%*(L17+L21+L22+L23)) -> -4899.2233 | M36: =-('Outras Informações'!I89*12.82%*(M17+M21+M22+M23)) -> -3921.4938 | ... Q36: =-('Outras Informações'!M89*12.82%*(Q17+Q21+Q22+Q23)) -> 0 | R36: =SUM(F36:Q36) -> -38467.502 | T36: =SUM(F36:K36) -> -29646.785 | U36: =SUM(L36:Q36) -> -8820.7171 | V36: =T36+U36 -> -38467.502
C37: ISS | F37: =F38+F39+F40 -> -62821.007 | G37: =G38+G39+G40 -> -44770.799 | H37: =H38+H39+H40 -> -45854.869 | I37: =I38+I39+I40 -> -47082.219 | J37: =J38+J39+J40 -> -40634.203 | K37: =K38+K39+K40 -> -31680.229 | L37: =L38+L39+L40 -> -37489.933 | M37: =M38+M39+M40 -> -28465.71 | ... R37: =R38+R39+R40 -> -338798.97 | T37: =SUM(F37:K37) -> -272843.33 | U37: =SUM(L37:Q37) -> -65955.644 | V37: =T37+U37 -> -338798.97
D38: ISS - V E | F38: =-5%*(F5+F8+F11+F14)-5%*F102 -> -46382.452 | G38: =-5%*(G5+G8+G11+G14)-5%*G102 -> -32444.43 | H38: =-5%*(H5+H8+H11+H14)-5%*H102 -> -33064.732 | I38: =-5%*(I5+I8+I11+I14)-5%*I102 -> -34245.428 | J38: =-5%*('Outras Informações'!F60+J11+J14)-5%*J102-2%*'Outras Informações'!F61 -> -13572.593 | K38: =-5%*('Outras Informações'!G60+K11+K14)-5%*K102-2%*'Outras Informações'!G61 -> -17709.308 | L38: =-5%*('Outras Informações'!H60+L11+L14)-5%*L102-2%*'Outras Informações'!H61 -> -21565.747 | M38: =-5%*('Outras Informações'!I60+M11+M14)-5%*M102-2%*'Outras Informações'!I61 -> -15015.573 | N38: =-5%*('Outras Informações'!J60+N11+N14)-5%*N102-2%*'Outras Informações'!J61 -> 0 | O38: =-5%*('Outras Informações'!K60+O11+O14)-5%*O102-2%*'Outras Informações'!K61 -> 0 | P38: =-5%*('Outras Informações'!L60+P11+P14)-5%*P102-2%*'Outras Informações'!L61 -> 0 | Q38: =-5%*('Outras Informações'!M60+Q11+Q14)-5%*Q102-2%*'Outras Informações'!M61 -> 0 | R38: =SUM(F38:Q38) -> -214000.26 | T38: =SUM(F38:K38) -> -177418.94 | U38: =SUM(L38:Q38) -> -36581.321 | V38: =T38+U38 -> -214000.26
D39: ISS - SPDX | F39: =-('Outras Informações'!B90*32.5%*(F16)) -> -3104.7323 | G39: =-('Outras Informações'!C90*32.5%*(G16)) -> -2982.927 | H39: =-('Outras Informações'!D90*32.5%*(H16)) -> -2914.6722 | I39: =-('Outras Informações'!E90*32.5%*(I16)) -> -2882.5492 | J39: =-('Outras Informações'!F90*32.5%*(J16)) -> -3033.7037 | K39: =-('Outras Informações'!G90*32.5%*(K16)) -> -3035.6522 | L39: =-('Outras Informações'!H90*32.5%*(L16)) -> -3122.0034 | M39: =-('Outras Informações'!I90*32.5%*(M16)) -> -3202.8638 | ... Q39: =-('Outras Informações'!M90*32.5%*(Q16)) -> 0 | R39: =SUM(F39:Q39) -> -24279.104 | T39: =SUM(F39:K39) -> -17954.237 | U39: =SUM(L39:Q39) -> -6324.8672 | V39: =T39+U39 -> -24279.104
D40: ISS - Dataforte | F40: =-('Outras Informações'!B89*33.5%*(F17+F21+F22+F23)) -> -13333.823 | G40: =-('Outras Informações'!C89*33.5%*(G17+G21+G22+G23)) -> -9343.4413 | H40: =-('Outras Informações'!D89*33.5%*(H17+H21+H22+H23)) -> -9875.4655 | I40: =-('Outras Informações'!E89*33.5%*(I17+I21+I22+I23)) -> -9954.2426 | J40: =-('Outras Informações'!F89*33.5%*(J17+J21+J22+J23)) -> -24027.905 | K40: =-('Outras Informações'!G89*33.5%*(K17+K21+K22+K23)) -> -10935.269 | L40: =-('Outras Informações'!H89*33.5%*(L17+L21+L22+L23)) -> -12802.183 | M40: =-('Outras Informações'!I89*33.5%*(M17+M21+M22+M23)) -> -10247.273 | ... Q40: =-('Outras Informações'!M89*33.5%*(Q17+Q21+Q22+Q23)) -> 0 | R40: =SUM(F40:Q40) -> -100519.6 | T40: =SUM(F40:K40) -> -77470.147 | U40: =SUM(L40:Q40) -> -23049.456 | V40: =T40+U40 -> -100519.6
B41: Receita Operacional Líquida | F41: =F4+F27 -> 1582207.8 | G41: =G4+G27 -> 1204257.7 | H41: =H4+H27 -> 1371332.6 | I41: =I4+I27 -> 1343845.5 | J41: =J4+J27 -> 1521704.5 | K41: =K4+K27 -> 1378073.3 | L41: =L4+L27 -> 1572185.9 | M41: =M4+M27 -> 1327607.9 | ... R41: =R4+R27 -> 11301215 | T41: =SUM(F41:K41) -> 8401421.4 | U41: =SUM(L41:Q41) -> 2899793.7 | V41: =T41+U41 -> 11301215
B42: Custos com os Serviços Prestados | F42: =SUM(F43:F47) -> -75616.964 | G42: =SUM(G43:G47) -> -46012.15 | H42: =SUM(H43:H47) -> -61394.776 | I42: =SUM(I43:I47) -> -52504.502 | J42: =SUM(J43:J47) -> -235852.36 | K42: =SUM(K43:K47) -> -30271.711 | L42: =SUM(L43:L47) -> -54339.315 | M42: =SUM(M43:M47) -> -14711.093 | ... R42: =SUM(R43:R47) -> -570702.87 | T42: =SUM(F42:K42) -> -501652.47 | U42: =SUM(L42:Q42) -> -69050.408 | V42: =T42+U42 -> -570702.87
C43: Comissões | F43: =SUMIFS('Lançamentos Omie'!$G:$G,'Lançamentos Omie'!$I:$I,$C43,'Lançamentos Omie'!$F:$F,F$2)-'Outras Informações'!B97 -> -12966.67 | G43: =SUMIFS('Lançamentos Omie'!$G:$G,'Lançamentos Omie'!$I:$I,$C43,'Lançamentos Omie'!$F:$F,G$2)-'Outras Informações'!C97 -> -12966.67 | H43: =SUMIFS('Lançamentos Omie'!$G:$G,'Lançamentos Omie'!$I:$I,$C43,'Lançamentos Omie'!$F:$F,H$2)-'Outras Informações'!D97 -> -12966.67 | I43: =SUMIFS('Lançamentos Omie'!$G:$G,'Lançamentos Omie'!$I:$I,$C43,'Lançamentos Omie'!$F:$F,I$2)-'Outras Informações'!E97 -> -12966.67 | J43: =SUMIFS('Lançamentos Omie'!$G:$G,'Lançamentos Omie'!$I:$I,$C43,'Lançamentos Omie'!$F:$F,J$2)-'Outras Informações'!F97 -> -23166.67 | K43: =SUMIFS('Lançamentos Omie'!$G:$G,'Lançamentos Omie'!$I:$I,$C43,'Lançamentos Omie'!$F:$F,K$2)-'Outras Informações'!G97 -> -12966.67 | L43: =SUMIFS('Lançamentos Omie'!$G:$G,'Lançamentos Omie'!$I:$I,$C43,'Lançamentos Omie'!$F:$F,L$2)-'Outras Informações'!H97 -> -12966.67 | M43: =SUMIFS('Lançamentos Omie'!$G:$G,'Lançamentos Omie'!$I:$I,$C43,'Lançamentos Omie'!$F:$F,M$2)-'Outras Informações'!I97 -> -12966.67 | ... Q43: =SUMIFS('Lançamentos Omie'!$G:$G,'Lançamentos Omie'!$I:$I,$C43,'Lançamentos Omie'!$F:$F,Q$2)-'Outras Informações'!M97 -> 0 | R43: =SUM(F43:Q43) -> -113933.36 | T43: =SUM(F43:K43) -> -88000.02 | U43: =SUM(L43:Q43) -> -25933.34 | V43: =T43+U43 -> -113933.36
C44: Custos com Festas de Arrecadação | F44: =-'P&D'!C6-'P&D'!B25 -> -1535.494 | G44: =-'P&D'!D6-'P&D'!C25 -> -2166.0599 | H44: =-'P&D'!E6-'P&D'!D25 -> -2401.7164 | I44: =-'P&D'!F6-'P&D'!E25 -> -3363.4121 | J44: =-'P&D'!G6-'P&D'!F25 -> -188587.8 | K44: =-'P&D'!H6-'P&D'!G25 -> -4360.0908 | L44: =-'P&D'!I6-'P&D'!H25 -> -5077.9446 | M44: =-'P&D'!J6-'P&D'!I25 -> -1744.4233 | ... Q44: =-'P&D'!N6-'P&D'!M25 -> 0 | R44: =SUM(F44:Q44) -> -209236.94 | T44: =SUM(F44:K44) -> -202414.58 | U44: =SUM(L44:Q44) -> -6822.368 | V44: =T44+U44 -> -209236.94
C45: Custos com Treinamentos | F45: =-'Outras Informações'!B104+SUMIFS('Lançamentos Omie'!$G:$G,'Lançamentos Omie'!$I:$I,$C45,'Lançamentos Omie'!$F:$F,F$2) -> -45074.34 | G45: =-'Outras Informações'!C104+SUMIFS('Lançamentos Omie'!$G:$G,'Lançamentos Omie'!$I:$I,$C45,'Lançamentos Omie'!$F:$F,G$2) -> -9114.12 | H45: =-'Outras Informações'!D104+SUMIFS('Lançamentos Omie'!$G:$G,'Lançamentos Omie'!$I:$I,$C45,'Lançamentos Omie'!$F:$F,H$2) -> -2700 | I45: =-'Outras Informações'!E104+SUMIFS('Lançamentos Omie'!$G:$G,'Lançamentos Omie'!$I:$I,$C45,'Lançamentos Omie'!$F:$F,I$2) -> -3658 | J45: =-'Outras Informações'!F104+SUMIFS('Lançamentos Omie'!$G:$G,'Lançamentos Omie'!$I:$I,$C45,'Lançamentos Omie'!$F:$F,J$2) -> -4595.65 | K45: =-'Outras Informações'!G104+SUMIFS('Lançamentos Omie'!$G:$G,'Lançamentos Omie'!$I:$I,$C45,'Lançamentos Omie'!$F:$F,K$2) -> -5880.9 | L45: =-'Outras Informações'!H104+SUMIFS('Lançamentos Omie'!$G:$G,'Lançamentos Omie'!$I:$I,$C45,'Lançamentos Omie'!$F:$F,L$2) -> -20072.44 | M45: =-'Outras Informações'!I104+SUMIFS('Lançamentos Omie'!$G:$G,'Lançamentos Omie'!$I:$I,$C45,'Lançamentos Omie'!$F:$F,M$2) -> 0 | ... Q45: =-'Outras Informações'!M104+SUMIFS('Lançamentos Omie'!$G:$G,'Lançamentos Omie'!$I:$I,$C45,'Lançamentos Omie'!$F:$F,Q$2) -> 0 | R45: =SUM(F45:Q45) -> -91095.45 | T45: =SUM(F45:K45) -> -71023.01 | U45: =SUM(L45:Q45) -> -20072.44 | V45: =T45+U45 -> -91095.45
C46: Custos Serviços Prestados - Diárias Consultorias | F46: =SUMIFS('Lançamentos Omie'!$G:$G,'Lançamentos Omie'!$I:$I,$C46,'Lançamentos Omie'!$F:$F,F$2)-'Viagens Consultoria'!C13 -> -9757.37 | G46: =SUMIFS('Lançamentos Omie'!$G:$G,'Lançamentos Omie'!$I:$I,$C46,'Lançamentos Omie'!$F:$F,G$2)-'Viagens Consultoria'!D13 -> -21765.3 | H46: =SUMIFS('Lançamentos Omie'!$G:$G,'Lançamentos Omie'!$I:$I,$C46,'Lançamentos Omie'!$F:$F,H$2)-'Viagens Consultoria'!E13 -> -43326.39 | I46: =SUMIFS('Lançamentos Omie'!$G:$G,'Lançamentos Omie'!$I:$I,$C46,'Lançamentos Omie'!$F:$F,I$2)-'Viagens Consultoria'!F13 -> -32516.42 | J46: =SUMIFS('Lançamentos Omie'!$G:$G,'Lançamentos Omie'!$I:$I,$C46,'Lançamentos Omie'!$F:$F,J$2)-'Viagens Consultoria'!G13+'Viagens Consultoria'!J43+'Viagens Consultoria'!J44+'Viagens Consultoria'!J46+'Viagens Consultoria'!J48 -> -19502.24 | K46: =SUMIFS('Lançamentos Omie'!$G:$G,'Lançamentos Omie'!$I:$I,$C46,'Lançamentos Omie'!$F:$F,K$2)-'Viagens Consultoria'!H13+'Viagens Consultoria'!H11 -> -7064.05 | L46: =SUMIFS('Lançamentos Omie'!$G:$G,'Lançamentos Omie'!$I:$I,$C46,'Lançamentos Omie'!$F:$F,L$2)-'Viagens Consultoria'!I13+'Viagens Consultoria'!I11 -> -16222.26 | R46: =SUM(F46:Q46) -> -150154.03 | T46: =SUM(F46:K46) -> -133931.77 | U46: =SUM(L46:Q46) -> -16222.26 | V46: =T46+U46 -> -150154.03
C47: Custo de Seguro da Arrecadação | F47: =SUMIFS('Lançamentos Omie'!$G:$G,'Lançamentos Omie'!$I:$I,$C47,'Lançamentos Omie'!$F:$F,F$2)-'Outras Informações'!B101 -> -6283.09 | G47: =SUMIFS('Lançamentos Omie'!$G:$G,'Lançamentos Omie'!$I:$I,$C47,'Lançamentos Omie'!$F:$F,G$2)-'Outras Informações'!C101 -> 0 | H47: =SUMIFS('Lançamentos Omie'!$G:$G,'Lançamentos Omie'!$I:$I,$C47,'Lançamentos Omie'!$F:$F,H$2)-'Outras Informações'!D101 -> 0 | I47: =SUMIFS('Lançamentos Omie'!$G:$G,'Lançamentos Omie'!$I:$I,$C47,'Lançamentos Omie'!$F:$F,I$2)-'Outras Informações'!E101 -> 0 | J47: =SUMIFS('Lançamentos Omie'!$G:$G,'Lançamentos Omie'!$I:$I,$C47,'Lançamentos Omie'!$F:$F,J$2)-'Outras Informações'!F101 -> 0 | K47: =SUMIFS('Lançamentos Omie'!$G:$G,'Lançamentos Omie'!$I:$I,$C47,'Lançamentos Omie'!$F:$F,K$2)-'Outras Informações'!G101 -> 0 | L47: =SUMIFS('Lançamentos Omie'!$G:$G,'Lançamentos Omie'!$I:$I,$C47,'Lançamentos Omie'!$F:$F,L$2)-'Outras Informações'!H101 -> 0 | M47: =SUMIFS('Lançamentos Omie'!$G:$G,'Lançamentos Omie'!$I:$I,$C47,'Lançamentos Omie'!$F:$F,M$2)-'Outras Informações'!I101 -> 0 | ... Q47: =SUMIFS('Lançamentos Omie'!$G:$G,'Lançamentos Omie'!$I:$I,$C47,'Lançamentos Omie'!$F:$F,Q$2)-'Outras Informações'!M101 -> 0 | R47: =SUM(F47:Q47) -> -6283.09 | T47: =SUM(F47:K47) -> -6283.09 | U47: =SUM(L47:Q47) -> 0 | V47: =T47+U47 -> -6283.09
B48: Lucro Operacional Bruto | F48: =F41+F42 -> 1506590.8 | G48: =G41+G42 -> 1158245.6 | H48: =H41+H42 -> 1309937.8 | I48: =I41+I42 -> 1291341 | J48: =J41+J42 -> 1285852.1 | K48: =K41+K42 -> 1347801.6 | L48: =L41+L42 -> 1517846.6 | M48: =M41+M42 -> 1312896.8 | ... R48: =R41+R42 -> 10730512 | T48: =SUM(F48:K48) -> 7899768.9 | U48: =SUM(L48:Q48) -> 2830743.3 | V48: =T48+U48 -> 10730512
B49: Despesas Operacionais | F49: =F50+F52+F77+F93+F98 -> -798679.77 | G49: =G50+G52+G77+G93+G98 -> -797902.93 | H49: =H50+H52+H77+H93+H98 -> -811408.82 | I49: =I50+I52+I77+I93+I98 -> -819658.86 | J49: =J50+J52+J77+J93+J98 -> -812642.89 | K49: =K50+K52+K77+K93+K98 -> -790160.48 | L49: =L50+L52+L77+L93+L98 -> -784338.05 | M49: =M50+M52+M77+M93+M98 -> -771611.06 | ... R49: =R50+R52+R77+R93+R98 -> -6386402.9 | T49: =SUM(F49:K49) -> -4830453.8 | U49: =SUM(L49:Q49) -> -1555949.1 | V49: =T49+U49 -> -6386402.9
C50: Despesas de Vendas e Marketing | F50: =F51 -> -5904.09 | G50: =G51 -> -1572.44 | H50: =H51 -> -1868.52 | I50: =I51 -> -18760.59 | J50: =J51 -> -6865.39 | K50: =K51 -> -10164.83 | L50: =L51 -> -3093.07 | M50: =M51 -> -6624.71 | ... R50: =R51 -> -54853.64 | T50: =SUM(F50:K50) -> -45135.86 | U50: =SUM(L50:Q50) -> -9717.78 | V50: =T50+U50 -> -54853.64
D51: Marketing | F51: =SUMIFS('Lançamentos Omie'!$G:$G,'Lançamentos Omie'!$I:$I,$D51,'Lançamentos Omie'!$F:$F,F$2) -> -5904.09 | G51: =SUMIFS('Lançamentos Omie'!$G:$G,'Lançamentos Omie'!$I:$I,$D51,'Lançamentos Omie'!$F:$F,G$2) -> -1572.44 | H51: =SUMIFS('Lançamentos Omie'!$G:$G,'Lançamentos Omie'!$I:$I,$D51,'Lançamentos Omie'!$F:$F,H$2) -> -1868.52 | I51: =SUMIFS('Lançamentos Omie'!$G:$G,'Lançamentos Omie'!$I:$I,$D51,'Lançamentos Omie'!$F:$F,I$2) -> -18760.59 | J51: =SUMIFS('Lançamentos Omie'!$G:$G,'Lançamentos Omie'!$I:$I,$D51,'Lançamentos Omie'!$F:$F,J$2) -> -6865.39 | K51: =SUMIFS('Lançamentos Omie'!$G:$G,'Lançamentos Omie'!$I:$I,$D51,'Lançamentos Omie'!$F:$F,K$2) -> -10164.83 | L51: =SUMIFS('Lançamentos Omie'!$G:$G,'Lançamentos Omie'!$I:$I,$D51,'Lançamentos Omie'!$F:$F,L$2) -> -3093.07 | M51: =SUMIFS('Lançamentos Omie'!$G:$G,'Lançamentos Omie'!$I:$I,$D51,'Lançamentos Omie'!$F:$F,M$2) -> -6624.71 | ... Q51: =SUMIFS('Lançamentos Omie'!$G:$G,'Lançamentos Omie'!$I:$I,$D51,'Lançamentos Omie'!$F:$F,Q$2) -> 0 | R51: =SUM(F51:Q51) -> -54853.64 | T51: =SUM(F51:K51) -> -45135.86 | U51: =SUM(L51:Q51) -> -9717.78 | V51: =T51+U51 -> -54853.64
C52: Despesas com Pessoal | F52: =SUM(F53:F57,F61:F76) -> -672343.47 | G52: =SUM(G53:G57,G61:G76) -> -695742.35 | H52: =SUM(H53:H57,H61:H76) -> -710300.6 | I52: =SUM(I53:I57,I61:I76) -> -680701.65 | J52: =SUM(J53:J57,J61:J76) -> -694374.99 | K52: =SUM(K53:K57,K61:K76) -> -677412.03 | L52: =SUM(L53:L57,L61:L76) -> -701124.28 | M52: =SUM(M53:M57,M61:M76) -> -683122.67 | ... R52: =SUM(R53:R57,R61:R76) -> -5515122.1 | T52: =SUM(F52:K52) -> -4130875.1 | U52: =SUM(L52:Q52) -> -1384247 | V52: =T52+U52 -> -5515122.1
D53: Salários | F53: =-Pessoal!D4-6766.5 -> -240113.48 | G53: =-Pessoal!E4 -> -242102.74 | H53: =-Pessoal!F4 -> -236025.11 | I53: =-Pessoal!G4 -> -225382.29 | J53: =-Pessoal!H4 -> -225809.01 | K53: =-Pessoal!I4 -> -232624.79 | L53: =-Pessoal!J4 -> -236097.42 | M53: =-Pessoal!K4 -> -237979.84 | R53: =SUM(F53:Q53) -> -1876134.7 | T53: =SUM(F53:K53) -> -1402057.4 | U53: =SUM(L53:Q53) -> -474077.26 | V53: =T53+U53 -> -1876134.7
D54: Férias | F54: =-Pessoal!D90-203 -> -8011.5885 | G54: =-Pessoal!E90 -> -8109.3939 | H54: =-Pessoal!F90 -> -8022.6528 | I54: =-Pessoal!G90 -> -7659.9706 | J54: =-Pessoal!H90 -> -7627.16 | K54: =-Pessoal!I90 -> -7863.8277 | L54: =-Pessoal!J90 -> -7856.1561 | M54: =-Pessoal!K90 -> -7883.5261 | R54: =SUM(F54:Q54) -> -63034.276 | T54: =SUM(F54:K54) -> -47294.594 | U54: =SUM(L54:Q54) -> -15739.682 | V54: =T54+U54 -> -63034.276
D55: Rescisões | F55: =-Pessoal!D614 -> -1800.23 | G55: =-Pessoal!E614 -> 0 | H55: =-Pessoal!F614 -> -25560.77 | I55: =-Pessoal!G614 -> -11451.61 | J55: =-Pessoal!H614 -> -4477.71 | K55: =-Pessoal!I614 -> -3847.35 | L55: =-Pessoal!J614 -> -14621.74 | M55: =-Pessoal!K614 -> 0 | ... Q55: =-Pessoal!O614 -> 0 | R55: =SUM(F55:Q55) -> -61759.41 | T55: =SUM(F55:K55) -> -47137.67 | U55: =SUM(L55:Q55) -> -14621.74 | V55: =T55+U55 -> -61759.41
D56: 13º Salário | F56: =-Pessoal!D176-608.99 -> -24034.756 | G56: =-Pessoal!E176 -> -24328.182 | H56: =-Pessoal!F176 -> -24067.958 | I56: =-Pessoal!G176 -> -22979.912 | J56: =-Pessoal!H176 -> -22881.48 | K56: =-Pessoal!I176 -> -23594.403 | L56: =-Pessoal!J176 -> -23504.748 | M56: =-Pessoal!K176 -> -23536.878 | R56: =SUM(F56:Q56) -> -188928.32 | T56: =SUM(F56:K56) -> -141886.69 | U56: =SUM(L56:Q56) -> -47041.625 | V56: =T56+U56 -> -188928.32
D57: INSS | F57: =SUM(F58:F60) -> -58074.727 | G57: =SUM(G58:G60) -> -54927.448 | H57: =SUM(H58:H60) -> -54131.204 | I57: =SUM(I58:I60) -> -50530.478 | J57: =SUM(J58:J60) -> -69114.838 | K57: =SUM(K58:K60) -> -53713.328 | L57: =SUM(L58:L60) -> -56424.701 | M57: =SUM(M58:M60) -> -53351.47 | ... Q57: =SUM(Q58:Q60) -> 0 | R57: =R58+R59+R60 -> -450268.19 | T57: =SUM(F57:K57) -> -340492.02 | U57: =SUM(L57:Q57) -> -109776.17 | V57: =T57+U57 -> -450268.19
E58: INSS - V E | F58: =-Pessoal!D262 -> -36654.449 | G58: =-Pessoal!E262 -> -38839.456 | H58: =-Pessoal!F262 -> -37445.109 | I58: =-Pessoal!G262 -> -33785.222 | J58: =-Pessoal!H262 -> -33934.988 | K58: =-Pessoal!I262 -> -35492.679 | L58: =-Pessoal!J262 -> -35670.112 | M58: =-Pessoal!K262 -> -35798.843 | R58: =SUM(F58:Q58) -> -287620.86 | T58: =SUM(F58:K58) -> -216151.9 | U58: =SUM(L58:Q58) -> -71468.955
E59: INSS - SPDX | F59: =-('Outras Informações'!B90*43.4%*(F16)) -> -4146.0117 | G59: =-('Outras Informações'!C90*43.4%*(G16)) -> -3983.3548 | H59: =-('Outras Informações'!D90*43.4%*(H16)) -> -3892.2084 | I59: =-('Outras Informações'!E90*43.4%*(I16)) -> -3849.3119 | J59: =-('Outras Informações'!F90*43.4%*(J16)) -> -4051.1613 | K59: =-('Outras Informações'!G90*43.4%*(K16)) -> -4053.7633 | L59: =-('Outras Informações'!H90*43.4%*(L16)) -> -4169.0753 | M59: =-('Outras Informações'!I90*43.4%*(M16)) -> -4277.055 | ... Q59: =-('Outras Informações'!M90*43.4%*(Q16)) -> 0 | R59: =SUM(F59:Q59) -> -32421.942 | T59: =SUM(F59:K59) -> -23975.811 | U59: =SUM(L59:Q59) -> -8446.1303
E60: INSS - Dataforte | F60: =-('Outras Informações'!B89*43.4%*(F17+F21+F22+F23)) -> -17274.266 | G60: =-('Outras Informações'!C89*43.4%*(G17+G21+G22+G23)) -> -12104.637 | H60: =-('Outras Informações'!D89*43.4%*(H17+H21+H22+H23)) -> -12793.887 | I60: =-('Outras Informações'!E89*43.4%*(I17+I21+I22+I23)) -> -12895.944 | J60: =-('Outras Informações'!F89*43.4%*(J17+J21+J22+J23)) -> -31128.689 | K60: =-('Outras Informações'!G89*43.4%*(K17+K21+K22+K23)) -> -14166.886 | L60: =-('Outras Informações'!H89*43.4%*(L17+L21+L22+L23)) -> -16585.514 | M60: =-('Outras Informações'!I89*43.4%*(M17+M21+M22+M23)) -> -13275.572 | ... Q60: =-('Outras Informações'!M89*43.4%*(Q17+Q21+Q22+Q23)) -> 0 | R60: =SUM(F60:Q60) -> -130225.4 | T60: =SUM(F60:K60) -> -100364.31 | U60: =SUM(L60:Q60) -> -29861.086
D61: FGTS | F61: =-Pessoal!D348- 541.32 -> -18649.078 | G61: =-Pessoal!E348 -> -18808.219 | H61: =-Pessoal!F348 -> -18402.009 | I61: =-Pessoal!G348 -> -17550.583 | J61: =-Pessoal!H348 -> -17664.721 | K61: =-Pessoal!I348 -> -18209.983 | L61: =-Pessoal!J348 -> -17683.278 | M61: =-Pessoal!K348 -> -17833.871 | N61: =-Pessoal!L348 -> 0 | ... Q61: =-Pessoal!O348 -> 0 | R61: =SUM(F61:Q61) -> -144801.74 | T61: =SUM(F61:K61) -> -109284.59 | U61: =SUM(L61:Q61) -> -35517.149 | V61: =T61+U61 -> -144801.74
D62: IRRF | F62: 0 | G62: 0 | H62: 0 | I62: 0 | J62: 0 | K62: 0 | L62: 0 | M62: 0 | N62: 0 | O62: 0 | P62: 0 | Q62: 0 | R62: =SUM(F62:Q62) -> 0 | T62: =SUM(F62:K62) -> 0 | U62: =SUM(L62:Q62) -> 0 | V62: =T62+U62 -> 0
D63: Pensão Alimentícia | F63: =SUMIFS('Lançamentos Omie'!$G:$G,'Lançamentos Omie'!$I:$I,$D63,'Lançamentos Omie'!$F:$F,F$2) -> 0 | G63: =SUMIFS('Lançamentos Omie'!$G:$G,'Lançamentos Omie'!$I:$I,$D63,'Lançamentos Omie'!$F:$F,G$2) -> 0 | H63: =SUMIFS('Lançamentos Omie'!$G:$G,'Lançamentos Omie'!$I:$I,$D63,'Lançamentos Omie'!$F:$F,H$2) -> 0 | I63: =SUMIFS('Lançamentos Omie'!$G:$G,'Lançamentos Omie'!$I:$I,$D63,'Lançamentos Omie'!$F:$F,I$2) -> 0 | J63: =SUMIFS('Lançamentos Omie'!$G:$G,'Lançamentos Omie'!$I:$I,$D63,'Lançamentos Omie'!$F:$F,J$2) -> 0 | K63: =SUMIFS('Lançamentos Omie'!$G:$G,'Lançamentos Omie'!$I:$I,$D63,'Lançamentos Omie'!$F:$F,K$2) -> 0 | L63: =SUMIFS('Lançamentos Omie'!$G:$G,'Lançamentos Omie'!$I:$I,$D63,'Lançamentos Omie'!$F:$F,L$2) -> 0 | M63: =SUMIFS('Lançamentos Omie'!$G:$G,'Lançamentos Omie'!$I:$I,$D63,'Lançamentos Omie'!$F:$F,M$2) -> 0 | ... Q63: =SUMIFS('Lançamentos Omie'!$G:$G,'Lançamentos Omie'!$I:$I,$D63,'Lançamentos Omie'!$F:$F,Q$2) -> 0 | R63: =SUM(F63:Q63) -> 0 | T63: =SUM(F63:K63) -> 0 | U63: =SUM(L63:Q63) -> 0 | V63: =T63+U63 -> 0
D64: Assistência Médica | F64: =SUMIFS('Lançamentos Omie'!$G:$G,'Lançamentos Omie'!$I:$I,$D64,'Lançamentos Omie'!$F:$F,F$2) -> -8370.35 | G64: =SUMIFS('Lançamentos Omie'!$G:$G,'Lançamentos Omie'!$I:$I,$D64,'Lançamentos Omie'!$F:$F,G$2) -> -6571.82 | H64: =SUMIFS('Lançamentos Omie'!$G:$G,'Lançamentos Omie'!$I:$I,$D64,'Lançamentos Omie'!$F:$F,H$2) -> -3866.92 | I64: =SUMIFS('Lançamentos Omie'!$G:$G,'Lançamentos Omie'!$I:$I,$D64,'Lançamentos Omie'!$F:$F,I$2) -> -2196.5 | J64: =SUMIFS('Lançamentos Omie'!$G:$G,'Lançamentos Omie'!$I:$I,$D64,'Lançamentos Omie'!$F:$F,J$2) -> -3276.4 | K64: =SUMIFS('Lançamentos Omie'!$G:$G,'Lançamentos Omie'!$I:$I,$D64,'Lançamentos Omie'!$F:$F,K$2) -> -2115.08 | L64: =SUMIFS('Lançamentos Omie'!$G:$G,'Lançamentos Omie'!$I:$I,$D64,'Lançamentos Omie'!$F:$F,L$2) -> -3812.39 | M64: =SUMIFS('Lançamentos Omie'!$G:$G,'Lançamentos Omie'!$I:$I,$D64,'Lançamentos Omie'!$F:$F,M$2) -> -3677.87 | ... Q64: =SUMIFS('Lançamentos Omie'!$G:$G,'Lançamentos Omie'!$I:$I,$D64,'Lançamentos Omie'!$F:$F,Q$2) -> 0 | R64: =SUM(F64:Q64) -> -33887.33 | T64: =SUM(F64:K64) -> -26397.07 | U64: =SUM(L64:Q64) -> -7490.26 | V64: =T64+U64 -> -33887.33
D65: Benefícios Flexíveis | F65: =-Pessoal!D434-695-600 -> -37118.14 | G65: =-Pessoal!E434 -> -39531.39 | H65: =-Pessoal!F434 -> -40001.38 | I65: =-Pessoal!G434 -> -39103.17 | J65: =-Pessoal!H434 -> -38078.13 | K65: =-Pessoal!I434 -> -38841.6 | L65: =-Pessoal!J434 -> -37844.81 | M65: =-Pessoal!K434 -> -37735.17 | N65: =-Pessoal!L434 -> 0 | ... Q65: =-Pessoal!O434 -> 0 | R65: =SUM(F65:Q65) -> -308253.79 | T65: =SUM(F65:K65) -> -232673.81 | U65: =SUM(L65:Q65) -> -75579.98 | V65: =T65+U65 -> -308253.79
D66: Vale Transporte / Mobilidade | F66: =-Pessoal!D605 -> -464.81 | G66: =-Pessoal!E605 -> -404.1 | H66: =-Pessoal!F605 -> -506.76 | I66: =-Pessoal!G605 -> -227.53 | J66: =-Pessoal!H605 -> -150 | K66: =-Pessoal!I605 -> -157.5 | L66: =-Pessoal!J605 -> -90 | M66: =-Pessoal!K605 -> -157.5 | ... Q66: =-Pessoal!O605 -> 0 | R66: =SUM(F66:Q66) -> -2158.2 | T66: =SUM(F66:K66) -> -1910.7 | U66: =SUM(L66:Q66) -> -247.5 | V66: =T66+U66 -> -2158.2
D67: Seguro de Vida | F67: =SUMIFS('Lançamentos Omie'!$G:$G,'Lançamentos Omie'!$I:$I,$D67,'Lançamentos Omie'!$F:$F,F$2) -> 0 | G67: =SUMIFS('Lançamentos Omie'!$G:$G,'Lançamentos Omie'!$I:$I,$D67,'Lançamentos Omie'!$F:$F,G$2) -> 0 | H67: =SUMIFS('Lançamentos Omie'!$G:$G,'Lançamentos Omie'!$I:$I,$D67,'Lançamentos Omie'!$F:$F,H$2) -> 0 | I67: =SUMIFS('Lançamentos Omie'!$G:$G,'Lançamentos Omie'!$I:$I,$D67,'Lançamentos Omie'!$F:$F,I$2) -> 0 | J67: =SUMIFS('Lançamentos Omie'!$G:$G,'Lançamentos Omie'!$I:$I,$D67,'Lançamentos Omie'!$F:$F,J$2) -> 0 | K67: =SUMIFS('Lançamentos Omie'!$G:$G,'Lançamentos Omie'!$I:$I,$D67,'Lançamentos Omie'!$F:$F,K$2) -> -26.25 | L67: =SUMIFS('Lançamentos Omie'!$G:$G,'Lançamentos Omie'!$I:$I,$D67,'Lançamentos Omie'!$F:$F,L$2) -> 0 | M67: =SUMIFS('Lançamentos Omie'!$G:$G,'Lançamentos Omie'!$I:$I,$D67,'Lançamentos Omie'!$F:$F,M$2) -> 0 | ... Q67: =SUMIFS('Lançamentos Omie'!$G:$G,'Lançamentos Omie'!$I:$I,$D67,'Lançamentos Omie'!$F:$F,Q$2) -> 0 | R67: =SUM(F67:Q67) -> -26.25 | T67: =SUM(F67:K67) -> -26.25 | U67: =SUM(L67:Q67) -> 0 | V67: =T67+U67 -> -26.25
D68: Refeições | F68: =SUMIFS('Lançamentos Omie'!$G:$G,'Lançamentos Omie'!$I:$I,$D68,'Lançamentos Omie'!$F:$F,F$2) -> -15429.9 | G68: =SUMIFS('Lançamentos Omie'!$G:$G,'Lançamentos Omie'!$I:$I,$D68,'Lançamentos Omie'!$F:$F,G$2) -> -17038.6 | H68: =SUMIFS('Lançamentos Omie'!$G:$G,'Lançamentos Omie'!$I:$I,$D68,'Lançamentos Omie'!$F:$F,H$2) -> -18171.3 | I68: =SUMIFS('Lançamentos Omie'!$G:$G,'Lançamentos Omie'!$I:$I,$D68,'Lançamentos Omie'!$F:$F,I$2) -> -16265 | J68: =SUMIFS('Lançamentos Omie'!$G:$G,'Lançamentos Omie'!$I:$I,$D68,'Lançamentos Omie'!$F:$F,J$2) -> -16897.6 | K68: =SUMIFS('Lançamentos Omie'!$G:$G,'Lançamentos Omie'!$I:$I,$D68,'Lançamentos Omie'!$F:$F,K$2) -> -16980.9 | L68: =SUMIFS('Lançamentos Omie'!$G:$G,'Lançamentos Omie'!$I:$I,$D68,'Lançamentos Omie'!$F:$F,L$2) -> -21649.6 | M68: =SUMIFS('Lançamentos Omie'!$G:$G,'Lançamentos Omie'!$I:$I,$D68,'Lançamentos Omie'!$F:$F,M$2) -> -20481.1 | ... Q68: =SUMIFS('Lançamentos Omie'!$G:$G,'Lançamentos Omie'!$I:$I,$D68,'Lançamentos Omie'!$F:$F,Q$2) -> 0 | R68: =SUM(F68:Q68) -> -142914 | T68: =SUM(F68:K68) -> -100783.3 | U68: =SUM(L68:Q68) -> -42130.7 | V68: =T68+U68 -> -142914
D69: Auxílio Home Office | F69: =-Pessoal!D519 -> -3690 | G69: =-Pessoal!E519 -> -3540 | H69: =-Pessoal!F519 -> -3540 | I69: =-Pessoal!G519 -> -3540 | J69: =-Pessoal!H519 -> -3240 | K69: =-Pessoal!I519 -> -3390 | L69: =-Pessoal!J519 -> -3390 | M69: =-Pessoal!K519 -> -3390 | ... Q69: =-Pessoal!O519 -> 0 | R69: =SUM(F69:Q69) -> -27720 | T69: =SUM(F69:K69) -> -20940 | U69: =SUM(L69:Q69) -> -6780 | V69: =T69+U69 -> -27720
D70: Pró Labore Sócios | F70: =-'Outras Informações'!B94 -> -205685 | G70: =-'Outras Informações'!C94 -> -226448.95 | H70: =-'Outras Informações'!D94 -> -226448.95 | I70: =-'Outras Informações'!E94 -> -226448.95 | J70: =-'Outras Informações'!F94 -> -226448.95 | K70: =-'Outras Informações'!G94 -> -226448.95 | L70: =-'Outras Informações'!H94 -> -226448.95 | M70: =-'Outras Informações'!I94 -> -226448.95 | ... Q70: =-'Outras Informações'!M94 -> 0 | R70: =SUM(F70:Q70) -> -1790827.6 | T70: =SUM(F70:K70) -> -1337929.8 | U70: =SUM(L70:Q70) -> -452897.9 | V70: =T70+U70 -> -1790827.6
D71: Bônus EBITDA | F71: =-'Outras Informações'!B100 -> -36375 | G71: =-'Outras Informações'!C100 -> -36375 | H71: =-'Outras Informações'!D100 -> -36375 | I71: =-'Outras Informações'!E100 -> -36375 | J71: =-'Outras Informações'!F100 -> -36375 | K71: =-'Outras Informações'!G100 -> -36375 | L71: =-'Outras Informações'!H100 -> -36375 | M71: =-'Outras Informações'!I100 -> -36375 | ... Q71: =-'Outras Informações'!M100 -> 0 | R71: =SUM(F71:Q71) -> -291000 | T71: =SUM(F71:K71) -> -218250 | U71: =SUM(L71:Q71) -> -72750 | V71: =T71+U71 -> -291000
D72: Outros ( Contribuição Sindical - PCMO, Exames...) | F72: =SUMIFS('Lançamentos Omie'!$G:$G,'Lançamentos Omie'!$I:$I,$D72,'Lançamentos Omie'!$F:$F,F$2) -> -460.56 | G72: =SUMIFS('Lançamentos Omie'!$G:$G,'Lançamentos Omie'!$I:$I,$D72,'Lançamentos Omie'!$F:$F,G$2) -> -540.87 | H72: =SUMIFS('Lançamentos Omie'!$G:$G,'Lançamentos Omie'!$I:$I,$D72,'Lançamentos Omie'!$F:$F,H$2) -> -603.97 | I72: =SUMIFS('Lançamentos Omie'!$G:$G,'Lançamentos Omie'!$I:$I,$D72,'Lançamentos Omie'!$F:$F,I$2) -> -440.23 | J72: =SUMIFS('Lançamentos Omie'!$G:$G,'Lançamentos Omie'!$I:$I,$D72,'Lançamentos Omie'!$F:$F,J$2) -> -714.85 | K72: =SUMIFS('Lançamentos Omie'!$G:$G,'Lançamentos Omie'!$I:$I,$D72,'Lançamentos Omie'!$F:$F,K$2) -> -1250.76 | L72: =SUMIFS('Lançamentos Omie'!$G:$G,'Lançamentos Omie'!$I:$I,$D72,'Lançamentos Omie'!$F:$F,L$2) -> -501.73 | M72: =SUMIFS('Lançamentos Omie'!$G:$G,'Lançamentos Omie'!$I:$I,$D72,'Lançamentos Omie'!$F:$F,M$2) -> -505 | ... Q72: =SUMIFS('Lançamentos Omie'!$G:$G,'Lançamentos Omie'!$I:$I,$D72,'Lançamentos Omie'!$F:$F,Q$2) -> 0 | R72: =SUM(F72:Q72) -> -5017.97 | T72: =SUM(F72:K72) -> -4011.24 | U72: =SUM(L72:Q72) -> -1006.73 | V72: =T72+U72 -> -5017.97
D73: Contratados Pessoas Jurídicas | F73: =SUMIFS('Lançamentos Omie'!$G:$G,'Lançamentos Omie'!$I:$I,$D73,'Lançamentos Omie'!$F:$F,F$2)-6402.31 -> -6852.31 | G73: =SUMIFS('Lançamentos Omie'!$G:$G,'Lançamentos Omie'!$I:$I,$D73,'Lançamentos Omie'!$F:$F,G$2) -> -10800 | H73: =SUMIFS('Lançamentos Omie'!$G:$G,'Lançamentos Omie'!$I:$I,$D73,'Lançamentos Omie'!$F:$F,H$2) -> -10450 | I73: =SUMIFS('Lançamentos Omie'!$G:$G,'Lançamentos Omie'!$I:$I,$D73,'Lançamentos Omie'!$F:$F,I$2) -> -14050 | J73: =SUMIFS('Lançamentos Omie'!$G:$G,'Lançamentos Omie'!$I:$I,$D73,'Lançamentos Omie'!$F:$F,J$2) -> -11850 | K73: =SUMIFS('Lançamentos Omie'!$G:$G,'Lançamentos Omie'!$I:$I,$D73,'Lançamentos Omie'!$F:$F,K$2) -> -8200 | L73: =SUMIFS('Lançamentos Omie'!$G:$G,'Lançamentos Omie'!$I:$I,$D73,'Lançamentos Omie'!$F:$F,L$2) -> -9000 | M73: =SUMIFS('Lançamentos Omie'!$G:$G,'Lançamentos Omie'!$I:$I,$D73,'Lançamentos Omie'!$F:$F,M$2) -> -11450 | N73: =SUMIFS('Lançamentos Omie'!$G:$G,'Lançamentos Omie'!$I:$I,$D73,'Lançamentos Omie'!$F:$F,N$2) -> 0 | ... Q73: =SUMIFS('Lançamentos Omie'!$G:$G,'Lançamentos Omie'!$I:$I,$D73,'Lançamentos Omie'!$F:$F,Q$2) -> 0 | R73: =SUM(F73:Q73) -> -82652.31 | T73: =SUM(F73:K73) -> -62202.31 | U73: =SUM(L73:Q73) -> -20450 | V73: =T73+U73 -> -82652.31
D74: Ações Endomarketing | F74: =SUMIFS('Lançamentos Omie'!$G:$G,'Lançamentos Omie'!$I:$I,$D74,'Lançamentos Omie'!$F:$F,F$2) -> -7213.54 | G74: =SUMIFS('Lançamentos Omie'!$G:$G,'Lançamentos Omie'!$I:$I,$D74,'Lançamentos Omie'!$F:$F,G$2) -> -6215.64 | H74: =SUMIFS('Lançamentos Omie'!$G:$G,'Lançamentos Omie'!$I:$I,$D74,'Lançamentos Omie'!$F:$F,H$2) -> -4126.62 | I74: =SUMIFS('Lançamentos Omie'!$G:$G,'Lançamentos Omie'!$I:$I,$D74,'Lançamentos Omie'!$F:$F,I$2) -> -6500.43 | J74: =SUMIFS('Lançamentos Omie'!$G:$G,'Lançamentos Omie'!$I:$I,$D74,'Lançamentos Omie'!$F:$F,J$2) -> -9769.14 | K74: =SUMIFS('Lançamentos Omie'!$G:$G,'Lançamentos Omie'!$I:$I,$D74,'Lançamentos Omie'!$F:$F,K$2) -> -3772.31 | L74: =SUMIFS('Lançamentos Omie'!$G:$G,'Lançamentos Omie'!$I:$I,$D74,'Lançamentos Omie'!$F:$F,L$2) -> -5823.76 | M74: =SUMIFS('Lançamentos Omie'!$G:$G,'Lançamentos Omie'!$I:$I,$D74,'Lançamentos Omie'!$F:$F,M$2) -> -2316.5 | ... Q74: =SUMIFS('Lançamentos Omie'!$G:$G,'Lançamentos Omie'!$I:$I,$D74,'Lançamentos Omie'!$F:$F,Q$2) -> 0 | R74: =SUM(F74:Q74) -> -45737.94 | T74: =SUM(F74:K74) -> -37597.68 | U74: =SUM(L74:Q74) -> -8140.26 | V74: =T74+U74 -> -45737.94
D75: Transporte e Hospedagem Colaboradores para Sede da Empresa | F75: =SUMIFS('Lançamentos Omie'!$G:$G,'Lançamentos Omie'!$I:$I,$D75,'Lançamentos Omie'!$F:$F,F$2) -> 0 | G75: =SUMIFS('Lançamentos Omie'!$G:$G,'Lançamentos Omie'!$I:$I,$D75,'Lançamentos Omie'!$F:$F,G$2) -> 0 | H75: =SUMIFS('Lançamentos Omie'!$G:$G,'Lançamentos Omie'!$I:$I,$D75,'Lançamentos Omie'!$F:$F,H$2) -> 0 | I75: =SUMIFS('Lançamentos Omie'!$G:$G,'Lançamentos Omie'!$I:$I,$D75,'Lançamentos Omie'!$F:$F,I$2) -> 0 | J75: =SUMIFS('Lançamentos Omie'!$G:$G,'Lançamentos Omie'!$I:$I,$D75,'Lançamentos Omie'!$F:$F,J$2) -> 0 | K75: =SUMIFS('Lançamentos Omie'!$G:$G,'Lançamentos Omie'!$I:$I,$D75,'Lançamentos Omie'!$F:$F,K$2) -> 0 | L75: =SUMIFS('Lançamentos Omie'!$G:$G,'Lançamentos Omie'!$I:$I,$D75,'Lançamentos Omie'!$F:$F,L$2) -> 0 | M75: =SUMIFS('Lançamentos Omie'!$G:$G,'Lançamentos Omie'!$I:$I,$D75,'Lançamentos Omie'!$F:$F,M$2) -> 0 | ... Q75: =SUMIFS('Lançamentos Omie'!$G:$G,'Lançamentos Omie'!$I:$I,$D75,'Lançamentos Omie'!$F:$F,Q$2) -> 0 | R75: =SUM(F75:Q75) -> 0 | T75: =SUM(F75:K75) -> 0 | U75: =SUM(L75:Q75) -> 0 | V75: =T75+U75 -> 0
A76: 0.0755 | D76: Participação nos Lucros e Resultados | R76: =SUM(F76:Q76) -> 0 | T76: =SUM(F76:K76) -> 0 | U76: =SUM(L76:Q76) -> 0 | V76: =T76+U76 -> 0
C77: Despesas Administrativas | F77: =SUM(F78:F92) -> -118408.19 | G77: =SUM(G78:G92) -> -98402.51 | H77: =SUM(H78:H92) -> -96863.74 | I77: =SUM(I78:I92) -> -116123.89 | J77: =SUM(J78:J92) -> -110268.5 | K77: =SUM(K78:K92) -> -100921.62 | L77: =SUM(L78:L92) -> -77424.04 | M77: =SUM(M78:M92) -> -80931.22 | ... R77: =SUM(R78:R92) -> -799343.71 | T77: =SUM(F77:K77) -> -640988.45 | U77: =SUM(L77:Q77) -> -158355.26 | V77: =T77+U77 -> -799343.71
D78: Aluguel | F78: =SUMIFS('Lançamentos Omie'!$G:$G,'Lançamentos Omie'!$I:$I,$D78,'Lançamentos Omie'!$F:$F,F$2) -> -16414 | G78: =SUMIFS('Lançamentos Omie'!$G:$G,'Lançamentos Omie'!$I:$I,$D78,'Lançamentos Omie'!$F:$F,G$2) -> -17589.54 | H78: =SUMIFS('Lançamentos Omie'!$G:$G,'Lançamentos Omie'!$I:$I,$D78,'Lançamentos Omie'!$F:$F,H$2) -> -17001.77 | I78: =SUMIFS('Lançamentos Omie'!$G:$G,'Lançamentos Omie'!$I:$I,$D78,'Lançamentos Omie'!$F:$F,I$2) -> -17014.45 | J78: =SUMIFS('Lançamentos Omie'!$G:$G,'Lançamentos Omie'!$I:$I,$D78,'Lançamentos Omie'!$F:$F,J$2) -> -17014.45 | K78: =SUMIFS('Lançamentos Omie'!$G:$G,'Lançamentos Omie'!$I:$I,$D78,'Lançamentos Omie'!$F:$F,K$2) -> -17014.45 | L78: =SUMIFS('Lançamentos Omie'!$G:$G,'Lançamentos Omie'!$I:$I,$D78,'Lançamentos Omie'!$F:$F,L$2) -> -17014.45 | M78: =SUMIFS('Lançamentos Omie'!$G:$G,'Lançamentos Omie'!$I:$I,$D78,'Lançamentos Omie'!$F:$F,M$2) -> -17014.45 | ... Q78: =SUMIFS('Lançamentos Omie'!$G:$G,'Lançamentos Omie'!$I:$I,$D78,'Lançamentos Omie'!$F:$F,Q$2) -> 0 | R78: =SUM(F78:Q78) -> -136077.56 | T78: =SUM(F78:K78) -> -102048.66 | U78: =SUM(L78:Q78) -> -34028.9 | V78: =T78+U78 -> -136077.56
D79: Energia Elétrica | F79: =SUMIFS('Lançamentos Omie'!$G:$G,'Lançamentos Omie'!$I:$I,$D79,'Lançamentos Omie'!$F:$F,F$2) -> -2591.85 | G79: =SUMIFS('Lançamentos Omie'!$G:$G,'Lançamentos Omie'!$I:$I,$D79,'Lançamentos Omie'!$F:$F,G$2) -> -3025.01 | H79: =SUMIFS('Lançamentos Omie'!$G:$G,'Lançamentos Omie'!$I:$I,$D79,'Lançamentos Omie'!$F:$F,H$2) -> -2739.52 | I79: =SUMIFS('Lançamentos Omie'!$G:$G,'Lançamentos Omie'!$I:$I,$D79,'Lançamentos Omie'!$F:$F,I$2) -> -2655.52 | J79: =SUMIFS('Lançamentos Omie'!$G:$G,'Lançamentos Omie'!$I:$I,$D79,'Lançamentos Omie'!$F:$F,J$2) -> -2448.71 | K79: =SUMIFS('Lançamentos Omie'!$G:$G,'Lançamentos Omie'!$I:$I,$D79,'Lançamentos Omie'!$F:$F,K$2) -> -2257.34 | L79: =SUMIFS('Lançamentos Omie'!$G:$G,'Lançamentos Omie'!$I:$I,$D79,'Lançamentos Omie'!$F:$F,L$2) -> -2517.6 | M79: =SUMIFS('Lançamentos Omie'!$G:$G,'Lançamentos Omie'!$I:$I,$D79,'Lançamentos Omie'!$F:$F,M$2) -> -2177.1 | ... Q79: =SUMIFS('Lançamentos Omie'!$G:$G,'Lançamentos Omie'!$I:$I,$D79,'Lançamentos Omie'!$F:$F,Q$2) -> 0 | R79: =SUM(F79:Q79) -> -20412.65 | T79: =SUM(F79:K79) -> -15717.95 | U79: =SUM(L79:Q79) -> -4694.7 | V79: =T79+U79 -> -20412.65
D80: Telefonia e Internet | F80: =SUMIFS('Lançamentos Omie'!$G:$G,'Lançamentos Omie'!$I:$I,$D80,'Lançamentos Omie'!$F:$F,F$2) -> -1115.34 | G80: =SUMIFS('Lançamentos Omie'!$G:$G,'Lançamentos Omie'!$I:$I,$D80,'Lançamentos Omie'!$F:$F,G$2) -> -1752.44 | H80: =SUMIFS('Lançamentos Omie'!$G:$G,'Lançamentos Omie'!$I:$I,$D80,'Lançamentos Omie'!$F:$F,H$2) -> -1258.79 | I80: =SUMIFS('Lançamentos Omie'!$G:$G,'Lançamentos Omie'!$I:$I,$D80,'Lançamentos Omie'!$F:$F,I$2) -> -1985.67 | J80: =SUMIFS('Lançamentos Omie'!$G:$G,'Lançamentos Omie'!$I:$I,$D80,'Lançamentos Omie'!$F:$F,J$2) -> -1202.11 | K80: =SUMIFS('Lançamentos Omie'!$G:$G,'Lançamentos Omie'!$I:$I,$D80,'Lançamentos Omie'!$F:$F,K$2) -> -1897.54 | L80: =SUMIFS('Lançamentos Omie'!$G:$G,'Lançamentos Omie'!$I:$I,$D80,'Lançamentos Omie'!$F:$F,L$2) -> -1171.51 | M80: =SUMIFS('Lançamentos Omie'!$G:$G,'Lançamentos Omie'!$I:$I,$D80,'Lançamentos Omie'!$F:$F,M$2) -> -1277.68 | ... Q80: =SUMIFS('Lançamentos Omie'!$G:$G,'Lançamentos Omie'!$I:$I,$D80,'Lançamentos Omie'!$F:$F,Q$2) -> 0 | R80: =SUM(F80:Q80) -> -11661.08 | T80: =SUM(F80:K80) -> -9211.89 | U80: =SUM(L80:Q80) -> -2449.19 | V80: =T80+U80 -> -11661.08
D81: Manutenção de Imobilizado | F81: =SUMIFS('Lançamentos Omie'!$G:$G,'Lançamentos Omie'!$I:$I,$D81,'Lançamentos Omie'!$F:$F,F$2) -> -1937.6 | G81: =SUMIFS('Lançamentos Omie'!$G:$G,'Lançamentos Omie'!$I:$I,$D81,'Lançamentos Omie'!$F:$F,G$2) -> -1585 | H81: =SUMIFS('Lançamentos Omie'!$G:$G,'Lançamentos Omie'!$I:$I,$D81,'Lançamentos Omie'!$F:$F,H$2) -> -1900 | I81: =SUMIFS('Lançamentos Omie'!$G:$G,'Lançamentos Omie'!$I:$I,$D81,'Lançamentos Omie'!$F:$F,I$2) -> -942.29 | J81: =SUMIFS('Lançamentos Omie'!$G:$G,'Lançamentos Omie'!$I:$I,$D81,'Lançamentos Omie'!$F:$F,J$2) -> -1298.1 | K81: =SUMIFS('Lançamentos Omie'!$G:$G,'Lançamentos Omie'!$I:$I,$D81,'Lançamentos Omie'!$F:$F,K$2) -> -3244.9 | L81: =SUMIFS('Lançamentos Omie'!$G:$G,'Lançamentos Omie'!$I:$I,$D81,'Lançamentos Omie'!$F:$F,L$2) -> -2092.56 | M81: =SUMIFS('Lançamentos Omie'!$G:$G,'Lançamentos Omie'!$I:$I,$D81,'Lançamentos Omie'!$F:$F,M$2) -> -1219.2 | ... Q81: =SUMIFS('Lançamentos Omie'!$G:$G,'Lançamentos Omie'!$I:$I,$D81,'Lançamentos Omie'!$F:$F,Q$2) -> 0 | R81: =SUM(F81:Q81) -> -14219.65 | T81: =SUM(F81:K81) -> -10907.89 | U81: =SUM(L81:Q81) -> -3311.76 | V81: =T81+U81 -> -14219.65
D82: Seguros | F82: =SUMIFS('Lançamentos Omie'!$G:$G,'Lançamentos Omie'!$I:$I,$D82,'Lançamentos Omie'!$F:$F,F$2) -> 0 | G82: =SUMIFS('Lançamentos Omie'!$G:$G,'Lançamentos Omie'!$I:$I,$D82,'Lançamentos Omie'!$F:$F,G$2) -> 0 | H82: =SUMIFS('Lançamentos Omie'!$G:$G,'Lançamentos Omie'!$I:$I,$D82,'Lançamentos Omie'!$F:$F,H$2) -> 0 | I82: =SUMIFS('Lançamentos Omie'!$G:$G,'Lançamentos Omie'!$I:$I,$D82,'Lançamentos Omie'!$F:$F,I$2) -> 0 | J82: =SUMIFS('Lançamentos Omie'!$G:$G,'Lançamentos Omie'!$I:$I,$D82,'Lançamentos Omie'!$F:$F,J$2) -> 0 | K82: =SUMIFS('Lançamentos Omie'!$G:$G,'Lançamentos Omie'!$I:$I,$D82,'Lançamentos Omie'!$F:$F,K$2) -> 0 | L82: =SUMIFS('Lançamentos Omie'!$G:$G,'Lançamentos Omie'!$I:$I,$D82,'Lançamentos Omie'!$F:$F,L$2) -> 0 | M82: =SUMIFS('Lançamentos Omie'!$G:$G,'Lançamentos Omie'!$I:$I,$D82,'Lançamentos Omie'!$F:$F,M$2) -> 0 | ... Q82: =SUMIFS('Lançamentos Omie'!$G:$G,'Lançamentos Omie'!$I:$I,$D82,'Lançamentos Omie'!$F:$F,Q$2) -> 0 | R82: =SUM(F82:Q82) -> 0 | T82: =SUM(F82:K82) -> 0 | U82: =SUM(L82:Q82) -> 0 | V82: =T82+U82 -> 0
D83: Contabilidade | F83: =SUMIFS('Lançamentos Omie'!$G:$G,'Lançamentos Omie'!$I:$I,$D83,'Lançamentos Omie'!$F:$F,F$2) -> -10450.89 | G83: =SUMIFS('Lançamentos Omie'!$G:$G,'Lançamentos Omie'!$I:$I,$D83,'Lançamentos Omie'!$F:$F,G$2) -> -7580.89 | H83: =SUMIFS('Lançamentos Omie'!$G:$G,'Lançamentos Omie'!$I:$I,$D83,'Lançamentos Omie'!$F:$F,H$2) -> -7611.05 | I83: =SUMIFS('Lançamentos Omie'!$G:$G,'Lançamentos Omie'!$I:$I,$D83,'Lançamentos Omie'!$F:$F,I$2) -> -9799.69 | J83: =SUMIFS('Lançamentos Omie'!$G:$G,'Lançamentos Omie'!$I:$I,$D83,'Lançamentos Omie'!$F:$F,J$2) -> -8326.25 | K83: =SUMIFS('Lançamentos Omie'!$G:$G,'Lançamentos Omie'!$I:$I,$D83,'Lançamentos Omie'!$F:$F,K$2) -> -8382.65 | L83: =SUMIFS('Lançamentos Omie'!$G:$G,'Lançamentos Omie'!$I:$I,$D83,'Lançamentos Omie'!$F:$F,L$2) -> -8382.65 | M83: =SUMIFS('Lançamentos Omie'!$G:$G,'Lançamentos Omie'!$I:$I,$D83,'Lançamentos Omie'!$F:$F,M$2) -> -10700.47 | ... Q83: =SUMIFS('Lançamentos Omie'!$G:$G,'Lançamentos Omie'!$I:$I,$D83,'Lançamentos Omie'!$F:$F,Q$2) -> 0 | R83: =SUM(F83:Q83) -> -71234.54 | T83: =SUM(F83:K83) -> -52151.42 | U83: =SUM(L83:Q83) -> -19083.12 | V83: =T83+U83 -> -71234.54
D84: Advogados | F84: =SUMIFS('Lançamentos Omie'!$G:$G,'Lançamentos Omie'!$I:$I,$D84,'Lançamentos Omie'!$F:$F,F$2) -> -7285.66 | G84: =SUMIFS('Lançamentos Omie'!$G:$G,'Lançamentos Omie'!$I:$I,$D84,'Lançamentos Omie'!$F:$F,G$2) -> -7285.66 | H84: =SUMIFS('Lançamentos Omie'!$G:$G,'Lançamentos Omie'!$I:$I,$D84,'Lançamentos Omie'!$F:$F,H$2) -> -7285.66 | I84: =SUMIFS('Lançamentos Omie'!$G:$G,'Lançamentos Omie'!$I:$I,$D84,'Lançamentos Omie'!$F:$F,I$2) -> -7285.66 | J84: =SUMIFS('Lançamentos Omie'!$G:$G,'Lançamentos Omie'!$I:$I,$D84,'Lançamentos Omie'!$F:$F,J$2) -> -7646.31 | K84: =SUMIFS('Lançamentos Omie'!$G:$G,'Lançamentos Omie'!$I:$I,$D84,'Lançamentos Omie'!$F:$F,K$2) -> -7285.66 | L84: =SUMIFS('Lançamentos Omie'!$G:$G,'Lançamentos Omie'!$I:$I,$D84,'Lançamentos Omie'!$F:$F,L$2) -> -7285.66 | M84: =SUMIFS('Lançamentos Omie'!$G:$G,'Lançamentos Omie'!$I:$I,$D84,'Lançamentos Omie'!$F:$F,M$2) -> -7285.66 | ... Q84: =SUMIFS('Lançamentos Omie'!$G:$G,'Lançamentos Omie'!$I:$I,$D84,'Lançamentos Omie'!$F:$F,Q$2) -> 0 | R84: =SUM(F84:Q84) -> -58645.93 | T84: =SUM(F84:K84) -> -44074.61 | U84: =SUM(L84:Q84) -> -14571.32 | V84: =T84+U84 -> -58645.93
D85: Segurança | F85: =SUMIFS('Lançamentos Omie'!$G:$G,'Lançamentos Omie'!$I:$I,$D85,'Lançamentos Omie'!$F:$F,F$2) -> 0 | G85: =SUMIFS('Lançamentos Omie'!$G:$G,'Lançamentos Omie'!$I:$I,$D85,'Lançamentos Omie'!$F:$F,G$2) -> 0 | H85: =SUMIFS('Lançamentos Omie'!$G:$G,'Lançamentos Omie'!$I:$I,$D85,'Lançamentos Omie'!$F:$F,H$2) -> 0 | I85: =SUMIFS('Lançamentos Omie'!$G:$G,'Lançamentos Omie'!$I:$I,$D85,'Lançamentos Omie'!$F:$F,I$2) -> 0 | J85: =SUMIFS('Lançamentos Omie'!$G:$G,'Lançamentos Omie'!$I:$I,$D85,'Lançamentos Omie'!$F:$F,J$2) -> 0 | K85: =SUMIFS('Lançamentos Omie'!$G:$G,'Lançamentos Omie'!$I:$I,$D85,'Lançamentos Omie'!$F:$F,K$2) -> 0 | L85: =SUMIFS('Lançamentos Omie'!$G:$G,'Lançamentos Omie'!$I:$I,$D85,'Lançamentos Omie'!$F:$F,L$2) -> 0 | M85: =SUMIFS('Lançamentos Omie'!$G:$G,'Lançamentos Omie'!$I:$I,$D85,'Lançamentos Omie'!$F:$F,M$2) -> 0 | ... Q85: =SUMIFS('Lançamentos Omie'!$G:$G,'Lançamentos Omie'!$I:$I,$D85,'Lançamentos Omie'!$F:$F,Q$2) -> 0 | R85: =SUM(F85:Q85) -> 0 | T85: =SUM(F85:K85) -> 0 | U85: =SUM(L85:Q85) -> 0 | V85: =T85+U85 -> 0
D86: Softwares, Sistemas e Servidores | F86: =SUMIFS('Lançamentos Omie'!$G:$G,'Lançamentos Omie'!$I:$I,$D86,'Lançamentos Omie'!$F:$F,F$2) -> -51072.67 | G86: =SUMIFS('Lançamentos Omie'!$G:$G,'Lançamentos Omie'!$I:$I,$D86,'Lançamentos Omie'!$F:$F,G$2) -> -35665.6 | H86: =SUMIFS('Lançamentos Omie'!$G:$G,'Lançamentos Omie'!$I:$I,$D86,'Lançamentos Omie'!$F:$F,H$2) -> -27032.5 | I86: =SUMIFS('Lançamentos Omie'!$G:$G,'Lançamentos Omie'!$I:$I,$D86,'Lançamentos Omie'!$F:$F,I$2) -> -34367.67 | J86: =SUMIFS('Lançamentos Omie'!$G:$G,'Lançamentos Omie'!$I:$I,$D86,'Lançamentos Omie'!$F:$F,J$2) -> -24784.68 | K86: =SUMIFS('Lançamentos Omie'!$G:$G,'Lançamentos Omie'!$I:$I,$D86,'Lançamentos Omie'!$F:$F,K$2) -> -29033.32 | L86: =SUMIFS('Lançamentos Omie'!$G:$G,'Lançamentos Omie'!$I:$I,$D86,'Lançamentos Omie'!$F:$F,L$2) -> -23828.51 | M86: =SUMIFS('Lançamentos Omie'!$G:$G,'Lançamentos Omie'!$I:$I,$D86,'Lançamentos Omie'!$F:$F,M$2) -> -29329.72 | ... Q86: =SUMIFS('Lançamentos Omie'!$G:$G,'Lançamentos Omie'!$I:$I,$D86,'Lançamentos Omie'!$F:$F,Q$2) -> 0 | R86: =SUM(F86:Q86) -> -255114.67 | T86: =SUM(F86:K86) -> -201956.44 | U86: =SUM(L86:Q86) -> -53158.23 | V86: =T86+U86 -> -255114.67
D87: Outras Despesas Administrativas | F87: =SUMIFS('Lançamentos Omie'!$G:$G,'Lançamentos Omie'!$I:$I,$D87,'Lançamentos Omie'!$F:$F,F$2) -> -700 | G87: =SUMIFS('Lançamentos Omie'!$G:$G,'Lançamentos Omie'!$I:$I,$D87,'Lançamentos Omie'!$F:$F,G$2) -> -499.37 | H87: =SUMIFS('Lançamentos Omie'!$G:$G,'Lançamentos Omie'!$I:$I,$D87,'Lançamentos Omie'!$F:$F,H$2) -> -3796.26 | I87: =SUMIFS('Lançamentos Omie'!$G:$G,'Lançamentos Omie'!$I:$I,$D87,'Lançamentos Omie'!$F:$F,I$2) -> -3444.99 | J87: =SUMIFS('Lançamentos Omie'!$G:$G,'Lançamentos Omie'!$I:$I,$D87,'Lançamentos Omie'!$F:$F,J$2)-'Viagens Consultoria'!J43-'Viagens Consultoria'!J44-'Viagens Consultoria'!J46-'Viagens Consultoria'!J48 -> -13735.64 | K87: =SUMIFS('Lançamentos Omie'!$G:$G,'Lançamentos Omie'!$I:$I,$D87,'Lançamentos Omie'!$F:$F,K$2) -> -5976.48 | L87: =SUMIFS('Lançamentos Omie'!$G:$G,'Lançamentos Omie'!$I:$I,$D87,'Lançamentos Omie'!$F:$F,L$2) -> -1735.47 | M87: =SUMIFS('Lançamentos Omie'!$G:$G,'Lançamentos Omie'!$I:$I,$D87,'Lançamentos Omie'!$F:$F,M$2) -> -2904.59 | N87: =SUMIFS('Lançamentos Omie'!$G:$G,'Lançamentos Omie'!$I:$I,$D87,'Lançamentos Omie'!$F:$F,N$2) -> 0 | O87: =SUMIFS('Lançamentos Omie'!$G:$G,'Lançamentos Omie'!$I:$I,$D87,'Lançamentos Omie'!$F:$F,O$2) -> 0 | P87: =SUMIFS('Lançamentos Omie'!$G:$G,'Lançamentos Omie'!$I:$I,$D87,'Lançamentos Omie'!$F:$F,P$2) -> 0 | Q87: =SUMIFS('Lançamentos Omie'!$G:$G,'Lançamentos Omie'!$I:$I,$D87,'Lançamentos Omie'!$F:$F,Q$2) -> 0 | R87: =SUM(F87:Q87) -> -32792.8 | T87: =SUM(F87:K87) -> -28152.74 | U87: =SUM(L87:Q87) -> -4640.06 | V87: =T87+U87 -> -32792.8
D88: Material Limpeza / Escritório / Mercado / Padaria | F88: =SUMIFS('Lançamentos Omie'!$G:$G,'Lançamentos Omie'!$I:$I,$D88,'Lançamentos Omie'!$F:$F,F$2) -> -2240.56 | G88: =SUMIFS('Lançamentos Omie'!$G:$G,'Lançamentos Omie'!$I:$I,$D88,'Lançamentos Omie'!$F:$F,G$2) -> -2146.37 | H88: =SUMIFS('Lançamentos Omie'!$G:$G,'Lançamentos Omie'!$I:$I,$D88,'Lançamentos Omie'!$F:$F,H$2) -> -4186.5 | I88: =SUMIFS('Lançamentos Omie'!$G:$G,'Lançamentos Omie'!$I:$I,$D88,'Lançamentos Omie'!$F:$F,I$2) -> -2283.37 | J88: =SUMIFS('Lançamentos Omie'!$G:$G,'Lançamentos Omie'!$I:$I,$D88,'Lançamentos Omie'!$F:$F,J$2) -> -4127.13 | K88: =SUMIFS('Lançamentos Omie'!$G:$G,'Lançamentos Omie'!$I:$I,$D88,'Lançamentos Omie'!$F:$F,K$2) -> -2695.64 | L88: =SUMIFS('Lançamentos Omie'!$G:$G,'Lançamentos Omie'!$I:$I,$D88,'Lançamentos Omie'!$F:$F,L$2) -> -2947.17 | M88: =SUMIFS('Lançamentos Omie'!$G:$G,'Lançamentos Omie'!$I:$I,$D88,'Lançamentos Omie'!$F:$F,M$2) -> -4247.05 | ... Q88: =SUMIFS('Lançamentos Omie'!$G:$G,'Lançamentos Omie'!$I:$I,$D88,'Lançamentos Omie'!$F:$F,Q$2) -> 0 | R88: =SUM(F88:Q88) -> -24873.79 | T88: =SUM(F88:K88) -> -17679.57 | U88: =SUM(L88:Q88) -> -7194.22 | V88: =T88+U88 -> -24873.79
D89: Fretes e Transportes em Geral | F89: =SUMIFS('Lançamentos Omie'!$G:$G,'Lançamentos Omie'!$I:$I,$D89,'Lançamentos Omie'!$F:$F,F$2) -> -1286.69 | G89: =SUMIFS('Lançamentos Omie'!$G:$G,'Lançamentos Omie'!$I:$I,$D89,'Lançamentos Omie'!$F:$F,G$2) -> -1215.98 | H89: =SUMIFS('Lançamentos Omie'!$G:$G,'Lançamentos Omie'!$I:$I,$D89,'Lançamentos Omie'!$F:$F,H$2) -> -1194.08 | I89: =SUMIFS('Lançamentos Omie'!$G:$G,'Lançamentos Omie'!$I:$I,$D89,'Lançamentos Omie'!$F:$F,I$2) -> -1260.93 | J89: =SUMIFS('Lançamentos Omie'!$G:$G,'Lançamentos Omie'!$I:$I,$D89,'Lançamentos Omie'!$F:$F,J$2) -> -642.47 | K89: =SUMIFS('Lançamentos Omie'!$G:$G,'Lançamentos Omie'!$I:$I,$D89,'Lançamentos Omie'!$F:$F,K$2) -> -466.6 | L89: =SUMIFS('Lançamentos Omie'!$G:$G,'Lançamentos Omie'!$I:$I,$D89,'Lançamentos Omie'!$F:$F,L$2) -> -1148.81 | M89: =SUMIFS('Lançamentos Omie'!$G:$G,'Lançamentos Omie'!$I:$I,$D89,'Lançamentos Omie'!$F:$F,M$2) -> -1076.8 | ... Q89: =SUMIFS('Lançamentos Omie'!$G:$G,'Lançamentos Omie'!$I:$I,$D89,'Lançamentos Omie'!$F:$F,Q$2) -> 0 | R89: =SUM(F89:Q89) -> -8292.36 | T89: =SUM(F89:K89) -> -6066.75 | U89: =SUM(L89:Q89) -> -2225.61 | V89: =T89+U89 -> -8292.36
D90: Consultorias e Treinamentos | F90: =SUMIFS('Lançamentos Omie'!$G:$G,'Lançamentos Omie'!$I:$I,$D90,'Lançamentos Omie'!$F:$F,F$2) -> -18961.65 | G90: =SUMIFS('Lançamentos Omie'!$G:$G,'Lançamentos Omie'!$I:$I,$D90,'Lançamentos Omie'!$F:$F,G$2) -> -18962.65 | H90: =SUMIFS('Lançamentos Omie'!$G:$G,'Lançamentos Omie'!$I:$I,$D90,'Lançamentos Omie'!$F:$F,H$2) -> -21763.61 | I90: =SUMIFS('Lançamentos Omie'!$G:$G,'Lançamentos Omie'!$I:$I,$D90,'Lançamentos Omie'!$F:$F,I$2) -> -33989.65 | J90: =SUMIFS('Lançamentos Omie'!$G:$G,'Lançamentos Omie'!$I:$I,$D90,'Lançamentos Omie'!$F:$F,J$2) -> -27948.65 | K90: =SUMIFS('Lançamentos Omie'!$G:$G,'Lançamentos Omie'!$I:$I,$D90,'Lançamentos Omie'!$F:$F,K$2)-'Viagens Consultoria'!H11 -> -20936.71 | L90: =SUMIFS('Lançamentos Omie'!$G:$G,'Lançamentos Omie'!$I:$I,$D90,'Lançamentos Omie'!$F:$F,L$2) -> -6205.65 | M90: =SUMIFS('Lançamentos Omie'!$G:$G,'Lançamentos Omie'!$I:$I,$D90,'Lançamentos Omie'!$F:$F,M$2) -> -604.5 | N90: =SUMIFS('Lançamentos Omie'!$G:$G,'Lançamentos Omie'!$I:$I,$D90,'Lançamentos Omie'!$F:$F,N$2) -> 0 | O90: =SUMIFS('Lançamentos Omie'!$G:$G,'Lançamentos Omie'!$I:$I,$D90,'Lançamentos Omie'!$F:$F,O$2) -> 0 | P90: =SUMIFS('Lançamentos Omie'!$G:$G,'Lançamentos Omie'!$I:$I,$D90,'Lançamentos Omie'!$F:$F,P$2) -> 0 | Q90: =SUMIFS('Lançamentos Omie'!$G:$G,'Lançamentos Omie'!$I:$I,$D90,'Lançamentos Omie'!$F:$F,Q$2) -> 0 | R90: =SUM(F90:Q90) -> -149373.07 | T90: =SUM(F90:K90) -> -142562.92 | U90: =SUM(L90:Q90) -> -6810.15 | V90: =T90+U90 -> -149373.07
D91: Associações de Classe | F91: =SUMIFS('Lançamentos Omie'!$G:$G,'Lançamentos Omie'!$I:$I,$D91,'Lançamentos Omie'!$F:$F,F$2) -> -4194 | G91: =SUMIFS('Lançamentos Omie'!$G:$G,'Lançamentos Omie'!$I:$I,$D91,'Lançamentos Omie'!$F:$F,G$2) -> -1094 | H91: =SUMIFS('Lançamentos Omie'!$G:$G,'Lançamentos Omie'!$I:$I,$D91,'Lançamentos Omie'!$F:$F,H$2) -> -1094 | I91: =SUMIFS('Lançamentos Omie'!$G:$G,'Lançamentos Omie'!$I:$I,$D91,'Lançamentos Omie'!$F:$F,I$2) -> -1094 | J91: =SUMIFS('Lançamentos Omie'!$G:$G,'Lançamentos Omie'!$I:$I,$D91,'Lançamentos Omie'!$F:$F,J$2) -> -1094 | K91: =SUMIFS('Lançamentos Omie'!$G:$G,'Lançamentos Omie'!$I:$I,$D91,'Lançamentos Omie'!$F:$F,K$2) -> -1094 | L91: =SUMIFS('Lançamentos Omie'!$G:$G,'Lançamentos Omie'!$I:$I,$D91,'Lançamentos Omie'!$F:$F,L$2) -> -3094 | M91: =SUMIFS('Lançamentos Omie'!$G:$G,'Lançamentos Omie'!$I:$I,$D91,'Lançamentos Omie'!$F:$F,M$2) -> -3094 | ... Q91: =SUMIFS('Lançamentos Omie'!$G:$G,'Lançamentos Omie'!$I:$I,$D91,'Lançamentos Omie'!$F:$F,Q$2) -> 0 | R91: =SUM(F91:Q91) -> -15852 | T91: =SUM(F91:K91) -> -9664 | U91: =SUM(L91:Q91) -> -6188 | V91: =T91+U91 -> -15852
D92: Taxas Municipais | F92: =SUMIFS('Lançamentos Omie'!$G:$G,'Lançamentos Omie'!$I:$I,$D92,'Lançamentos Omie'!$F:$F,F$2) -> -157.28 | G92: =SUMIFS('Lançamentos Omie'!$G:$G,'Lançamentos Omie'!$I:$I,$D92,'Lançamentos Omie'!$F:$F,G$2) -> 0 | H92: =SUMIFS('Lançamentos Omie'!$G:$G,'Lançamentos Omie'!$I:$I,$D92,'Lançamentos Omie'!$F:$F,H$2) -> 0 | I92: =SUMIFS('Lançamentos Omie'!$G:$G,'Lançamentos Omie'!$I:$I,$D92,'Lançamentos Omie'!$F:$F,I$2) -> 0 | J92: =SUMIFS('Lançamentos Omie'!$G:$G,'Lançamentos Omie'!$I:$I,$D92,'Lançamentos Omie'!$F:$F,J$2) -> 0 | K92: =SUMIFS('Lançamentos Omie'!$G:$G,'Lançamentos Omie'!$I:$I,$D92,'Lançamentos Omie'!$F:$F,K$2) -> -636.33 | L92: =SUMIFS('Lançamentos Omie'!$G:$G,'Lançamentos Omie'!$I:$I,$D92,'Lançamentos Omie'!$F:$F,L$2) -> 0 | M92: =SUMIFS('Lançamentos Omie'!$G:$G,'Lançamentos Omie'!$I:$I,$D92,'Lançamentos Omie'!$F:$F,M$2) -> 0 | ... Q92: =SUMIFS('Lançamentos Omie'!$G:$G,'Lançamentos Omie'!$I:$I,$D92,'Lançamentos Omie'!$F:$F,Q$2) -> 0 | R92: =SUM(F92:Q92) -> -793.61 | T92: =SUM(F92:K92) -> -793.61 | U92: =SUM(L92:Q92) -> 0 | V92: =T92+U92 -> -793.61
C93: Despesas Financeiras / Bancos | F93: =SUM(F94:F97) -> -1905.02 | G93: =SUM(G94:G97) -> -2066.63 | H93: =SUM(H94:H97) -> -2208.3 | I93: =SUM(I94:I97) -> -1825.06 | J93: =SUM(J94:J97) -> -870.58 | K93: =SUM(K94:K97) -> -1353.55 | L93: =SUM(L94:L97) -> -1123.21 | M93: =SUM(M94:M97) -> -807.76 | ... R93: =SUM(R94:R97) -> -12160.11 | T93: =SUM(F93:K93) -> -10229.14 | U93: =SUM(L93:Q93) -> -1930.97 | V93: =T93+U93 -> -12160.11
D94: Juros sobre Empréstimos | F94: =SUMIFS('Lançamentos Omie'!$G:$G,'Lançamentos Omie'!$I:$I,$D94,'Lançamentos Omie'!$F:$F,F$2) -> 0 | G94: =SUMIFS('Lançamentos Omie'!$G:$G,'Lançamentos Omie'!$I:$I,$D94,'Lançamentos Omie'!$F:$F,G$2) -> 0 | H94: =SUMIFS('Lançamentos Omie'!$G:$G,'Lançamentos Omie'!$I:$I,$D94,'Lançamentos Omie'!$F:$F,H$2) -> 0 | I94: =SUMIFS('Lançamentos Omie'!$G:$G,'Lançamentos Omie'!$I:$I,$D94,'Lançamentos Omie'!$F:$F,I$2) -> 0 | J94: =SUMIFS('Lançamentos Omie'!$G:$G,'Lançamentos Omie'!$I:$I,$D94,'Lançamentos Omie'!$F:$F,J$2) -> 0 | K94: =SUMIFS('Lançamentos Omie'!$G:$G,'Lançamentos Omie'!$I:$I,$D94,'Lançamentos Omie'!$F:$F,K$2) -> 0 | L94: =SUMIFS('Lançamentos Omie'!$G:$G,'Lançamentos Omie'!$I:$I,$D94,'Lançamentos Omie'!$F:$F,L$2) -> 0 | M94: =SUMIFS('Lançamentos Omie'!$G:$G,'Lançamentos Omie'!$I:$I,$D94,'Lançamentos Omie'!$F:$F,M$2) -> 0 | ... Q94: =SUMIFS('Lançamentos Omie'!$G:$G,'Lançamentos Omie'!$I:$I,$D94,'Lançamentos Omie'!$F:$F,Q$2) -> 0 | R94: =SUM(F94:Q94) -> 0 | T94: =SUM(F94:K94) -> 0 | U94: =SUM(L94:Q94) -> 0 | V94: =T94+U94 -> 0
D95: Multas | F95: =SUMIFS('Lançamentos Omie'!$G:$G,'Lançamentos Omie'!$I:$I,$D95,'Lançamentos Omie'!$F:$F,F$2) -> 0 | G95: =SUMIFS('Lançamentos Omie'!$G:$G,'Lançamentos Omie'!$I:$I,$D95,'Lançamentos Omie'!$F:$F,G$2) -> 0 | H95: =SUMIFS('Lançamentos Omie'!$G:$G,'Lançamentos Omie'!$I:$I,$D95,'Lançamentos Omie'!$F:$F,H$2) -> 0 | I95: =SUMIFS('Lançamentos Omie'!$G:$G,'Lançamentos Omie'!$I:$I,$D95,'Lançamentos Omie'!$F:$F,I$2) -> 0 | J95: =SUMIFS('Lançamentos Omie'!$G:$G,'Lançamentos Omie'!$I:$I,$D95,'Lançamentos Omie'!$F:$F,J$2) -> 0 | K95: =SUMIFS('Lançamentos Omie'!$G:$G,'Lançamentos Omie'!$I:$I,$D95,'Lançamentos Omie'!$F:$F,K$2) -> 0 | L95: =SUMIFS('Lançamentos Omie'!$G:$G,'Lançamentos Omie'!$I:$I,$D95,'Lançamentos Omie'!$F:$F,L$2) -> 0 | M95: =SUMIFS('Lançamentos Omie'!$G:$G,'Lançamentos Omie'!$I:$I,$D95,'Lançamentos Omie'!$F:$F,M$2) -> 0 | ... Q95: =SUMIFS('Lançamentos Omie'!$G:$G,'Lançamentos Omie'!$I:$I,$D95,'Lançamentos Omie'!$F:$F,Q$2) -> 0 | R95: =SUM(F95:Q95) -> 0 | T95: =SUM(F95:K95) -> 0 | U95: =SUM(L95:Q95) -> 0 | V95: =T95+U95 -> 0
D96: Tarifas Bancárias | F96: =SUMIFS('Lançamentos Omie'!$G:$G,'Lançamentos Omie'!$I:$I,$D96,'Lançamentos Omie'!$F:$F,F$2) -> -1035.33 | G96: =SUMIFS('Lançamentos Omie'!$G:$G,'Lançamentos Omie'!$I:$I,$D96,'Lançamentos Omie'!$F:$F,G$2) -> -1383.57 | H96: =SUMIFS('Lançamentos Omie'!$G:$G,'Lançamentos Omie'!$I:$I,$D96,'Lançamentos Omie'!$F:$F,H$2) -> -1878.89 | I96: =SUMIFS('Lançamentos Omie'!$G:$G,'Lançamentos Omie'!$I:$I,$D96,'Lançamentos Omie'!$F:$F,I$2) -> -983.22 | J96: =SUMIFS('Lançamentos Omie'!$G:$G,'Lançamentos Omie'!$I:$I,$D96,'Lançamentos Omie'!$F:$F,J$2) -> -838.97 | K96: =SUMIFS('Lançamentos Omie'!$G:$G,'Lançamentos Omie'!$I:$I,$D96,'Lançamentos Omie'!$F:$F,K$2) -> -1254.83 | L96: =SUMIFS('Lançamentos Omie'!$G:$G,'Lançamentos Omie'!$I:$I,$D96,'Lançamentos Omie'!$F:$F,L$2) -> -1093 | M96: =SUMIFS('Lançamentos Omie'!$G:$G,'Lançamentos Omie'!$I:$I,$D96,'Lançamentos Omie'!$F:$F,M$2) -> -807.76 | ... Q96: =SUMIFS('Lançamentos Omie'!$G:$G,'Lançamentos Omie'!$I:$I,$D96,'Lançamentos Omie'!$F:$F,Q$2) -> 0 | R96: =SUM(F96:Q96) -> -9275.57 | T96: =SUM(F96:K96) -> -7374.81 | U96: =SUM(L96:Q96) -> -1900.76 | V96: =T96+U96 -> -9275.57
D97: IOF | F97: =SUMIFS('Lançamentos Omie'!$G:$G,'Lançamentos Omie'!$I:$I,$D97,'Lançamentos Omie'!$F:$F,F$2) -> -869.69 | G97: =SUMIFS('Lançamentos Omie'!$G:$G,'Lançamentos Omie'!$I:$I,$D97,'Lançamentos Omie'!$F:$F,G$2) -> -683.06 | H97: =SUMIFS('Lançamentos Omie'!$G:$G,'Lançamentos Omie'!$I:$I,$D97,'Lançamentos Omie'!$F:$F,H$2) -> -329.41 | I97: =SUMIFS('Lançamentos Omie'!$G:$G,'Lançamentos Omie'!$I:$I,$D97,'Lançamentos Omie'!$F:$F,I$2) -> -841.84 | J97: =SUMIFS('Lançamentos Omie'!$G:$G,'Lançamentos Omie'!$I:$I,$D97,'Lançamentos Omie'!$F:$F,J$2) -> -31.61 | K97: =SUMIFS('Lançamentos Omie'!$G:$G,'Lançamentos Omie'!$I:$I,$D97,'Lançamentos Omie'!$F:$F,K$2) -> -98.72 | L97: =SUMIFS('Lançamentos Omie'!$G:$G,'Lançamentos Omie'!$I:$I,$D97,'Lançamentos Omie'!$F:$F,L$2) -> -30.21 | M97: =SUMIFS('Lançamentos Omie'!$G:$G,'Lançamentos Omie'!$I:$I,$D97,'Lançamentos Omie'!$F:$F,M$2) -> 0 | ... Q97: =SUMIFS('Lançamentos Omie'!$G:$G,'Lançamentos Omie'!$I:$I,$D97,'Lançamentos Omie'!$F:$F,Q$2) -> 0 | R97: =SUM(F97:Q97) -> -2884.54 | T97: =SUM(F97:K97) -> -2854.33 | U97: =SUM(L97:Q97) -> -30.21 | V97: =T97+U97 -> -2884.54
C98: Outras Despesas | F98: =SUM(F99:F100) -> -119 | G98: =SUM(G99:G100) -> -119 | H98: =SUM(H99:H100) -> -167.66 | I98: =SUM(I99:I100) -> -2247.67 | J98: =SUM(J99:J100) -> -263.43 | K98: =SUM(K99:K100) -> -308.45 | L98: =SUM(L99:L100) -> -1573.45 | M98: =SUM(M99:M100) -> -124.7 | ... R98: =SUM(R99:R100) -> -4923.36 | T98: =SUM(F98:K98) -> -3225.21 | U98: =SUM(L98:Q98) -> -1698.15 | V98: =T98+U98 -> -4923.36
D99: Doações | F99: =SUMIFS('Lançamentos Omie'!$G:$G,'Lançamentos Omie'!$I:$I,$D99,'Lançamentos Omie'!$F:$F,F$2) -> -119 | G99: =SUMIFS('Lançamentos Omie'!$G:$G,'Lançamentos Omie'!$I:$I,$D99,'Lançamentos Omie'!$F:$F,G$2) -> -119 | H99: =SUMIFS('Lançamentos Omie'!$G:$G,'Lançamentos Omie'!$I:$I,$D99,'Lançamentos Omie'!$F:$F,H$2) -> -124.7 | I99: =SUMIFS('Lançamentos Omie'!$G:$G,'Lançamentos Omie'!$I:$I,$D99,'Lançamentos Omie'!$F:$F,I$2) -> -482.94 | J99: =SUMIFS('Lançamentos Omie'!$G:$G,'Lançamentos Omie'!$I:$I,$D99,'Lançamentos Omie'!$F:$F,J$2) -> -124.7 | K99: =SUMIFS('Lançamentos Omie'!$G:$G,'Lançamentos Omie'!$I:$I,$D99,'Lançamentos Omie'!$F:$F,K$2) -> -124.7 | L99: =SUMIFS('Lançamentos Omie'!$G:$G,'Lançamentos Omie'!$I:$I,$D99,'Lançamentos Omie'!$F:$F,L$2) -> -1389.7 | M99: =SUMIFS('Lançamentos Omie'!$G:$G,'Lançamentos Omie'!$I:$I,$D99,'Lançamentos Omie'!$F:$F,M$2) -> -124.7 | ... Q99: =SUMIFS('Lançamentos Omie'!$G:$G,'Lançamentos Omie'!$I:$I,$D99,'Lançamentos Omie'!$F:$F,Q$2) -> 0 | R99: =SUM(F99:Q99) -> -2609.44 | T99: =SUM(F99:K99) -> -1095.04 | U99: =SUM(L99:Q99) -> -1514.4 | V99: =T99+U99 -> -2609.44
D100: Pesquisa e Desenvolvimento | F100: =SUMIFS('Lançamentos Omie'!$G:$G,'Lançamentos Omie'!$I:$I,$D100,'Lançamentos Omie'!$F:$F,F$2) -> 0 | G100: =SUMIFS('Lançamentos Omie'!$G:$G,'Lançamentos Omie'!$I:$I,$D100,'Lançamentos Omie'!$F:$F,G$2) -> 0 | H100: =SUMIFS('Lançamentos Omie'!$G:$G,'Lançamentos Omie'!$I:$I,$D100,'Lançamentos Omie'!$F:$F,H$2) -> -42.96 | I100: =SUMIFS('Lançamentos Omie'!$G:$G,'Lançamentos Omie'!$I:$I,$D100,'Lançamentos Omie'!$F:$F,I$2) -> -1764.73 | J100: =SUMIFS('Lançamentos Omie'!$G:$G,'Lançamentos Omie'!$I:$I,$D100,'Lançamentos Omie'!$F:$F,J$2) -> -138.73 | K100: =SUMIFS('Lançamentos Omie'!$G:$G,'Lançamentos Omie'!$I:$I,$D100,'Lançamentos Omie'!$F:$F,K$2) -> -183.75 | L100: =SUMIFS('Lançamentos Omie'!$G:$G,'Lançamentos Omie'!$I:$I,$D100,'Lançamentos Omie'!$F:$F,L$2) -> -183.75 | M100: =SUMIFS('Lançamentos Omie'!$G:$G,'Lançamentos Omie'!$I:$I,$D100,'Lançamentos Omie'!$F:$F,M$2) -> 0 | ... Q100: =SUMIFS('Lançamentos Omie'!$G:$G,'Lançamentos Omie'!$I:$I,$D100,'Lançamentos Omie'!$F:$F,Q$2) -> 0 | R100: =SUM(F100:Q100) -> -2313.92 | T100: =SUM(F100:K100) -> -2130.17 | U100: =SUM(L100:Q100) -> -183.75 | V100: =T100+U100 -> -2313.92
B101: Lucro ou Prejuízo Operacional | F101: =F48+F49 -> 707911.07 | G101: =G48+G49 -> 360342.62 | H101: =H48+H49 -> 498529 | I101: =I48+I49 -> 471682.1 | J101: =J48+J49 -> 473209.26 | K101: =K48+K49 -> 557641.13 | L101: =L48+L49 -> 733508.5 | M101: =M48+M49 -> 541285.71 | ... R101: =R48+R49 -> 4344109.4 | T101: =SUM(F101:K101) -> 3069315.2 | U101: =SUM(L101:Q101) -> 1274794.2 | V101: =T101+U101 -> 4344109.4
C102: Receitas Não Operacionais | F102: =SUMIFS('Lançamentos Omie'!$G:$G,'Lançamentos Omie'!$I:$I,$C102,'Lançamentos Omie'!$F:$F,F$2) -> 15584.31 | G102: =SUMIFS('Lançamentos Omie'!$G:$G,'Lançamentos Omie'!$I:$I,$C102,'Lançamentos Omie'!$F:$F,G$2) -> 14237.36 | H102: =SUMIFS('Lançamentos Omie'!$G:$G,'Lançamentos Omie'!$I:$I,$C102,'Lançamentos Omie'!$F:$F,H$2) -> 14183.15 | I102: =SUMIFS('Lançamentos Omie'!$G:$G,'Lançamentos Omie'!$I:$I,$C102,'Lançamentos Omie'!$F:$F,I$2) -> 15216.83 | J102: =SUMIFS('Lançamentos Omie'!$G:$G,'Lançamentos Omie'!$I:$I,$C102,'Lançamentos Omie'!$F:$F,J$2) -> 13209.71 | K102: =SUMIFS('Lançamentos Omie'!$G:$G,'Lançamentos Omie'!$I:$I,$C102,'Lançamentos Omie'!$F:$F,K$2) -> 8721.03 | L102: =SUMIFS('Lançamentos Omie'!$G:$G,'Lançamentos Omie'!$I:$I,$C102,'Lançamentos Omie'!$F:$F,L$2) -> 17437.35 | M102: =SUMIFS('Lançamentos Omie'!$G:$G,'Lançamentos Omie'!$I:$I,$C102,'Lançamentos Omie'!$F:$F,M$2) -> 11672.58 | ... Q102: =SUMIFS('Lançamentos Omie'!$G:$G,'Lançamentos Omie'!$I:$I,$C102,'Lançamentos Omie'!$F:$F,Q$2) -> 0 | R102: =SUM(F102:Q102) -> 110262.32 | T102: =SUM(F102:K102) -> 81152.39 | U102: =SUM(L102:Q102) -> 29109.93 | V102: =T102+U102 -> 110262.32
...

Sheet Lançamentos Omie
A1: Empresa | B1: Tipo | C1: Categoria | D1: Cliente ou Fornecedor (Nome Fantasia) | E1: Descrição | F1: Mês da Emissão | G1: Pago ou Recebido | H1: Valor da Conta | I1: Conta DRE | J1: Setor | K1: Observação
A2: V EVENTOS BRASIL LTDA | B2: 2. Contas a Pagar | C2: Ações de Endomarketing (*) | D2: 46.067.579 MICHELE SOARES HENRIQUES | E2: PIX - REF AÇÃO DIA DAS MULHERES 2026 | F2: Março | G2: -764 | H2: -764 | I2: Ações Endomarketing | J2: Gestão de Pessoas
A3: V EVENTOS BRASIL LTDA | B3: 2. Contas a Pagar | C3: Ações de Endomarketing (*) | D3: ALEXANDER DE BARROS ARAUJO | E3: PIX - REF AO HAPPY DE CARNAVAL - VALOR DO ORÇAMENTO | F3: Fevereiro | G3: -1800 | H3: -1800 | I3: Ações Endomarketing | J3: Gestão de Pessoas
A4: V EVENTOS BRASIL LTDA | B4: 2. Contas a Pagar | C4: Ações de Endomarketing (*) | D4: BK BRINDES E BEEK | E4: DIN - COMPRA DE BRINDES FIM DE ANO COLABORADORES - ENVIAR DIN PARA SALVATERRA MATRIZ - detalhes em anexo | F4: Janeiro | G4: -75.8 | H4: -75.8 | I4: Ações Endomarketing | J4: Gestão de Pessoas
A5: V EVENTOS BRASIL LTDA | B5: 2. Contas a Pagar | C5: Ações de Endomarketing (*) | D5: BK BRINDES E BEEK | E5: DIN - COMPRA DE BRINDES FIM DE ANO COLABORADORES - ENVIAR DIN PARA CUBO - detalhes em anexo | F5: Janeiro | G5: -379 | H5: -379 | I5: Ações Endomarketing | J5: Gestão de Pessoas
A6: V EVENTOS BRASIL LTDA | B6: 2. Contas a Pagar | C6: Ações de Endomarketing (*) | D6: CVC BRASIL | E6: BOL - REF A VIAGEM 10 ANOS - THOMAS - PARCELA xx/04 | F6: Abril | G6: -1051.86 | H6: -1051.86 | I6: Ações Endomarketing | J6: Gestão de Pessoas
A7: V EVENTOS BRASIL LTDA | B7: 2. Contas a Pagar | C7: Ações de Endomarketing (*) | D7: CVC JF NORTE VIAGENS LTDA | E7: PIX- REF A VIAGEM 10 ANOS - THOMAS - ENTRADA | F7: Abril | G7: -468 | H7: -468 | I7: Ações Endomarketing | J7: Gestão de Pessoas
A8: V EVENTOS BRASIL LTDA | B8: 2. Contas a Pagar | C8: Ações de Endomarketing (*) | D8: CVC JF NORTE VIAGENS LTDA | E8: PIX- REF A VIAGEM 10 ANOS - CRIS - ENTRADA | F8: Abril | G8: -498 | H8: -498 | I8: Ações Endomarketing | J8: Gestão de Pessoas
A9: V EVENTOS BRASIL LTDA | B9: 2. Contas a Pagar | C9: Ações de Endomarketing (*) | D9: DIONISIO SOUZA LOURO | E9: PIX - REF A AÇÃO TIME MKT | F9: Abril | G9: -110 | H9: -110 | I9: Ações Endomarketing | J9: Marketing e Growth
A10: V EVENTOS BRASIL LTDA | B10: 2. Contas a Pagar | C10: Ações de Endomarketing (*) | D10: DIVERSOS | E10: DIN - Compras para reunião lançamento de quarter DIA 20/01/2026 | F10: Janeiro | G10: -237.18 | H10: -237.18 | I10: Ações Endomarketing | J10: Gestão
A11: V EVENTOS BRASIL LTDA | B11: 2. Contas a Pagar | C11: Ações de Endomarketing (*) | D11: DIVERSOS | E11: PIX - REF A AÇÃO DO MÊS DE JANEIRO - TIME QUOKKA | F11: Janeiro | G11: -23.36 | H11: -23.36 | I11: Ações Endomarketing | J11: Financeiro CSC
A12: V EVENTOS BRASIL LTDA | B12: 2. Contas a Pagar | C12: Ações de Endomarketing (*) | D12: DIVERSOS | E12: DIN - Ação roleta de aniversário - ganhador João | F12: Março | G12: -50 | H12: -50 | I12: Ações Endomarketing | J12: Gestão de Pessoas
A13: V EVENTOS BRASIL LTDA | B13: 2. Contas a Pagar | C13: Ações de Endomarketing (*) | D13: EMPORIO DOS PAES JF LTDA | E13: PIX - REF A AÇÃO DO MÊS DE FEVEREIRO - TIME QUOKKA | F13: Fevereiro | G13: -68.4 | H13: -68.4 | I13: Ações Endomarketing | J13: Financeiro CSC
... A30: V EVENTOS BRASIL LTDA | B30: 2. Contas a Pagar | C30: Ações de Endomarketing (*) | D30: PEDRO PAULO DIAS DE SOUZA | E30: BOL - REF A REUNIÃO ATD - FEV / MARÇO / ABRIL | F30: Abril | G30: -600 | H30: -600 | I30: Ações Endomarketing | J30: Atendimento
A31: V EVENTOS BRASIL LTDA | B31: 2. Contas a Pagar | C31: Ações de Endomarketing (*) | D31: THOMAS SOUZA REIS | E31: PIX- REF A VIAGEM 10 ANOS - THOMAS | F31: Abril | G31: -1000 | H31: -1000 | I31: Ações Endomarketing | J31: Gestão de Pessoas | K31: Previsão
A32: V EVENTOS BRASIL LTDA | B32: 2. Contas a Pagar | C32: Ações de Endomarketing (*) | D32: THOMAS SOUZA REIS | E32: PIX - REF A AÇÃO CARRETA FURACÃO ESTORNO DE 195,77 NO DIA 22/04/2026 | F32: Abril | G32: -804.23 | H32: -804.23 | I32: Ações Endomarketing | J32: Gestão de Pessoas
A33: V EVENTOS BRASIL LTDA | B33: 2. Contas a Pagar | C33: Ações de Endomarketing (*) | D33: THOMAS SOUZA REIS | E33: PIX - REF A AÇÃO TIME CAF | F33: Março | G33: -200 | H33: -200 | I33: Ações Endomarketing | J33: Pós Vendas e CAF
A34: V EVENTOS BRASIL LTDA | B34: 2. Contas a Pagar | C34: Ações de Endomarketing (*) | D34: TRINCA CAMISAS PERSONALIZADAS | E34: Incluído pela importação a partir de um código de barras. BOL - Ref a compra de camisas para venda da lojinha - campanha viva 2026 - venda master plan | F34: Janeiro | G34: -1317.8 | H34: -1317.8 | I34: Ações Endomarketing | J34: Gestão de Pessoas
A35: V EVENTOS BRASIL LTDA | B35: 2. Contas a Pagar | C35: Ações de Endomarketing (*) | D35: UBER DO BRASIL TECNOLOGIA LTDA. | E35: REF UBER - REGIS - Vt festa final de ano | F35: Janeiro | G35: -42.44 | H35: -42.44 | I35: Ações Endomarketing | J35: Gestão de Pessoas
A36: V EVENTOS BRASIL LTDA | B36: 2. Contas a Pagar | C36: Ações de Endomarketing (*) | D36: UBER DO BRASIL TECNOLOGIA LTDA. | E36: REF UBER - Guilherme - Visita tecnica brinde final de ano R$ 35,83 + Comboio do bem R$ 48,82 | F36: Janeiro | G36: -84.65 | H36: -84.65 | I36: Ações Endomarketing | J36: Gestão de Pessoas
A37: V EVENTOS BRASIL LTDA | B37: 2. Contas a Pagar | C37: Ações Endomarketing | D37: ASSUNTA | E37: Incluído a partir do recebimento da NF-e. PIX- REUNIÃO DE SÓCIOS 15/01 | F37: Janeiro | G37: -3134.8 | H37: -3134.8 | I37: Ações Endomarketing | J37: Diretoria
A38: V EVENTOS BRASIL LTDA | B38: 2. Contas a Pagar | C38: Ações Endomarketing | D38: COMERCIAL MEGA BRINDES | E38: Incluído a partir do recebimento da NF-e. BOL - REF A COMPRA DE ITENS PARA O KIT ONBOARDING | F38: Março | G38: -977 | H38: -977 | I38: Ações Endomarketing | J38: Gestão de Pessoas
A39: V COMPANY | B39: 2. Contas a Pagar | C39: Ações Endomarketing | D39: EMPRESA FUNERARIA NOSSA SENHORA DA CANDELARIA LTDA | E39: PIX - Referente a compra e envio de uma coroa de flores para o velório do pai da Nath. CHAVE : 21.567.458/0001-05 | F39: Fevereiro | G39: -450 | H39: -450 | I39: Ações Endomarketing | J39: Gestão de Pessoas
A40: V COMPANY | B40: 2. Contas a Pagar | C40: Ações Endomarketing | D40: FEAT PRODUCOES | E40: DIN - Ref a compra de 22 unidades de capivaras de pelúcia para a Lojinha da Viva | F40: Fevereiro | G40: -459.8 | H40: -459.8 | I40: Ações Endomarketing | J40: Gestão de Pessoas
A41: V COMPANY | B41: 2. Contas a Pagar | C41: Ações Endomarketing | D41: GUILHERME GONCALVES MELLO | E41: DIN REF A AÇÃO DO ROLETA ANIVERSARIO | F41: Fevereiro | G41: -50 | H41: -50 | I41: Ações Endomarketing | J41: Gestão de Pessoas
A42: V COMPANY | B42: 2. Contas a Pagar | C42: Ações Endomarketing | D42: GUILHERME GONCALVES MELLO | E42: PIX - ref a compra de isqueiro para utilizar nas ações aniversario do hub - Chave Pix: 24992683148 - Xp | F42: Fevereiro | G42: -6.98 | H42: -6.98 | I42: Ações Endomarketing | J42: Gestão de Pessoas
A43: V COMPANY | B43: 2. Contas a Pagar | C43: Ações Endomarketing | D43: LAURA CACADOR BRANCO | E43: DIN - REF A AÇÃO - ROLETA ANIVERSARIO | F43: Abril | G43: -50 | H43: -50 | I43: Ações Endomarketing | J43: Gestão de Pessoas
... A92: V EVENTOS BRASIL LTDA | B92: 2. Contas a Pagar | C92: Associações de classe | D92: ORDEM DOS ADVOGADOS DO BRASIL SECAO MINAS GERAIS | E92: REF A ANUIDADE 2026 - OAB VITOR PEDROSA SITE: https://www.oabmg.org.br/tesouraria/anuidade n° ordem: 107755 cpf 05253792660 pagar a vista | F92: Janeiro | G92: -1100 | H92: -1100 | I92: Associações de Classe | J92: Diretoria
A93: V EVENTOS BRASIL LTDA | B93: 2. Contas a Pagar | C93: Bens de pequeno valor | D93: C g center games ltda | E93: 23/01 MP*2PRODUTOS - COMPRA DE 1 CELULAR PARA PARA ADM | F93: Fevereiro | G93: -825 | H93: -825 | I93: CAPEX | J93: DESPESAS GERAIS | K93: CAPEX
A94: V EVENTOS BRASIL LTDA | B94: 2. Contas a Pagar | C94: Bens de pequeno valor | D94: J A Equipamentos | E94: Incluído a partir do recebimento da NF-e. BOL REF A COMPRA DE BATERIA PARA NOBREAKS | F94: Abril | G94: -534 | H94: -534 | I94: CAPEX | J94: DESPESAS GERAIS
A95: V EVENTOS BRASIL LTDA | B95: 2. Contas a Pagar | C95: Bens de pequeno valor | D95: J A Equipamentos | E95: Incluído a partir do recebimento da NF-e. BOL REF A COMPRA DE BATERIA PARA NOBREAKS | F95: Março | G95: -270 | H95: -270 | I95: CAPEX | J95: Administrativo
A96: V EVENTOS BRASIL LTDA | B96: 2. Contas a Pagar | C96: Bens de pequeno valor | D96: J A Equipamentos | E96: BOL REF A COMPRA DE BATERIA PARA NOBREAKS ** PAGAR PELO BB POR CAUSA DO DESCONTO DO BOLETO ** | F96: Março | G96: -130.02 | H96: -136 | I96: CAPEX | J96: Administrativo
A97: V EVENTOS BRASIL LTDA | B97: 2. Contas a Pagar | C97: Bens de pequeno valor | D97: MIANOFIX LTDA | E97: 19/01 MP*MAQUINHAMP - PASSADOR DE SLIDE | F97: Fevereiro | G97: -72.18 | H97: -72.18 | I97: CAPEX | J97: DESPESAS GERAIS | K97: CAPEX
A98: V EVENTOS BRASIL LTDA | B98: 2. Contas a Pagar | C98: Bens de pequeno valor | D98: PALACIO DAS FERRAMENTAS E PARAFUSOS LTDA | E98: 22/01 MP*2PRODUTOS - FURADEIRA HUB | F98: Fevereiro | G98: -497.9 | H98: -497.9 | I98: CAPEX | J98: DESPESAS GERAIS | K98: CAPEX
A99: V EVENTOS BRASIL LTDA | B99: 2. Contas a Pagar | C99: Bens de pequeno valor | D99: PHAETON | E99: Microfone Sem Fio Ulanzi - PARA O MKT | F99: Março | G99: -159.99 | H99: -159.99 | I99: CAPEX | J99: Administrativo
A100: V EVENTOS BRASIL LTDA | B100: 2. Contas a Pagar | C100: Bens de pequeno valor | D100: PHAETON | E100: 19/02 MP*2PRODUTOS - Microfone Ulanzi J12 2 Microfones Sem Fio - PARA O HUB | F100: Março | G100: -199.99 | H100: -199.99 | I100: CAPEX | J100: Administrativo
A101: V EVENTOS BRASIL LTDA | B101: 2. Contas a Pagar | C101: Bens de pequeno valor | D101: R7 SOLUCOES EM TECNOLOGIA LTDA | E101: Teclado E Mouse Sem Fio Dell - Para o Vitor | F101: Março | G101: -182.9 | H101: -182.9 | I101: CAPEX | J101: Administrativo
A102: V EVENTOS BRASIL LTDA | B102: 2. Contas a Pagar | C102: Bens de pequeno valor | D102: SET-SERVICOS TECNICOS EM INFORMATICA LTDA | E102: PIX - REF A COMPRA DE FOTE PC JESSICA CARVALHO | F102: Março | G102: -214.9 | H102: -214.9 | I102: CAPEX | J102: Administrativo
A103: V EVENTOS BRASIL LTDA | B103: 2. Contas a Pagar | C103: Bens de pequeno valor | D103: WS SMARTHOME | E103: 06/01 MP*MERCADOLIVRE - Ref a compra de 02 fontes para roteadores wifi | F103: Fevereiro | G103: -314 | H103: -314 | I103: CAPEX | J103: DESPESAS GERAIS | K103: CAPEX
A104: V EVENTOS BRASIL LTDA | B104: 2. Contas a Pagar | C104: Bens de pequeno valor (*) | D104: R10 COMERCIO E SERVICOS DE INFORMATICA LTDA | E104: 17/03 MP*MERCADOLIVRE -compra roteador TP LINK TL ER | F104: Abril | G104: -836.1 | H104: -836.1 | I104: CAPEX | J104: DESPESAS GERAIS
A105: V EVENTOS BRASIL LTDA | B105: 2. Contas a Pagar | C105: Bens de pequeno valor (*) | D105: SEBASTIAO ROCHA REIS | E105: PIX - REF A COMPRA DE ESTABILIZADOR GIMBAL | F105: Fevereiro | G105: -400 | H105: -400 | I105: CAPEX | J105: DESPESAS GERAIS | K105: CAPEX
A106: V EVENTOS BRASIL LTDA | B106: 2. Contas a Pagar | C106: Bonificações (*) | D106: ANA CLARA COLOMBO | E106: PIX - REF A CAMPANHA NPS - FDM LUCAS.HERNANDES UFSM-MED 2029.1 (PAC) · Porto Alegre - ORÇAMENTO NPS | F106: Abril | G106: -200 | H106: -200 | I106: Marketing | J106: FUNDO DE MARKETING
A107: V EVENTOS BRASIL LTDA | B107: 2. Contas a Pagar | C107: Bonificações (*) | D107: ANNA DUENHA GARANHANI | E107: PIX - REF A CAMPANHA NPS - FDM ISADORA-GUIMARÃES MED-UEMS 2027-2 VIVA (PAC) · Campo Grande - ORÇAMENTO NPS | F107: Abril | G107: -200 | H107: -200 | I107: Marketing | J107: FUNDO DE MARKETING
A108: V EVENTOS BRASIL LTDA | B108: 2. Contas a Pagar | C108: Bonificações (*) | D108: CARTAO DE CREDITO SANTANDER | E108: REF - 02/02 THE WALT DISNEY COMPANY - ASSINATURA DISNEY + CAMPANHA VIVA Round PIX - **PAGAR NA CONTA SANTANDER DO VITOR ** FATURA 01 | F108: Fevereiro | G108: -26.5 | H108: -26.5 | I108: Marketing | J108: FUNDO DE MARKETING
A109: V EVENTOS BRASIL LTDA | B109: 2. Contas a Pagar | C109: Bonificações (*) | D109: CARTAO DE CREDITO SANTANDER | E109: REF - 02/01 THE WALT DISNEY COMPANY - ASSINATURA DISNEY + CAMPANHA VIVA Round PIX - **PAGAR NA CONTA SANTANDER DO VITOR ** FATURA 01 | F109: Janeiro | G109: -26.5 | H109: -26.5 | I109: Marketing | J109: FUNDO DE MARKETING
A110: V EVENTOS BRASIL LTDA | B110: 2. Contas a Pagar | C110: Bonificações (*) | D110: FRANQUIA MONTES CLAROS | E110: PIX - premiação puxada pós vendas - 2026-1 | F110: Abril | G110: -400 | H110: -400 | I110: Custos com Treinamentos | J110: Pós Vendas e CAF
A111: V EVENTOS BRASIL LTDA | B111: 2. Contas a Pagar | C111: Bonificações (*) | D111: JOSE FELLIPE SANTIAGO DE SOUSA | E111: PIX - REF AO PROJETO DE ENTREVISTAS DO MKT | F111: Janeiro | G111: -50 | H111: -50 | I111: Marketing | J111: FUNDO DE MARKETING
A112: V EVENTOS BRASIL LTDA | B112: 2. Contas a Pagar | C112: Bonificações (*) | D112: LUIS DE PAULA MOURA PASCOAL DE OLIVEIRA | E112: Incluído pela importação a partir de um código de barras. BOL - Ref a ação : To fechado com a VIVA | F112: Janeiro | G112: -3177.74 | H112: -3177.74 | I112: Marketing | J112: FUNDO DE MARKETING
A113: V EVENTOS BRASIL LTDA | B113: 2. Contas a Pagar | C113: Bonificações (*) | D113: LUIZA PEREIRA - LINHARES - POUPANÇA | E113: PIX - premiação puxada pós vendas - 2026-1 | F113: Março | G113: -600 | H113: -600 | I113: Custos com Treinamentos | J113: Pós Vendas e CAF
A114: V EVENTOS BRASIL LTDA | B114: 2. Contas a Pagar | C114: Bonificações (*) | D114: LUIZA PEREIRA - LINHARES - POUPANÇA | E114: PIX - premiação puxada pós vendas - 2026-1 | F114: Março | G114: -1000 | H114: -1000 | I114: Custos com Treinamentos | J114: Pós Vendas e CAF
A115: V EVENTOS BRASIL LTDA | B115: 2. Contas a Pagar | C115: Bonificações (*) | D115: MARIA DAS GRACAS ALVES FERREIRA | E115: PIX - REF A CAMPANHA NPS - FDM GABRIELA-TONIETO UNIFAGOC-ENF-UNIFICADA 2027-2 (PAC) · Uba - ORÇAMENTO NPS | F115: Abril | G115: -200 | H115: -200 | I115: Marketing | J115: FUNDO DE MARKETING
A116: V EVENTOS BRASIL LTDA | B116: 2. Contas a Pagar | C116: Bonificações (*) | D116: MARIA FERNANDA DE OLIVEIRA VIEIRA | E116: PIX - REF A CAMPANHA NPS - FDM IVES.CARVALHO MED-UNIDOMPEDRO 2029-2 (PAC) · Salvador - ORÇAMENTO NPS | F116: Abril | G116: -200 | H116: -200 | I116: Marketing | J116: FUNDO DE MARKETING
A117: SPDX ADMINISTRADORA DE FUNDOS DE FORMATURA LTDA | B117: 2. Contas a Pagar | C117: Bonificações (*) | D117: THE WALT DISNEY COMPANY (BRASIL) LTDA | E117: 02/03 Disney Plus - ASSINATURA DISNEY + CAMPANHA VIVA Round PIX | F117: Abril | G117: -26.5 | H117: -26.5 | I117: Marketing | J117: FUNDO DE MARKETING
... A135: V EVENTOS BRASIL LTDA | B135: 2. Contas a Pagar | C135: Consultorias e treinamentos (*) | D135: CONQUER | E135: REF CONQUER CURSOS **PAGAR NA CONTA SANTANDER DO VITOR ** FATURA 02 | F135: Março | G135: -119 | H135: -119 | I135: Consultorias e Treinamentos | J135: Gestão de Pessoas
A136: V EVENTOS BRASIL LTDA | B136: 2. Contas a Pagar | C136: Ações de Endomarketing (*) | D136: THOMAS SOUZA REIS | E136: PIX - REF A AÇÃO TIME POS VENDA | F136: Junho | G136: -200 | H136: -200 | I136: Ações Endomarketing | J136: Pós Vendas e CAF | K136: Mês
A137: V EVENTOS BRASIL LTDA | B137: 2. Contas a Pagar | C137: Consultorias e treinamentos (*) | D137: ONFLY | E137: VIAGEM REGIS E BARBARA - VALOR DA PLANILHA DE VIAGENS | F137: Março | G137: -2801.96 | H137: -2801.96 | I137: Consultorias e Treinamentos | J137: Gestão de Pessoas
A138: SPDX ADMINISTRADORA DE FUNDOS DE FORMATURA LTDA | B138: 2. Contas a Pagar | C138: Contabilidade | D138: BR PEOPLE SOLUCOES EM DP LTDA | E138: BOL REF A CONTABILIDADE REF.04/2026- ROTINA DE DEPARTAMENTO DE PESSOAL | F138: Abril | G138: -73.44 | H138: -73.44 | I138: Contabilidade | J138: Financeiro CSC | K138: Previsão
A139: V EVENTOS BRASIL LTDA | B139: 2. Contas a Pagar | C139: Contabilidade | D139: BR PEOPLE SOLUCOES EM DP LTDA | E139: BOL REF A CONTABILIDADE REF. 04/2026 - ROTINA DE DEPARTAMENTO DE PESSOAL | F139: Abril | G139: -1175.04 | H139: -1175.04 | I139: Contabilidade | J139: Financeiro CSC | K139: Previsão
A140: SPDX ADMINISTRADORA DE FUNDOS DE FORMATURA LTDA | B140: 2. Contas a Pagar | C140: Contabilidade | D140: BR PEOPLE SOLUCOES EM DP LTDA | E140: DEP REF A CONTABILIDADE REF. 02/2026 - ROTINA DE DEPARTAMENTO DE PESSOAL | F140: Fevereiro | G140: -73.44 | H140: -73.44 | I140: Contabilidade | J140: Financeiro CSC
A141: V EVENTOS BRASIL LTDA | B141: 2. Contas a Pagar | C141: Contabilidade | D141: BR PEOPLE SOLUCOES EM DP LTDA | E141: DEP REF A CONTABILIDADE REF. 02/2026 - ROTINA DE DEPARTAMENTO DE PESSOAL | F141: Fevereiro | G141: -1175.04 | H141: -1175.04 | I141: Contabilidade | J141: Financeiro CSC
A142: SPDX ADMINISTRADORA DE FUNDOS DE FORMATURA LTDA | B142: 2. Contas a Pagar | C142: Contabilidade | D142: BR PEOPLE SOLUCOES EM DP LTDA | E142: BOL REF A CONTABILIDADE REF.01/2026 - ROTINA DE DEPARTAMENTO DE PESSOAL | F142: Janeiro | G142: -73.44 | H142: -73.44 | I142: Contabilidade | J142: Financeiro CSC
A143: V EVENTOS BRASIL LTDA | B143: 2. Contas a Pagar | C143: Contabilidade | D143: BR PEOPLE SOLUCOES EM DP LTDA | E143: BOL REF A CONTABILIDADE REF. 01/2026 - ROTINA DE DEPARTAMENTO DE PESSOAL | F143: Janeiro | G143: -1175.04 | H143: -1175.04 | I143: Contabilidade | J143: Financeiro CSC
A144: SPDX ADMINISTRADORA DE FUNDOS DE FORMATURA LTDA | B144: 2. Contas a Pagar | C144: Contabilidade | D144: BR PEOPLE SOLUCOES EM DP LTDA | E144: BOL- REF A CONTABILIDADE REF. 03/2026 - ROTINA DE DEPARTAMENTO DE PESSOAL | F144: Março | G144: -73.44 | H144: -73.44 | I144: Contabilidade | J144: Financeiro CSC
A145: V EVENTOS BRASIL LTDA | B145: 2. Contas a Pagar | C145: Contabilidade | D145: BR PEOPLE SOLUCOES EM DP LTDA | E145: BOL - REF A CONTABILIDADE REF. 03/2026 - ROTINA DE DEPARTAMENTO DE PESSOAL | F145: Março | G145: -1224 | H145: -1224 | I145: Contabilidade | J145: Financeiro CSC
A146: SPDX ADMINISTRADORA DE FUNDOS DE FORMATURA LTDA | B146: 2. Contas a Pagar | C146: Contabilidade | D146: BRIT CONTABILIDADE LTDA | E146: BOL REF A CONTABILIDADE REF. 04/2026 | F146: Abril | G146: -2647.76 | H146: -2647.76 | I146: Contabilidade | J146: Financeiro CSC
A147: V EVENTOS BRASIL LTDA | B147: 2. Contas a Pagar | C147: Contabilidade | D147: BRIT CONTABILIDADE LTDA | E147: BOL REF A CONTABILIDADE REF. 04/2026 | F147: Abril | G147: -2144.65 | H147: -2144.65 | I147: Contabilidade | J147: Financeiro CSC
A148: V EVENTOS BRASIL LTDA | B148: 2. Contas a Pagar | C148: Contabilidade | D148: BRIT CONTABILIDADE LTDA | E148: Dep ref ao reembolso Brit - Serviços Adicionais Ref. OneFlow Omie - COMP 04/2026 | F148: Abril | G148: -130 | H148: -130 | I148: Contabilidade | J148: Financeiro CSC
A149: SPDX ADMINISTRADORA DE FUNDOS DE FORMATURA LTDA | B149: 2. Contas a Pagar | C149: Contabilidade | D149: BRIT CONTABILIDADE LTDA | E149: BOL REF A CONTABILIDADE REF. 02/2026 | F149: Fevereiro | G149: -2647.76 | H149: -2647.76 | I149: Contabilidade | J149: Financeiro CSC
A150: V EVENTOS BRASIL LTDA | B150: 2. Contas a Pagar | C150: Contabilidade | D150: BRIT CONTABILIDADE LTDA | E150: BOL REF A CONTABILIDADE REF.: 02/2026 | F150: Fevereiro | G150: -2144.65 | H150: -2144.65 | I150: Contabilidade | J150: Financeiro CSC
A151: V EVENTOS BRASIL LTDA | B151: 2. Contas a Pagar | C151: Contabilidade | D151: BRIT CONTABILIDADE LTDA | E151: Dep ref ao reembolso Brit - Serviços Adicionais Ref. OneFlow Omie - COMP02/2026 | F151: Fevereiro | G151: -130 | H151: -130 | I151: Contabilidade | J151: Financeiro CSC
... A200: V EVENTOS BRASIL LTDA | B200: 2. Contas a Pagar | C200: Equipamentos de Informática | D200: AGP | E200: 20/01 MLP*KaBuM Ace PARC 02/10 - REF A COMPRA NOTEBOOK GUILHERME GP | F200: Abril | G200: -574.9 | H200: -574.9 | I200: CAPEX | J200: Administrativo
A201: V EVENTOS BRASIL LTDA | B201: 2. Contas a Pagar | C201: Equipamentos de Informática | D201: AGP | E201: 20/01 MLP*KaBuM Ace PARC 01/10 - REF A COMPRA NOTEBOOK GUILHERME GP | F201: Fevereiro | G201: -574.9 | H201: -574.9 | I201: CAPEX | J201: DESPESAS GERAIS | K201: CAPEX
A202: V EVENTOS BRASIL LTDA | B202: 2. Contas a Pagar | C202: Equipamentos de Informática | D202: KALUNGA SA | E202: 23/05 MagaluPay*Mag PARC 10/10 - COMPRAS DE 3 NOTES | F202: Abril | G202: -999.34 | H202: -999.34 | I202: CAPEX | J202: Administrativo
A203: V EVENTOS BRASIL LTDA | B203: 2. Contas a Pagar | C203: Equipamentos de Informática | D203: KALUNGA SA | E203: 23/05 MagaluPay*Mag PARC 08/10 - COMPRAS DE 3 NOTES | F203: Fevereiro | G203: -999.34 | H203: -999.34 | I203: CAPEX | J203: DESPESAS GERAIS | K203: CAPEX
A204: V EVENTOS BRASIL LTDA | B204: 2. Contas a Pagar | C204: Equipamentos de Informática | D204: KALUNGA SA | E204: 23/05 MagaluPay*Mag PARC 09/10 - COMPRAS DE 3 NOTES | F204: Março | G204: -999.34 | H204: -999.34 | I204: CAPEX | J204: Administrativo
A205: V EVENTOS BRASIL LTDA | B205: 2. Contas a Pagar | C205: Fretes e Transportes em Geral | D205: THRANSPORTA ENTREGA LTDA | E205: BOL - REF AO MOTOBOY COMP 04/2026 | F205: Abril | G205: -139.17 | H205: -142.5 | I205: Fretes e Transportes em Geral | J205: Gestão de Pessoas
A206: V EVENTOS BRASIL LTDA | B206: 2. Contas a Pagar | C206: Fretes e Transportes em Geral | D206: THRANSPORTA ENTREGA LTDA | E206: BOL - REF AO MOTOBOY COMP 02/2026 ** PAGAR PELO BB POR CAUSA DO COD DE BARRAS ** | F206: Fevereiro | G206: -330.1 | H206: -330.1 | I206: Fretes e Transportes em Geral | J206: Gestão de Pessoas
A207: V EVENTOS BRASIL LTDA | B207: 2. Contas a Pagar | C207: Fretes e Transportes em Geral | D207: THRANSPORTA ENTREGA LTDA | E207: BOL- REF AO MOTOBOY COMP 01/2026 | F207: Janeiro | G207: -417.01 | H207: -427 | I207: Fretes e Transportes em Geral | J207: Gestão de Pessoas
A208: V EVENTOS BRASIL LTDA | B208: 2. Contas a Pagar | C208: Fretes e Transportes em Geral | D208: THRANSPORTA ENTREGA LTDA | E208: DEP - REF AO MOTOBOY COMP 03/2026 | F208: Março | G208: -173.84 | H208: -178 | I208: Fretes e Transportes em Geral | J208: Gestão de Pessoas
A209: V EVENTOS BRASIL LTDA | B209: 2. Contas a Pagar | C209: Fretes e Transportes em Geral | D209: UBER DO BRASIL TECNOLOGIA LTDA. | E209: REF UBER - Alexander - IDA/VOLTA evento sabin sinai - R$ 53,19 + Gravacao TV integracao comboio do bem- R$ 22,92 | F209: Janeiro | G209: -76.11 | H209: -76.11 | I209: Fretes e Transportes em Geral | J209: Gestão de Pessoas
A210: V EVENTOS BRASIL LTDA | B210: 2. Contas a Pagar | C210: Fretes e Transportes em Geral (*) | D210: AMAZON.COM.BR | E210: 27/12 AmazonPrimeBR - PLATAFORMA DE COMPRAS COM FRETE GRÁTIS | F210: Fevereiro | G210: -19.9 | H210: -19.9 | I210: Softwares, Sistemas e Servidores | J210: Gestão de Pessoas
A211: V EVENTOS BRASIL LTDA | B211: 2. Contas a Pagar | C211: Fretes e Transportes em Geral (*) | D211: ESTACIONAMENTOS ADMINISTRATIVOS | E211: DIN - REF AO ESTACIONAMENTO BANCO - r$ 29,00 - Estacionamento banco dia 07/04 + r$ 11,00 - Estacionamento banco dia 31/03 + r$ 17,00 - Estacionamento + gasolina banco dia 01/04 | F211: Abril | G211: -57 | H211: -57 | I211: Fretes e Transportes em Geral | J211: Financeiro CSC
A212: V EVENTOS BRASIL LTDA | B212: 2. Contas a Pagar | C212: Fretes e Transportes em Geral (*) | D212: ESTACIONAMENTOS ADMINISTRATIVOS | E212: DIN - Estacionamento banco dia 14/04 | F212: Abril | G212: -20 | H212: -20 | I212: Fretes e Transportes em Geral | J212: Financeiro CSC
A213: V EVENTOS BRASIL LTDA | B213: 2. Contas a Pagar | C213: Fretes e Transportes em Geral (*) | D213: ESTACIONAMENTOS ADMINISTRATIVOS | E213: DIN - ESTACIONAMENTO SERVIÇO DE BANCO - 10,00 - Estacionamento banco dia 19/02 18,00 - Estacionamento banco dia 25/02 10,50 - Estacionamento banco dia 26/02 | F213: Fevereiro | G213: -38.5 | H213: -38.5 | I213: Fretes e Transportes em Geral | J213: Financeiro CSC
A214: V EVENTOS BRASIL LTDA | B214: 2. Contas a Pagar | C214: Fretes e Transportes em Geral (*) | D214: ESTACIONAMENTOS ADMINISTRATIVOS | E214: DIN - ESTACIONAMENTO SERVIÇO DE BANCO r$ 13,00 - Estacionamento banco dia 27/01 + r$ 21,00 - Estacionamento banco dia 29/01 + r$ 16,50 - Estacionamento banco dia 03/02 | F214: Fevereiro | G214: -50.5 | H214: -50.5 | I214: Fretes e Transportes em Geral | J214: Financeiro CSC
A215: V EVENTOS BRASIL LTDA | B215: 2. Contas a Pagar | C215: Fretes e Transportes em Geral (*) | D215: ESTACIONAMENTOS ADMINISTRATIVOS | E215: DIN ESTACIONAMENTO - r$ 3,00 - Estacionamento banco dia 12/02 + r$ 21,50 - Estacionamento banco dia 10/2 | F215: Fevereiro | G215: -24.5 | H215: -24.5 | I215: Fretes e Transportes em Geral | J215: Financeiro CSC
... A306: V EVENTOS BRASIL LTDA | B306: 2. Contas a Pagar | C306: Marketing | D306: QUEIJARIA LA PORTA | E306: PIX - REF A COMPRA DE BRINDES PARA PARCEIROS - FINANCEIRO QUOKKA estorno imposto : R$ 10,22 | F306: Janeiro | G306: -92.88 | H306: -92.88 | I306: Marketing | J306: Financeiro CSC
A307: V EVENTOS BRASIL LTDA | B307: 2. Contas a Pagar | C307: Marketing | D307: SAD CONSULTORIA LTDA. | E307: BOL REF A PAGAMENTO PLATAFORMA - COMP 04/2025 | F307: Abril | G307: -545.68 | H307: -545.68 | I307: Marketing | J307: Gestão de Pessoas | K307: Previsão
A308: V EVENTOS BRASIL LTDA | B308: 2. Contas a Pagar | C308: Marketing | D308: SAD CONSULTORIA LTDA. | E308: BOL REF A PAGAMENTO PLATAFORMA - COMP 02/2026 | F308: Fevereiro | G308: -545.68 | H308: -545.68 | I308: Marketing | J308: Gestão de Pessoas
A309: V EVENTOS BRASIL LTDA | B309: 2. Contas a Pagar | C309: Marketing | D309: SAD CONSULTORIA LTDA. | E309: BOL REF A PAGAMENTO PLATAFORMA - COMP 01/2026 | F309: Janeiro | G309: -545.68 | H309: -545.68 | I309: Marketing | J309: Gestão de Pessoas
A310: V EVENTOS BRASIL LTDA | B310: 2. Contas a Pagar | C310: Marketing | D310: SAD CONSULTORIA LTDA. | E310: BOL REF A PAGAMENTO PLATAFORMA - COMP 03/2026 | F310: Março | G310: -545.68 | H310: -545.68 | I310: Marketing | J310: Gestão de Pessoas | K310: Estava Fevereiro
A311: V EVENTOS BRASIL LTDA | B311: 2. Contas a Pagar | C311: Marketing | D311: SMASHPOINTS TECNOLOGIA LTDA. | E311: Ref a campanha Viva em Dia março - **CARTÃO PJ** | F311: Março | G311: -330 | H311: -330 | I311: Marketing | J311: FUNDO DE MARKETING
A312: V EVENTOS BRASIL LTDA | B312: 2. Contas a Pagar | C312: Marketing | D312: STRIPE BRASIL SOLUCOES DE PAGAMENTO INSTITUICAO DE PAGAMENTO LTDA | E312: Incluído pela importação a partir de um código de barras. BOL - REF A CAMPANHA VIVA EM DIA - Campanhas de adesão, fundos e adimplência | F312: Abril | G312: -220 | H312: -220 | I312: Marketing | J312: FUNDO DE MARKETING
A313: V COMPANY | B313: 2. Contas a Pagar | C313: Marketing | D313: VITORIA DUTRA ZANCANELA | E313: BOL - REF AO SERVIÇO DE MKT FREELA SOCIAL MEDIA - 05/04 A 11/04 | F313: Abril | G313: -700 | H313: -700 | I313: Contratados Pessoas Jurídicas | J313: FUNDO DE MARKETING
A314: V COMPANY | B314: 2. Contas a Pagar | C314: Marketing | D314: VITORIA DUTRA ZANCANELA | E314: BOL - REF AO SERVIÇO DE MKT FREELA SOCIAL MEDIA - 12/04 A 25/04 | F314: Abril | G314: -1400 | H314: -1400 | I314: Contratados Pessoas Jurídicas | J314: FUNDO DE MARKETING
A315: V COMPANY | B315: 2. Contas a Pagar | C315: Marketing | D315: VITORIA DUTRA ZANCANELA | E315: BOL - REF AO SERVIÇO DE MKT FREELA SOCIAL MEDIA - 26/04 A 01/05 | F315: Abril | G315: -700 | H315: -700 | I315: Contratados Pessoas Jurídicas | J315: FUNDO DE MARKETING
A316: V EVENTOS BRASIL LTDA | B316: 2. Contas a Pagar | C316: Fretes e Transportes em Geral (*) | D316: ESTACIONAMENTOS ADMINISTRATIVOS | E316: DIN - REF AO ESTACIONAMENTO BANCO - 3,00 - Estacionamento dia 28/07 + 6,00 - Estacionamento dia 16/07 + 9,00 - Estacionamento dia 16/07 + 11,00 - Estacionamento dia 21/07 + 9,00 - Estacionamento dia 23/07 | F316: Julho | G316: -38 | H316: -38 | I316: Fretes e Transportes em Geral | J316: Financeiro CSC
A317: V EVENTOS BRASIL LTDA | B317: 2. Contas a Pagar | C317: Marketing (*) | D317: AMAZON SERVICOS DE VAREJO DO BRASIL LTDA. | E317: Ref a campanha Viva em Dia março - compra de kindle- **CARTÃO PJ** | F317: Março | G317: -594.68 | H317: -594.68 | I317: Marketing | J317: FUNDO DE MARKETING
A318: V EVENTOS BRASIL LTDA | B318: 2. Contas a Pagar | C318: Marketing (*) | D318: AMAZON SERVICOS DE VAREJO DO BRASIL LTDA. | E318: Ref a campanha Viva em Dia março - compra de headphone - **CARTÃO PJ** | F318: Março | G318: -193.67 | H318: -193.67 | I318: Marketing | J318: FUNDO DE MARKETING
A319: V EVENTOS BRASIL LTDA | B319: 2. Contas a Pagar | C319: Marketing (*) | D319: BNI BRASIL | E319: ENCONTRO Evento BNI ZMV Empreendedores - 06/01/2025 solicitação Marcos - JSR Negócios Nome fornecedor | F319: Janeiro | G319: -100 | H319: -100 | I319: Marketing | J319: Expansão
...

Sheet Página60
A1: Mês da Emissão | B1: Pago ou Recebido | C1: Setor | E1: SUM of Pago ou Recebido | F1: Mês da Emissão
A2: Julho | B2: 150 | C2: Diretoria | E2: Setor | F2: Julho | G2: Agosto | H2: Total Geral
A3: Julho | B3: 3385.05 | C3: Gestão de Pessoas | E3: Atendimento | F3: 2745.92 | G3: 4455.27 | H3: 7201.19 | I3: =G3 -> 4455.27 | J3: =F3 -> 2745.92
A4: Agosto | B4: 214.44 | C4: Financeiro Cash Out | E4: Consultoria e Performance | F4: 20817.19 | G4: 7245.32 | H4: 28062.51 | I4: =G4 -> 7245.32 | J4: =F4 -> 20817.19
A5: Agosto | B5: 117.95 | C5: FUNDO DE MARKETING | E5: DESPESAS GERAIS | F5: 9113.86 | G5: 11514.26 | H5: 20628.12 | I5: =G5 -> 11514.26 | J5: =F5 -> 9113.86
A6: Agosto | B6: 1845.2 | C6: Financeiro Cash Out | E6: Diretoria | F6: 13991.4 | G6: 22420.87 | H6: 36412.27 | I6: =G6 -> 22420.87 | J6: =F6 -> 13991.4 | L6: =I6+I5 -> 33935.13 | M6: =J6+J5 -> 23105.26
A7: Julho | B7: 38 | C7: Financeiro CSC | E7: EVENTOS OFICIAIS | F7: 17585.98 | H7: 17585.98 | I7: =G7 -> 0 | J7: =F7 -> 17585.98
A8: Julho | B8: 1485.2 | C8: Financeiro CSC | E8: Expansão | F8: 4732.11 | G8: 1757.02 | H8: 6489.13 | I8: =G8 -> 1757.02 | J8: =F8 -> 4732.11
A9: Julho | B9: 120 | C9: DESPESAS GERAIS | E9: Financeiro Cash Out | F9: 11.98 | G9: 3611.16 | H9: 3623.14 | I9: =G9 -> 3611.16 | J9: =F9 -> 11.98
A10: Julho | B10: -8344.22 | C10: Diretoria | E10: Financeiro CSC | F10: 13701.7 | G10: 14987.98 | H10: 28689.68 | I10: =G10 -> 14987.98 | J10: =F10 -> 13701.7
A11: Julho | B11: -6703.22 | C11: Diretoria | E11: FUNDO DE MARKETING | F11: 121.63 | G11: 723.56 | H11: 845.19 | I11: =G11 -> 723.56 | J11: =F11 -> 121.63
A12: Julho | B12: 60.49 | C12: Gestão de Pessoas | E12: Gestão | F12: 3484.17 | G12: 3673.93 | H12: 7158.1 | I12: =G12 -> 3673.93 | J12: =F12 -> 3484.17
A13: Julho | B13: -1738 | C13: Expansão | E13: Gestão de Pessoas | F13: 36887.95 | G13: 30632.46 | H13: 67520.41 | I13: =G13 -> 30632.46 | J13: =F13 -> 36887.95
A14: Julho | B14: 814.42 | C14: Financeiro CSC | E14: Marketing e Growth | F14: 8863.94 | G14: 14265.5 | H14: 23129.44 | I14: =G14 -> 14265.5 | J14: =F14 -> 8863.94
A15: Julho | B15: -0.01 | C15: Diretoria | E15: Pós-Vendas | F15: 5463.69 | G15: 2085.82 | H15: 7549.51 | I15: =G15 -> 2085.82 | J15: =F15 -> 5463.69
A16: Julho | B16: 93.1 | C16: Financeiro CSC | E16: TI | F16: 6613.34 | G16: 5066.16 | H16: 11679.5 | I16: =G16 -> 5066.16 | J16: =F16 -> 6613.34
A17: Julho | B17: 1.99 | C17: Financeiro CSC | E17: Total Geral | F17: 144134.86 | G17: 122439.31 | H17: 266574.17 | I17: =G17 -> 122439.31 | J17: =F17 -> 144134.86
A18: julho | B18: 427.34 | C18: Gestão de Pessoas
A19: Agosto | B19: 252.82 | C19: Gestão de Pessoas
A20: Julho | B20: 0.5 | C20: Financeiro CSC
A21: Julho | B21: 0.5 | C21: Financeiro CSC
A22: Julho | B22: 0.5 | C22: Financeiro CSC
A23: Julho | B23: 0.5 | C23: Financeiro CSC
A24: Julho | B24: 205.11 | C24: Gestão de Pessoas
A25: Julho | B25: 0.5 | C25: Financeiro CSC
A26: Julho | B26: 0.5 | C26: Financeiro CSC
A27: Julho | B27: 0.5 | C27: Financeiro CSC
A28: Julho | B28: 162.54 | C28: Gestão de Pessoas
A29: Julho | B29: 36.59 | C29: Gestão de Pessoas
... A708: Agosto | B708: 3500.39 | C708: Consultoria e Performance

Sheet Outras Informações
A2: RECEITAS
A4: Receitas inseridas manualmente | B4: janeiro | C4: fevereiro | D4: março | E4: abril | F4: maio | G4: junho | H4: julho | I4: agosto | J4: setembro | K4: outubro | L4: novembro | M4: dezembro | N4: TOTAL
A5: Royalties - Recorrentes | B5: =B32 -> 742596.16 | C5: =C32 -> 520688.71 | D5: =D32 -> 578703 | E5: =E32 -> 609147.54 | F5: =F32 -> 518335.49 | G5: =G32 -> 638364.5 | H5: =H32 -> 678311.33 | I5: =I32 -> 534530.06 | ... M5: =M32 -> 0 | N5: =SUM(B5:M5) -> 4820676.8
A6: Royalties - Fechamentos | B6: 115973.71 | C6: 77935.03 | D6: 28138.34 | E6: 23279.68 | F6: 12413.5 | G6: 111726.61 | H6: 87587.98 | I6: 71816.82 | N6: =SUM(B6:M6) -> 528871.67
A7: Fundo de Marketing - Recorrentes | B7: =B39 -> 46209.41 | C7: =C39 -> 30939.14 | D7: =D39 -> 38474.08 | E7: =E39 -> 35766.61 | F7: =F39 -> 32874.72 | G7: =G39 -> 44826.72 | H7: =H39 -> 43952.66 | I7: =I39 -> 36368.87 | ... M7: =M39 -> 0 | N7: =SUM(B7:M7) -> 309412.21
A8: Fundo de Marketing - Fechamentos | B8: 7285.45 | C8: 5088.37 | D8: 1796.06 | E8: 1497.89 | F8: 4076.76 | G8: 1291.73 | H8: 1291.73 | I8: 2333.17 | N8: =SUM(B8:M8) -> 24661.16
A9: Receita com Patrocínios | B9: 0 | C9: 0 | D9: 0 | E9: 0 | F9: 0 | G9: 0 | H9: 0 | I9: 0 | N9: =SUM(B9:M9) -> 0
A10: Receita SPDX | B10: =B22+B24 -> 435100.22 | C10: =C22+C24 -> 385150.49 | D10: =D22+D24 -> 538232.09 | E10: =E22+E24 -> 487174.31 | F10: =F22+F24 -> 486610.35 | G10: =G22+G24 -> 486259.18 | H10: =H22+H24 -> 517608.2 | I10: =I22+I24 -> 467285.15 | ... M10: =M22+M24 -> 0 | N10: =SUM(B10:M10) -> 3803420
A11: Receitas - Taxa Mundo Viva | B11: 76119.7 | C11: 73017 | D11: 71232.9 | E11: 70336.1 | F11: 73790.3 | G11: 73663 | H11: 76239.4 | I11: 77537.1 | N11: =SUM(B11:M11) -> 591935.5
A12: Markup de Liquidação de boletos | B12: =20493.31+13228.48 -> 33721.79 | C12: =18030.03+11473.79 -> 29503.82 | D12: =19882.64+17978.93 -> 37861.57 | E12: =15905.59+16071.59 -> 31977.18 | F12: =15840.02+16415.91 -> 32255.93 | G12: =17019.76+20571.26 -> 37591.02 | H12: =21429.4+18173.96 -> 39603.36 | I12: =15180.45+21515.92 -> 36696.37 | N12: =SUM(B12:M12) -> 279211.04
A13: Markup de cartão | B13: =137935.87+120.62 -> 138056.49 | C13: =72860.4+130.34 -> 72990.74 | D13: =72864.25+136.83 -> 73001.08 | E13: =73106.36+75.3 -> 73181.66 | F13: =109.41+90811.31 -> 90920.72 | G13: =89720.57+135.91 -> 89856.48 | H13: =116193.18+93.52 -> 116286.7 | I13: =69999.01+80.11 -> 70079.12 | N13: =SUM(B13:M13) -> 724372.99
A14: Markup de tarifas bancárias | B14: 3759.03 | C14: =2964.59 -> 2964.59 | D14: 4515 | E14: 2531.39 | F14: 2196.99 | G14: 2788.14 | H14: 3690.27 | I14: 3629.18 | N14: =SUM(B14:M14) -> 26074.59
A15: Receitas - Festas de Arrecadação | B15: ='P&D'!C3+'P&D'!B21 -> 3762.29 | C15: ='P&D'!D3+'P&D'!C21 -> 6307.8 | D15: ='P&D'!E3+'P&D'!D21 -> 6771.63 | E15: ='P&D'!F3+'P&D'!E21 -> 7115.56 | F15: ='P&D'!G3+'P&D'!F21 -> 263540.41 | G15: ='P&D'!H3+'P&D'!G21 -> 12085.48 | H15: ='P&D'!I3+'P&D'!H21 -> 9083.4 | I15: ='P&D'!J3+'P&D'!I21 -> 10163.01 | ... M15: ='P&D'!N3+'P&D'!M21 -> 0 | N15: =SUM(B15:M15) -> 318829.58
A16: Receita com Projetos | B16: ='P&D'!B40 -> 1640.5782 | C16: ='P&D'!C40 -> 1146.6088 | D16: ='P&D'!D40 -> 1200.1852 | E16: ='P&D'!E40 -> 220.52859 | F16: ='P&D'!F40 -> 146.8843 | G16: ='P&D'!G40 -> 984.60246 | H16: ='P&D'!H40 -> 2093.0596 | I16: ='P&D'!I40 -> 1140.343 | ... M16: ='P&D'!M40 -> 0 | N16: =SUM(B16:M16) -> 8572.7901
A17: Assessoria CSC - Quokka | B17: 49703 | C17: 46767 | D17: 41835.5 | E17: 41835.5 | F17: 45335.5 | G17: =22944+17270.5 -> 40214.5 | H17: 39404 | I17: 37783 | N17: =SUM(B17:M17) -> 342878
A18: Assessoria Central de Talentos | B18: 3774.8 | C18: 3380.94 | D18: 5299.13 | E18: 12245.03 | F18: 4283.01 | G18: 0 | H18: 3023.16 | I18: 4967.1 | N18: =SUM(B18:M18) -> 36973.17
A19: CSC Atendimento | B19: 29000 | C19: 24000 | D19: 25000 | E19: 26252.5 | F19: 29500 | G19: =6900+19500 -> 26400 | H19: 29300 | I19: 34300 | N19: =SUM(B19:M19) -> 223752.5
A21: Rendimentos | B21: janeiro | C21: fevereiro | D21: março | E21: abril | F21: maio | G21: junho | H21: julho | I21: agosto | J21: setembro | K21: outubro | L21: novembro | M21: dezembro | N21: TOTAL
A22: Rendimentos | B22: ='Rendimentos SPDX'!B28 -> 433450.98 | C22: ='Rendimentos SPDX'!D28 -> 382491.67 | D22: ='Rendimentos SPDX'!F28 -> 534870.28 | E22: ='Rendimentos SPDX'!H28 -> 483440.39 | F22: ='Rendimentos SPDX'!J28 -> 483102.93 | G22: ='Rendimentos SPDX'!L28 -> 482631.66 | H22: ='Rendimentos SPDX'!N28 -> 510797.87 | I22: ='Rendimentos SPDX'!P28 -> 467285.15 | J22: ='Rendimentos SPDX'!R28 -> 0 | K22: ='Rendimentos SPDX'!T28 -> 0 | L22: ='Rendimentos SPDX'!V28 -> 0 | M22: ='Rendimentos SPDX'!X28 -> 0 | N22: =SUM(B22:M22) -> 3778070.9
A23: IR s/ Rendimentos | B23: =-16.5%*B22 -> -71519.412 | C23: =16.5%*C22 -> 63111.125 | D23: =16.5%*D22 -> 88253.596 | E23: =16.5%*E22 -> 79767.665 | F23: =16.5%*F22 -> 79711.984 | G23: =16.5%*G22 -> 79634.224 | H23: =16.5%*H22 -> 84281.648 | I23: =16.5%*I22 -> 77102.05 | J23: =16.5%*J22 -> 0 | ... M23: =16.5%*M22 -> 0 | N23: =SUM(B23:M23) -> 480342.88
A24: Rendimentos da Conta (Lançamentos fora da planilha SPDX) | B24: =SUMIFS('Lançamentos Omie'!$G:$G,'Lançamentos Omie'!$I:$I,$A24,'Lançamentos Omie'!$F:$F,B$21) -> 1649.24 | C24: =SUMIFS('Lançamentos Omie'!$G:$G,'Lançamentos Omie'!$I:$I,$A24,'Lançamentos Omie'!$F:$F,C$21) -> 2658.82 | D24: =SUMIFS('Lançamentos Omie'!$G:$G,'Lançamentos Omie'!$I:$I,$A24,'Lançamentos Omie'!$F:$F,D$21) -> 3361.81 | E24: =SUMIFS('Lançamentos Omie'!$G:$G,'Lançamentos Omie'!$I:$I,$A24,'Lançamentos Omie'!$F:$F,E$21) -> 3733.92 | F24: =SUMIFS('Lançamentos Omie'!$G:$G,'Lançamentos Omie'!$I:$I,$A24,'Lançamentos Omie'!$F:$F,F$21) -> 3507.42 | G24: =SUMIFS('Lançamentos Omie'!$G:$G,'Lançamentos Omie'!$I:$I,$A24,'Lançamentos Omie'!$F:$F,G$21) -> 3627.52 | H24: =SUMIFS('Lançamentos Omie'!$G:$G,'Lançamentos Omie'!$I:$I,$A24,'Lançamentos Omie'!$F:$F,H$21) -> 6810.33 | I24: =SUMIFS('Lançamentos Omie'!$G:$G,'Lançamentos Omie'!$I:$I,$A24,'Lançamentos Omie'!$F:$F,I$21) -> 0 | ... M24: =SUMIFS('Lançamentos Omie'!$G:$G,'Lançamentos Omie'!$I:$I,$A24,'Lançamentos Omie'!$F:$F,M$21) -> 0 | N24: =SUM(B24:M24) -> 25349.06
A25: IR s/ Rendimentos (Lançamentos fora da planilha SPDX) | B25: =SUMIFS('Lançamentos Omie'!$G:$G,'Lançamentos Omie'!$I:$I,$A25,'Lançamentos Omie'!$F:$F,B$21) -> -101.72 | C25: =SUMIFS('Lançamentos Omie'!$G:$G,'Lançamentos Omie'!$I:$I,$A25,'Lançamentos Omie'!$F:$F,C$21) -> -366.19 | D25: =SUMIFS('Lançamentos Omie'!$G:$G,'Lançamentos Omie'!$I:$I,$A25,'Lançamentos Omie'!$F:$F,D$21) -> -583.33 | E25: =SUMIFS('Lançamentos Omie'!$G:$G,'Lançamentos Omie'!$I:$I,$A25,'Lançamentos Omie'!$F:$F,E$21) -> -403.59 | F25: =SUMIFS('Lançamentos Omie'!$G:$G,'Lançamentos Omie'!$I:$I,$A25,'Lançamentos Omie'!$F:$F,F$21) -> -643.54 | G25: =SUMIFS('Lançamentos Omie'!$G:$G,'Lançamentos Omie'!$I:$I,$A25,'Lançamentos Omie'!$F:$F,G$21) -> -1793.1 | H25: =SUMIFS('Lançamentos Omie'!$G:$G,'Lançamentos Omie'!$I:$I,$A25,'Lançamentos Omie'!$F:$F,H$21) -> -1523.31 | I25: =SUMIFS('Lançamentos Omie'!$G:$G,'Lançamentos Omie'!$I:$I,$A25,'Lançamentos Omie'!$F:$F,I$21) -> 0 | ... M25: =SUMIFS('Lançamentos Omie'!$G:$G,'Lançamentos Omie'!$I:$I,$A25,'Lançamentos Omie'!$F:$F,M$21) -> 0 | N25: =SUM(B25:M25) -> -5414.78
A27: Royalties Recorrentes | B27: janeiro | C27: fevereiro | D27: março | E27: abril | F27: maio | G27: junho | H27: julho | I27: agosto | J27: setembro | K27: outubro | L27: novembro | M27: dezembro | N27: TOTAL | P27: Para fazer a parte da categoria “Recorrência” a ideia é:
A28: Royalties Recebidos no mês de referência | B28: 889574.35 | C28: 670197.21 | D28: 454658.3 | E28: 621561.65 | F28: 490885.85 | G28: =573034.17-14259.4 -> 558774.77 | H28: 670749.86 | I28: 607150.71 | N28: =SUM(B28:M28) -> 4963552.7 | P28: 1- Após a separação de tudo aquilo que é categoria pós, pegar o volume pago no mês em análise de Serviços Prestados (sem pós) - Relatório por data de pagamento no Omie
A29: Royalties Recebidos no mês REF ao mês anterior | B29: 685870.61 | C29: 538892.42 | D29: 394160.42 | E29: 518287.37 | F29: 463479.71 | G29: 492995.39 | H29: 552324.88 | I29: 559886.35 | N29: =SUM(B29:M29) -> 4205897.1 | P29: 2- Subtrair desse volume, o valor recebido naquele mês referente aos títulos pagos do mês anterior (pegar pela base do bujão) (ex. do volume recebido em janeiro, pegar na planilha do MV tudo o que foi tit. pagos de dezembro, compensando em janeiro e subtrair) - E tudo aquilo que é refetrente a junho de 2026 em diante, pois essa é a data de corte do novo formato de apuração.
A30: Recebidos no mês de REF - não recorrentes | B30: =B28-B29 -> 203703.74 | C30: =C28-C29 -> 131304.79 | D30: =D28-D29 -> 60497.88 | E30: =E28-E29 -> 103274.28 | F30: =F28-F29 -> 27406.14 | G30: =G28-G29 -> 65779.38 | H30: =H28-H29 -> 118424.98 | I30: =I28-I29 -> 47264.36 | ... M30: =M28-M29 -> 0 | N30: =SUM(B30:M30) -> 757655.55 | P30: 3- Assim, a diferença será referente a todos os recebimentos no mês de janeiro que passaram ou não pelo MV, mas que não são referentes aos títulos do mês de análise;
A31: Recorrência Ref ao mês de Ref (pago no mês seguinte) | B31: 538892.42 | C31: 389383.92 | D31: 518205.12 | E31: 505873.26 | F31: 490929.35 | G31: 572585.12 | H31: 559886.35 | I31: 487265.7 | N31: =SUM(B31:M31) -> 4063021.2 | P31: 4- Pegar tudo o que foi gerado na recorrência do mês de análise e adicionar à diferença dita acima. Assim teremos tudo o que foi pago via MV e Omie de outras competências + a competência certa do mês analisado
A32: Total Royalties de Recorrência | B32: =B30+B31 -> 742596.16 | C32: =C30+C31 -> 520688.71 | D32: =D30+D31 -> 578703 | E32: =E30+E31 -> 609147.54 | F32: =F30+F31 -> 518335.49 | G32: =G30+G31 -> 638364.5 | H32: =H30+H31 -> 678311.33 | I32: =I30+I31 -> 534530.06 | ... M32: =M30+M31 -> 0 | N32: =SUM(B32:M32) -> 4820676.8 | P32: 5- a categoria pós já estará separada, com tudo aquilo que passou ou não pelo MV
A34: Fundo de Marketing Recorrentes | B34: janeiro | C34: fevereiro | D34: março | E34: abril | F34: maio | G34: junho | H34: julho | I34: agosto | J34: setembro | K34: outubro | L34: novembro | M34: dezembro | N34: TOTAL | P34: Para fazer a parte da categoria “Recorrência” a ideia é:
A35: FDM Recebidos no mês de referência | B35: 56562.46 | C35: 41873.46 | D35: 30327.03 | E35: 39098.56 | F35: 31836.68 | G35: 39750.54 | H35: 43688.96 | I35: 39056.33 | N35: =SUM(B35:M35) -> 322194.02 | P35: 1- Após a separação de tudo aquilo que é categoria pós, pegar o volume pago no mês em análise de Serviços Prestados (sem pós) - Relatório por data de pagamento no Omie
A36: FDM Recebidos no mês REF ao mês anterior | B36: 48667.27 | C36: 38314.22 | D36: 27670.41 | E36: 35622.99 | F36: 30303.91 | G36: 31474.57 | H36: 35770.47 | I36: 36034.17 | N36: =SUM(B36:M36) -> 283858.01 | P36: 2- Subtrair desse volume, o valor recebido naquele mês referente aos títulos pagos do mês anterior (pegar pela base do bujão) (ex. do volume recebido em janeiro, pegar na planilha do MV tudo o que foi tit. pagos de dezembro, compensando em janeiro e subtrair)
A37: Recebidos no mês de REF - não recorrentes | B37: =B35-B36 -> 7895.19 | C37: =C35-C36 -> 3559.24 | D37: =D35-D36 -> 2656.62 | E37: =E35-E36 -> 3475.57 | F37: =F35-F36 -> 1532.77 | G37: =G35-G36 -> 8275.97 | H37: =H35-H36 -> 7918.49 | I37: =I35-I36 -> 3022.16 | ... M37: =M35-M36 -> 0 | N37: =SUM(B37:M37) -> 38336.01 | P37: 3- Assim, a diferença será referente a todos os recebimentos no mês de janeiro que passaram ou não pelo MV, mas que não são referentes aos títulos de dezembro;
A38: Recorrência Ref ao mês de Ref (pago no mês seguinte) | B38: 38314.22 | C38: 27379.9 | D38: 35817.46 | E38: 32291.04 | F38: 31341.95 | G38: 36550.75 | H38: 36034.17 | I38: 33346.71 | N38: =SUM(B38:M38) -> 271076.2 | P38: 4- Pegar na planilha do MV tudo o que é referente aos tit. pagos no mês em análise e foi pago no M+1 e adicionar à diferença dita acima (ex. Pegar os recebimentos de fevereiro relativos aos tit. pagos em janeiro e somar na diferença). Assim teremos tudo o que foi pago via MV e Omie e que não são da categoria pós.
A39: Total Royalties de Recorrência | B39: =B37+B38 -> 46209.41 | C39: =C37+C38 -> 30939.14 | D39: =D37+D38 -> 38474.08 | E39: =E37+E38 -> 35766.61 | F39: =F37+F38 -> 32874.72 | G39: =G37+G38 -> 44826.72 | H39: =H37+H38 -> 43952.66 | I39: =I37+I38 -> 36368.87 | ... M39: =M37+M38 -> 0 | N39: =SUM(B39:M39) -> 309412.21 | P39: 5- a categoria pós já estará separada, com tudo aquilo que passou ou não pelo MV
A41: FATURADOS EXCETO VIVA JF PARA CÁLCULO DO ISS EM CHÁCARA
A42: Royalties Recorrentes | B42: janeiro | C42: fevereiro | D42: março | E42: abril | F42: maio | G42: junho | H42: julho | I42: agosto | J42: setembro | K42: outubro | L42: novembro | M42: dezembro | N42: TOTAL
A43: Royalties Recebidos no mês de referência | F43: 455362.15 | G43: =526626.89-14259.4 -> 512367.49 | H43: 537428.06 | I43: 564440.75 | N43: =SUM(B43:M43) -> 2069598.5
A44: Royalties Recebidos no mês REF ao mês anterior | F44: 431409.79 | G44: 457516.31 | H44: 517997.83 | I44: 513397.17 | N44: =SUM(B44:M44) -> 1920321.1
A45: Recebidos no mês de REF - não recorrentes | B45: =B43-B44 -> 0 | C45: =C43-C44 -> 0 | D45: =D43-D44 -> 0 | E45: =E43-E44 -> 0 | F45: =F43-F44 -> 23952.36 | G45: =G43-G44 -> 54851.18 | H45: =H43-H44 -> 19430.23 | I45: =I43-I44 -> 51043.58 | ... M45: =M43-M44 -> 0 | N45: =SUM(B45:M45) -> 149277.35
A46: Recorrência Ref ao mês de Ref (pago no mês seguinte) | F46: 449306.67 | G46: 540589.56 | H46: 513397.17 | I46: 487265.7 | N46: =SUM(B46:M46) -> 1990559.1
A47: Total Royalties de Recorrência | B47: =B45+B46 -> 0 | C47: =C45+C46 -> 0 | D47: =D45+D46 -> 0 | E47: =E45+E46 -> 0 | F47: =F45+F46 -> 473259.03 | G47: =G45+G46 -> 595440.74 | H47: =H45+H46 -> 532827.4 | I47: =I45+I46 -> 538309.28 | ... M47: =M45+M46 -> 0 | N47: =SUM(B47:M47) -> 2139836.5
A49: Fundo de Marketing Recorrentes | B49: janeiro | C49: fevereiro | D49: março | E49: abril | F49: maio | G49: junho | H49: julho | I49: agosto | J49: setembro | K49: outubro | L49: novembro | M49: dezembro | N49: TOTAL
A50: FDM Recebidos no mês de referência | F50: 29538.15 | G50: 37100.34 | H50: 41252.72 | I50: 36330.75 | N50: =SUM(B50:M50) -> 144221.96
A51: FDM Recebidos no mês REF ao mês anterior | F51: 28256.46 | G51: 28826.82 | H51: 33579.03 | I51: 33066.8 | N51: =SUM(B51:M51) -> 123729.11
A52: Recebidos no mês de REF - não recorrentes | B52: =B50-B51 -> 0 | C52: =C50-C51 -> 0 | D52: =D50-D51 -> 0 | E52: =E50-E51 -> 0 | F52: =F50-F51 -> 1281.69 | G52: =G50-G51 -> 8273.52 | H52: =H50-H51 -> 7673.69 | I52: =I50-I51 -> 3263.95 | ... M52: =M50-M51 -> 0 | N52: =SUM(B52:M52) -> 20492.85
A53: Recorrência Ref ao mês de Ref (pago no mês seguinte) | F53: 28256.46 | G53: 34508.12 | H53: 33066.8 | I53: 31101.92 | N53: =SUM(B53:M53) -> 126933.3
A54: Total Royalties de Recorrência | B54: =B52+B53 -> 0 | C54: =C52+C53 -> 0 | D54: =D52+D53 -> 0 | E54: =E52+E53 -> 0 | F54: =F52+F53 -> 29538.15 | G54: =G52+G53 -> 42781.64 | H54: =H52+H53 -> 40740.49 | I54: =I52+I53 -> 34365.87 | ... M54: =M52+M53 -> 0 | N54: =SUM(B54:M54) -> 147426.15
A56: Categoria Pós - Exceto Viva JF | B56: janeiro | C56: fevereiro | D56: março | E56: abril | F56: maio | G56: junho | H56: julho | I56: agosto | J56: setembro | K56: outubro | L56: novembro | M56: dezembro | N56: TOTAL
A57: Royalties | F57: 11674.94 | G57: 111726.61 | H57: 87238.33 | I57: 20049.84 | N57: =SUM(B57:M57) -> 230689.72
A58: Fundo de Marketing | F58: 1291.73 | G58: 1291.73 | H58: 1303.95 | I58: 1291.73 | N58: =SUM(B58:M58) -> 5179.14
A60: ISS de 5% | F60: =(F32+F39)-(F47+F54)+(F6+F8)-(F57+F58) -> 51936.62 | G60: =(G32+G39)-(G47+G54)+(G6+G8)-(G57+G58) -> 44968.84 | H60: =(H32+H39)-(H47+H54)+(H6+H8)-(H57+H58) -> 149033.53 | I60: =(I32+I39)-(I47+I54)+(I6+I8)-(I57+I58) -> 51032.2 | J60: =(J32+J39)-(J47+J54)+(J6+J8)-(J57+J58) -> 0 | K60: =(K32+K39)-(K47+K54)+(K6+K8)-(K57+K58) -> 0 | L60: =(L32+L39)-(L47+L54)+(L6+L8)-(L57+L58) -> 0 | M60: =(M32+M39)-(M47+M54)+(M6+M8)-(M57+M58) -> 0
A61: ISS de 2% | F61: =F54+F47+F57+F58 -> 515763.85 | G61: =G54+G47+G57+G58 -> 751240.72 | H61: =H54+H47+H57+H58 -> 662110.17 | I61: =I54+I47+I57+I58 -> 594016.72 | J61: =J54+J47+J57+J58 -> 0 | K61: =K54+K47+K57+K58 -> 0 | L61: =L54+L47+L57+L58 -> 0 | M61: =M54+M47+M57+M58 -> 0
A64: Vendas e Renovações de Franquias | B64: janeiro | C64: fevereiro | D64: março | E64: abril | F64: maio | G64: junho | H64: julho | I64: agosto | J64: setembro | K64: outubro | L64: novembro | M64: dezembro | N64: TOTAL
A65: Vendas de Franquias | B65: =SUM(B66:B73) -> 0 | C65: =SUM(C66:C73) -> 0 | D65: =SUM(D66:D73) -> 0 | E65: =SUM(E66:E73) -> 0 | F65: =SUM(F66:F73) -> 0 | G65: =SUM(G66:G73) -> 0 | H65: =SUM(H66:H73) -> 0 | I65: =SUM(I66:I73) -> 0 | ... M65: =SUM(M66:M73) -> 0 | N65: =SUM(B65:M65) -> 0
A66: Franquia 1 | N66: =SUM(B66:M66) -> 0
A67: Franquia 2 | N67: =SUM(B67:M67) -> 0
A68: Franquia 3 | N68: =SUM(B68:M68) -> 0
A69: Franquia 4 | N69: =SUM(B69:M69) -> 0
A70: Franquia 5 | N70: =SUM(B70:M70) -> 0
A71: Franquia 6 | N71: =SUM(B71:M71) -> 0
A72: Franquia 7 | N72: =SUM(B72:M72) -> 0
A73: Franquia 8 | N73: =SUM(B73:M73) -> 0
A74: Renovações de Franquias | B74: =SUM(B75:B79) -> 0 | C74: =SUM(C75:C79) -> 0 | D74: =SUM(D75:D79) -> 0 | E74: =SUM(E75:E79) -> 0 | F74: =SUM(F75:F79) -> 0 | G74: =SUM(G75:G79) -> 0 | H74: =SUM(H75:H79) -> 0 | I74: =SUM(I75:I79) -> 0 | ... M74: =SUM(M75:M79) -> 0 | N74: =SUM(B74:M74) -> 0
A75: Franquia 1 | N75: =SUM(B75:M75) -> 0
A76: Franquia 2 | N76: =SUM(B76:M76) -> 0
A77: Franquia 3 | N77: =SUM(B77:M77) -> 0
A78: Franquia 4 | N78: =SUM(B78:M78) -> 0
A79: Franquia 5 | N79: =SUM(B79:M79) -> 0
A86: DESPESAS
A88: Alíquotas Simples | B88: janeiro | C88: fevereiro | D88: março | E88: abril | F88: maio | G88: junho | H88: julho | I88: agosto | J88: setembro | K88: outubro | L88: novembro | M88: dezembro
A89: Dataforte | B89: 0.1511 | C89: 0.1491 | D89: 0.1508 | E89: 0.1521 | F89: 0.1532 | G89: 0.1555 | H89: 0.1576 | I89: 0.1539
A90: SPDX | B90: 0.1255 | C90: 0.1257 | D90: 0.1259 | E90: 0.1261 | F90: 0.1265 | G90: 0.1268 | H90: 0.126 | I90: 0.1271
C92: 226448.95
A93: Pró-labore | B93: janeiro | C93: fevereiro | D93: março | E93: abril | F93: maio | G93: junho | H93: julho | I93: agosto | J93: setembro | K93: outubro | L93: novembro | M93: dezembro | N93: TOTAL
A94: Pró-labore | B94: 205685 | C94: =$C$92 -> 226448.95 | D94: =$C$92 -> 226448.95 | E94: =$C$92 -> 226448.95 | F94: =$C$92 -> 226448.95 | G94: =$C$92 -> 226448.95 | H94: =$C$92 -> 226448.95 | I94: =$C$92 -> 226448.95 | N94: =SUM(B94:M94) -> 1790827.6
B95: =B97*12 -> 155600.04
A96: Comissões Comerciais - Previsão | B96: janeiro | C96: fevereiro | D96: março | E96: abril | F96: maio | G96: junho | H96: julho | I96: agosto | J96: setembro | K96: outubro | L96: novembro | M96: dezembro | N96: TOTAL
A97: Comissões | B97: 12966.67 | C97: 12966.67 | D97: 12966.67 | E97: 12966.67 | F97: 12966.67 | G97: 12966.67 | H97: 12966.67 | I97: 12966.67 | N97: =SUM(B97:M97) -> 103733.36
B98: =B100*12 -> 436500
A99: Bônus - metas | B99: janeiro | C99: fevereiro | D99: março | E99: abril | F99: maio | G99: junho | H99: julho | I99: agosto | J99: setembro | K99: outubro | L99: novembro | M99: dezembro | N99: TOTAL
A100: Bônus | B100: 36375 | C100: 36375 | D100: 36375 | E100: 36375 | F100: 36375 | G100: 36375 | H100: 36375 | I100: 36375 | N100: =SUM(B100:M100) -> 291000
A103: Custos com Treinamentos | B103: janeiro | C103: fevereiro | D103: março | E103: abril | F103: maio | G103: junho | H103: julho | I103: agosto | J103: setembro | K103: outubro | L103: novembro | M103: dezembro | N103: TOTAL
A104: TOTAL | B104: =SUM(B105:B115) -> 45074.34 | C104: =SUM(C105:C115) -> 8564.12 | D104: =SUM(D105:D115) -> 0 | E104: =SUM(E105:E115) -> 2408 | F104: =SUM(F105:F115) -> 4595.65 | G104: =SUM(G105:G115) -> 5880.9 | H104: =SUM(H105:H115) -> 17572.44 | I104: =SUM(I105:I115) -> 0 | ... M104: =SUM(M105:M115) -> 0 | N104: =SUM(B104:M104) -> 84095.45
A105: 27 E 28/01/2026 MASTER PLAN | B105: =3005+34825.54 -> 37830.54 | N105: =SUM(B105:M105) -> 37830.54
A106: 12 A 17/01/2026 TREINAMENTO DE NOVOS FRANQUEADOS | B106: =2968.59+4275.21 -> 7243.8 | N106: =SUM(B106:M106) -> 7243.8
A107: 10 A 12/02/2026 MASTER CONECT ROCKETS E EXPERTS | C107: 8564.12 | N107: =SUM(B107:M107) -> 8564.12
A108: 27 A 28/04/2026 MERSÃO DE VENDAS RECIFE | E108: 2408 | N108: =SUM(B108:M108) -> 2408
A109: 19 A 20/05/2026 IMERSÃO DE VENDAS CURITIBA | F109: 4595.65 | N109: =SUM(B109:M109) -> 4595.65
A110: 09 A10/06/2026 IMERSÃO DE VENDAS VOLTA REDONDA | G110: 5880.9 | N110: =SUM(B110:M110) -> 5880.9
A111: 06-07-2026 A 09-07-2026 IMERSÃO DE VENDAS BELO HORIZONTE | H111: 13588.1
A112: 27-07-2026 A 01-08-2026 TREINAMENTO DE NOVOS FRANQUEADOS | H112: 3984.34 | N112: =SUM(B112:M112) -> 3984.34
A113: 31/08/2026 A 02/09/2026 CONVIVA | N113: =SUM(B113:M113) -> 0
A114: Evento 9 | N114: =SUM(B114:M114) -> 0
A115: Evento 10 | N115: =SUM(B115:M115) -> 0

Sheet Rendimentos SPDX
B2: 46053 | D2: 46081 | F2: 46112 | H2: 46142 | J2: 46173 | L2: 46203 | N2: 46234 | P2: 46265 | R2: 46295 | T2: 46326 | V2: 46356 | X2: 46387
A3: Conta Corrente BB | B3: =IFERROR(__xludf.DUMMYFUNCTION("importrange(""1iHVqxVBewNFSJrROFpS_EK7gNT03Cal9Cc8kCFxBtds"",""'Apuração'!FY3:GQ32"")"),"") | C3: =IFERROR(__xludf.DUMMYFUNCTION("""COMPUTED_VALUE"""),0) -> 0 | E3: =IFERROR(__xludf.DUMMYFUNCTION("""COMPUTED_VALUE"""),0) -> 0 | G3: =IFERROR(__xludf.DUMMYFUNCTION("""COMPUTED_VALUE"""),0) -> 0 | I3: =IFERROR(__xludf.DUMMYFUNCTION("""COMPUTED_VALUE"""),0) -> 0 | K3: =IFERROR(__xludf.DUMMYFUNCTION("""COMPUTED_VALUE"""),0) -> 0 | M3: =IFERROR(__xludf.DUMMYFUNCTION("""COMPUTED_VALUE"""),0) -> 0
A4: Aplicação BB Corp 10 MM | C4: =IFERROR(__xludf.DUMMYFUNCTION("""COMPUTED_VALUE"""),0) -> 0 | E4: =IFERROR(__xludf.DUMMYFUNCTION("""COMPUTED_VALUE"""),0) -> 0 | G4: =IFERROR(__xludf.DUMMYFUNCTION("""COMPUTED_VALUE"""),0) -> 0 | I4: =IFERROR(__xludf.DUMMYFUNCTION("""COMPUTED_VALUE"""),0) -> 0 | K4: =IFERROR(__xludf.DUMMYFUNCTION("""COMPUTED_VALUE"""),0) -> 0 | M4: =IFERROR(__xludf.DUMMYFUNCTION("""COMPUTED_VALUE"""),0) -> 0
A5: Rendimento Aplicação | C5: =IFERROR(__xludf.DUMMYFUNCTION("""COMPUTED_VALUE"""),"#DIV/0!") -> #DIV/0! | E5: =IFERROR(__xludf.DUMMYFUNCTION("""COMPUTED_VALUE"""),"#DIV/0!") -> #DIV/0! | G5: =IFERROR(__xludf.DUMMYFUNCTION("""COMPUTED_VALUE"""),"#DIV/0!") -> #DIV/0! | I5: =IFERROR(__xludf.DUMMYFUNCTION("""COMPUTED_VALUE"""),"#DIV/0!") -> #DIV/0! | K5: =IFERROR(__xludf.DUMMYFUNCTION("""COMPUTED_VALUE"""),"#DIV/0!") -> #DIV/0! | M5: =IFERROR(__xludf.DUMMYFUNCTION("""COMPUTED_VALUE"""),"#DIV/0!") -> #DIV/0!
A6: Aplicação BB Corp 4 MM | C6: =IFERROR(__xludf.DUMMYFUNCTION("""COMPUTED_VALUE"""),0) -> 0 | E6: =IFERROR(__xludf.DUMMYFUNCTION("""COMPUTED_VALUE"""),0) -> 0 | G6: =IFERROR(__xludf.DUMMYFUNCTION("""COMPUTED_VALUE"""),0) -> 0 | I6: =IFERROR(__xludf.DUMMYFUNCTION("""COMPUTED_VALUE"""),0) -> 0 | K6: =IFERROR(__xludf.DUMMYFUNCTION("""COMPUTED_VALUE"""),0) -> 0 | M6: =IFERROR(__xludf.DUMMYFUNCTION("""COMPUTED_VALUE"""),0) -> 0
A7: Rendimento Aplicação | C7: =IFERROR(__xludf.DUMMYFUNCTION("""COMPUTED_VALUE"""),"#DIV/0!") -> #DIV/0! | E7: =IFERROR(__xludf.DUMMYFUNCTION("""COMPUTED_VALUE"""),"#DIV/0!") -> #DIV/0! | G7: =IFERROR(__xludf.DUMMYFUNCTION("""COMPUTED_VALUE"""),"#DIV/0!") -> #DIV/0! | I7: =IFERROR(__xludf.DUMMYFUNCTION("""COMPUTED_VALUE"""),"#DIV/0!") -> #DIV/0! | K7: =IFERROR(__xludf.DUMMYFUNCTION("""COMPUTED_VALUE"""),"#DIV/0!") -> #DIV/0! | M7: =IFERROR(__xludf.DUMMYFUNCTION("""COMPUTED_VALUE"""),"#DIV/0!") -> #DIV/0!
A8: Conta Corrente Sicoob | C8: =IFERROR(__xludf.DUMMYFUNCTION("""COMPUTED_VALUE"""),0) -> 0 | E8: =IFERROR(__xludf.DUMMYFUNCTION("""COMPUTED_VALUE"""),0) -> 0 | G8: =IFERROR(__xludf.DUMMYFUNCTION("""COMPUTED_VALUE"""),0) -> 0 | I8: =IFERROR(__xludf.DUMMYFUNCTION("""COMPUTED_VALUE"""),0) -> 0 | K8: =IFERROR(__xludf.DUMMYFUNCTION("""COMPUTED_VALUE"""),0) -> 0 | M8: =IFERROR(__xludf.DUMMYFUNCTION("""COMPUTED_VALUE"""),0) -> 0
A9: Aplicação Sicoob | B9: =IFERROR(__xludf.DUMMYFUNCTION("""COMPUTED_VALUE"""),2549757.21) -> 2549757.2 | C9: =IFERROR(__xludf.DUMMYFUNCTION("""COMPUTED_VALUE"""),0.0543179816895041) -> 0.054317982 | D9: =IFERROR(__xludf.DUMMYFUNCTION("""COMPUTED_VALUE"""),2575610.89) -> 2575610.9 | E9: =IFERROR(__xludf.DUMMYFUNCTION("""COMPUTED_VALUE"""),0.0558610111721857) -> 0.055861011 | F9: =IFERROR(__xludf.DUMMYFUNCTION("""COMPUTED_VALUE"""),2607382) -> 2607382 | G9: =IFERROR(__xludf.DUMMYFUNCTION("""COMPUTED_VALUE"""),0.0573826414138794) -> 0.057382641 | H9: =IFERROR(__xludf.DUMMYFUNCTION("""COMPUTED_VALUE"""),2636311.24) -> 2636311.2 | I9: =IFERROR(__xludf.DUMMYFUNCTION("""COMPUTED_VALUE"""),0.0555817563760341) -> 0.055581756 | J9: =IFERROR(__xludf.DUMMYFUNCTION("""COMPUTED_VALUE"""),2665091.52) -> 2665091.5 | K9: =IFERROR(__xludf.DUMMYFUNCTION("""COMPUTED_VALUE"""),0.0553249761470871) -> 0.055324976 | L9: =IFERROR(__xludf.DUMMYFUNCTION("""COMPUTED_VALUE"""),2695458.57) -> 2695458.6 | M9: =IFERROR(__xludf.DUMMYFUNCTION("""COMPUTED_VALUE"""),0.052423255496314) -> 0.052423255 | N9: =IFERROR(__xludf.DUMMYFUNCTION("""COMPUTED_VALUE"""),2728771.23) -> 2728771.2 | P9: =IFERROR(__xludf.DUMMYFUNCTION("""COMPUTED_VALUE"""),2577534.97) -> 2577535
A10: Rendimento Sicoob | B10: =IFERROR(__xludf.DUMMYFUNCTION("""COMPUTED_VALUE"""),29834.8) -> 29834.8 | C10: =IFERROR(__xludf.DUMMYFUNCTION("""COMPUTED_VALUE"""),0.01170103564488) -> 0.011701036 | D10: =IFERROR(__xludf.DUMMYFUNCTION("""COMPUTED_VALUE"""),25853.68) -> 25853.68 | E10: =IFERROR(__xludf.DUMMYFUNCTION("""COMPUTED_VALUE"""),0.0100378827020722) -> 0.010037883 | F10: =IFERROR(__xludf.DUMMYFUNCTION("""COMPUTED_VALUE"""),31771.86) -> 31771.86 | G10: =IFERROR(__xludf.DUMMYFUNCTION("""COMPUTED_VALUE"""),0.0121853491356464) -> 0.012185349 | H10: =IFERROR(__xludf.DUMMYFUNCTION("""COMPUTED_VALUE"""),28928.49) -> 28928.49 | I10: =IFERROR(__xludf.DUMMYFUNCTION("""COMPUTED_VALUE"""),0.0109730936018009) -> 0.010973094 | J10: =IFERROR(__xludf.DUMMYFUNCTION("""COMPUTED_VALUE"""),28780.28) -> 28780.28 | K10: =IFERROR(__xludf.DUMMYFUNCTION("""COMPUTED_VALUE"""),0.0107989837437177) -> 0.010798984 | L10: =IFERROR(__xludf.DUMMYFUNCTION("""COMPUTED_VALUE"""),30367.05) -> 30367.05 | M10: =IFERROR(__xludf.DUMMYFUNCTION("""COMPUTED_VALUE"""),0.0112660051013138) -> 0.011266005 | N10: =IFERROR(__xludf.DUMMYFUNCTION("""COMPUTED_VALUE"""),33313.16) -> 33313.16 | P10: =IFERROR(__xludf.DUMMYFUNCTION("""COMPUTED_VALUE"""),30360.58) -> 30360.58
A11: XP MONTE BRAVO | B11: =IFERROR(__xludf.DUMMYFUNCTION("""COMPUTED_VALUE"""),17394680.96) -> 17394681 | C11: =IFERROR(__xludf.DUMMYFUNCTION("""COMPUTED_VALUE"""),0.370562325767497) -> 0.37056233 | D11: =IFERROR(__xludf.DUMMYFUNCTION("""COMPUTED_VALUE"""),17443759.86) -> 17443760 | E11: =IFERROR(__xludf.DUMMYFUNCTION("""COMPUTED_VALUE"""),0.378328134970879) -> 0.37832813 | F11: =IFERROR(__xludf.DUMMYFUNCTION("""COMPUTED_VALUE"""),17645272.42) -> 17645272 | G11: =IFERROR(__xludf.DUMMYFUNCTION("""COMPUTED_VALUE"""),0.388332948500479) -> 0.38833295 | H11: =IFERROR(__xludf.DUMMYFUNCTION("""COMPUTED_VALUE"""),17841583.34) -> 17841583 | I11: =IFERROR(__xludf.DUMMYFUNCTION("""COMPUTED_VALUE"""),0.376156852620554) -> 0.37615685 | J11: =IFERROR(__xludf.DUMMYFUNCTION("""COMPUTED_VALUE"""),17645272.42) -> 17645272 | K11: =IFERROR(__xludf.DUMMYFUNCTION("""COMPUTED_VALUE"""),0.366300469765989) -> 0.36630047 | L11: =IFERROR(__xludf.DUMMYFUNCTION("""COMPUTED_VALUE"""),18752135.11) -> 18752135 | M11: =IFERROR(__xludf.DUMMYFUNCTION("""COMPUTED_VALUE"""),0.364705279062379) -> 0.36470528 | N11: =IFERROR(__xludf.DUMMYFUNCTION("""COMPUTED_VALUE"""),18870004.03) -> 18870004 | P11: =IFERROR(__xludf.DUMMYFUNCTION("""COMPUTED_VALUE"""),18350662.92) -> 18350663
A12: Rendimento XP MB | B12: =IFERROR(__xludf.DUMMYFUNCTION("""COMPUTED_VALUE"""),94726.87) -> 94726.87 | C12: =IFERROR(__xludf.DUMMYFUNCTION("""COMPUTED_VALUE"""),0.0054457377067064) -> 0.0054457377 | D12: =IFERROR(__xludf.DUMMYFUNCTION("""COMPUTED_VALUE"""),94460.03) -> 94460.03 | E12: =IFERROR(__xludf.DUMMYFUNCTION("""COMPUTED_VALUE"""),0.00541511868760614) -> 0.0054151187 | F12: =IFERROR(__xludf.DUMMYFUNCTION("""COMPUTED_VALUE"""),210378.99) -> 210378.99 | G12: =IFERROR(__xludf.DUMMYFUNCTION("""COMPUTED_VALUE"""),0.0119226830276389) -> 0.011922683 | H12: =IFERROR(__xludf.DUMMYFUNCTION("""COMPUTED_VALUE"""),201084.92) -> 201084.92 | I12: =IFERROR(__xludf.DUMMYFUNCTION("""COMPUTED_VALUE"""),0.0112705759442984) -> 0.011270576 | J12: =IFERROR(__xludf.DUMMYFUNCTION("""COMPUTED_VALUE"""),165697.58) -> 165697.58 | K12: =IFERROR(__xludf.DUMMYFUNCTION("""COMPUTED_VALUE"""),0.00939048012725438) -> 0.0093904801 | L12: =IFERROR(__xludf.DUMMYFUNCTION("""COMPUTED_VALUE"""),148354.43) -> 148354.43 | M12: =IFERROR(__xludf.DUMMYFUNCTION("""COMPUTED_VALUE"""),0.00791133538286457) -> 0.0079113354 | N12: =IFERROR(__xludf.DUMMYFUNCTION("""COMPUTED_VALUE"""),126468.53) -> 126468.53 | P12: =IFERROR(__xludf.DUMMYFUNCTION("""COMPUTED_VALUE"""),116734) -> 116734
A13: XP MATRIZ | B13: =IFERROR(__xludf.DUMMYFUNCTION("""COMPUTED_VALUE"""),18974911.72) -> 18974912 | C13: =IFERROR(__xludf.DUMMYFUNCTION("""COMPUTED_VALUE"""),0.404226293909339) -> 0.40422629 | D13: =IFERROR(__xludf.DUMMYFUNCTION("""COMPUTED_VALUE"""),18061773.66) -> 18061774 | E13: =IFERROR(__xludf.DUMMYFUNCTION("""COMPUTED_VALUE"""),0.391731897130917) -> 0.3917319 | F13: =IFERROR(__xludf.DUMMYFUNCTION("""COMPUTED_VALUE"""),17131451.29) -> 17131451 | G13: =IFERROR(__xludf.DUMMYFUNCTION("""COMPUTED_VALUE"""),0.377024895574722) -> 0.3770249 | H13: =IFERROR(__xludf.DUMMYFUNCTION("""COMPUTED_VALUE"""),18958780.46) -> 18958780 | I13: =IFERROR(__xludf.DUMMYFUNCTION("""COMPUTED_VALUE"""),0.399710891766496) -> 0.39971089 | J13: =IFERROR(__xludf.DUMMYFUNCTION("""COMPUTED_VALUE"""),19903443.1) -> 19903443 | K13: =IFERROR(__xludf.DUMMYFUNCTION("""COMPUTED_VALUE"""),0.413178124086487) -> 0.41317812 | L13: =IFERROR(__xludf.DUMMYFUNCTION("""COMPUTED_VALUE"""),22011574.31) -> 22011574 | M13: =IFERROR(__xludf.DUMMYFUNCTION("""COMPUTED_VALUE"""),0.428097243553341) -> 0.42809724 | N13: =IFERROR(__xludf.DUMMYFUNCTION("""COMPUTED_VALUE"""),22567086.36) -> 22567086 | P13: =IFERROR(__xludf.DUMMYFUNCTION("""COMPUTED_VALUE"""),21924975.62) -> 21924976
A14: Rendimento XP MATRIZ | B14: =IFERROR(__xludf.DUMMYFUNCTION("""COMPUTED_VALUE"""),222112.51) -> 222112.51 | C14: =IFERROR(__xludf.DUMMYFUNCTION("""COMPUTED_VALUE"""),0.0117055885833654) -> 0.011705589 | D14: =IFERROR(__xludf.DUMMYFUNCTION("""COMPUTED_VALUE"""),188346.39) -> 188346.39 | E14: =IFERROR(__xludf.DUMMYFUNCTION("""COMPUTED_VALUE"""),0.0104279011322745) -> 0.010427901 | F14: =IFERROR(__xludf.DUMMYFUNCTION("""COMPUTED_VALUE"""),226799.51) -> 226799.51 | G14: =IFERROR(__xludf.DUMMYFUNCTION("""COMPUTED_VALUE"""),0.0132387797251239) -> 0.01323878 | H14: =IFERROR(__xludf.DUMMYFUNCTION("""COMPUTED_VALUE"""),194270.47) -> 194270.47 | I14: =IFERROR(__xludf.DUMMYFUNCTION("""COMPUTED_VALUE"""),0.0102469919101536) -> 0.010246992 | J14: =IFERROR(__xludf.DUMMYFUNCTION("""COMPUTED_VALUE"""),215772.74) -> 215772.74 | K14: =IFERROR(__xludf.DUMMYFUNCTION("""COMPUTED_VALUE"""),0.0108409755496022) -> 0.010840976 | L14: =IFERROR(__xludf.DUMMYFUNCTION("""COMPUTED_VALUE"""),231727.78) -> 231727.78 | M14: =IFERROR(__xludf.DUMMYFUNCTION("""COMPUTED_VALUE"""),0.0105275423164405) -> 0.010527542 | N14: =IFERROR(__xludf.DUMMYFUNCTION("""COMPUTED_VALUE"""),279457.49) -> 279457.49 | P14: =IFERROR(__xludf.DUMMYFUNCTION("""COMPUTED_VALUE"""),248087.61) -> 248087.61
A15: AF | C15: =IFERROR(__xludf.DUMMYFUNCTION("""COMPUTED_VALUE"""),0) -> 0 | E15: =IFERROR(__xludf.DUMMYFUNCTION("""COMPUTED_VALUE"""),0) -> 0 | G15: =IFERROR(__xludf.DUMMYFUNCTION("""COMPUTED_VALUE"""),0) -> 0 | I15: =IFERROR(__xludf.DUMMYFUNCTION("""COMPUTED_VALUE"""),0) -> 0 | K15: =IFERROR(__xludf.DUMMYFUNCTION("""COMPUTED_VALUE"""),0) -> 0 | M15: =IFERROR(__xludf.DUMMYFUNCTION("""COMPUTED_VALUE"""),0) -> 0
A16: Rendimento AF | C16: =IFERROR(__xludf.DUMMYFUNCTION("""COMPUTED_VALUE"""),"#DIV/0!") -> #DIV/0! | E16: =IFERROR(__xludf.DUMMYFUNCTION("""COMPUTED_VALUE"""),"#DIV/0!") -> #DIV/0! | G16: =IFERROR(__xludf.DUMMYFUNCTION("""COMPUTED_VALUE"""),"#DIV/0!") -> #DIV/0! | I16: =IFERROR(__xludf.DUMMYFUNCTION("""COMPUTED_VALUE"""),"#DIV/0!") -> #DIV/0! | K16: =IFERROR(__xludf.DUMMYFUNCTION("""COMPUTED_VALUE"""),"#DIV/0!") -> #DIV/0! | M16: =IFERROR(__xludf.DUMMYFUNCTION("""COMPUTED_VALUE"""),"#DIV/0!") -> #DIV/0!
A17: Genial | B17: =IFERROR(__xludf.DUMMYFUNCTION("""COMPUTED_VALUE"""),78715.81) -> 78715.81 | C17: =IFERROR(__xludf.DUMMYFUNCTION("""COMPUTED_VALUE"""),0.00167689845507074) -> 0.0016768985 | D17: =IFERROR(__xludf.DUMMYFUNCTION("""COMPUTED_VALUE"""),77911.67) -> 77911.67 | E17: =IFERROR(__xludf.DUMMYFUNCTION("""COMPUTED_VALUE"""),0.00168978345495101) -> 0.0016897835 | F17: =IFERROR(__xludf.DUMMYFUNCTION("""COMPUTED_VALUE"""),79893.59) -> 79893.59 | G17: =IFERROR(__xludf.DUMMYFUNCTION("""COMPUTED_VALUE"""),0.00175827908079349) -> 0.0017582791 | H17: =IFERROR(__xludf.DUMMYFUNCTION("""COMPUTED_VALUE"""),76583.32) -> 76583.32 | I17: =IFERROR(__xludf.DUMMYFUNCTION("""COMPUTED_VALUE"""),0.00161461794424085) -> 0.0016146179 | J17: =IFERROR(__xludf.DUMMYFUNCTION("""COMPUTED_VALUE"""),75155.95) -> 75155.95 | K17: =IFERROR(__xludf.DUMMYFUNCTION("""COMPUTED_VALUE"""),0.00156017199028935) -> 0.001560172 | L17: =IFERROR(__xludf.DUMMYFUNCTION("""COMPUTED_VALUE"""),73536.89) -> 73536.89 | M17: =IFERROR(__xludf.DUMMYFUNCTION("""COMPUTED_VALUE"""),0.00143019937897778) -> 0.0014301994 | N17: =IFERROR(__xludf.DUMMYFUNCTION("""COMPUTED_VALUE"""),73536.89) -> 73536.89 | P17: =IFERROR(__xludf.DUMMYFUNCTION("""COMPUTED_VALUE"""),73536.89) -> 73536.89
A18: Rendmiento Genial | B18: =IFERROR(__xludf.DUMMYFUNCTION("""COMPUTED_VALUE"""),4517.58999999999) -> 4517.59 | C18: =IFERROR(__xludf.DUMMYFUNCTION("""COMPUTED_VALUE"""),0.0573911390862902) -> 0.057391139 | D18: =IFERROR(__xludf.DUMMYFUNCTION("""COMPUTED_VALUE"""),-804.139999999999) -> -804.14 | E18: =IFERROR(__xludf.DUMMYFUNCTION("""COMPUTED_VALUE"""),-0.0103211752488426) -> -0.010321175 | F18: =IFERROR(__xludf.DUMMYFUNCTION("""COMPUTED_VALUE"""),1981.91999999999) -> 1981.92 | G18: =IFERROR(__xludf.DUMMYFUNCTION("""COMPUTED_VALUE"""),0.0248069964060946) -> 0.024806996 | H18: =IFERROR(__xludf.DUMMYFUNCTION("""COMPUTED_VALUE"""),-3310.26999999998) -> -3310.27 | I18: =IFERROR(__xludf.DUMMYFUNCTION("""COMPUTED_VALUE"""),-0.0432244253709553) -> -0.043224425 | J18: =IFERROR(__xludf.DUMMYFUNCTION("""COMPUTED_VALUE"""),-1427.37000000001) -> -1427.37 | K18: =IFERROR(__xludf.DUMMYFUNCTION("""COMPUTED_VALUE"""),-0.0189921090745311) -> -0.018992109 | L18: =IFERROR(__xludf.DUMMYFUNCTION("""COMPUTED_VALUE"""),-1619.05999999999) -> -1619.06 | M18: =IFERROR(__xludf.DUMMYFUNCTION("""COMPUTED_VALUE"""),-0.0220169767853929) -> -0.022016977 | N18: =IFERROR(__xludf.DUMMYFUNCTION("""COMPUTED_VALUE"""),0) -> 0 | P18: =IFERROR(__xludf.DUMMYFUNCTION("""COMPUTED_VALUE"""),0) -> 0
A19: Warren | C19: =IFERROR(__xludf.DUMMYFUNCTION("""COMPUTED_VALUE"""),0) -> 0 | E19: =IFERROR(__xludf.DUMMYFUNCTION("""COMPUTED_VALUE"""),0) -> 0 | G19: =IFERROR(__xludf.DUMMYFUNCTION("""COMPUTED_VALUE"""),0) -> 0 | I19: =IFERROR(__xludf.DUMMYFUNCTION("""COMPUTED_VALUE"""),0) -> 0 | K19: =IFERROR(__xludf.DUMMYFUNCTION("""COMPUTED_VALUE"""),0) -> 0 | M19: =IFERROR(__xludf.DUMMYFUNCTION("""COMPUTED_VALUE"""),0) -> 0
A20: Rendimento Warren | C20: =IFERROR(__xludf.DUMMYFUNCTION("""COMPUTED_VALUE"""),"#DIV/0!") -> #DIV/0! | E20: =IFERROR(__xludf.DUMMYFUNCTION("""COMPUTED_VALUE"""),"#DIV/0!") -> #DIV/0! | G20: =IFERROR(__xludf.DUMMYFUNCTION("""COMPUTED_VALUE"""),"#DIV/0!") -> #DIV/0! | I20: =IFERROR(__xludf.DUMMYFUNCTION("""COMPUTED_VALUE"""),"#DIV/0!") -> #DIV/0! | K20: =IFERROR(__xludf.DUMMYFUNCTION("""COMPUTED_VALUE"""),"#DIV/0!") -> #DIV/0! | M20: =IFERROR(__xludf.DUMMYFUNCTION("""COMPUTED_VALUE"""),"#DIV/0!") -> #DIV/0!
A21: Toro Investimentos | B21: =IFERROR(__xludf.DUMMYFUNCTION("""COMPUTED_VALUE"""),3446789.8) -> 3446789.8 | C21: =IFERROR(__xludf.DUMMYFUNCTION("""COMPUTED_VALUE"""),0.00085176067286424) -> 0.00085176067 | D21: =IFERROR(__xludf.DUMMYFUNCTION("""COMPUTED_VALUE"""),3449692.77) -> 3449692.8 | E21: =IFERROR(__xludf.DUMMYFUNCTION("""COMPUTED_VALUE"""),0.000748184933965621) -> 0.00074818493 | F21: =IFERROR(__xludf.DUMMYFUNCTION("""COMPUTED_VALUE"""),3472380) -> 3472380 | G21: =IFERROR(__xludf.DUMMYFUNCTION("""COMPUTED_VALUE"""),0.000499295148836728) -> 0.00049929515 | H21: =IFERROR(__xludf.DUMMYFUNCTION("""COMPUTED_VALUE"""),3416221.56) -> 3416221.6 | I21: =IFERROR(__xludf.DUMMYFUNCTION("""COMPUTED_VALUE"""),0.000504173081370061) -> 0.00050417308 | J21: =IFERROR(__xludf.DUMMYFUNCTION("""COMPUTED_VALUE"""),3404250.78) -> 3404250.8 | K21: =IFERROR(__xludf.DUMMYFUNCTION("""COMPUTED_VALUE"""),0.00075616127331476) -> 0.00075616127 | L21: =IFERROR(__xludf.DUMMYFUNCTION("""COMPUTED_VALUE"""),3404250.78) -> 3404250.8 | M21: =IFERROR(__xludf.DUMMYFUNCTION("""COMPUTED_VALUE"""),0.000662083663239039) -> 0.00066208366 | N21: =IFERROR(__xludf.DUMMYFUNCTION("""COMPUTED_VALUE"""),3327915.61) -> 3327915.6 | P21: =IFERROR(__xludf.DUMMYFUNCTION("""COMPUTED_VALUE"""),3498518.21) -> 3498518.2
A22: Rendimento Toro | B22: =IFERROR(__xludf.DUMMYFUNCTION("""COMPUTED_VALUE"""),39982.7616799999) -> 39982.762 | C22: =IFERROR(__xludf.DUMMYFUNCTION("""COMPUTED_VALUE"""),0.0116) -> 0.0116 | D22: =IFERROR(__xludf.DUMMYFUNCTION("""COMPUTED_VALUE"""),34496.9277) -> 34496.928 | E22: =IFERROR(__xludf.DUMMYFUNCTION("""COMPUTED_VALUE"""),0.01) -> 0.01 | F22: =IFERROR(__xludf.DUMMYFUNCTION("""COMPUTED_VALUE"""),22687.2299999999) -> 22687.23 | G22: =IFERROR(__xludf.DUMMYFUNCTION("""COMPUTED_VALUE"""),0.00653362535206399) -> 0.0065336254 | H22: =IFERROR(__xludf.DUMMYFUNCTION("""COMPUTED_VALUE"""),23913.55092) -> 23913.551 | I22: =IFERROR(__xludf.DUMMYFUNCTION("""COMPUTED_VALUE"""),0.007) -> 0.007 | J22: =IFERROR(__xludf.DUMMYFUNCTION("""COMPUTED_VALUE"""),36425.4833459999) -> 36425.483 | K22: =IFERROR(__xludf.DUMMYFUNCTION("""COMPUTED_VALUE"""),0.0107) -> 0.0107 | L22: =IFERROR(__xludf.DUMMYFUNCTION("""COMPUTED_VALUE"""),34042.5078) -> 34042.508 | M22: =IFERROR(__xludf.DUMMYFUNCTION("""COMPUTED_VALUE"""),0.0107) -> 0.0107 | N22: =IFERROR(__xludf.DUMMYFUNCTION("""COMPUTED_VALUE"""),30949.6151729999) -> 30949.615 | O22: =IFERROR(__xludf.DUMMYFUNCTION("""COMPUTED_VALUE"""),0.0093) -> 0.0093 | P22: =IFERROR(__xludf.DUMMYFUNCTION("""COMPUTED_VALUE"""),30728.91) -> 30728.91 | Q22: =IFERROR(__xludf.DUMMYFUNCTION("""COMPUTED_VALUE"""),0.0093) -> 0.0093
